Workbook

Sheet LEEME
A1: Kingspan Middle Americas · Commercial Review – Motor de datos (Data Engine)
A3: Cómo usar este archivo
A4: 1. Diligencie SOLO las celdas amarillas con texto azul (inputs). Todo lo demás (%, YoY, MoM, totales, mix, rankings, semáforos, Top 5) se calcula solo.
A5: 2. Cada hoja corresponde a un slide del deck (01 = Commercial Overview … 15 = Highlights). El número de la hoja = número del slide de contenido.
A6: 3. Los rankings de consultores (hojas 09–14) y los Top 5 (hojas 07–08) se reordenan automáticamente al cambiar los datos.
A7: 4. Para actualizar el PowerPoint: en cada gráfico clic derecho › "Editar datos" y pegue los valores de la tabla "Fuente gráfico" de la hoja correspondiente; en las tablas, pegue valores (Pegado especial › Valores) desde el bloque "Tabla slide".
A8: Alternativa: copie el bloque de la hoja y en PowerPoint use Pegado especial › "Pegar vínculo" (Hoja de Microsoft Excel) para dejar la tabla vinculada a este archivo.
A9: 5. Mes de corte: hoja 02_OI celda B4 y 06_Perf_Forecast celda B4 (número de mes, 9 = septiembre).
A10: 6. Revise la hoja "Validaciones": lista inconsistencias detectadas en el deck original y cómo se corrigieron.
A12: Convenciones
A13: Amarillo + azul = input · Negro = fórmula · Verde/Ámbar/Rojo = semáforo de cumplimiento (≥100% / 70–99% / <70%).
A14: Unidades: volumen en m²; ingresos en COP MM (millones de pesos); pipeline en USD.
... A24: • Mapa actual: 1 Portada · 2 Resumen ejecutivo · 3 Overview · 4 OI · 5 OI canal · 6 Backlog · 7 Backlog canal · 8 Performed/Forecast · 9 Top Opps · 10–11 Key Projects · 12 Resumen canales · 13 Sales vs Budget & margen · 14 Qué explica la desviación · 15–16 Iniciativas · 17 Actividad→Impacto · 18 Highlights · 19 Decisiones · 20 Cierre.

Sheet 00_Resumen_Ejecutivo
A1: 00 · Resumen ejecutivo – 4 preguntas
A2: Slide 2: qué nos comprometimos (amarillo = input), qué logramos (fórmula), desviación y estado (automáticos), qué la explica y acción (input).
A4: Indicador | B4: Unidad | C4: Compromiso / meta | D4: Resultado | E4: Desviación (Res − Comp) | F4: % vs compromiso | G4: Estado sugerido | H4: Estado final (override) | I4: Qué la explica | J4: Acción / decisión | K4: Responsable | L4: Fecha
A5: Order Intake YTD | B5: m² | D5: ='02_OI'!E7 -> 1400088 | E5: =IF(C5="","",D5-C5) | F5: =IF(OR(C5="",C5=0),"",D5/C5) | G5: =IF(F5="","Definir",IF(ROUND(F5,2)>=1,"Verde",IF(ROUND(F5,2)>=0.85,"Amarillo","Rojo"))) -> Definir
A6: Ventas YTD | B6: m² | C6: =RSM_Resumen_Canales!E11 -> 1247362.9 | D6: =RSM_Resumen_Canales!D11 -> 1058016 | E6: =IF(C6="","",D6-C6) -> -189346.88 | F6: =IF(OR(C6="",C6=0),"",D6/C6) -> 0.84820225 | G6: =IF(F6="","Definir",IF(ROUND(F6,2)>=1,"Verde",IF(ROUND(F6,2)>=0.85,"Amarillo","Rojo"))) -> Amarillo | I6: Industrial y Otras Geografías = 98% de la brecha | J6: Plan de cobertura territorios Industrial + plan de recuperación cuentas Ecuador / Costa Rica
A7: Margen OI YTD (Gross-STD) | B7: % | D7: ='02_OI'!E12 -> 0.25 | E7: =IF(C7="","",D7-C7) | F7: =IF(OR(C7="",C7=0),"",D7/C7) | G7: =IF(F7="","Definir",IF(ROUND(F7,2)>=1,"Verde",IF(ROUND(F7,2)>=0.85,"Amarillo","Rojo"))) -> Definir
A8: Backlog IMP | B8: m² | D8: ='04_Backlog'!B5 -> 525529 | E8: =IF(C8="","",D8-C8) | F8: =IF(OR(C8="",C8=0),"",D8/C8) | G8: =IF(F8="","Definir",IF(ROUND(F8,2)>=1,"Verde",IF(ROUND(F8,2)>=0.85,"Amarillo","Rojo"))) -> Definir
A9: Margen backlog (ponderado) | B9: % | D9: =RSM_Resumen_Canales!J11 -> 0.26897602 | E9: =IF(C9="","",D9-C9) | F9: =IF(OR(C9="",C9=0),"",D9/C9) | G9: =IF(F9="","Definir",IF(ROUND(F9,2)>=1,"Verde",IF(ROUND(F9,2)>=0.85,"Amarillo","Rojo"))) -> Definir
A10: Cierre año OI (real + forecast) | B10: m² | D10: ='06_Perf_Forecast'!B30 -> 1651050 | E10: =IF(C10="","",D10-C10) | F10: =IF(OR(C10="",C10=0),"",D10/C10) | G10: =IF(F10="","Definir",IF(ROUND(F10,2)>=1,"Verde",IF(ROUND(F10,2)>=0.85,"Amarillo","Rojo"))) -> Definir | I10: Forecast Q4 400k m² (+7,6% vs Q4-25)
A11: Iniciativas estratégicas en verde | B11: # | C11: 8 | D11: =COUNTIF('16_Iniciativas'!J5:J12,"Verde") -> 0 | E11: =IF(C11="","",D11-C11) -> -8 | F11: =IF(OR(C11="",C11=0),"",D11/C11) -> 0 | G11: =IF(COUNTA('16_Iniciativas'!J5:J12)=0,"Definir",IF(ROUND(F11,2)>=1,"Verde",IF(ROUND(F11,2)>=0.85,"Amarillo","Rojo"))) -> Definir
A13: Regla de estado sugerido: ≥100% del compromiso = Verde · 85–99% = Amarillo · <85% = Rojo. Si se diligencia "Estado final", ese prevalece en el slide.
A14: Mensaje clave del slide (1 línea): | C14: Estamos al 85% del budget de ventas YTD con OI y margen por encima del año anterior; la brecha está en territorios Industrial y dos cuentas de exportación.

Sheet 01_Overview
A1: 01 · Commercial Overview
A2: Ventas y Order Intake del mes, YTD, YoY y MoM · mix de ventas por canal y geografía
A4: Concepto (m²) | B4: Mes actual (Sep-26) | C4: Mismo mes PY (Sep-25) | D4: Mes anterior (Ago-26) | E4: YTD 2026 | F4: YTD 2025 | G4: YoY mes | H4: MoM | I4: YoY YTD
A5: Ventas (Sales) | B5: 141231 | C5: 99001 | D5: 125933 | E5: 1199504 | F5: 1120888 | G5: =IF(OR(B5="",C5=""),"",IF(C5=0,"n.a.",B5/C5-1)) -> 0.42656135 | H5: =IF(OR(B5="",D5=""),"",IF(D5=0,"n.a.",B5/D5-1)) -> 0.12147729 | I5: =IF(OR(E5="",F5=""),"",IF(F5=0,"n.a.",E5/F5-1)) -> 0.070137248
A6: Order Intake | B6: 160547 | C6: 132769 | D6: 146446 | E6: 1400088 | F6: 988103 | G6: =IF(OR(B6="",C6=""),"",IF(C6=0,"n.a.",B6/C6-1)) -> 0.20922053 | H6: =IF(OR(B6="",D6=""),"",IF(D6=0,"n.a.",B6/D6-1)) -> 0.096288052 | I6: =IF(OR(E6="",F6=""),"",IF(F6=0,"n.a.",E6/F6-1)) -> 0.4169454
A7: Book-to-bill YTD (OI / Ventas) | E7: =IFERROR(E6/E5,"") -> 1.1672225
A8: Book-to-bill mes | B8: =IFERROR(B6/B5,"") -> 1.1367688
A10: Ventas del mes por canal | B10: m² | C10: Mix %
A11: Industrial | C11: =IFERROR(B11/SUM($B$11:$B$12),0) -> 0
A12: Distribution | C12: =IFERROR(B12/SUM($B$11:$B$12),0) -> 0
A14: Ventas del mes por geografía | B14: m² | C14: Mix %
A15: Colombia | C15: =IFERROR(B15/SUM($B$15:$B$16),0) -> 0
A16: Other Geographies | C16: =IFERROR(B16/SUM($B$15:$B$16),0) -> 0
A18: Otras geografías – país | B18: m² mes | C18: % del total OG | D18: Ranking
A19: Ecuador | B19: 8828 | C19: =IFERROR(B19/SUM($B$19:$B$23),0) -> 0.21965117 | D19: =RANK(B19,$B$19:$B$23) -> 3
A20: Others | B20: 6421 | C20: =IFERROR(B20/SUM($B$19:$B$23),0) -> 0.15976214 | D20: =RANK(B20,$B$19:$B$23) -> 4
A21: Republica Dominicana | B21: 15144 | C21: =IFERROR(B21/SUM($B$19:$B$23),0) -> 0.37680078 | D21: =RANK(B21,$B$19:$B$23) -> 1
A22: Venezuela | B22: 9798 | C22: =IFERROR(B22/SUM($B$19:$B$23),0) -> 0.24378592 | D22: =RANK(B22,$B$19:$B$23) -> 2
C23: =IFERROR(B23/SUM($B$19:$B$23),0) -> 0 | D23: =RANK(B23,$B$19:$B$23) -> #N/A
A24: Total | B24: =SUM(B19:B23) -> 40191 | C24: =SUM(C19:C23) -> 1
A26: Top pedidos del mes – Cliente | B26: Proyecto | C26: Canal | D26: Valor (USD mm, según deck)
A27: Envases Tropicales | B27: Cubierta Envases Tropicales | LTORR-02071 | C27: Other Geographies | D27: 306
A28: Industrial Nutricional Avícola | B28: Industria Nutricional Avícola | C28: Cold Storage | D28: 236
A29: C.C. Chipichape P.H. | B29: Recambio cubierta Chipichape – Bodega 04 | C29: Industrial | D29: 173

Sheet 02_OI
A1: 02 · Order Intake – Octuber
A2: Tabla por producto + progresión mensual de ingresos y margen
A4: Mes de corte (1-12) | B4: 9
A6: Producto / métrica | B6: Mes actual | C6: PY | D6: YoY mes | E6: YTD | F6: Prior YTD | G6: YoY YTD
A7: IMP – Volume (m²) | B7: 160547 | C7: 132786 | D7: =IF(OR(B7="",C7=""),"",IF(C7=0,"n.a.",B7/C7-1)) -> 0.20906571 | E7: 1400088 | F7: 112088 | G7: =IF(OR(E7="",F7=""),"",IF(F7=0,"n.a.",E7/F7-1)) -> 11.490971
A8: Kingcore – Volume (m²) | B8: 20793 | C8: 10126 | D8: =IF(OR(B8="",C8=""),"",IF(C8=0,"n.a.",B8/C8-1)) -> 1.0534268 | E8: 229903 | F8: 88736 | G8: =IF(OR(E8="",F8=""),"",IF(F8=0,"n.a.",E8/F8-1)) -> 1.590865
A9: Single Skin – Volume (m²) | B9: 16271 | C9: 13834 | D9: =IF(OR(B9="",C9=""),"",IF(C9=0,"n.a.",B9/C9-1)) -> 0.17616019 | E9: 122613 | F9: 52330 | G9: =IF(OR(E9="",F9=""),"",IF(F9=0,"n.a.",E9/F9-1)) -> 1.3430728
A10: Benchmark – Volume (m²) | B10: 7880 | C10: 0 | D10: =IF(OR(B10="",C10=""),"",IF(C10=0,"n.a.",B10/C10-1)) -> n.a. | E10: 5817 | F10: 563 | G10: =IF(OR(E10="",F10=""),"",IF(F10=0,"n.a.",E10/F10-1)) -> 9.3321492
A11: IMP – Revenue (COP MM) | B11: 14484 | C11: 12723 | D11: =IF(OR(B11="",C11=""),"",IF(C11=0,"n.a.",B11/C11-1)) -> 0.13841075 | E11: 144659 | F11: 108228 | G11: =IF(OR(E11="",F11=""),"",IF(F11=0,"n.a.",E11/F11-1)) -> 0.33661345
A12: Margen (Gross-STD) | B12: 0.27 | C12: 0.24 | D12: =IF(OR(B12="",C12=""),"",(B12-C12)*100) -> 3 | E12: 0.25 | F12: 0.24 | G12: =IF(OR(E12="",F12=""),"",(E12-F12)*100) -> 1
A14: N° mes | B14: Mes | C14: Ingresos CY (COP MM) | D14: Ingresos PY (COP MM) | E14: YoY | F14: Margen CY % | G14: Fuente gráfico: CY | H14: Fuente gráfico: PY
A15: 1 | B15: Jan | C15: 9968.166 | D15: 7958.8 | E15: =IF(OR(C15="",D15=""),"",IF(D15=0,"n.a.",C15/D15-1)) -> 0.25247098 | F15: 0.251 | G15: =IF(A15<=$B$4,C15,"") -> 9968.166 | H15: =D15 -> 7958.8
A16: 2 | B16: Feb | C16: 12767.714 | D16: 10536.7 | E16: =IF(OR(C16="",D16=""),"",IF(D16=0,"n.a.",C16/D16-1)) -> 0.21173745 | F16: 0.254 | G16: =IF(A16<=$B$4,C16,"") -> 12767.714 | H16: =D16 -> 10536.7
A17: 3 | B17: Mar | C17: 14462.925 | D17: 12471.2 | E17: =IF(OR(C17="",D17=""),"",IF(D17=0,"n.a.",C17/D17-1)) -> 0.15970596 | F17: 0.261 | G17: =IF(A17<=$B$4,C17,"") -> 14462.925 | H17: =D17 -> 12471.2
A18: 4 | B18: Apr | C18: 12270.448 | D18: 9577 | E18: =IF(OR(C18="",D18=""),"",IF(D18=0,"n.a.",C18/D18-1)) -> 0.28124131 | F18: 0.257 | G18: =IF(A18<=$B$4,C18,"") -> 12270.448 | H18: =D18 -> 9577
A19: 5 | B19: May | C19: 27093.858 | D19: 8092 | E19: =IF(OR(C19="",D19=""),"",IF(D19=0,"n.a.",C19/D19-1)) -> 2.3482276 | F19: 0.209 | G19: =IF(A19<=$B$4,C19,"") -> 27093.858 | H19: =D19 -> 8092
A20: 6 | B20: Jun | C20: 13652.194 | D20: 11810.8 | E20: =IF(OR(C20="",D20=""),"",IF(D20=0,"n.a.",C20/D20-1)) -> 0.15590764 | F20: 0.285 | G20: =IF(A20<=$B$4,C20,"") -> 13652.194 | H20: =D20 -> 11810.8
A21: 7 | B21: Jul | C21: 11718.909 | D21: 7612.5 | E21: =IF(OR(C21="",D21=""),"",IF(D21=0,"n.a.",C21/D21-1)) -> 0.53942975 | F21: 0.273 | G21: =IF(A21<=$B$4,C21,"") -> 11718.909 | H21: =D21 -> 7612.5
A22: 8 | B22: Aug | C22: 14500.72 | D22: 16772.6 | E22: =IF(OR(C22="",D22=""),"",IF(D22=0,"n.a.",C22/D22-1)) -> -0.13545187 | F22: 0.268 | G22: =IF(A22<=$B$4,C22,"") -> 14500.72 | H22: =D22 -> 16772.6
A23: 9 | B23: Sep | C23: 13740.67 | D23: 10673.6 | E23: =IF(OR(C23="",D23=""),"",IF(D23=0,"n.a.",C23/D23-1)) -> 0.28735103 | F23: 0.271 | G23: =IF(A23<=$B$4,C23,"") -> 13740.67 | H23: =D23 -> 10673.6
A24: 10 | B24: Oct | C24: 14484 | D24: 12723.1 | E24: =IF(OR(C24="",D24=""),"",IF(D24=0,"n.a.",C24/D24-1)) -> 0.1384018 | G24: =IF(A24<=$B$4,C24,"") | H24: =D24 -> 12723.1
A25: 11 | B25: Nov | D25: 12445.1 | E25: =IF(OR(C25="",D25=""),"",IF(D25=0,"n.a.",C25/D25-1)) | G25: =IF(A25<=$B$4,C25,"") | H25: =D25 -> 12445.1
A26: 12 | B26: Dec | D26: 10462.4 | E26: =IF(OR(C26="",D26=""),"",IF(D26=0,"n.a.",C26/D26-1)) | G26: =IF(A26<=$B$4,C26,"") | H26: =D26 -> 10462.4
B27: YTD | C27: =SUMIFS(C15:C26,A15:A26,"<="&$B$4) -> 130175.6 | D27: =SUMIFS(D15:D26,A15:A26,"<="&$B$4) -> 95505.2 | E27: =IF(OR(C27="",D27=""),"",IF(D27=0,"n.a.",C27/D27-1)) -> 0.36302111
B28: Control vs tabla | C28: =C27-E11 -> -14483.396

Sheet 03_OI_Canal
A1: 03 · Order Intake por canal (IMP)
A2: CM / PY / YoY / Gross Margin por canal · YTD y mix se alimentan de las hojas RSM (09–14) | G2: 157039 | H2: 160547 | I2: {=H2-G1:G2} -> 160547
I3: 3508
A4: Canal | B4: OI mes CM (m²) | C4: OI mes PY (m²) | D4: YoY mes | E4: GM % CM | F4: GM % PY | G4: Δ GM (pp) | H4: OI YTD m² (RSM) | I4: Mix YTD % | J4: Ventas YTD m² | K4: Budget YTD m² | L4: % Cumpl. ventas
A5: Industrial | B5: =62296-13276+3508 -> 52528 | C5: 40646 | D5: =IF(OR(B5="",C5=""),"",IF(C5=0,"n.a.",B5/C5-1)) -> 0.29232889 | E5: 0.3307481 | F5: 0.28692083 | G5: =IF(OR(E5="",F5=""),"",(E5-F5)*100) -> 4.3827271 | H5: ='09_RSM_Industrial'!C18 -> 430568 | I5: =IFERROR(H5/$H$11,0) -> 0.33926393 | J5: ='09_RSM_Industrial'!D18 -> 339588 | K5: ='09_RSM_Industrial'!E18 -> 443901.88 | L5: =IFERROR(J5/K5,0) -> 0.76500691
A6: Distribución | B6: 29274 | C6: 53212 | D6: =IF(OR(B6="",C6=""),"",IF(C6=0,"n.a.",B6/C6-1)) -> -0.44986093 | E6: 0.3307481 | F6: 0.2701004 | G6: =IF(OR(E6="",F6=""),"",(E6-F6)*100) -> 6.0647695 | H6: ='10_RSM_Distribucion'!C20 -> 236351 | I6: =IFERROR(H6/$H$11,0) -> 0.18623161 | J6: ='10_RSM_Distribucion'!D20 -> 227016 | K6: ='10_RSM_Distribucion'!E20 -> 248524 | L6: =IFERROR(J6/K6,0) -> 0.91345705
A7: Otras Geografías | B7: 55560 | C7: 36701 | D7: =IF(OR(B7="",C7=""),"",IF(C7=0,"n.a.",B7/C7-1)) -> 0.51385521 | E7: 0.16021742 | F7: 0.10427401 | G7: =IF(OR(E7="",F7=""),"",(E7-F7)*100) -> 5.5943403 | H7: ='11_RSM_Otras_Geo'!C20 -> 367237 | I7: =IFERROR(H7/$H$11,0) -> 0.28936258 | J7: ='11_RSM_Otras_Geo'!D20 -> 306076 | K7: ='11_RSM_Otras_Geo'!E20 -> 388113 | L7: =IFERROR(J7/K7,0) -> 0.78862599
A8: Cold Storage | B8: 10911 | C8: 0 | D8: =IF(OR(B8="",C8=""),"",IF(C8=0,"n.a.",B8/C8-1)) -> n.a. | E8: 0.28710517 | F8: 0.38680242 | G8: =IF(OR(E8="",F8=""),"",(E8-F8)*100) -> -9.9697257 | H8: ='12_RSM_Cold_Storage'!C20 -> 36425 | I8: =IFERROR(H8/$H$11,0) -> 0.028700899 | J8: ='12_RSM_Cold_Storage'!D20 -> 9191 | K8: ='12_RSM_Cold_Storage'!E20 -> 10000 | L8: =IFERROR(J8/K8,0) -> 0.9191
A9: Site Cali | B9: 6625 | C9: 0 | D9: =IF(OR(B9="",C9=""),"",IF(C9=0,"n.a.",B9/C9-1)) -> n.a. | E9: 0.35059275 | F9: 0 | G9: =IF(OR(E9="",F9=""),"",(E9-F9)*100) -> 35.059275 | H9: ='13_RSM_Site_Cali'!C20 -> 140132 | I9: =IFERROR(H9/$H$11,0) -> 0.11041632 | J9: ='13_RSM_Site_Cali'!D20 -> 106715 | K9: ='13_RSM_Site_Cali'!E20 -> 111456 | L9: =IFERROR(J9/K9,0) -> 0.95746303
A10: Ventas Alternativas | B10: 5649 | C10: 2669 | D10: =IF(OR(B10="",C10=""),"",IF(C10=0,"n.a.",B10/C10-1)) -> 1.116523 | E10: 0.41498837 | F10: 0.36956934 | G10: =IF(OR(E10="",F10=""),"",(E10-F10)*100) -> 4.5419035 | H10: ='14_RSM_Vtas_Alt'!C20 -> 58411 | I10: =IFERROR(H10/$H$11,0) -> 0.04602466 | J10: ='14_RSM_Vtas_Alt'!D20 -> 69430 | K10: ='14_RSM_Vtas_Alt'!E20 -> 45368 | L10: =IFERROR(J10/K10,0) -> 1.5303738
A11: TOTAL | B11: =IF(COUNT(B5:B10)=0,"",SUM(B5:B10)) -> 160547 | C11: =IF(COUNT(C5:C10)=0,"",SUM(C5:C10)) -> 133228 | D11: =IF(OR(B11="",C11=""),"",IF(C11=0,"n.a.",B11/C11-1)) -> 0.20505449 | G11: =IF(OR(E11="",F11=""),"",(E11-F11)*100) | H11: =IF(COUNT(H5:H10)=0,"",SUM(H5:H10)) -> 1269124 | I11: =SUM(I5:I10) -> 1 | J11: =IF(COUNT(J5:J10)=0,"",SUM(J5:J10)) -> 1058016 | K11: =IF(COUNT(K5:K10)=0,"",SUM(K5:K10)) -> 1247362.9 | L11: =IFERROR(J11/K11,0) -> 0.84820225
A12: Control: Σ CM canales vs OI IMP mes (hoja 02) | B12: =IF(B11="","Pendiente",B11-'02_OI'!B7) -> 0
A13: Control: OI YTD RSM vs OI YTD IMP (hoja 02) | C13: 114611 | H13: =H11-'02_OI'!E7 -> -130964
C14: =+C13-C11 -> -18617

Sheet 04_Backlog
A1: 04 · Backlog – Octuber
A2: Tabla por producto + progresión mensual del backlog (COP MM) y margen
A4: Producto / métrica | B4: Mes actual | C4: PY | D4: Δ vs PY | E4: 1 Ene 2026 | F4: Δ vs 1 Ene
A5: IMP – Volume (m²) | B5: 525529 | C5: 360246 | D5: =IF(OR(B5="",C5=""),"",IF(C5=0,"n.a.",B5/C5-1)) -> 0.45880593 | E5: 364496 | F5: =IF(OR(B5="",E5=""),"",IF(E5=0,"n.a.",B5/E5-1)) -> 0.44179634
A6: Kingcore – Volume (m²) | B6: 78432 | C6: 38588 | D6: =IF(OR(B6="",C6=""),"",IF(C6=0,"n.a.",B6/C6-1)) -> 1.032549 | E6: 22362 | F6: =IF(OR(B6="",E6=""),"",IF(E6=0,"n.a.",B6/E6-1)) -> 2.5073786
A7: Single Skin – Volume (m²) | B7: 57196 | C7: 21370 | D7: =IF(OR(B7="",C7=""),"",IF(C7=0,"n.a.",B7/C7-1)) -> 1.6764623 | E7: 21486 | F7: =IF(OR(B7="",E7=""),"",IF(E7=0,"n.a.",B7/E7-1)) -> 1.6620125
A8: Benchmark – Volume (m²) | B8: 12167 | C8: 894 | D8: =IF(OR(B8="",C8=""),"",IF(C8=0,"n.a.",B8/C8-1)) -> 12.60962 | E8: 349 | F8: =IF(OR(B8="",E8=""),"",IF(E8=0,"n.a.",B8/E8-1)) -> 33.862464
A9: IMP – Revenue (COP MM) | B9: 49836 | C9: 35225 | D9: =IF(OR(B9="",C9=""),"",IF(C9=0,"n.a.",B9/C9-1)) -> 0.41479063 | E9: 35477 | F9: =IF(OR(B9="",E9=""),"",IF(E9=0,"n.a.",B9/E9-1)) -> 0.4047411
A10: Margen (Std) | B10: 0.273 | C10: 0.25 | D10: =(B10-C10)*100 -> 2.3 | E10: 0.25 | F10: =(B10-E10)*100 -> 2.3
A11: Margen (Std) sin Canpack | B11: 0.277 | C11: 0.25 | D11: =(B11-C11)*100 -> 2.7 | E11: 0.25 | F11: =(B11-E11)*100 -> 2.7
A13: N° mes | B13: Mes | C13: Backlog CY (COP MM) | D13: Backlog PY (COP MM) | E13: YoY | F13: Margen CY %
A14: 1 | B14: Jan | C14: 35566.1 | D14: 30422.1 | E14: =IF(OR(C14="",D14=""),"",IF(D14=0,"n.a.",C14/D14-1)) -> 0.1690876 | F14: 0.251
A15: 2 | B15: Feb | C15: 36104.5 | D15: 31461.6 | E15: =IF(OR(C15="",D15=""),"",IF(D15=0,"n.a.",C15/D15-1)) -> 0.14757355 | F15: 0.254
A16: 3 | B16: Mar | C16: 39420.9 | D16: 36223.7 | E16: =IF(OR(C16="",D16=""),"",IF(D16=0,"n.a.",C16/D16-1)) -> 0.088262657 | F16: 0.259
A17: 4 | B17: Apr | C17: 38886.8 | D17: 34454.1 | E17: =IF(OR(C17="",D17=""),"",IF(D17=0,"n.a.",C17/D17-1)) -> 0.12865523 | F17: 0.253
A18: 5 | B18: May | C18: 55927.6 | D18: 31842.8 | E18: =IF(OR(C18="",D18=""),"",IF(D18=0,"n.a.",C18/D18-1)) -> 0.75636565 | F18: 0.226
A19: 6 | B19: Jun | C19: 56477.9 | D19: 33251.2 | E19: =IF(OR(C19="",D19=""),"",IF(D19=0,"n.a.",C19/D19-1)) -> 0.69852216 | F19: 0.239
A20: 7 | B20: Jul | C20: 57136.5 | D20: 30680.1 | E20: =IF(OR(C20="",D20=""),"",IF(D20=0,"n.a.",C20/D20-1)) -> 0.86233096 | F20: 0.241
A21: 8 | B21: Aug | C21: 51456.1 | D21: 34736.9 | E21: =IF(OR(C21="",D21=""),"",IF(D21=0,"n.a.",C21/D21-1)) -> 0.4813095 | F21: 0.241
A22: 9 | B22: Sep | C22: 50189 | D22: 33247.5 | E22: =IF(OR(C22="",D22=""),"",IF(D22=0,"n.a.",C22/D22-1)) -> 0.50955711 | F22: 0.273
A23: 10 | B23: Oct | C23: 49836 | D23: 35224.5 | E23: =IF(OR(C23="",D23=""),"",IF(D23=0,"n.a.",C23/D23-1)) -> 0.41481071
A24: 11 | B24: Nov | D24: 34456 | E24: =IF(OR(C24="",D24=""),"",IF(D24=0,"n.a.",C24/D24-1))
A25: 12 | B25: Dec | D25: 35476.9 | E25: =IF(OR(C25="",D25=""),"",IF(D25=0,"n.a.",C25/D25-1))

Sheet 05_Backlog_Canal
A1: 05 · Backlog por canal (IMP)
A2: CM se alimenta del backlog por RSM (hojas 09–14); PY y márgenes se diligencian | F2: 537065 | G2: 525529 | H2: =F2-G2 -> 11536
A4: Canal | B4: Backlog CM (m²) – RSM | C4: Backlog PY (m²) | D4: YoY | E4: GM % CM | F4: GM % PY | G4: Δ GM (pp) | H4: Mix % | I4: Backlog paneles | J4: Backlog otros
A5: Industrial | B5: =251984-11536 -> 240448 | C5: 170762.19 | D5: =IF(OR(B5="",C5=""),"",IF(C5=0,"n.a.",B5/C5-1)) -> 0.4080869 | E5: 0.33117136 | F5: 0.28692083 | G5: =IF(OR(E5="",F5=""),"",(E5-F5)*100) -> 4.425053 | H5: =IFERROR(B5/$B$11,0) -> 0.45753517 | I5: ='09_RSM_Industrial'!H18 -> 210755 | J5: ='09_RSM_Industrial'!I18 -> 1913
A6: Distribución | B6: 62499 | C6: 50628.625 | D6: =IF(OR(B6="",C6=""),"",IF(C6=0,"n.a.",B6/C6-1)) -> 0.23445976 | E6: 0.29966956 | F6: 0.2701004 | G6: =IF(OR(E6="",F6=""),"",(E6-F6)*100) -> 2.9569156 | H6: =IFERROR(B6/$B$11,0) -> 0.11892588 | I6: ='10_RSM_Distribucion'!H20 -> 62537 | J6: ='10_RSM_Distribucion'!I20 -> 1979
A7: Otras Geografías | B7: 166377 | C7: 121006.42 | D7: =IF(OR(B7="",C7=""),"",IF(C7=0,"n.a.",B7/C7-1)) -> 0.37494359 | E7: 0.14624363 | F7: 0.10427401 | G7: =IF(OR(E7="",F7=""),"",(E7-F7)*100) -> 4.1969622 | H7: =IFERROR(B7/$B$11,0) -> 0.31658957 | I7: ='11_RSM_Otras_Geo'!H20 -> 136132 | J7: ='11_RSM_Otras_Geo'!I20 -> 580
A8: Cold Storage | B8: 28642 | C8: 1127.0509 | D8: =IF(OR(B8="",C8=""),"",IF(C8=0,"n.a.",B8/C8-1)) -> 24.413226 | E8: 0.28058377 | F8: 0.38680242 | G8: =IF(OR(E8="",F8=""),"",(E8-F8)*100) -> -10.621865 | H8: =IFERROR(B8/$B$11,0) -> 0.054501274 | I8: ='12_RSM_Cold_Storage'!H20 -> 27233 | J8: ='12_RSM_Cold_Storage'!I20 -> 3202
A9: Site Cali | B9: 21774 | C9: 0 | D9: =IF(OR(B9="",C9=""),"",IF(C9=0,"n.a.",B9/C9-1)) -> n.a. | E9: 0.36773598 | F9: 0 | G9: =IF(OR(E9="",F9=""),"",(E9-F9)*100) -> 36.773598 | H9: =IFERROR(B9/$B$11,0) -> 0.041432538 | I9: ='13_RSM_Site_Cali'!H20 -> 34419 | J9: ='13_RSM_Site_Cali'!I20 -> 14946
A10: Ventas Alternativas | B10: 5789 | C10: 4309.7179 | D10: =IF(OR(B10="",C10=""),"",IF(C10=0,"n.a.",B10/C10-1)) -> 0.34324339 | E10: 0.45275886 | F10: 0.36956934 | G10: =IF(OR(E10="",F10=""),"",(E10-F10)*100) -> 8.3189517 | H10: =IFERROR(B10/$B$11,0) -> 0.011015567 | I10: ='14_RSM_Vtas_Alt'!H20 -> 6066 | J10: ='14_RSM_Vtas_Alt'!I20 -> 0
A11: TOTAL | B11: =SUM(B5:B10) -> 525529 | C11: =IF(COUNT(C5:C10)=0,"",SUM(C5:C10)) -> 347834 | D11: =IF(OR(B11="",C11=""),"",IF(C11=0,"n.a.",B11/C11-1)) -> 0.5108615 | G11: =IF(OR(E11="",F11=""),"",(E11-F11)*100) | H11: =SUM(H5:H10) -> 1 | I11: =SUM(I5:I10) -> 477142 | J11: =SUM(J5:J10) -> 22620
A12: Control: backlog RSM vs backlog IMP (hoja 04) | B12: =B11-'04_Backlog'!B5 -> 0

Sheet 06_Perf_Forecast
A1: 06 · Performed / Forecast OI 2026
A2: Real vs forecast mensual, acumulados, trimestres y comparativo vs PY
A4: Mes de corte (último mes real) | B4: 9
A6: N° mes | B6: Mes | C6: Trimestre | D6: Estado | E6: Volumen m² | F6: Ingresos COP MM | G6: Acum. volumen m² | H6: Acum. ingresos COP MM | I6: Fuente gráfico: Real | J6: Fuente gráfico: Forecast
A7: 1 | B7: Jan | C7: ="Q"&ROUNDUP(A7/3,0) -> Q1 | D7: =IF(A7<=$B$4,"Real","Forecast") -> Real | E7: 104582 | F7: 9968.166 | G7: =SUM($E$7:E7) -> 104582 | H7: =SUM($F$7:F7) -> 9968.166 | I7: =IF(D7="Real",E7,0) -> 104582 | J7: =IF(D7="Forecast",E7,0) -> 0
A8: 2 | B8: Feb | C8: ="Q"&ROUNDUP(A8/3,0) -> Q1 | D8: =IF(A8<=$B$4,"Real","Forecast") -> Real | E8: 127405 | F8: 12767.714 | G8: =SUM($E$7:E8) -> 231987 | H8: =SUM($F$7:F8) -> 22735.88 | I8: =IF(D8="Real",E8,0) -> 127405 | J8: =IF(D8="Forecast",E8,0) -> 0
A9: 3 | B9: Mar | C9: ="Q"&ROUNDUP(A9/3,0) -> Q1 | D9: =IF(A9<=$B$4,"Real","Forecast") -> Real | E9: 152049 | F9: 14462.925 | G9: =SUM($E$7:E9) -> 384036 | H9: =SUM($F$7:F9) -> 37198.805 | I9: =IF(D9="Real",E9,0) -> 152049 | J9: =IF(D9="Forecast",E9,0) -> 0
A10: 4 | B10: Apr | C10: ="Q"&ROUNDUP(A10/3,0) -> Q2 | D10: =IF(A10<=$B$4,"Real","Forecast") -> Real | E10: 126530 | F10: 12270.448 | G10: =SUM($E$7:E10) -> 510566 | H10: =SUM($F$7:F10) -> 49469.253 | I10: =IF(D10="Real",E10,0) -> 126530 | J10: =IF(D10="Forecast",E10,0) -> 0
A11: 5 | B11: May | C11: ="Q"&ROUNDUP(A11/3,0) -> Q2 | D11: =IF(A11<=$B$4,"Real","Forecast") -> Real | E11: 181126 | F11: 27093.858 | G11: =SUM($E$7:E11) -> 691692 | H11: =SUM($F$7:F11) -> 76563.111 | I11: =IF(D11="Real",E11,0) -> 181126 | J11: =IF(D11="Forecast",E11,0) -> 0
A12: 6 | B12: Jun | C12: ="Q"&ROUNDUP(A12/3,0) -> Q2 | D12: =IF(A12<=$B$4,"Real","Forecast") -> Real | E12: 124406 | F12: 12022.773 | G12: =SUM($E$7:E12) -> 816098 | H12: =SUM($F$7:F12) -> 88585.884 | I12: =IF(D12="Real",E12,0) -> 124406 | J12: =IF(D12="Forecast",E12,0) -> 0
A13: 7 | B13: Jul | C13: ="Q"&ROUNDUP(A13/3,0) -> Q3 | D13: =IF(A13<=$B$4,"Real","Forecast") -> Real | E13: 114336 | F13: 11718.909 | G13: =SUM($E$7:E13) -> 930434 | H13: =SUM($F$7:F13) -> 100304.79 | I13: =IF(D13="Real",E13,0) -> 114336 | J13: =IF(D13="Forecast",E13,0) -> 0
A14: 8 | B14: Aug | C14: ="Q"&ROUNDUP(A14/3,0) -> Q3 | D14: =IF(A14<=$B$4,"Real","Forecast") -> Real | E14: 151623 | F14: 14500.72 | G14: =SUM($E$7:E14) -> 1082057 | H14: =SUM($F$7:F14) -> 114805.51 | I14: =IF(D14="Real",E14,0) -> 151623 | J14: =IF(D14="Forecast",E14,0) -> 0
A15: 9 | B15: Sep | C15: ="Q"&ROUNDUP(A15/3,0) -> Q3 | D15: =IF(A15<=$B$4,"Real","Forecast") -> Real | E15: 146446 | F15: 13740.67 | G15: =SUM($E$7:E15) -> 1228503 | H15: =SUM($F$7:F15) -> 128546.18 | I15: =IF(D15="Real",E15,0) -> 146446 | J15: =IF(D15="Forecast",E15,0) -> 0
A16: 10 | B16: Oct | C16: ="Q"&ROUNDUP(A16/3,0) -> Q4 | D16: Real | E16: 160547 | F16: 14484 | G16: =SUM($E$7:E16) -> 1389050 | H16: =SUM($F$7:F16) -> 143030.18 | I16: =IF(D16="Real",E16,0) -> 160547 | J16: =IF(D16="Forecast",E16,0) -> 0
A17: 11 | B17: Nov | C17: ="Q"&ROUNDUP(A17/3,0) -> Q4 | D17: =IF(A17<=$B$4,"Real","Forecast") -> Forecast | E17: 140000 | F17: 15077.152 | G17: =SUM($E$7:E17) -> 1529050 | H17: =SUM($F$7:F17) -> 158107.34 | I17: =IF(D17="Real",E17,0) -> 0 | J17: =IF(D17="Forecast",E17,0) -> 140000
A18: 12 | B18: Dec | C18: ="Q"&ROUNDUP(A18/3,0) -> Q4 | D18: =IF(A18<=$B$4,"Real","Forecast") -> Forecast | E18: 122000 | F18: 13335.741 | G18: =SUM($E$7:E18) -> 1651050 | H18: =SUM($F$7:F18) -> 171443.08 | I18: =IF(D18="Real",E18,0) -> 0 | J18: =IF(D18="Forecast",E18,0) -> 122000
A20: Trimestre | E20: Volumen m² | F20: Ingresos COP MM
A21: Q1 | E21: =SUMIFS($E$7:$E$18,$C$7:$C$18,A21) -> 384036 | F21: =SUMIFS($F$7:$F$18,$C$7:$C$18,A21) -> 37198.805
A22: Q2 | E22: =SUMIFS($E$7:$E$18,$C$7:$C$18,A22) -> 432062 | F22: =SUMIFS($F$7:$F$18,$C$7:$C$18,A22) -> 51387.079
A23: Q3 | E23: =SUMIFS($E$7:$E$18,$C$7:$C$18,A23) -> 412405 | F23: =SUMIFS($F$7:$F$18,$C$7:$C$18,A23) -> 39960.299
A24: Q4 | E24: =SUMIFS($E$7:$E$18,$C$7:$C$18,A24) -> 422547 | F24: =SUMIFS($F$7:$F$18,$C$7:$C$18,A24) -> 42896.894
A26: Comparativo IMP | B26: 2026 (m²) | C26: 2025 PY (m²) | D26: YoY m² | E26: 2026 COP MM | F26: 2025 COP MM | G26: YoY COP | H26: GM 2026 | I26: GM 2025 | J26: Δ GM pp
A27: Mes actual (CM) | B27: 160547 | C27: 132619 | D27: =IF(OR(B27="",C27=""),"",IF(C27=0,"n.a.",B27/C27-1)) -> 0.21058823 | E27: 14484 | F27: 10674 | G27: =IF(OR(E27="",F27=""),"",IF(F27=0,"n.a.",E27/F27-1)) -> 0.3569421 | H27: 0.27 | I27: 0.24 | J27: =IF(OR(H27="",I27=""),"",(H27-I27)*100) -> 3
A28: YTD real | B28: 1400088 | C28: 1120898 | D28: =IF(OR(B28="",C28=""),"",IF(C28=0,"n.a.",B28/C28-1)) -> 0.24907708 | E28: =SUMIFS(F7:F18,A7:A18,"<="&$B$4) -> 128546.18 | F28: 95505 | G28: =IF(OR(E28="",F28=""),"",IF(F28=0,"n.a.",E28/F28-1)) -> 0.34596286 | H28: 0.25 | I28: 0.24 | J28: =IF(OR(H28="",I28=""),"",(H28-I28)*100) -> 1
A29: Forecast resto del año | B29: =SUMIFS(E7:E18,A7:A18,">"&$B$4) -> 422547 | C29: =C30-C28 -> 238943 | D29: =IF(OR(B29="",C29=""),"",IF(C29=0,"n.a.",B29/C29-1)) -> 0.76840083 | E29: =SUMIFS(F7:F18,A7:A18,">"&$B$4) -> 42896.894 | F29: =F30-F28 -> 35630.754 | G29: =IF(OR(E29="",F29=""),"",IF(F29=0,"n.a.",E29/F29-1)) -> 0.20392888 | J29: =IF(OR(H29="",I29=""),"",(H29-I29)*100)
A30: Cierre año (Real + Fcst) | B30: =SUM(E7:E18) -> 1651050 | C30: 1359841 | D30: =IF(OR(B30="",C30=""),"",IF(C30=0,"n.a.",B30/C30-1)) -> 0.2141493 | E30: =SUM(F7:F18) -> 171443.08 | F30: 131135.75 | G30: =IF(OR(E30="",F30=""),"",IF(F30=0,"n.a.",E30/F30-1)) -> 0.30737096 | J30: =IF(OR(H30="",I30=""),"",(H30-I30)*100)
A32: Avance vs cierre año (volumen) | B32: =B28/B30 -> 0.84799855

Sheet 07_Top_Opps
A1: 07 · Top Opportunities (pipeline abierto)
A2: Top 5 por segmento, automático desde la hoja Pipeline · criterio seleccionable
A4: Criterio de orden (cambiar en hoja Pipeline!C4): | E4: =Pipeline!C4 -> USD
A6: Industrial – Top 5 oportunidades abiertas
A7: # | B7: Cliente | C7: Proyecto | D7: País | E7: Portafolio (Type) | F7: Ejecutivo | G7: m² | H7: USD | I7: Estado | J7: % Cierre | K7: Fecha cierre | L7: Valor ponderado
A8: 1 | B8: =IFERROR(IF(INDEX(Pipeline!$B$7:$B$67,MATCH(LARGE(Pipeline!$M$7:$M$67,1),Pipeline!$M$7:$M$67,0))="","—",INDEX(Pipeline!$B$7:$B$67,MATCH(LARGE(Pipeline!$M$7:$M$67,1),Pipeline!$M$7:$M$67,0))),"") -> Construplan | C8: =IFERROR(IF(INDEX(Pipeline!$C$7:$C$67,MATCH(LARGE(Pipeline!$M$7:$M$67,1),Pipeline!$M$7:$M$67,0))="","—",INDEX(Pipeline!$C$7:$C$67,MATCH(LARGE(Pipeline!$M$7:$M$67,1),Pipeline!$M$7:$M$67,0))),"") -> Walmart | D8: =IFERROR(IF(INDEX(Pipeline!$E$7:$E$67,MATCH(LARGE(Pipeline!$M$7:$M$67,1),Pipeline!$M$7:$M$67,0))="","—",INDEX(Pipeline!$E$7:$E$67,MATCH(LARGE(Pipeline!$M$7:$M$67,1),Pipeline!$M$7:$M$67,0))),"") -> Guatemala | E8: =IFERROR(IF(INDEX(Pipeline!$F$7:$F$67,MATCH(LARGE(Pipeline!$M$7:$M$67,1),Pipeline!$M$7:$M$67,0))="","—",INDEX(Pipeline!$F$7:$F$67,MATCH(LARGE(Pipeline!$M$7:$M$67,1),Pipeline!$M$7:$M$67,0))),"") -> King Wall / King Frio / King Roof | F8: =IFERROR(IF(INDEX(Pipeline!$D$7:$D$67,MATCH(LARGE(Pipeline!$M$7:$M$67,1),Pipeline!$M$7:$M$67,0))="","—",INDEX(Pipeline!$D$7:$D$67,MATCH(LARGE(Pipeline!$M$7:$M$67,1),Pipeline!$M$7:$M$67,0))),"") -> Carlos Rodriguez | G8: =IFERROR(IF(INDEX(Pipeline!$G$7:$G$67,MATCH(LARGE(Pipeline!$M$7:$M$67,1),Pipeline!$M$7:$M$67,0))="","—",INDEX(Pipeline!$G$7:$G$67,MATCH(LARGE(Pipeline!$M$7:$M$67,1),Pipeline!$M$7:$M$67,0))),"") -> 100000 | H8: =IFERROR(IF(INDEX(Pipeline!$H$7:$H$67,MATCH(LARGE(Pipeline!$M$7:$M$67,1),Pipeline!$M$7:$M$67,0))="","—",INDEX(Pipeline!$H$7:$H$67,MATCH(LARGE(Pipeline!$M$7:$M$67,1),Pipeline!$M$7:$M$67,0))),"") -> 2787794 | I8: =IFERROR(IF(INDEX(Pipeline!$I$7:$I$67,MATCH(LARGE(Pipeline!$M$7:$M$67,1),Pipeline!$M$7:$M$67,0))="","—",INDEX(Pipeline!$I$7:$I$67,MATCH(LARGE(Pipeline!$M$7:$M$67,1),Pipeline!$M$7:$M$67,0))),"") -> Specification | J8: =IFERROR(IF(INDEX(Pipeline!$J$7:$J$67,MATCH(LARGE(Pipeline!$M$7:$M$67,1),Pipeline!$M$7:$M$67,0))="","—",INDEX(Pipeline!$J$7:$J$67,MATCH(LARGE(Pipeline!$M$7:$M$67,1),Pipeline!$M$7:$M$67,0))),"") -> 0.75 | K8: =IFERROR(IF(INDEX(Pipeline!$K$7:$K$67,MATCH(LARGE(Pipeline!$M$7:$M$67,1),Pipeline!$M$7:$M$67,0))="","—",INDEX(Pipeline!$K$7:$K$67,MATCH(LARGE(Pipeline!$M$7:$M$67,1),Pipeline!$M$7:$M$67,0))),"") -> Noviembre | L8: =IFERROR(IF(INDEX(Pipeline!$L$7:$L$67,MATCH(LARGE(Pipeline!$M$7:$M$67,1),Pipeline!$M$7:$M$67,0))="","—",INDEX(Pipeline!$L$7:$L$67,MATCH(LARGE(Pipeline!$M$7:$M$67,1),Pipeline!$M$7:$M$67,0))),"") -> 2090845.5
A9: 2 | B9: =IFERROR(IF(INDEX(Pipeline!$B$7:$B$67,MATCH(LARGE(Pipeline!$M$7:$M$67,2),Pipeline!$M$7:$M$67,0))="","—",INDEX(Pipeline!$B$7:$B$67,MATCH(LARGE(Pipeline!$M$7:$M$67,2),Pipeline!$M$7:$M$67,0))),"") -> Haceb | C9: =IFERROR(IF(INDEX(Pipeline!$C$7:$C$67,MATCH(LARGE(Pipeline!$M$7:$M$67,2),Pipeline!$M$7:$M$67,0))="","—",INDEX(Pipeline!$C$7:$C$67,MATCH(LARGE(Pipeline!$M$7:$M$67,2),Pipeline!$M$7:$M$67,0))),"") -> Recambio | D9: =IFERROR(IF(INDEX(Pipeline!$E$7:$E$67,MATCH(LARGE(Pipeline!$M$7:$M$67,2),Pipeline!$M$7:$M$67,0))="","—",INDEX(Pipeline!$E$7:$E$67,MATCH(LARGE(Pipeline!$M$7:$M$67,2),Pipeline!$M$7:$M$67,0))),"") -> Colombia | E9: =IFERROR(IF(INDEX(Pipeline!$F$7:$F$67,MATCH(LARGE(Pipeline!$M$7:$M$67,2),Pipeline!$M$7:$M$67,0))="","—",INDEX(Pipeline!$F$7:$F$67,MATCH(LARGE(Pipeline!$M$7:$M$67,2),Pipeline!$M$7:$M$67,0))),"") -> KingWall / KingRoof | F9: =IFERROR(IF(INDEX(Pipeline!$D$7:$D$67,MATCH(LARGE(Pipeline!$M$7:$M$67,2),Pipeline!$M$7:$M$67,0))="","—",INDEX(Pipeline!$D$7:$D$67,MATCH(LARGE(Pipeline!$M$7:$M$67,2),Pipeline!$M$7:$M$67,0))),"") -> Ana Arias | G9: 61000 | H9: 1694102 | I9: =IFERROR(IF(INDEX(Pipeline!$I$7:$I$67,MATCH(LARGE(Pipeline!$M$7:$M$67,2),Pipeline!$M$7:$M$67,0))="","—",INDEX(Pipeline!$I$7:$I$67,MATCH(LARGE(Pipeline!$M$7:$M$67,2),Pipeline!$M$7:$M$67,0))),"") -> Pending | J9: =IFERROR(IF(INDEX(Pipeline!$J$7:$J$67,MATCH(LARGE(Pipeline!$M$7:$M$67,2),Pipeline!$M$7:$M$67,0))="","—",INDEX(Pipeline!$J$7:$J$67,MATCH(LARGE(Pipeline!$M$7:$M$67,2),Pipeline!$M$7:$M$67,0))),"") -> 0.8 | K9: =IFERROR(IF(INDEX(Pipeline!$K$7:$K$67,MATCH(LARGE(Pipeline!$M$7:$M$67,2),Pipeline!$M$7:$M$67,0))="","—",INDEX(Pipeline!$K$7:$K$67,MATCH(LARGE(Pipeline!$M$7:$M$67,2),Pipeline!$M$7:$M$67,0))),"") -> Noviembre | L9: =IFERROR(IF(INDEX(Pipeline!$L$7:$L$67,MATCH(LARGE(Pipeline!$M$7:$M$67,2),Pipeline!$M$7:$M$67,0))="","—",INDEX(Pipeline!$L$7:$L$67,MATCH(LARGE(Pipeline!$M$7:$M$67,2),Pipeline!$M$7:$M$67,0))),"") -> 1360404
A10: 3 | B10: =IFERROR(IF(INDEX(Pipeline!$B$7:$B$67,MATCH(LARGE(Pipeline!$M$7:$M$67,3),Pipeline!$M$7:$M$67,0))="","—",INDEX(Pipeline!$B$7:$B$67,MATCH(LARGE(Pipeline!$M$7:$M$67,3),Pipeline!$M$7:$M$67,0))),"") -> Ménsula / Conconcreto | C10: =IFERROR(IF(INDEX(Pipeline!$C$7:$C$67,MATCH(LARGE(Pipeline!$M$7:$M$67,3),Pipeline!$M$7:$M$67,0))="","—",INDEX(Pipeline!$C$7:$C$67,MATCH(LARGE(Pipeline!$M$7:$M$67,3),Pipeline!$M$7:$M$67,0))),"") -> Viva Suba / Claro | D10: =IFERROR(IF(INDEX(Pipeline!$E$7:$E$67,MATCH(LARGE(Pipeline!$M$7:$M$67,3),Pipeline!$M$7:$M$67,0))="","—",INDEX(Pipeline!$E$7:$E$67,MATCH(LARGE(Pipeline!$M$7:$M$67,3),Pipeline!$M$7:$M$67,0))),"") -> Colombia | E10: =IFERROR(IF(INDEX(Pipeline!$F$7:$F$67,MATCH(LARGE(Pipeline!$M$7:$M$67,3),Pipeline!$M$7:$M$67,0))="","—",INDEX(Pipeline!$F$7:$F$67,MATCH(LARGE(Pipeline!$M$7:$M$67,3),Pipeline!$M$7:$M$67,0))),"") -> KingRoof / Benchmark | F10: =IFERROR(IF(INDEX(Pipeline!$D$7:$D$67,MATCH(LARGE(Pipeline!$M$7:$M$67,3),Pipeline!$M$7:$M$67,0))="","—",INDEX(Pipeline!$D$7:$D$67,MATCH(LARGE(Pipeline!$M$7:$M$67,3),Pipeline!$M$7:$M$67,0))),"") -> Ana Arias | G10: =IFERROR(IF(INDEX(Pipeline!$G$7:$G$67,MATCH(LARGE(Pipeline!$M$7:$M$67,3),Pipeline!$M$7:$M$67,0))="","—",INDEX(Pipeline!$G$7:$G$67,MATCH(LARGE(Pipeline!$M$7:$M$67,3),Pipeline!$M$7:$M$67,0))),"") -> 10289 | H10: =IFERROR(IF(INDEX(Pipeline!$H$7:$H$67,MATCH(LARGE(Pipeline!$M$7:$M$67,3),Pipeline!$M$7:$M$67,0))="","—",INDEX(Pipeline!$H$7:$H$67,MATCH(LARGE(Pipeline!$M$7:$M$67,3),Pipeline!$M$7:$M$67,0))),"") -> 1600000 | I10: =IFERROR(IF(INDEX(Pipeline!$I$7:$I$67,MATCH(LARGE(Pipeline!$M$7:$M$67,3),Pipeline!$M$7:$M$67,0))="","—",INDEX(Pipeline!$I$7:$I$67,MATCH(LARGE(Pipeline!$M$7:$M$67,3),Pipeline!$M$7:$M$67,0))),"") -> Pending | J10: =IFERROR(IF(INDEX(Pipeline!$J$7:$J$67,MATCH(LARGE(Pipeline!$M$7:$M$67,3),Pipeline!$M$7:$M$67,0))="","—",INDEX(Pipeline!$J$7:$J$67,MATCH(LARGE(Pipeline!$M$7:$M$67,3),Pipeline!$M$7:$M$67,0))),"") -> — | K10: =IFERROR(IF(INDEX(Pipeline!$K$7:$K$67,MATCH(LARGE(Pipeline!$M$7:$M$67,3),Pipeline!$M$7:$M$67,0))="","—",INDEX(Pipeline!$K$7:$K$67,MATCH(LARGE(Pipeline!$M$7:$M$67,3),Pipeline!$M$7:$M$67,0))),"") -> — | L10: =IFERROR(IF(INDEX(Pipeline!$L$7:$L$67,MATCH(LARGE(Pipeline!$M$7:$M$67,3),Pipeline!$M$7:$M$67,0))="","—",INDEX(Pipeline!$L$7:$L$67,MATCH(LARGE(Pipeline!$M$7:$M$67,3),Pipeline!$M$7:$M$67,0))),"") -> —
A11: 4 | B11: =IFERROR(IF(INDEX(Pipeline!$B$7:$B$67,MATCH(LARGE(Pipeline!$M$7:$M$67,4),Pipeline!$M$7:$M$67,0))="","—",INDEX(Pipeline!$B$7:$B$67,MATCH(LARGE(Pipeline!$M$7:$M$67,4),Pipeline!$M$7:$M$67,0))),"") -> Imbert Dominguez | C11: =IFERROR(IF(INDEX(Pipeline!$C$7:$C$67,MATCH(LARGE(Pipeline!$M$7:$M$67,4),Pipeline!$M$7:$M$67,0))="","—",INDEX(Pipeline!$C$7:$C$67,MATCH(LARGE(Pipeline!$M$7:$M$67,4),Pipeline!$M$7:$M$67,0))),"") -> INDAL-IDA | D11: =IFERROR(IF(INDEX(Pipeline!$E$7:$E$67,MATCH(LARGE(Pipeline!$M$7:$M$67,4),Pipeline!$M$7:$M$67,0))="","—",INDEX(Pipeline!$E$7:$E$67,MATCH(LARGE(Pipeline!$M$7:$M$67,4),Pipeline!$M$7:$M$67,0))),"") -> Dominicana | E11: =IFERROR(IF(INDEX(Pipeline!$F$7:$F$67,MATCH(LARGE(Pipeline!$M$7:$M$67,4),Pipeline!$M$7:$M$67,0))="","—",INDEX(Pipeline!$F$7:$F$67,MATCH(LARGE(Pipeline!$M$7:$M$67,4),Pipeline!$M$7:$M$67,0))),"") -> KingRoof / KingWall / KingFrigo | F11: =IFERROR(IF(INDEX(Pipeline!$D$7:$D$67,MATCH(LARGE(Pipeline!$M$7:$M$67,4),Pipeline!$M$7:$M$67,0))="","—",INDEX(Pipeline!$D$7:$D$67,MATCH(LARGE(Pipeline!$M$7:$M$67,4),Pipeline!$M$7:$M$67,0))),"") -> Laura Torres | G11: =IFERROR(IF(INDEX(Pipeline!$G$7:$G$67,MATCH(LARGE(Pipeline!$M$7:$M$67,4),Pipeline!$M$7:$M$67,0))="","—",INDEX(Pipeline!$G$7:$G$67,MATCH(LARGE(Pipeline!$M$7:$M$67,4),Pipeline!$M$7:$M$67,0))),"") -> 50000 | H11: =IFERROR(IF(INDEX(Pipeline!$H$7:$H$67,MATCH(LARGE(Pipeline!$M$7:$M$67,4),Pipeline!$M$7:$M$67,0))="","—",INDEX(Pipeline!$H$7:$H$67,MATCH(LARGE(Pipeline!$M$7:$M$67,4),Pipeline!$M$7:$M$67,0))),"") -> 1550000 | I11: =IFERROR(IF(INDEX(Pipeline!$I$7:$I$67,MATCH(LARGE(Pipeline!$M$7:$M$67,4),Pipeline!$M$7:$M$67,0))="","—",INDEX(Pipeline!$I$7:$I$67,MATCH(LARGE(Pipeline!$M$7:$M$67,4),Pipeline!$M$7:$M$67,0))),"") -> Pending | J11: =IFERROR(IF(INDEX(Pipeline!$J$7:$J$67,MATCH(LARGE(Pipeline!$M$7:$M$67,4),Pipeline!$M$7:$M$67,0))="","—",INDEX(Pipeline!$J$7:$J$67,MATCH(LARGE(Pipeline!$M$7:$M$67,4),Pipeline!$M$7:$M$67,0))),"") -> 0.75 | K11: =IFERROR(IF(INDEX(Pipeline!$K$7:$K$67,MATCH(LARGE(Pipeline!$M$7:$M$67,4),Pipeline!$M$7:$M$67,0))="","—",INDEX(Pipeline!$K$7:$K$67,MATCH(LARGE(Pipeline!$M$7:$M$67,4),Pipeline!$M$7:$M$67,0))),"") -> Noviembre | L11: =IFERROR(IF(INDEX(Pipeline!$L$7:$L$67,MATCH(LARGE(Pipeline!$M$7:$M$67,4),Pipeline!$M$7:$M$67,0))="","—",INDEX(Pipeline!$L$7:$L$67,MATCH(LARGE(Pipeline!$M$7:$M$67,4),Pipeline!$M$7:$M$67,0))),"") -> 1162500
A12: 5 | B12: =IFERROR(IF(INDEX(Pipeline!$B$7:$B$67,MATCH(LARGE(Pipeline!$M$7:$M$67,5),Pipeline!$M$7:$M$67,0))="","—",INDEX(Pipeline!$B$7:$B$67,MATCH(LARGE(Pipeline!$M$7:$M$67,5),Pipeline!$M$7:$M$67,0))),"") -> Scadia | C12: =IFERROR(IF(INDEX(Pipeline!$C$7:$C$67,MATCH(LARGE(Pipeline!$M$7:$M$67,5),Pipeline!$M$7:$M$67,0))="","—",INDEX(Pipeline!$C$7:$C$67,MATCH(LARGE(Pipeline!$M$7:$M$67,5),Pipeline!$M$7:$M$67,0))),"") -> Angar Avianca (Bogotá) | D12: =IFERROR(IF(INDEX(Pipeline!$E$7:$E$67,MATCH(LARGE(Pipeline!$M$7:$M$67,5),Pipeline!$M$7:$M$67,0))="","—",INDEX(Pipeline!$E$7:$E$67,MATCH(LARGE(Pipeline!$M$7:$M$67,5),Pipeline!$M$7:$M$67,0))),"") -> Colombia | E12: =IFERROR(IF(INDEX(Pipeline!$F$7:$F$67,MATCH(LARGE(Pipeline!$M$7:$M$67,5),Pipeline!$M$7:$M$67,0))="","—",INDEX(Pipeline!$F$7:$F$67,MATCH(LARGE(Pipeline!$M$7:$M$67,5),Pipeline!$M$7:$M$67,0))),"") -> KingWall / KingRoof o SS | F12: =IFERROR(IF(INDEX(Pipeline!$D$7:$D$67,MATCH(LARGE(Pipeline!$M$7:$M$67,5),Pipeline!$M$7:$M$67,0))="","—",INDEX(Pipeline!$D$7:$D$67,MATCH(LARGE(Pipeline!$M$7:$M$67,5),Pipeline!$M$7:$M$67,0))),"") -> Julio Guerrero | G12: =IFERROR(IF(INDEX(Pipeline!$G$7:$G$67,MATCH(LARGE(Pipeline!$M$7:$M$67,5),Pipeline!$M$7:$M$67,0))="","—",INDEX(Pipeline!$G$7:$G$67,MATCH(LARGE(Pipeline!$M$7:$M$67,5),Pipeline!$M$7:$M$67,0))),"") -> 13000 | H12: =IFERROR(IF(INDEX(Pipeline!$H$7:$H$67,MATCH(LARGE(Pipeline!$M$7:$M$67,5),Pipeline!$M$7:$M$67,0))="","—",INDEX(Pipeline!$H$7:$H$67,MATCH(LARGE(Pipeline!$M$7:$M$67,5),Pipeline!$M$7:$M$67,0))),"") -> 1203774 | I12: =IFERROR(IF(INDEX(Pipeline!$I$7:$I$67,MATCH(LARGE(Pipeline!$M$7:$M$67,5),Pipeline!$M$7:$M$67,0))="","—",INDEX(Pipeline!$I$7:$I$67,MATCH(LARGE(Pipeline!$M$7:$M$67,5),Pipeline!$M$7:$M$67,0))),"") -> Pending | J12: =IFERROR(IF(INDEX(Pipeline!$J$7:$J$67,MATCH(LARGE(Pipeline!$M$7:$M$67,5),Pipeline!$M$7:$M$67,0))="","—",INDEX(Pipeline!$J$7:$J$67,MATCH(LARGE(Pipeline!$M$7:$M$67,5),Pipeline!$M$7:$M$67,0))),"") -> 0.6 | K12: =IFERROR(IF(INDEX(Pipeline!$K$7:$K$67,MATCH(LARGE(Pipeline!$M$7:$M$67,5),Pipeline!$M$7:$M$67,0))="","—",INDEX(Pipeline!$K$7:$K$67,MATCH(LARGE(Pipeline!$M$7:$M$67,5),Pipeline!$M$7:$M$67,0))),"") -> Diciembre | L12: =IFERROR(IF(INDEX(Pipeline!$L$7:$L$67,MATCH(LARGE(Pipeline!$M$7:$M$67,5),Pipeline!$M$7:$M$67,0))="","—",INDEX(Pipeline!$L$7:$L$67,MATCH(LARGE(Pipeline!$M$7:$M$67,5),Pipeline!$M$7:$M$67,0))),"") -> 722264.4
B13: Total Top 5 | G13: =SUM(G8:G12) -> 234289 | H13: =SUM(H8:H12) -> 8835670
A15: Distribución – Top 5 oportunidades abiertas
A16: # | B16: Cliente | C16: Proyecto | D16: País | E16: Portafolio (Type) | F16: Ejecutivo | G16: m² | H16: USD | I16: Estado | J16: % Cierre | K16: Fecha cierre | L16: Valor ponderado
A17: 1 | B17: =IFERROR(IF(INDEX(Pipeline!$B$7:$B$67,MATCH(LARGE(Pipeline!$N$7:$N$67,1),Pipeline!$N$7:$N$67,0))="","—",INDEX(Pipeline!$B$7:$B$67,MATCH(LARGE(Pipeline!$N$7:$N$67,1),Pipeline!$N$7:$N$67,0))),"") -> Galvaceros | C17: =IFERROR(IF(INDEX(Pipeline!$C$7:$C$67,MATCH(LARGE(Pipeline!$N$7:$N$67,1),Pipeline!$N$7:$N$67,0))="","—",INDEX(Pipeline!$C$7:$C$67,MATCH(LARGE(Pipeline!$N$7:$N$67,1),Pipeline!$N$7:$N$67,0))),"") -> Panandina Data Center | D17: =IFERROR(IF(INDEX(Pipeline!$E$7:$E$67,MATCH(LARGE(Pipeline!$N$7:$N$67,1),Pipeline!$N$7:$N$67,0))="","—",INDEX(Pipeline!$E$7:$E$67,MATCH(LARGE(Pipeline!$N$7:$N$67,1),Pipeline!$N$7:$N$67,0))),"") -> Colombia | E17: =IFERROR(IF(INDEX(Pipeline!$F$7:$F$67,MATCH(LARGE(Pipeline!$N$7:$N$67,1),Pipeline!$N$7:$N$67,0))="","—",INDEX(Pipeline!$F$7:$F$67,MATCH(LARGE(Pipeline!$N$7:$N$67,1),Pipeline!$N$7:$N$67,0))),"") -> KingRoof / KingWall LMR | F17: =IFERROR(IF(INDEX(Pipeline!$D$7:$D$67,MATCH(LARGE(Pipeline!$N$7:$N$67,1),Pipeline!$N$7:$N$67,0))="","—",INDEX(Pipeline!$D$7:$D$67,MATCH(LARGE(Pipeline!$N$7:$N$67,1),Pipeline!$N$7:$N$67,0))),"") -> Joana Perez | G17: =IFERROR(IF(INDEX(Pipeline!$G$7:$G$67,MATCH(LARGE(Pipeline!$N$7:$N$67,1),Pipeline!$N$7:$N$67,0))="","—",INDEX(Pipeline!$G$7:$G$67,MATCH(LARGE(Pipeline!$N$7:$N$67,1),Pipeline!$N$7:$N$67,0))),"") -> 4106 | H17: =IFERROR(IF(INDEX(Pipeline!$H$7:$H$67,MATCH(LARGE(Pipeline!$N$7:$N$67,1),Pipeline!$N$7:$N$67,0))="","—",INDEX(Pipeline!$H$7:$H$67,MATCH(LARGE(Pipeline!$N$7:$N$67,1),Pipeline!$N$7:$N$67,0))),"") -> 494712 | I17: Closed | J17: 1 | K17: =IFERROR(IF(INDEX(Pipeline!$K$7:$K$67,MATCH(LARGE(Pipeline!$N$7:$N$67,1),Pipeline!$N$7:$N$67,0))="","—",INDEX(Pipeline!$K$7:$K$67,MATCH(LARGE(Pipeline!$N$7:$N$67,1),Pipeline!$N$7:$N$67,0))),"") -> Diciembre | L17: =IFERROR(IF(INDEX(Pipeline!$L$7:$L$67,MATCH(LARGE(Pipeline!$N$7:$N$67,1),Pipeline!$N$7:$N$67,0))="","—",INDEX(Pipeline!$L$7:$L$67,MATCH(LARGE(Pipeline!$N$7:$N$67,1),Pipeline!$N$7:$N$67,0))),"") -> 420505.2
A18: 2 | B18: =IFERROR(IF(INDEX(Pipeline!$B$7:$B$67,MATCH(LARGE(Pipeline!$N$7:$N$67,2),Pipeline!$N$7:$N$67,0))="","—",INDEX(Pipeline!$B$7:$B$67,MATCH(LARGE(Pipeline!$N$7:$N$67,2),Pipeline!$N$7:$N$67,0))),"") -> Colcover | C18: =IFERROR(IF(INDEX(Pipeline!$C$7:$C$67,MATCH(LARGE(Pipeline!$N$7:$N$67,2),Pipeline!$N$7:$N$67,0))="","—",INDEX(Pipeline!$C$7:$C$67,MATCH(LARGE(Pipeline!$N$7:$N$67,2),Pipeline!$N$7:$N$67,0))),"") -> Proyecto | D18: =IFERROR(IF(INDEX(Pipeline!$E$7:$E$67,MATCH(LARGE(Pipeline!$N$7:$N$67,2),Pipeline!$N$7:$N$67,0))="","—",INDEX(Pipeline!$E$7:$E$67,MATCH(LARGE(Pipeline!$N$7:$N$67,2),Pipeline!$N$7:$N$67,0))),"") -> Colombia | E18: =IFERROR(IF(INDEX(Pipeline!$F$7:$F$67,MATCH(LARGE(Pipeline!$N$7:$N$67,2),Pipeline!$N$7:$N$67,0))="","—",INDEX(Pipeline!$F$7:$F$67,MATCH(LARGE(Pipeline!$N$7:$N$67,2),Pipeline!$N$7:$N$67,0))),"") -> KingRoof | F18: =IFERROR(IF(INDEX(Pipeline!$D$7:$D$67,MATCH(LARGE(Pipeline!$N$7:$N$67,2),Pipeline!$N$7:$N$67,0))="","—",INDEX(Pipeline!$D$7:$D$67,MATCH(LARGE(Pipeline!$N$7:$N$67,2),Pipeline!$N$7:$N$67,0))),"") -> Henry Acosta | G18: =IFERROR(IF(INDEX(Pipeline!$G$7:$G$67,MATCH(LARGE(Pipeline!$N$7:$N$67,2),Pipeline!$N$7:$N$67,0))="","—",INDEX(Pipeline!$G$7:$G$67,MATCH(LARGE(Pipeline!$N$7:$N$67,2),Pipeline!$N$7:$N$67,0))),"") -> 21528 | H18: =IFERROR(IF(INDEX(Pipeline!$H$7:$H$67,MATCH(LARGE(Pipeline!$N$7:$N$67,2),Pipeline!$N$7:$N$67,0))="","—",INDEX(Pipeline!$H$7:$H$67,MATCH(LARGE(Pipeline!$N$7:$N$67,2),Pipeline!$N$7:$N$67,0))),"") -> 411564.71 | I18: =IFERROR(IF(INDEX(Pipeline!$I$7:$I$67,MATCH(LARGE(Pipeline!$N$7:$N$67,2),Pipeline!$N$7:$N$67,0))="","—",INDEX(Pipeline!$I$7:$I$67,MATCH(LARGE(Pipeline!$N$7:$N$67,2),Pipeline!$N$7:$N$67,0))),"") -> Pending | J18: =IFERROR(IF(INDEX(Pipeline!$J$7:$J$67,MATCH(LARGE(Pipeline!$N$7:$N$67,2),Pipeline!$N$7:$N$67,0))="","—",INDEX(Pipeline!$J$7:$J$67,MATCH(LARGE(Pipeline!$N$7:$N$67,2),Pipeline!$N$7:$N$67,0))),"") -> 0.8 | K18: =IFERROR(IF(INDEX(Pipeline!$K$7:$K$67,MATCH(LARGE(Pipeline!$N$7:$N$67,2),Pipeline!$N$7:$N$67,0))="","—",INDEX(Pipeline!$K$7:$K$67,MATCH(LARGE(Pipeline!$N$7:$N$67,2),Pipeline!$N$7:$N$67,0))),"") -> Noviembre | L18: =IFERROR(IF(INDEX(Pipeline!$L$7:$L$67,MATCH(LARGE(Pipeline!$N$7:$N$67,2),Pipeline!$N$7:$N$67,0))="","—",INDEX(Pipeline!$L$7:$L$67,MATCH(LARGE(Pipeline!$N$7:$N$67,2),Pipeline!$N$7:$N$67,0))),"") -> 329251.77
A19: 3 | B19: =IFERROR(IF(INDEX(Pipeline!$B$7:$B$67,MATCH(LARGE(Pipeline!$N$7:$N$67,3),Pipeline!$N$7:$N$67,0))="","—",INDEX(Pipeline!$B$7:$B$67,MATCH(LARGE(Pipeline!$N$7:$N$67,3),Pipeline!$N$7:$N$67,0))),"") -> CIA Caribe Mar | C19: =IFERROR(IF(INDEX(Pipeline!$C$7:$C$67,MATCH(LARGE(Pipeline!$N$7:$N$67,3),Pipeline!$N$7:$N$67,0))="","—",INDEX(Pipeline!$C$7:$C$67,MATCH(LARGE(Pipeline!$N$7:$N$67,3),Pipeline!$N$7:$N$67,0))),"") -> Antártica | D19: =IFERROR(IF(INDEX(Pipeline!$E$7:$E$67,MATCH(LARGE(Pipeline!$N$7:$N$67,3),Pipeline!$N$7:$N$67,0))="","—",INDEX(Pipeline!$E$7:$E$67,MATCH(LARGE(Pipeline!$N$7:$N$67,3),Pipeline!$N$7:$N$67,0))),"") -> Venezuela | E19: =IFERROR(IF(INDEX(Pipeline!$F$7:$F$67,MATCH(LARGE(Pipeline!$N$7:$N$67,3),Pipeline!$N$7:$N$67,0))="","—",INDEX(Pipeline!$F$7:$F$67,MATCH(LARGE(Pipeline!$N$7:$N$67,3),Pipeline!$N$7:$N$67,0))),"") -> KingFrigo | F19: =IFERROR(IF(INDEX(Pipeline!$D$7:$D$67,MATCH(LARGE(Pipeline!$N$7:$N$67,3),Pipeline!$N$7:$N$67,0))="","—",INDEX(Pipeline!$D$7:$D$67,MATCH(LARGE(Pipeline!$N$7:$N$67,3),Pipeline!$N$7:$N$67,0))),"") -> María Yelitza Calderón | G19: =IFERROR(IF(INDEX(Pipeline!$G$7:$G$67,MATCH(LARGE(Pipeline!$N$7:$N$67,3),Pipeline!$N$7:$N$67,0))="","—",INDEX(Pipeline!$G$7:$G$67,MATCH(LARGE(Pipeline!$N$7:$N$67,3),Pipeline!$N$7:$N$67,0))),"") -> 12000 | H19: =IFERROR(IF(INDEX(Pipeline!$H$7:$H$67,MATCH(LARGE(Pipeline!$N$7:$N$67,3),Pipeline!$N$7:$N$67,0))="","—",INDEX(Pipeline!$H$7:$H$67,MATCH(LARGE(Pipeline!$N$7:$N$67,3),Pipeline!$N$7:$N$67,0))),"") -> 360000 | I19: =IFERROR(IF(INDEX(Pipeline!$I$7:$I$67,MATCH(LARGE(Pipeline!$N$7:$N$67,3),Pipeline!$N$7:$N$67,0))="","—",INDEX(Pipeline!$I$7:$I$67,MATCH(LARGE(Pipeline!$N$7:$N$67,3),Pipeline!$N$7:$N$67,0))),"") -> Specification | J19: =IFERROR(IF(INDEX(Pipeline!$J$7:$J$67,MATCH(LARGE(Pipeline!$N$7:$N$67,3),Pipeline!$N$7:$N$67,0))="","—",INDEX(Pipeline!$J$7:$J$67,MATCH(LARGE(Pipeline!$N$7:$N$67,3),Pipeline!$N$7:$N$67,0))),"") -> 0.9 | K19: =IFERROR(IF(INDEX(Pipeline!$K$7:$K$67,MATCH(LARGE(Pipeline!$N$7:$N$67,3),Pipeline!$N$7:$N$67,0))="","—",INDEX(Pipeline!$K$7:$K$67,MATCH(LARGE(Pipeline!$N$7:$N$67,3),Pipeline!$N$7:$N$67,0))),"") -> Noviembre | L19: =IFERROR(IF(INDEX(Pipeline!$L$7:$L$67,MATCH(LARGE(Pipeline!$N$7:$N$67,3),Pipeline!$N$7:$N$67,0))="","—",INDEX(Pipeline!$L$7:$L$67,MATCH(LARGE(Pipeline!$N$7:$N$67,3),Pipeline!$N$7:$N$67,0))),"") -> 324000
A20: 4 | B20: =IFERROR(IF(INDEX(Pipeline!$B$7:$B$67,MATCH(LARGE(Pipeline!$N$7:$N$67,4),Pipeline!$N$7:$N$67,0))="","—",INDEX(Pipeline!$B$7:$B$67,MATCH(LARGE(Pipeline!$N$7:$N$67,4),Pipeline!$N$7:$N$67,0))),"") -> Galvaceros | C20: =IFERROR(IF(INDEX(Pipeline!$C$7:$C$67,MATCH(LARGE(Pipeline!$N$7:$N$67,4),Pipeline!$N$7:$N$67,0))="","—",INDEX(Pipeline!$C$7:$C$67,MATCH(LARGE(Pipeline!$N$7:$N$67,4),Pipeline!$N$7:$N$67,0))),"") -> Colegios Sucre | D20: =IFERROR(IF(INDEX(Pipeline!$E$7:$E$67,MATCH(LARGE(Pipeline!$N$7:$N$67,4),Pipeline!$N$7:$N$67,0))="","—",INDEX(Pipeline!$E$7:$E$67,MATCH(LARGE(Pipeline!$N$7:$N$67,4),Pipeline!$N$7:$N$67,0))),"") -> Colombia | E20: =IFERROR(IF(INDEX(Pipeline!$F$7:$F$67,MATCH(LARGE(Pipeline!$N$7:$N$67,4),Pipeline!$N$7:$N$67,0))="","—",INDEX(Pipeline!$F$7:$F$67,MATCH(LARGE(Pipeline!$N$7:$N$67,4),Pipeline!$N$7:$N$67,0))),"") -> KingRoof | F20: =IFERROR(IF(INDEX(Pipeline!$D$7:$D$67,MATCH(LARGE(Pipeline!$N$7:$N$67,4),Pipeline!$N$7:$N$67,0))="","—",INDEX(Pipeline!$D$7:$D$67,MATCH(LARGE(Pipeline!$N$7:$N$67,4),Pipeline!$N$7:$N$67,0))),"") -> Joana Perez | G20: =IFERROR(IF(INDEX(Pipeline!$G$7:$G$67,MATCH(LARGE(Pipeline!$N$7:$N$67,4),Pipeline!$N$7:$N$67,0))="","—",INDEX(Pipeline!$G$7:$G$67,MATCH(LARGE(Pipeline!$N$7:$N$67,4),Pipeline!$N$7:$N$67,0))),"") -> 14000 | H20: =IFERROR(IF(INDEX(Pipeline!$H$7:$H$67,MATCH(LARGE(Pipeline!$N$7:$N$67,4),Pipeline!$N$7:$N$67,0))="","—",INDEX(Pipeline!$H$7:$H$67,MATCH(LARGE(Pipeline!$N$7:$N$67,4),Pipeline!$N$7:$N$67,0))),"") -> 333529 | I20: =IFERROR(IF(INDEX(Pipeline!$I$7:$I$67,MATCH(LARGE(Pipeline!$N$7:$N$67,4),Pipeline!$N$7:$N$67,0))="","—",INDEX(Pipeline!$I$7:$I$67,MATCH(LARGE(Pipeline!$N$7:$N$67,4),Pipeline!$N$7:$N$67,0))),"") -> Pending | J20: =IFERROR(IF(INDEX(Pipeline!$J$7:$J$67,MATCH(LARGE(Pipeline!$N$7:$N$67,4),Pipeline!$N$7:$N$67,0))="","—",INDEX(Pipeline!$J$7:$J$67,MATCH(LARGE(Pipeline!$N$7:$N$67,4),Pipeline!$N$7:$N$67,0))),"") -> 0.82 | K20: =IFERROR(IF(INDEX(Pipeline!$K$7:$K$67,MATCH(LARGE(Pipeline!$N$7:$N$67,4),Pipeline!$N$7:$N$67,0))="","—",INDEX(Pipeline!$K$7:$K$67,MATCH(LARGE(Pipeline!$N$7:$N$67,4),Pipeline!$N$7:$N$67,0))),"") -> Noviembre | L20: =IFERROR(IF(INDEX(Pipeline!$L$7:$L$67,MATCH(LARGE(Pipeline!$N$7:$N$67,4),Pipeline!$N$7:$N$67,0))="","—",INDEX(Pipeline!$L$7:$L$67,MATCH(LARGE(Pipeline!$N$7:$N$67,4),Pipeline!$N$7:$N$67,0))),"") -> 273493.78
A21: 5 | B21: =IFERROR(IF(INDEX(Pipeline!$B$7:$B$67,MATCH(LARGE(Pipeline!$N$7:$N$67,5),Pipeline!$N$7:$N$67,0))="","—",INDEX(Pipeline!$B$7:$B$67,MATCH(LARGE(Pipeline!$N$7:$N$67,5),Pipeline!$N$7:$N$67,0))),"") -> Espuma SantaFe | C21: =IFERROR(IF(INDEX(Pipeline!$C$7:$C$67,MATCH(LARGE(Pipeline!$N$7:$N$67,5),Pipeline!$N$7:$N$67,0))="","—",INDEX(Pipeline!$C$7:$C$67,MATCH(LARGE(Pipeline!$N$7:$N$67,5),Pipeline!$N$7:$N$67,0))),"") -> Recambio | D21: =IFERROR(IF(INDEX(Pipeline!$E$7:$E$67,MATCH(LARGE(Pipeline!$N$7:$N$67,5),Pipeline!$N$7:$N$67,0))="","—",INDEX(Pipeline!$E$7:$E$67,MATCH(LARGE(Pipeline!$N$7:$N$67,5),Pipeline!$N$7:$N$67,0))),"") -> Colombia | E21: =IFERROR(IF(INDEX(Pipeline!$F$7:$F$67,MATCH(LARGE(Pipeline!$N$7:$N$67,5),Pipeline!$N$7:$N$67,0))="","—",INDEX(Pipeline!$F$7:$F$67,MATCH(LARGE(Pipeline!$N$7:$N$67,5),Pipeline!$N$7:$N$67,0))),"") -> KingRoof / KingWall | F21: =IFERROR(IF(INDEX(Pipeline!$D$7:$D$67,MATCH(LARGE(Pipeline!$N$7:$N$67,5),Pipeline!$N$7:$N$67,0))="","—",INDEX(Pipeline!$D$7:$D$67,MATCH(LARGE(Pipeline!$N$7:$N$67,5),Pipeline!$N$7:$N$67,0))),"") -> Henry Acosta | G21: 2088 | H21: =IFERROR(IF(INDEX(Pipeline!$H$7:$H$67,MATCH(LARGE(Pipeline!$N$7:$N$67,5),Pipeline!$N$7:$N$67,0))="","—",INDEX(Pipeline!$H$7:$H$67,MATCH(LARGE(Pipeline!$N$7:$N$67,5),Pipeline!$N$7:$N$67,0))),"") -> 152072 | I21: closed | J21: 1 | K21: Octuber | L21: =IFERROR(IF(INDEX(Pipeline!$L$7:$L$67,MATCH(LARGE(Pipeline!$N$7:$N$67,5),Pipeline!$N$7:$N$67,0))="","—",INDEX(Pipeline!$L$7:$L$67,MATCH(LARGE(Pipeline!$N$7:$N$67,5),Pipeline!$N$7:$N$67,0))),"") -> 121657.6
B22: Total Top 5 | G22: =SUM(G17:G21) -> 53722 | H22: =SUM(H17:H21) -> 1751877.7
B24: Top 5 Industrial / pipeline Industrial USD | H24: =H13/SUMIFS(Pipeline!H7:H67,Pipeline!A7:A67,"Industrial") -> 0.41998588
B25: Top 5 Distribución / pipeline Distribución USD | H25: =H22/SUMIFS(Pipeline!H7:H67,Pipeline!A7:A67,"Distribución") -> 0.71228824

Sheet 08_Key_Projects
A1: 08 · Key Projects – Industrial y Distribución
A2: Top 5 por m² (todos los estados) + resumen de pipeline
A6: Industrial – Top 5 proyectos por m² (todos los estados)
A7: # | B7: Cliente | C7: Proyecto | D7: País | E7: Portafolio (Type) | F7: Ejecutivo | G7: m² | H7: USD | I7: Estado | J7: % Cierre | K7: Fecha cierre | L7: Valor ponderado
A8: 1 | B8: =IFERROR(IF(INDEX(Pipeline!$B$7:$B$67,MATCH(LARGE(Pipeline!$O$7:$O$67,1),Pipeline!$O$7:$O$67,0))="","—",INDEX(Pipeline!$B$7:$B$67,MATCH(LARGE(Pipeline!$O$7:$O$67,1),Pipeline!$O$7:$O$67,0))),"") -> Construplan | C8: =IFERROR(IF(INDEX(Pipeline!$C$7:$C$67,MATCH(LARGE(Pipeline!$O$7:$O$67,1),Pipeline!$O$7:$O$67,0))="","—",INDEX(Pipeline!$C$7:$C$67,MATCH(LARGE(Pipeline!$O$7:$O$67,1),Pipeline!$O$7:$O$67,0))),"") -> Walmart | D8: =IFERROR(IF(INDEX(Pipeline!$E$7:$E$67,MATCH(LARGE(Pipeline!$O$7:$O$67,1),Pipeline!$O$7:$O$67,0))="","—",INDEX(Pipeline!$E$7:$E$67,MATCH(LARGE(Pipeline!$O$7:$O$67,1),Pipeline!$O$7:$O$67,0))),"") -> Guatemala | E8: =IFERROR(IF(INDEX(Pipeline!$F$7:$F$67,MATCH(LARGE(Pipeline!$O$7:$O$67,1),Pipeline!$O$7:$O$67,0))="","—",INDEX(Pipeline!$F$7:$F$67,MATCH(LARGE(Pipeline!$O$7:$O$67,1),Pipeline!$O$7:$O$67,0))),"") -> King Wall / King Frio / King Roof | F8: =IFERROR(IF(INDEX(Pipeline!$D$7:$D$67,MATCH(LARGE(Pipeline!$O$7:$O$67,1),Pipeline!$O$7:$O$67,0))="","—",INDEX(Pipeline!$D$7:$D$67,MATCH(LARGE(Pipeline!$O$7:$O$67,1),Pipeline!$O$7:$O$67,0))),"") -> Carlos Rodriguez | G8: =IFERROR(IF(INDEX(Pipeline!$G$7:$G$67,MATCH(LARGE(Pipeline!$O$7:$O$67,1),Pipeline!$O$7:$O$67,0))="","—",INDEX(Pipeline!$G$7:$G$67,MATCH(LARGE(Pipeline!$O$7:$O$67,1),Pipeline!$O$7:$O$67,0))),"") -> 100000 | H8: =IFERROR(IF(INDEX(Pipeline!$H$7:$H$67,MATCH(LARGE(Pipeline!$O$7:$O$67,1),Pipeline!$O$7:$O$67,0))="","—",INDEX(Pipeline!$H$7:$H$67,MATCH(LARGE(Pipeline!$O$7:$O$67,1),Pipeline!$O$7:$O$67,0))),"") -> 2787794 | I8: =IFERROR(IF(INDEX(Pipeline!$I$7:$I$67,MATCH(LARGE(Pipeline!$O$7:$O$67,1),Pipeline!$O$7:$O$67,0))="","—",INDEX(Pipeline!$I$7:$I$67,MATCH(LARGE(Pipeline!$O$7:$O$67,1),Pipeline!$O$7:$O$67,0))),"") -> Specification | J8: =IFERROR(IF(INDEX(Pipeline!$J$7:$J$67,MATCH(LARGE(Pipeline!$O$7:$O$67,1),Pipeline!$O$7:$O$67,0))="","—",INDEX(Pipeline!$J$7:$J$67,MATCH(LARGE(Pipeline!$O$7:$O$67,1),Pipeline!$O$7:$O$67,0))),"") -> 0.75 | K8: =IFERROR(IF(INDEX(Pipeline!$K$7:$K$67,MATCH(LARGE(Pipeline!$O$7:$O$67,1),Pipeline!$O$7:$O$67,0))="","—",INDEX(Pipeline!$K$7:$K$67,MATCH(LARGE(Pipeline!$O$7:$O$67,1),Pipeline!$O$7:$O$67,0))),"") -> Noviembre | L8: =IFERROR(IF(INDEX(Pipeline!$L$7:$L$67,MATCH(LARGE(Pipeline!$O$7:$O$67,1),Pipeline!$O$7:$O$67,0))="","—",INDEX(Pipeline!$L$7:$L$67,MATCH(LARGE(Pipeline!$O$7:$O$67,1),Pipeline!$O$7:$O$67,0))),"") -> 2090845.5
A9: 2 | B9: =IFERROR(IF(INDEX(Pipeline!$B$7:$B$67,MATCH(LARGE(Pipeline!$O$7:$O$67,2),Pipeline!$O$7:$O$67,0))="","—",INDEX(Pipeline!$B$7:$B$67,MATCH(LARGE(Pipeline!$O$7:$O$67,2),Pipeline!$O$7:$O$67,0))),"") -> Haceb | C9: =IFERROR(IF(INDEX(Pipeline!$C$7:$C$67,MATCH(LARGE(Pipeline!$O$7:$O$67,2),Pipeline!$O$7:$O$67,0))="","—",INDEX(Pipeline!$C$7:$C$67,MATCH(LARGE(Pipeline!$O$7:$O$67,2),Pipeline!$O$7:$O$67,0))),"") -> Recambio | D9: =IFERROR(IF(INDEX(Pipeline!$E$7:$E$67,MATCH(LARGE(Pipeline!$O$7:$O$67,2),Pipeline!$O$7:$O$67,0))="","—",INDEX(Pipeline!$E$7:$E$67,MATCH(LARGE(Pipeline!$O$7:$O$67,2),Pipeline!$O$7:$O$67,0))),"") -> Colombia | E9: =IFERROR(IF(INDEX(Pipeline!$F$7:$F$67,MATCH(LARGE(Pipeline!$O$7:$O$67,2),Pipeline!$O$7:$O$67,0))="","—",INDEX(Pipeline!$F$7:$F$67,MATCH(LARGE(Pipeline!$O$7:$O$67,2),Pipeline!$O$7:$O$67,0))),"") -> KingWall / KingRoof | F9: =IFERROR(IF(INDEX(Pipeline!$D$7:$D$67,MATCH(LARGE(Pipeline!$O$7:$O$67,2),Pipeline!$O$7:$O$67,0))="","—",INDEX(Pipeline!$D$7:$D$67,MATCH(LARGE(Pipeline!$O$7:$O$67,2),Pipeline!$O$7:$O$67,0))),"") -> Ana Arias | G9: =IFERROR(IF(INDEX(Pipeline!$G$7:$G$67,MATCH(LARGE(Pipeline!$O$7:$O$67,2),Pipeline!$O$7:$O$67,0))="","—",INDEX(Pipeline!$G$7:$G$67,MATCH(LARGE(Pipeline!$O$7:$O$67,2),Pipeline!$O$7:$O$67,0))),"") -> 61000 | H9: =IFERROR(IF(INDEX(Pipeline!$H$7:$H$67,MATCH(LARGE(Pipeline!$O$7:$O$67,2),Pipeline!$O$7:$O$67,0))="","—",INDEX(Pipeline!$H$7:$H$67,MATCH(LARGE(Pipeline!$O$7:$O$67,2),Pipeline!$O$7:$O$67,0))),"") -> 1700505 | I9: =IFERROR(IF(INDEX(Pipeline!$I$7:$I$67,MATCH(LARGE(Pipeline!$O$7:$O$67,2),Pipeline!$O$7:$O$67,0))="","—",INDEX(Pipeline!$I$7:$I$67,MATCH(LARGE(Pipeline!$O$7:$O$67,2),Pipeline!$O$7:$O$67,0))),"") -> Pending | J9: =IFERROR(IF(INDEX(Pipeline!$J$7:$J$67,MATCH(LARGE(Pipeline!$O$7:$O$67,2),Pipeline!$O$7:$O$67,0))="","—",INDEX(Pipeline!$J$7:$J$67,MATCH(LARGE(Pipeline!$O$7:$O$67,2),Pipeline!$O$7:$O$67,0))),"") -> 0.8 | K9: =IFERROR(IF(INDEX(Pipeline!$K$7:$K$67,MATCH(LARGE(Pipeline!$O$7:$O$67,2),Pipeline!$O$7:$O$67,0))="","—",INDEX(Pipeline!$K$7:$K$67,MATCH(LARGE(Pipeline!$O$7:$O$67,2),Pipeline!$O$7:$O$67,0))),"") -> Noviembre | L9: =IFERROR(IF(INDEX(Pipeline!$L$7:$L$67,MATCH(LARGE(Pipeline!$O$7:$O$67,2),Pipeline!$O$7:$O$67,0))="","—",INDEX(Pipeline!$L$7:$L$67,MATCH(LARGE(Pipeline!$O$7:$O$67,2),Pipeline!$O$7:$O$67,0))),"") -> 1360404
A10: 3 | B10: =IFERROR(IF(INDEX(Pipeline!$B$7:$B$67,MATCH(LARGE(Pipeline!$O$7:$O$67,3),Pipeline!$O$7:$O$67,0))="","—",INDEX(Pipeline!$B$7:$B$67,MATCH(LARGE(Pipeline!$O$7:$O$67,3),Pipeline!$O$7:$O$67,0))),"") -> Conmetal | C10: =IFERROR(IF(INDEX(Pipeline!$C$7:$C$67,MATCH(LARGE(Pipeline!$O$7:$O$67,3),Pipeline!$O$7:$O$67,0))="","—",INDEX(Pipeline!$C$7:$C$67,MATCH(LARGE(Pipeline!$O$7:$O$67,3),Pipeline!$O$7:$O$67,0))),"") -> Bodegas AMT | D10: =IFERROR(IF(INDEX(Pipeline!$E$7:$E$67,MATCH(LARGE(Pipeline!$O$7:$O$67,3),Pipeline!$O$7:$O$67,0))="","—",INDEX(Pipeline!$E$7:$E$67,MATCH(LARGE(Pipeline!$O$7:$O$67,3),Pipeline!$O$7:$O$67,0))),"") -> Guatemala | E10: =IFERROR(IF(INDEX(Pipeline!$F$7:$F$67,MATCH(LARGE(Pipeline!$O$7:$O$67,3),Pipeline!$O$7:$O$67,0))="","—",INDEX(Pipeline!$F$7:$F$67,MATCH(LARGE(Pipeline!$O$7:$O$67,3),Pipeline!$O$7:$O$67,0))),"") -> KingRoof / KingWall | F10: =IFERROR(IF(INDEX(Pipeline!$D$7:$D$67,MATCH(LARGE(Pipeline!$O$7:$O$67,3),Pipeline!$O$7:$O$67,0))="","—",INDEX(Pipeline!$D$7:$D$67,MATCH(LARGE(Pipeline!$O$7:$O$67,3),Pipeline!$O$7:$O$67,0))),"") -> Carlos Rodriguez | G10: =IFERROR(IF(INDEX(Pipeline!$G$7:$G$67,MATCH(LARGE(Pipeline!$O$7:$O$67,3),Pipeline!$O$7:$O$67,0))="","—",INDEX(Pipeline!$G$7:$G$67,MATCH(LARGE(Pipeline!$O$7:$O$67,3),Pipeline!$O$7:$O$67,0))),"") -> 50000 | H10: =IFERROR(IF(INDEX(Pipeline!$H$7:$H$67,MATCH(LARGE(Pipeline!$O$7:$O$67,3),Pipeline!$O$7:$O$67,0))="","—",INDEX(Pipeline!$H$7:$H$67,MATCH(LARGE(Pipeline!$O$7:$O$67,3),Pipeline!$O$7:$O$67,0))),"") -> 1200000 | I10: =IFERROR(IF(INDEX(Pipeline!$I$7:$I$67,MATCH(LARGE(Pipeline!$O$7:$O$67,3),Pipeline!$O$7:$O$67,0))="","—",INDEX(Pipeline!$I$7:$I$67,MATCH(LARGE(Pipeline!$O$7:$O$67,3),Pipeline!$O$7:$O$67,0))),"") -> Pending | J10: =IFERROR(IF(INDEX(Pipeline!$J$7:$J$67,MATCH(LARGE(Pipeline!$O$7:$O$67,3),Pipeline!$O$7:$O$67,0))="","—",INDEX(Pipeline!$J$7:$J$67,MATCH(LARGE(Pipeline!$O$7:$O$67,3),Pipeline!$O$7:$O$67,0))),"") -> 0.6 | K10: =IFERROR(IF(INDEX(Pipeline!$K$7:$K$67,MATCH(LARGE(Pipeline!$O$7:$O$67,3),Pipeline!$O$7:$O$67,0))="","—",INDEX(Pipeline!$K$7:$K$67,MATCH(LARGE(Pipeline!$O$7:$O$67,3),Pipeline!$O$7:$O$67,0))),"") -> Diciembre | L10: =IFERROR(IF(INDEX(Pipeline!$L$7:$L$67,MATCH(LARGE(Pipeline!$O$7:$O$67,3),Pipeline!$O$7:$O$67,0))="","—",INDEX(Pipeline!$L$7:$L$67,MATCH(LARGE(Pipeline!$O$7:$O$67,3),Pipeline!$O$7:$O$67,0))),"") -> 720000
A11: 4 | B11: =IFERROR(IF(INDEX(Pipeline!$B$7:$B$67,MATCH(LARGE(Pipeline!$O$7:$O$67,4),Pipeline!$O$7:$O$67,0))="","—",INDEX(Pipeline!$B$7:$B$67,MATCH(LARGE(Pipeline!$O$7:$O$67,4),Pipeline!$O$7:$O$67,0))),"") -> Imbert Dominguez | C11: =IFERROR(IF(INDEX(Pipeline!$C$7:$C$67,MATCH(LARGE(Pipeline!$O$7:$O$67,4),Pipeline!$O$7:$O$67,0))="","—",INDEX(Pipeline!$C$7:$C$67,MATCH(LARGE(Pipeline!$O$7:$O$67,4),Pipeline!$O$7:$O$67,0))),"") -> INDAL-IDA | D11: =IFERROR(IF(INDEX(Pipeline!$E$7:$E$67,MATCH(LARGE(Pipeline!$O$7:$O$67,4),Pipeline!$O$7:$O$67,0))="","—",INDEX(Pipeline!$E$7:$E$67,MATCH(LARGE(Pipeline!$O$7:$O$67,4),Pipeline!$O$7:$O$67,0))),"") -> Dominicana | E11: =IFERROR(IF(INDEX(Pipeline!$F$7:$F$67,MATCH(LARGE(Pipeline!$O$7:$O$67,4),Pipeline!$O$7:$O$67,0))="","—",INDEX(Pipeline!$F$7:$F$67,MATCH(LARGE(Pipeline!$O$7:$O$67,4),Pipeline!$O$7:$O$67,0))),"") -> KingRoof / KingWall / KingFrigo | F11: =IFERROR(IF(INDEX(Pipeline!$D$7:$D$67,MATCH(LARGE(Pipeline!$O$7:$O$67,4),Pipeline!$O$7:$O$67,0))="","—",INDEX(Pipeline!$D$7:$D$67,MATCH(LARGE(Pipeline!$O$7:$O$67,4),Pipeline!$O$7:$O$67,0))),"") -> Laura Torres | G11: =IFERROR(IF(INDEX(Pipeline!$G$7:$G$67,MATCH(LARGE(Pipeline!$O$7:$O$67,4),Pipeline!$O$7:$O$67,0))="","—",INDEX(Pipeline!$G$7:$G$67,MATCH(LARGE(Pipeline!$O$7:$O$67,4),Pipeline!$O$7:$O$67,0))),"") -> 50000 | H11: =IFERROR(IF(INDEX(Pipeline!$H$7:$H$67,MATCH(LARGE(Pipeline!$O$7:$O$67,4),Pipeline!$O$7:$O$67,0))="","—",INDEX(Pipeline!$H$7:$H$67,MATCH(LARGE(Pipeline!$O$7:$O$67,4),Pipeline!$O$7:$O$67,0))),"") -> 1550000 | I11: =IFERROR(IF(INDEX(Pipeline!$I$7:$I$67,MATCH(LARGE(Pipeline!$O$7:$O$67,4),Pipeline!$O$7:$O$67,0))="","—",INDEX(Pipeline!$I$7:$I$67,MATCH(LARGE(Pipeline!$O$7:$O$67,4),Pipeline!$O$7:$O$67,0))),"") -> Pending | J11: =IFERROR(IF(INDEX(Pipeline!$J$7:$J$67,MATCH(LARGE(Pipeline!$O$7:$O$67,4),Pipeline!$O$7:$O$67,0))="","—",INDEX(Pipeline!$J$7:$J$67,MATCH(LARGE(Pipeline!$O$7:$O$67,4),Pipeline!$O$7:$O$67,0))),"") -> 0.75 | K11: =IFERROR(IF(INDEX(Pipeline!$K$7:$K$67,MATCH(LARGE(Pipeline!$O$7:$O$67,4),Pipeline!$O$7:$O$67,0))="","—",INDEX(Pipeline!$K$7:$K$67,MATCH(LARGE(Pipeline!$O$7:$O$67,4),Pipeline!$O$7:$O$67,0))),"") -> Noviembre | L11: =IFERROR(IF(INDEX(Pipeline!$L$7:$L$67,MATCH(LARGE(Pipeline!$O$7:$O$67,4),Pipeline!$O$7:$O$67,0))="","—",INDEX(Pipeline!$L$7:$L$67,MATCH(LARGE(Pipeline!$O$7:$O$67,4),Pipeline!$O$7:$O$67,0))),"") -> 1162500
A12: 5 | B12: =IFERROR(IF(INDEX(Pipeline!$B$7:$B$67,MATCH(LARGE(Pipeline!$O$7:$O$67,5),Pipeline!$O$7:$O$67,0))="","—",INDEX(Pipeline!$B$7:$B$67,MATCH(LARGE(Pipeline!$O$7:$O$67,5),Pipeline!$O$7:$O$67,0))),"") -> Magnetron | C12: =IFERROR(IF(INDEX(Pipeline!$C$7:$C$67,MATCH(LARGE(Pipeline!$O$7:$O$67,5),Pipeline!$O$7:$O$67,0))="","—",INDEX(Pipeline!$C$7:$C$67,MATCH(LARGE(Pipeline!$O$7:$O$67,5),Pipeline!$O$7:$O$67,0))),"") -> — | D12: =IFERROR(IF(INDEX(Pipeline!$E$7:$E$67,MATCH(LARGE(Pipeline!$O$7:$O$67,5),Pipeline!$O$7:$O$67,0))="","—",INDEX(Pipeline!$E$7:$E$67,MATCH(LARGE(Pipeline!$O$7:$O$67,5),Pipeline!$O$7:$O$67,0))),"") -> Colombia | E12: =IFERROR(IF(INDEX(Pipeline!$F$7:$F$67,MATCH(LARGE(Pipeline!$O$7:$O$67,5),Pipeline!$O$7:$O$67,0))="","—",INDEX(Pipeline!$F$7:$F$67,MATCH(LARGE(Pipeline!$O$7:$O$67,5),Pipeline!$O$7:$O$67,0))),"") -> KingRoof, KingMetalRoof, KingWall | F12: =IFERROR(IF(INDEX(Pipeline!$D$7:$D$67,MATCH(LARGE(Pipeline!$O$7:$O$67,5),Pipeline!$O$7:$O$67,0))="","—",INDEX(Pipeline!$D$7:$D$67,MATCH(LARGE(Pipeline!$O$7:$O$67,5),Pipeline!$O$7:$O$67,0))),"") -> Julio Guerrero | G12: =IFERROR(IF(INDEX(Pipeline!$G$7:$G$67,MATCH(LARGE(Pipeline!$O$7:$O$67,5),Pipeline!$O$7:$O$67,0))="","—",INDEX(Pipeline!$G$7:$G$67,MATCH(LARGE(Pipeline!$O$7:$O$67,5),Pipeline!$O$7:$O$67,0))),"") -> 45000 | H12: =IFERROR(IF(INDEX(Pipeline!$H$7:$H$67,MATCH(LARGE(Pipeline!$O$7:$O$67,5),Pipeline!$O$7:$O$67,0))="","—",INDEX(Pipeline!$H$7:$H$67,MATCH(LARGE(Pipeline!$O$7:$O$67,5),Pipeline!$O$7:$O$67,0))),"") -> 892114 | I12: =IFERROR(IF(INDEX(Pipeline!$I$7:$I$67,MATCH(LARGE(Pipeline!$O$7:$O$67,5),Pipeline!$O$7:$O$67,0))="","—",INDEX(Pipeline!$I$7:$I$67,MATCH(LARGE(Pipeline!$O$7:$O$67,5),Pipeline!$O$7:$O$67,0))),"") -> Pending | J12: =IFERROR(IF(INDEX(Pipeline!$J$7:$J$67,MATCH(LARGE(Pipeline!$O$7:$O$67,5),Pipeline!$O$7:$O$67,0))="","—",INDEX(Pipeline!$J$7:$J$67,MATCH(LARGE(Pipeline!$O$7:$O$67,5),Pipeline!$O$7:$O$67,0))),"") -> — | K12: =IFERROR(IF(INDEX(Pipeline!$K$7:$K$67,MATCH(LARGE(Pipeline!$O$7:$O$67,5),Pipeline!$O$7:$O$67,0))="","—",INDEX(Pipeline!$K$7:$K$67,MATCH(LARGE(Pipeline!$O$7:$O$67,5),Pipeline!$O$7:$O$67,0))),"") -> — | L12: =IFERROR(IF(INDEX(Pipeline!$L$7:$L$67,MATCH(LARGE(Pipeline!$O$7:$O$67,5),Pipeline!$O$7:$O$67,0))="","—",INDEX(Pipeline!$L$7:$L$67,MATCH(LARGE(Pipeline!$O$7:$O$67,5),Pipeline!$O$7:$O$67,0))),"") -> —
B13: Total Top 5 | G13: =SUM(G8:G12) -> 306000 | H13: =SUM(H8:H12) -> 8130413
A15: Distribución – Top 5 proyectos por m² (todos los estados)
A16: # | B16: Cliente | C16: Proyecto | D16: País | E16: Portafolio (Type) | F16: Ejecutivo | G16: m² | H16: USD | I16: Estado | J16: % Cierre | K16: Fecha cierre | L16: Valor ponderado
A17: 1 | B17: =IFERROR(IF(INDEX(Pipeline!$B$7:$B$67,MATCH(LARGE(Pipeline!$P$7:$P$67,1),Pipeline!$P$7:$P$67,0))="","—",INDEX(Pipeline!$B$7:$B$67,MATCH(LARGE(Pipeline!$P$7:$P$67,1),Pipeline!$P$7:$P$67,0))),"") -> Colcover | C17: =IFERROR(IF(INDEX(Pipeline!$C$7:$C$67,MATCH(LARGE(Pipeline!$P$7:$P$67,1),Pipeline!$P$7:$P$67,0))="","—",INDEX(Pipeline!$C$7:$C$67,MATCH(LARGE(Pipeline!$P$7:$P$67,1),Pipeline!$P$7:$P$67,0))),"") -> Proyecto | D17: =IFERROR(IF(INDEX(Pipeline!$E$7:$E$67,MATCH(LARGE(Pipeline!$P$7:$P$67,1),Pipeline!$P$7:$P$67,0))="","—",INDEX(Pipeline!$E$7:$E$67,MATCH(LARGE(Pipeline!$P$7:$P$67,1),Pipeline!$P$7:$P$67,0))),"") -> Colombia | E17: =IFERROR(IF(INDEX(Pipeline!$F$7:$F$67,MATCH(LARGE(Pipeline!$P$7:$P$67,1),Pipeline!$P$7:$P$67,0))="","—",INDEX(Pipeline!$F$7:$F$67,MATCH(LARGE(Pipeline!$P$7:$P$67,1),Pipeline!$P$7:$P$67,0))),"") -> KingRoof | F17: =IFERROR(IF(INDEX(Pipeline!$D$7:$D$67,MATCH(LARGE(Pipeline!$P$7:$P$67,1),Pipeline!$P$7:$P$67,0))="","—",INDEX(Pipeline!$D$7:$D$67,MATCH(LARGE(Pipeline!$P$7:$P$67,1),Pipeline!$P$7:$P$67,0))),"") -> Henry Acosta | G17: =IFERROR(IF(INDEX(Pipeline!$G$7:$G$67,MATCH(LARGE(Pipeline!$P$7:$P$67,1),Pipeline!$P$7:$P$67,0))="","—",INDEX(Pipeline!$G$7:$G$67,MATCH(LARGE(Pipeline!$P$7:$P$67,1),Pipeline!$P$7:$P$67,0))),"") -> 21528 | H17: =IFERROR(IF(INDEX(Pipeline!$H$7:$H$67,MATCH(LARGE(Pipeline!$P$7:$P$67,1),Pipeline!$P$7:$P$67,0))="","—",INDEX(Pipeline!$H$7:$H$67,MATCH(LARGE(Pipeline!$P$7:$P$67,1),Pipeline!$P$7:$P$67,0))),"") -> 411564.71 | I17: =IFERROR(IF(INDEX(Pipeline!$I$7:$I$67,MATCH(LARGE(Pipeline!$P$7:$P$67,1),Pipeline!$P$7:$P$67,0))="","—",INDEX(Pipeline!$I$7:$I$67,MATCH(LARGE(Pipeline!$P$7:$P$67,1),Pipeline!$P$7:$P$67,0))),"") -> Pending | J17: =IFERROR(IF(INDEX(Pipeline!$J$7:$J$67,MATCH(LARGE(Pipeline!$P$7:$P$67,1),Pipeline!$P$7:$P$67,0))="","—",INDEX(Pipeline!$J$7:$J$67,MATCH(LARGE(Pipeline!$P$7:$P$67,1),Pipeline!$P$7:$P$67,0))),"") -> 0.8 | K17: =IFERROR(IF(INDEX(Pipeline!$K$7:$K$67,MATCH(LARGE(Pipeline!$P$7:$P$67,1),Pipeline!$P$7:$P$67,0))="","—",INDEX(Pipeline!$K$7:$K$67,MATCH(LARGE(Pipeline!$P$7:$P$67,1),Pipeline!$P$7:$P$67,0))),"") -> Noviembre | L17: =IFERROR(IF(INDEX(Pipeline!$L$7:$L$67,MATCH(LARGE(Pipeline!$P$7:$P$67,1),Pipeline!$P$7:$P$67,0))="","—",INDEX(Pipeline!$L$7:$L$67,MATCH(LARGE(Pipeline!$P$7:$P$67,1),Pipeline!$P$7:$P$67,0))),"") -> 329251.77
A18: 2 | B18: =IFERROR(IF(INDEX(Pipeline!$B$7:$B$67,MATCH(LARGE(Pipeline!$P$7:$P$67,2),Pipeline!$P$7:$P$67,0))="","—",INDEX(Pipeline!$B$7:$B$67,MATCH(LARGE(Pipeline!$P$7:$P$67,2),Pipeline!$P$7:$P$67,0))),"") -> Galvaceros | C18: =IFERROR(IF(INDEX(Pipeline!$C$7:$C$67,MATCH(LARGE(Pipeline!$P$7:$P$67,2),Pipeline!$P$7:$P$67,0))="","—",INDEX(Pipeline!$C$7:$C$67,MATCH(LARGE(Pipeline!$P$7:$P$67,2),Pipeline!$P$7:$P$67,0))),"") -> Colegios Sucre | D18: =IFERROR(IF(INDEX(Pipeline!$E$7:$E$67,MATCH(LARGE(Pipeline!$P$7:$P$67,2),Pipeline!$P$7:$P$67,0))="","—",INDEX(Pipeline!$E$7:$E$67,MATCH(LARGE(Pipeline!$P$7:$P$67,2),Pipeline!$P$7:$P$67,0))),"") -> Colombia | E18: =IFERROR(IF(INDEX(Pipeline!$F$7:$F$67,MATCH(LARGE(Pipeline!$P$7:$P$67,2),Pipeline!$P$7:$P$67,0))="","—",INDEX(Pipeline!$F$7:$F$67,MATCH(LARGE(Pipeline!$P$7:$P$67,2),Pipeline!$P$7:$P$67,0))),"") -> KingRoof | F18: =IFERROR(IF(INDEX(Pipeline!$D$7:$D$67,MATCH(LARGE(Pipeline!$P$7:$P$67,2),Pipeline!$P$7:$P$67,0))="","—",INDEX(Pipeline!$D$7:$D$67,MATCH(LARGE(Pipeline!$P$7:$P$67,2),Pipeline!$P$7:$P$67,0))),"") -> Joana Perez | G18: =IFERROR(IF(INDEX(Pipeline!$G$7:$G$67,MATCH(LARGE(Pipeline!$P$7:$P$67,2),Pipeline!$P$7:$P$67,0))="","—",INDEX(Pipeline!$G$7:$G$67,MATCH(LARGE(Pipeline!$P$7:$P$67,2),Pipeline!$P$7:$P$67,0))),"") -> 14000 | H18: =IFERROR(IF(INDEX(Pipeline!$H$7:$H$67,MATCH(LARGE(Pipeline!$P$7:$P$67,2),Pipeline!$P$7:$P$67,0))="","—",INDEX(Pipeline!$H$7:$H$67,MATCH(LARGE(Pipeline!$P$7:$P$67,2),Pipeline!$P$7:$P$67,0))),"") -> 333529 | I18: =IFERROR(IF(INDEX(Pipeline!$I$7:$I$67,MATCH(LARGE(Pipeline!$P$7:$P$67,2),Pipeline!$P$7:$P$67,0))="","—",INDEX(Pipeline!$I$7:$I$67,MATCH(LARGE(Pipeline!$P$7:$P$67,2),Pipeline!$P$7:$P$67,0))),"") -> Pending | J18: =IFERROR(IF(INDEX(Pipeline!$J$7:$J$67,MATCH(LARGE(Pipeline!$P$7:$P$67,2),Pipeline!$P$7:$P$67,0))="","—",INDEX(Pipeline!$J$7:$J$67,MATCH(LARGE(Pipeline!$P$7:$P$67,2),Pipeline!$P$7:$P$67,0))),"") -> 0.82 | K18: =IFERROR(IF(INDEX(Pipeline!$K$7:$K$67,MATCH(LARGE(Pipeline!$P$7:$P$67,2),Pipeline!$P$7:$P$67,0))="","—",INDEX(Pipeline!$K$7:$K$67,MATCH(LARGE(Pipeline!$P$7:$P$67,2),Pipeline!$P$7:$P$67,0))),"") -> Noviembre | L18: =IFERROR(IF(INDEX(Pipeline!$L$7:$L$67,MATCH(LARGE(Pipeline!$P$7:$P$67,2),Pipeline!$P$7:$P$67,0))="","—",INDEX(Pipeline!$L$7:$L$67,MATCH(LARGE(Pipeline!$P$7:$P$67,2),Pipeline!$P$7:$P$67,0))),"") -> 273493.78
A19: 3 | B19: =IFERROR(IF(INDEX(Pipeline!$B$7:$B$67,MATCH(LARGE(Pipeline!$P$7:$P$67,3),Pipeline!$P$7:$P$67,0))="","—",INDEX(Pipeline!$B$7:$B$67,MATCH(LARGE(Pipeline!$P$7:$P$67,3),Pipeline!$P$7:$P$67,0))),"") -> RFS | C19: =IFERROR(IF(INDEX(Pipeline!$C$7:$C$67,MATCH(LARGE(Pipeline!$P$7:$P$67,3),Pipeline!$P$7:$P$67,0))="","—",INDEX(Pipeline!$C$7:$C$67,MATCH(LARGE(Pipeline!$P$7:$P$67,3),Pipeline!$P$7:$P$67,0))),"") -> Cold Storage | D19: =IFERROR(IF(INDEX(Pipeline!$E$7:$E$67,MATCH(LARGE(Pipeline!$P$7:$P$67,3),Pipeline!$P$7:$P$67,0))="","—",INDEX(Pipeline!$E$7:$E$67,MATCH(LARGE(Pipeline!$P$7:$P$67,3),Pipeline!$P$7:$P$67,0))),"") -> Costa Rica | E19: =IFERROR(IF(INDEX(Pipeline!$F$7:$F$67,MATCH(LARGE(Pipeline!$P$7:$P$67,3),Pipeline!$P$7:$P$67,0))="","—",INDEX(Pipeline!$F$7:$F$67,MATCH(LARGE(Pipeline!$P$7:$P$67,3),Pipeline!$P$7:$P$67,0))),"") -> KingFrigo | F19: =IFERROR(IF(INDEX(Pipeline!$D$7:$D$67,MATCH(LARGE(Pipeline!$P$7:$P$67,3),Pipeline!$P$7:$P$67,0))="","—",INDEX(Pipeline!$D$7:$D$67,MATCH(LARGE(Pipeline!$P$7:$P$67,3),Pipeline!$P$7:$P$67,0))),"") -> Juan Carlos Menendez | G19: =IFERROR(IF(INDEX(Pipeline!$G$7:$G$67,MATCH(LARGE(Pipeline!$P$7:$P$67,3),Pipeline!$P$7:$P$67,0))="","—",INDEX(Pipeline!$G$7:$G$67,MATCH(LARGE(Pipeline!$P$7:$P$67,3),Pipeline!$P$7:$P$67,0))),"") -> 12500 | H19: =IFERROR(IF(INDEX(Pipeline!$H$7:$H$67,MATCH(LARGE(Pipeline!$P$7:$P$67,3),Pipeline!$P$7:$P$67,0))="","—",INDEX(Pipeline!$H$7:$H$67,MATCH(LARGE(Pipeline!$P$7:$P$67,3),Pipeline!$P$7:$P$67,0))),"") -> 312500 | I19: =IFERROR(IF(INDEX(Pipeline!$I$7:$I$67,MATCH(LARGE(Pipeline!$P$7:$P$67,3),Pipeline!$P$7:$P$67,0))="","—",INDEX(Pipeline!$I$7:$I$67,MATCH(LARGE(Pipeline!$P$7:$P$67,3),Pipeline!$P$7:$P$67,0))),"") -> Closed Won | J19: =IFERROR(IF(INDEX(Pipeline!$J$7:$J$67,MATCH(LARGE(Pipeline!$P$7:$P$67,3),Pipeline!$P$7:$P$67,0))="","—",INDEX(Pipeline!$J$7:$J$67,MATCH(LARGE(Pipeline!$P$7:$P$67,3),Pipeline!$P$7:$P$67,0))),"") -> — | K19: =IFERROR(IF(INDEX(Pipeline!$K$7:$K$67,MATCH(LARGE(Pipeline!$P$7:$P$67,3),Pipeline!$P$7:$P$67,0))="","—",INDEX(Pipeline!$K$7:$K$67,MATCH(LARGE(Pipeline!$P$7:$P$67,3),Pipeline!$P$7:$P$67,0))),"") -> — | L19: =IFERROR(IF(INDEX(Pipeline!$L$7:$L$67,MATCH(LARGE(Pipeline!$P$7:$P$67,3),Pipeline!$P$7:$P$67,0))="","—",INDEX(Pipeline!$L$7:$L$67,MATCH(LARGE(Pipeline!$P$7:$P$67,3),Pipeline!$P$7:$P$67,0))),"") -> —
A20: 4 | B20: =IFERROR(IF(INDEX(Pipeline!$B$7:$B$67,MATCH(LARGE(Pipeline!$P$7:$P$67,4),Pipeline!$P$7:$P$67,0))="","—",INDEX(Pipeline!$B$7:$B$67,MATCH(LARGE(Pipeline!$P$7:$P$67,4),Pipeline!$P$7:$P$67,0))),"") -> CIA Caribe Mar | C20: =IFERROR(IF(INDEX(Pipeline!$C$7:$C$67,MATCH(LARGE(Pipeline!$P$7:$P$67,4),Pipeline!$P$7:$P$67,0))="","—",INDEX(Pipeline!$C$7:$C$67,MATCH(LARGE(Pipeline!$P$7:$P$67,4),Pipeline!$P$7:$P$67,0))),"") -> Antártica | D20: =IFERROR(IF(INDEX(Pipeline!$E$7:$E$67,MATCH(LARGE(Pipeline!$P$7:$P$67,4),Pipeline!$P$7:$P$67,0))="","—",INDEX(Pipeline!$E$7:$E$67,MATCH(LARGE(Pipeline!$P$7:$P$67,4),Pipeline!$P$7:$P$67,0))),"") -> Venezuela | E20: =IFERROR(IF(INDEX(Pipeline!$F$7:$F$67,MATCH(LARGE(Pipeline!$P$7:$P$67,4),Pipeline!$P$7:$P$67,0))="","—",INDEX(Pipeline!$F$7:$F$67,MATCH(LARGE(Pipeline!$P$7:$P$67,4),Pipeline!$P$7:$P$67,0))),"") -> KingFrigo | F20: =IFERROR(IF(INDEX(Pipeline!$D$7:$D$67,MATCH(LARGE(Pipeline!$P$7:$P$67,4),Pipeline!$P$7:$P$67,0))="","—",INDEX(Pipeline!$D$7:$D$67,MATCH(LARGE(Pipeline!$P$7:$P$67,4),Pipeline!$P$7:$P$67,0))),"") -> María Yelitza Calderón | G20: =IFERROR(IF(INDEX(Pipeline!$G$7:$G$67,MATCH(LARGE(Pipeline!$P$7:$P$67,4),Pipeline!$P$7:$P$67,0))="","—",INDEX(Pipeline!$G$7:$G$67,MATCH(LARGE(Pipeline!$P$7:$P$67,4),Pipeline!$P$7:$P$67,0))),"") -> 12000 | H20: =IFERROR(IF(INDEX(Pipeline!$H$7:$H$67,MATCH(LARGE(Pipeline!$P$7:$P$67,4),Pipeline!$P$7:$P$67,0))="","—",INDEX(Pipeline!$H$7:$H$67,MATCH(LARGE(Pipeline!$P$7:$P$67,4),Pipeline!$P$7:$P$67,0))),"") -> 360000 | I20: =IFERROR(IF(INDEX(Pipeline!$I$7:$I$67,MATCH(LARGE(Pipeline!$P$7:$P$67,4),Pipeline!$P$7:$P$67,0))="","—",INDEX(Pipeline!$I$7:$I$67,MATCH(LARGE(Pipeline!$P$7:$P$67,4),Pipeline!$P$7:$P$67,0))),"") -> Specification | J20: =IFERROR(IF(INDEX(Pipeline!$J$7:$J$67,MATCH(LARGE(Pipeline!$P$7:$P$67,4),Pipeline!$P$7:$P$67,0))="","—",INDEX(Pipeline!$J$7:$J$67,MATCH(LARGE(Pipeline!$P$7:$P$67,4),Pipeline!$P$7:$P$67,0))),"") -> 0.9 | K20: =IFERROR(IF(INDEX(Pipeline!$K$7:$K$67,MATCH(LARGE(Pipeline!$P$7:$P$67,4),Pipeline!$P$7:$P$67,0))="","—",INDEX(Pipeline!$K$7:$K$67,MATCH(LARGE(Pipeline!$P$7:$P$67,4),Pipeline!$P$7:$P$67,0))),"") -> Noviembre | L20: =IFERROR(IF(INDEX(Pipeline!$L$7:$L$67,MATCH(LARGE(Pipeline!$P$7:$P$67,4),Pipeline!$P$7:$P$67,0))="","—",INDEX(Pipeline!$L$7:$L$67,MATCH(LARGE(Pipeline!$P$7:$P$67,4),Pipeline!$P$7:$P$67,0))),"") -> 324000
A21: 5 | B21: =IFERROR(IF(INDEX(Pipeline!$B$7:$B$67,MATCH(LARGE(Pipeline!$P$7:$P$67,5),Pipeline!$P$7:$P$67,0))="","—",INDEX(Pipeline!$B$7:$B$67,MATCH(LARGE(Pipeline!$P$7:$P$67,5),Pipeline!$P$7:$P$67,0))),"") -> Galvaceros | C21: =IFERROR(IF(INDEX(Pipeline!$C$7:$C$67,MATCH(LARGE(Pipeline!$P$7:$P$67,5),Pipeline!$P$7:$P$67,0))="","—",INDEX(Pipeline!$C$7:$C$67,MATCH(LARGE(Pipeline!$P$7:$P$67,5),Pipeline!$P$7:$P$67,0))),"") -> Panandina Data Center | D21: =IFERROR(IF(INDEX(Pipeline!$E$7:$E$67,MATCH(LARGE(Pipeline!$P$7:$P$67,5),Pipeline!$P$7:$P$67,0))="","—",INDEX(Pipeline!$E$7:$E$67,MATCH(LARGE(Pipeline!$P$7:$P$67,5),Pipeline!$P$7:$P$67,0))),"") -> Colombia | E21: =IFERROR(IF(INDEX(Pipeline!$F$7:$F$67,MATCH(LARGE(Pipeline!$P$7:$P$67,5),Pipeline!$P$7:$P$67,0))="","—",INDEX(Pipeline!$F$7:$F$67,MATCH(LARGE(Pipeline!$P$7:$P$67,5),Pipeline!$P$7:$P$67,0))),"") -> KingRoof / KingWall LMR | F21: =IFERROR(IF(INDEX(Pipeline!$D$7:$D$67,MATCH(LARGE(Pipeline!$P$7:$P$67,5),Pipeline!$P$7:$P$67,0))="","—",INDEX(Pipeline!$D$7:$D$67,MATCH(LARGE(Pipeline!$P$7:$P$67,5),Pipeline!$P$7:$P$67,0))),"") -> Joana Perez | G21: =IFERROR(IF(INDEX(Pipeline!$G$7:$G$67,MATCH(LARGE(Pipeline!$P$7:$P$67,5),Pipeline!$P$7:$P$67,0))="","—",INDEX(Pipeline!$G$7:$G$67,MATCH(LARGE(Pipeline!$P$7:$P$67,5),Pipeline!$P$7:$P$67,0))),"") -> 4106 | H21: =IFERROR(IF(INDEX(Pipeline!$H$7:$H$67,MATCH(LARGE(Pipeline!$P$7:$P$67,5),Pipeline!$P$7:$P$67,0))="","—",INDEX(Pipeline!$H$7:$H$67,MATCH(LARGE(Pipeline!$P$7:$P$67,5),Pipeline!$P$7:$P$67,0))),"") -> 494712 | I21: =IFERROR(IF(INDEX(Pipeline!$I$7:$I$67,MATCH(LARGE(Pipeline!$P$7:$P$67,5),Pipeline!$P$7:$P$67,0))="","—",INDEX(Pipeline!$I$7:$I$67,MATCH(LARGE(Pipeline!$P$7:$P$67,5),Pipeline!$P$7:$P$67,0))),"") -> Pending | J21: =IFERROR(IF(INDEX(Pipeline!$J$7:$J$67,MATCH(LARGE(Pipeline!$P$7:$P$67,5),Pipeline!$P$7:$P$67,0))="","—",INDEX(Pipeline!$J$7:$J$67,MATCH(LARGE(Pipeline!$P$7:$P$67,5),Pipeline!$P$7:$P$67,0))),"") -> 0.85 | K21: =IFERROR(IF(INDEX(Pipeline!$K$7:$K$67,MATCH(LARGE(Pipeline!$P$7:$P$67,5),Pipeline!$P$7:$P$67,0))="","—",INDEX(Pipeline!$K$7:$K$67,MATCH(LARGE(Pipeline!$P$7:$P$67,5),Pipeline!$P$7:$P$67,0))),"") -> Diciembre | L21: =IFERROR(IF(INDEX(Pipeline!$L$7:$L$67,MATCH(LARGE(Pipeline!$P$7:$P$67,5),Pipeline!$P$7:$P$67,0))="","—",INDEX(Pipeline!$L$7:$L$67,MATCH(LARGE(Pipeline!$P$7:$P$67,5),Pipeline!$P$7:$P$67,0))),"") -> 420505.2
B22: Total Top 5 | G22: =SUM(G17:G21) -> 64134 | H22: =SUM(H17:H21) -> 1912305.7
B25: Resumen pipeline | C25: Industrial | D25: Distribución | E25: Total
B26: N° proyectos (filas) | C26: 41 | D26: =COUNTIFS(Pipeline!$A$7:$A$67,"Distribución") -> 10 | E26: =C26+D26 -> 51
B27: m² total | C27: 749389 | D27: =SUMIFS(Pipeline!$G$7:$G$67,Pipeline!$A$7:$A$67,"Distribución") -> 79254 | E27: =C27+D27 -> 828643
B28: USD total | C28: =SUMIFS(Pipeline!$H$7:$H$67,Pipeline!$A$7:$A$67,"Industrial") -> 21038017 | D28: =SUMIFS(Pipeline!$H$7:$H$67,Pipeline!$A$7:$A$67,"Distribución") -> 2459506.7 | E28: =C28+D28 -> 23497524
B29: Closed Won – N° | C29: =COUNTIFS(Pipeline!$A$7:$A$67,"Industrial",Pipeline!$I$7:$I$67,"Closed Won") -> 5 | D29: =COUNTIFS(Pipeline!$A$7:$A$67,"Distribución",Pipeline!$I$7:$I$67,"Closed Won") -> 3 | E29: =C29+D29 -> 8
B30: Closed Won – USD | C30: =SUMIFS(Pipeline!$H$7:$H$67,Pipeline!$A$7:$A$67,"Industrial",Pipeline!$I$7:$I$67,"Closed Won") -> 1956120 | D30: =SUMIFS(Pipeline!$H$7:$H$67,Pipeline!$A$7:$A$67,"Distribución",Pipeline!$I$7:$I$67,"Closed Won") -> 491937 | E30: =C30+D30 -> 2448057
B31: Specification – N° | C31: =COUNTIFS(Pipeline!$A$7:$A$67,"Industrial",Pipeline!$I$7:$I$67,"Specification") -> 1 | D31: =COUNTIFS(Pipeline!$A$7:$A$67,"Distribución",Pipeline!$I$7:$I$67,"Specification") -> 1 | E31: =C31+D31 -> 2
B32: Pending – N° | C32: =COUNTIFS(Pipeline!$A$7:$A$67,"Industrial",Pipeline!$I$7:$I$67,"Pending") -> 22 | D32: =COUNTIFS(Pipeline!$A$7:$A$67,"Distribución",Pipeline!$I$7:$I$67,"Pending") -> 6 | E32: =C32+D32 -> 28
B33: Pending – USD | C33: =SUMIFS(Pipeline!$H$7:$H$67,Pipeline!$A$7:$A$67,"Industrial",Pipeline!$I$7:$I$67,"Pending") -> 16294103 | D33: =SUMIFS(Pipeline!$H$7:$H$67,Pipeline!$A$7:$A$67,"Distribución",Pipeline!$I$7:$I$67,"Pending") -> 1607569.7 | E33: =C33+D33 -> 17901673
B34: N° proyectos reportado (incl. grupo "Others") | C34: 38 | D34: =D26 -> 10 | E34: =C34+D34 -> 48
B35: Insight (texto para slide) | C35: =E34&" proyectos activos · USD "&TEXT(E28/1000000,"0.0")&" M · "&TEXT(E27/1000,"#,##0")&"k m²" -> 48 proyectos activos · USD 23 M · 828,643k m²

Sheet RSM_Resumen_Canales
A1: Resumen por canal – Order Intake, Ventas, Budget, Cumplimiento y Backlog (YTD)
A2: Alimenta el slide "Sales Performance by Channel (YTD)". Todo es fórmula: se actualiza desde las hojas RSM (detalle por consultor, no se presenta) y 05_Backlog_Canal.
A4: Canal (slide) | B4: Hoja RSM fuente | C4: Order Intake YTD (m²) | D4: Ventas YTD (m²) | E4: Budget YTD (m²) | F4: Brecha vs budget (m²) | G4: % Cumplimiento | H4: Semáforo | I4: Backlog (m²) | J4: Margen backlog CM | K4: Margen backlog PY | L4: Δ margen (pp) | M4: Mix backlog | N4: Book-to-bill (OI/Ventas) | P4: # | Q4: Ranking cumplimiento (fuente gráfico) | R4: % Cumpl.
A5: Industrial | B5: 09_RSM_Industrial | C5: =INDEX('09_RSM_Industrial'!$C:$C,MATCH("TOTAL CANAL",'09_RSM_Industrial'!$A:$A,0)) -> 430568 | D5: =INDEX('09_RSM_Industrial'!$D:$D,MATCH("TOTAL CANAL",'09_RSM_Industrial'!$A:$A,0)) -> 339588 | E5: =INDEX('09_RSM_Industrial'!$E:$E,MATCH("TOTAL CANAL",'09_RSM_Industrial'!$A:$A,0)) -> 443901.88 | F5: =D5-E5 -> -104313.88 | G5: =IF(E5=0,0,D5/E5) -> 0.76500691 | H5: =IF(ROUND(G5*100,0)<=60,"Rojo",IF(ROUND(G5*100,0)<=84,"Naranja",IF(ROUND(G5*100,0)<=100,"Verde claro","Verde oscuro"))) -> Naranja | I5: ='05_Backlog_Canal'!B5 -> 240448 | J5: ='05_Backlog_Canal'!E5 -> 0.33117136 | K5: ='05_Backlog_Canal'!F5 -> 0.28692083 | L5: =IF(OR(J5="",K5="",K5=0),"n.a.",(J5-K5)*100) -> 4.425053 | M5: =IFERROR(I5/$I$11,0) -> 0.45753517 | N5: =IFERROR(C5/D5,"") -> 1.2679129 | O5: =G5+(20-ROW())/1000000000 -> 0.76500692 | P5: 1 | Q5: =INDEX($A$5:$A$10,MATCH(LARGE($O$5:$O$10,P5),$O$5:$O$10,0)) -> Alternative Sales | R5: =INDEX($G$5:$G$10,MATCH(LARGE($O$5:$O$10,P5),$O$5:$O$10,0)) -> 1.5303738
A6: Distribution | B6: 10_RSM_Distribucion | C6: =INDEX('10_RSM_Distribucion'!$C:$C,MATCH("TOTAL CANAL",'10_RSM_Distribucion'!$A:$A,0)) -> 236351 | D6: =INDEX('10_RSM_Distribucion'!$D:$D,MATCH("TOTAL CANAL",'10_RSM_Distribucion'!$A:$A,0)) -> 227016 | E6: =INDEX('10_RSM_Distribucion'!$E:$E,MATCH("TOTAL CANAL",'10_RSM_Distribucion'!$A:$A,0)) -> 248524 | F6: =D6-E6 -> -21508 | G6: =IF(E6=0,0,D6/E6) -> 0.91345705 | H6: =IF(ROUND(G6*100,0)<=60,"Rojo",IF(ROUND(G6*100,0)<=84,"Naranja",IF(ROUND(G6*100,0)<=100,"Verde claro","Verde oscuro"))) -> Verde claro | I6: ='05_Backlog_Canal'!B6 -> 62499 | J6: ='05_Backlog_Canal'!E6 -> 0.29966956 | K6: ='05_Backlog_Canal'!F6 -> 0.2701004 | L6: =IF(OR(J6="",K6="",K6=0),"n.a.",(J6-K6)*100) -> 2.9569156 | M6: =IFERROR(I6/$I$11,0) -> 0.11892588 | N6: =IFERROR(C6/D6,"") -> 1.0411204 | O6: =G6+(20-ROW())/1000000000 -> 0.91345706 | P6: 2 | Q6: =INDEX($A$5:$A$10,MATCH(LARGE($O$5:$O$10,P6),$O$5:$O$10,0)) -> Site Cali | R6: =INDEX($G$5:$G$10,MATCH(LARGE($O$5:$O$10,P6),$O$5:$O$10,0)) -> 0.95746303
A7: Other Geographies | B7: 11_RSM_Otras_Geo | C7: =INDEX('11_RSM_Otras_Geo'!$C:$C,MATCH("TOTAL CANAL",'11_RSM_Otras_Geo'!$A:$A,0)) -> 367237 | D7: =INDEX('11_RSM_Otras_Geo'!$D:$D,MATCH("TOTAL CANAL",'11_RSM_Otras_Geo'!$A:$A,0)) -> 306076 | E7: =INDEX('11_RSM_Otras_Geo'!$E:$E,MATCH("TOTAL CANAL",'11_RSM_Otras_Geo'!$A:$A,0)) -> 388113 | F7: =D7-E7 -> -82037 | G7: =IF(E7=0,0,D7/E7) -> 0.78862599 | H7: =IF(ROUND(G7*100,0)<=60,"Rojo",IF(ROUND(G7*100,0)<=84,"Naranja",IF(ROUND(G7*100,0)<=100,"Verde claro","Verde oscuro"))) -> Naranja | I7: ='05_Backlog_Canal'!B7 -> 166377 | J7: ='05_Backlog_Canal'!E7 -> 0.14624363 | K7: ='05_Backlog_Canal'!F7 -> 0.10427401 | L7: =IF(OR(J7="",K7="",K7=0),"n.a.",(J7-K7)*100) -> 4.1969622 | M7: =IFERROR(I7/$I$11,0) -> 0.31658957 | N7: =IFERROR(C7/D7,"") -> 1.1998229 | O7: =G7+(20-ROW())/1000000000 -> 0.78862601 | P7: 3 | Q7: =INDEX($A$5:$A$10,MATCH(LARGE($O$5:$O$10,P7),$O$5:$O$10,0)) -> Cold Storage | R7: =INDEX($G$5:$G$10,MATCH(LARGE($O$5:$O$10,P7),$O$5:$O$10,0)) -> 0.9191
A8: Cold Storage | B8: 12_RSM_Cold_Storage | C8: =INDEX('12_RSM_Cold_Storage'!$C:$C,MATCH("TOTAL CANAL",'12_RSM_Cold_Storage'!$A:$A,0)) -> 36425 | D8: =INDEX('12_RSM_Cold_Storage'!$D:$D,MATCH("TOTAL CANAL",'12_RSM_Cold_Storage'!$A:$A,0)) -> 9191 | E8: =INDEX('12_RSM_Cold_Storage'!$E:$E,MATCH("TOTAL CANAL",'12_RSM_Cold_Storage'!$A:$A,0)) -> 10000 | F8: =D8-E8 -> -809 | G8: =IF(E8=0,0,D8/E8) -> 0.9191 | H8: =IF(ROUND(G8*100,0)<=60,"Rojo",IF(ROUND(G8*100,0)<=84,"Naranja",IF(ROUND(G8*100,0)<=100,"Verde claro","Verde oscuro"))) -> Verde claro | I8: ='05_Backlog_Canal'!B8 -> 28642 | J8: ='05_Backlog_Canal'!E8 -> 0.28058377 | K8: ='05_Backlog_Canal'!F8 -> 0.38680242 | L8: =IF(OR(J8="",K8="",K8=0),"n.a.",(J8-K8)*100) -> -10.621865 | M8: =IFERROR(I8/$I$11,0) -> 0.054501274 | N8: =IFERROR(C8/D8,"") -> 3.9631161 | O8: =G8+(20-ROW())/1000000000 -> 0.91910001 | P8: 4 | Q8: =INDEX($A$5:$A$10,MATCH(LARGE($O$5:$O$10,P8),$O$5:$O$10,0)) -> Distribution | R8: =INDEX($G$5:$G$10,MATCH(LARGE($O$5:$O$10,P8),$O$5:$O$10,0)) -> 0.91345705
A9: Site Cali | B9: 13_RSM_Site_Cali | C9: =INDEX('13_RSM_Site_Cali'!$C:$C,MATCH("TOTAL CANAL",'13_RSM_Site_Cali'!$A:$A,0)) -> 140132 | D9: =INDEX('13_RSM_Site_Cali'!$D:$D,MATCH("TOTAL CANAL",'13_RSM_Site_Cali'!$A:$A,0)) -> 106715 | E9: =INDEX('13_RSM_Site_Cali'!$E:$E,MATCH("TOTAL CANAL",'13_RSM_Site_Cali'!$A:$A,0)) -> 111456 | F9: =D9-E9 -> -4741 | G9: =IF(E9=0,0,D9/E9) -> 0.95746303 | H9: =IF(ROUND(G9*100,0)<=60,"Rojo",IF(ROUND(G9*100,0)<=84,"Naranja",IF(ROUND(G9*100,0)<=100,"Verde claro","Verde oscuro"))) -> Verde claro | I9: ='05_Backlog_Canal'!B9 -> 21774 | J9: ='05_Backlog_Canal'!E9 -> 0.36773598 | K9: ='05_Backlog_Canal'!F9 -> 0 | L9: =IF(OR(J9="",K9="",K9=0),"n.a.",(J9-K9)*100) -> n.a. | M9: =IFERROR(I9/$I$11,0) -> 0.041432538 | N9: =IFERROR(C9/D9,"") -> 1.3131425 | O9: =G9+(20-ROW())/1000000000 -> 0.95746305 | P9: 5 | Q9: =INDEX($A$5:$A$10,MATCH(LARGE($O$5:$O$10,P9),$O$5:$O$10,0)) -> Other Geographies | R9: =INDEX($G$5:$G$10,MATCH(LARGE($O$5:$O$10,P9),$O$5:$O$10,0)) -> 0.78862599
A10: Alternative Sales | B10: 14_RSM_Vtas_Alt | C10: =INDEX('14_RSM_Vtas_Alt'!$C:$C,MATCH("TOTAL CANAL",'14_RSM_Vtas_Alt'!$A:$A,0)) -> 58411 | D10: =INDEX('14_RSM_Vtas_Alt'!$D:$D,MATCH("TOTAL CANAL",'14_RSM_Vtas_Alt'!$A:$A,0)) -> 69430 | E10: =INDEX('14_RSM_Vtas_Alt'!$E:$E,MATCH("TOTAL CANAL",'14_RSM_Vtas_Alt'!$A:$A,0)) -> 45368 | F10: =D10-E10 -> 24062 | G10: =IF(E10=0,0,D10/E10) -> 1.5303738 | H10: =IF(ROUND(G10*100,0)<=60,"Rojo",IF(ROUND(G10*100,0)<=84,"Naranja",IF(ROUND(G10*100,0)<=100,"Verde claro","Verde oscuro"))) -> Verde oscuro | I10: ='05_Backlog_Canal'!B10 -> 5789 | J10: ='05_Backlog_Canal'!E10 -> 0.45275886 | K10: ='05_Backlog_Canal'!F10 -> 0.36956934 | L10: =IF(OR(J10="",K10="",K10=0),"n.a.",(J10-K10)*100) -> 8.3189517 | M10: =IFERROR(I10/$I$11,0) -> 0.011015567 | N10: =IFERROR(C10/D10,"") -> 0.84129339 | O10: =G10+(20-ROW())/1000000000 -> 1.5303738 | P10: 6 | Q10: =INDEX($A$5:$A$10,MATCH(LARGE($O$5:$O$10,P10),$O$5:$O$10,0)) -> Industrial | R10: =INDEX($G$5:$G$10,MATCH(LARGE($O$5:$O$10,P10),$O$5:$O$10,0)) -> 0.76500691
A11: TOTAL | C11: =SUM(C5:C10) -> 1269124 | D11: =SUM(D5:D10) -> 1058016 | E11: =SUM(E5:E10) -> 1247362.9 | F11: =SUM(F5:F10) -> -189346.88 | G11: =IF(E11=0,0,D11/E11) -> 0.84820225 | H11: =IF(ROUND(G11*100,0)<=60,"Rojo",IF(ROUND(G11*100,0)<=84,"Naranja",IF(ROUND(G11*100,0)<=100,"Verde claro","Verde oscuro"))) -> Verde claro | I11: =SUM(I5:I10) -> 525529 | J11: =IFERROR(SUMPRODUCT(I5:I10,J5:J10)/I11,0) -> 0.26897602 | K11: =IFERROR(SUMPRODUCT('05_Backlog_Canal'!C5:C10,K5:K10)/'05_Backlog_Canal'!C11,0) -> 0.22228003 | L11: =(J11-K11)*100 -> 4.6695996 | M11: =SUM(M5:M10) -> 1 | N11: =IFERROR(C11/D11,"") -> 1.199532
A13: KPIs del slide
A14: Order Intake YTD (m²) | C14: =C11 -> 1269124
A15: Ventas YTD (m²) | C15: =D11 -> 1058016
A16: Budget YTD (m²) | C16: =E11 -> 1247362.9
A17: Brecha total (m²) | C17: =F11 -> -189346.88
A18: % Cumplimiento total | C18: =G11 -> 0.84820225
A19: Canales ≥100% budget | C19: =COUNTIF(G5:G10,">=1")&" de 6" -> 1 de 6
A20: Backlog total (m²) | C20: =I11 -> 525529
A21: Margen backlog ponderado | C21: =J11 -> 0.26897602
A22: Control: backlog vs IMP (hoja 04) | C22: =I11-'04_Backlog'!B5 -> 0
A23: % de la brecha explicado por Industrial + Otras Geo | C23: =IFERROR((F5+F7)/F11,0) -> 0.98417719
A26: Semáforo cumplimiento: Rojo 0–60% · Naranja 61–84% · Verde claro 85–100% · Verde oscuro >100%
A28: Fuente slide "Sales vs Budget & Margin Evolution" (k m² y margen de backlog PY → CM)
A29: Canal | B29: Ventas YTD (k m²) | C29: Budget YTD (k m²) | D29: Margen Sep-25 (PY) | E29: Margen Sep-26 (CM) | F29: Δ margen (pp) | G29: % Cumplimiento
A30: =A5 -> Industrial | B30: =D5/1000 -> 339.588 | C30: =E5/1000 -> 443.90188 | D30: =IF(K5=0,"n.a.",K5) -> 0.28692083 | E30: =J5 -> 0.33117136 | F30: =L5 -> 4.425053 | G30: =G5 -> 0.76500691
A31: =A6 -> Distribution | B31: =D6/1000 -> 227.016 | C31: =E6/1000 -> 248.524 | D31: =IF(K6=0,"n.a.",K6) -> 0.2701004 | E31: =J6 -> 0.29966956 | F31: =L6 -> 2.9569156 | G31: =G6 -> 0.91345705
A32: =A7 -> Other Geographies | B32: =D7/1000 -> 306.076 | C32: =E7/1000 -> 388.113 | D32: =IF(K7=0,"n.a.",K7) -> 0.10427401 | E32: =J7 -> 0.14624363 | F32: =L7 -> 4.1969622 | G32: =G7 -> 0.78862599
A33: =A8 -> Cold Storage | B33: =D8/1000 -> 9.191 | C33: =E8/1000 -> 10 | D33: =IF(K8=0,"n.a.",K8) -> 0.38680242 | E33: =J8 -> 0.28058377 | F33: =L8 -> -10.621865 | G33: =G8 -> 0.9191
A34: =A9 -> Site Cali | B34: =D9/1000 -> 106.715 | C34: =E9/1000 -> 111.456 | D34: =IF(K9=0,"n.a.",K9) -> n.a. | E34: =J9 -> 0.36773598 | F34: =L9 -> n.a. | G34: =G9 -> 0.95746303
A35: =A10 -> Alternative Sales | B35: =D10/1000 -> 69.43 | C35: =E10/1000 -> 45.368 | D35: =IF(K10=0,"n.a.",K10) -> 0.36956934 | E35: =J10 -> 0.45275886 | F35: =L10 -> 8.3189517 | G35: =G10 -> 1.5303738
A36: =A11 -> TOTAL | B36: =D11/1000 -> 1058.016 | C36: =E11/1000 -> 1247.3629 | D36: =IF(K11=0,"n.a.",K11) -> 0.22228003 | E36: =J11 -> 0.26897602 | F36: =L11 -> 4.6695996 | G36: =G11 -> 0.84820225
A37: Nota: n.a. en margen PY = canal sin base PY. Para ver evolución mensual, agregar ventas/budget/margen por mes por canal.

Sheet 09_RSM_Industrial
A1: 09 · RSM Industrial – Cumplimiento y Backlog (YTD) [detalle interno – no se presenta en el deck]
A2: Diligencie la tabla izquierda; el ranking (derecha), totales y semáforos se calculan solos
A4: RSM (nombre completo) | B4: Nombre corto (slide) | C4: Order Intake m² | D4: Ventas Total m² | E4: Budget m² (paneles) | F4: % Cumpl. Budget | G4: Semáforo | H4: Backlog paneles m² | I4: Backlog otros m² | J4: Clave orden (aux) | L4: # | M4: Ranking – Fuente gráfico (mayor → menor cumplimiento) | N4: % Cumpl. | O4: Ventas m² | P4: Budget m²
A5: ARIAS GIRALDO ANA ISABEL | B5: Ana I. Arias | C5: 135074 | D5: 140201 | E5: 83093 | F5: =IF(A5="","",IF(E5=0,0,D5/E5)) -> 1.6872781 | G5: =IF(F5="","",IF(F5>=1,"Verde",IF(F5>=0.7,"Ámbar","Rojo"))) -> Verde | H5: 74948 | I5: 0 | J5: =IF(A5="","",F5+D5/1000000000+(100-ROW())/1000000000000) -> 1.6874183 | L5: 1 | M5: =IF(L5>COUNT($J$5:$J$17),"",INDEX($B$5:$B$17,MATCH(LARGE($J$5:$J$17,L5),$J$5:$J$17,0))) -> Ana I. Arias | N5: =IF(M5="","",INDEX($F$5:$F$17,MATCH(LARGE($J$5:$J$17,L5),$J$5:$J$17,0))) -> 1.6872781 | O5: =IF(M5="","",INDEX($D$5:$D$17,MATCH(LARGE($J$5:$J$17,L5),$J$5:$J$17,0))) -> 140201 | P5: =IF(M5="","",INDEX($E$5:$E$17,MATCH(LARGE($J$5:$J$17,L5),$J$5:$J$17,0))) -> 83093
A6: EJECUTIVO VENTAS ZONA NORTE | B6: Ejec. Zona Norte | C6: =47727+2040+2699 -> 52466 | D6: =30473+4728 -> 35201 | E6: =36220+27698 -> 63918 | F6: =IF(A6="","",IF(E6=0,0,D6/E6)) -> 0.55072124 | G6: =IF(F6="","",IF(F6>=1,"Verde",IF(F6>=0.7,"Ámbar","Rojo"))) -> Rojo | H6: 29686 | I6: 0 | J6: =IF(A6="","",F6+D6/1000000000+(100-ROW())/1000000000000) -> 0.55075644 | L6: 2 | M6: =IF(L6>COUNT($J$5:$J$17),"",INDEX($B$5:$B$17,MATCH(LARGE($J$5:$J$17,L6),$J$5:$J$17,0))) -> Julio C. Guerrero | N6: =IF(M6="","",INDEX($F$5:$F$17,MATCH(LARGE($J$5:$J$17,L6),$J$5:$J$17,0))) -> 1.4024235 | O6: =IF(M6="","",INDEX($D$5:$D$17,MATCH(LARGE($J$5:$J$17,L6),$J$5:$J$17,0))) -> 103583 | P6: =IF(M6="","",INDEX($E$5:$E$17,MATCH(LARGE($J$5:$J$17,L6),$J$5:$J$17,0))) -> 73860
A7: GUERRERO ESPINOSA JULIO CESAR | B7: Julio C. Guerrero | C7: 115336 | D7: 103583 | E7: 73860 | F7: =IF(A7="","",IF(E7=0,0,D7/E7)) -> 1.4024235 | G7: =IF(F7="","",IF(F7>=1,"Verde",IF(F7>=0.7,"Ámbar","Rojo"))) -> Verde | H7: 18759 | I7: 0 | J7: =IF(A7="","",F7+D7/1000000000+(100-ROW())/1000000000000) -> 1.4025271 | L7: 3 | M7: =IF(L7>COUNT($J$5:$J$17),"",INDEX($B$5:$B$17,MATCH(LARGE($J$5:$J$17,L7),$J$5:$J$17,0))) -> Diego A. Calderón | N7: =IF(M7="","",INDEX($F$5:$F$17,MATCH(LARGE($J$5:$J$17,L7),$J$5:$J$17,0))) -> 0.82003046 | O7: =IF(M7="","",INDEX($D$5:$D$17,MATCH(LARGE($J$5:$J$17,L7),$J$5:$J$17,0))) -> 29075 | P7: =IF(M7="","",INDEX($E$5:$E$17,MATCH(LARGE($J$5:$J$17,L7),$J$5:$J$17,0))) -> 35456
A8: CALDERON CHANTRE DIEGO ALFONSO | B8: Diego A. Calderón | C8: 42594 | D8: 29075 | E8: 35456 | F8: =IF(A8="","",IF(E8=0,0,D8/E8)) -> 0.82003046 | G8: =IF(F8="","",IF(F8>=1,"Verde",IF(F8>=0.7,"Ámbar","Rojo"))) -> Ámbar | H8: 27745 | I8: 0 | J8: =IF(A8="","",F8+D8/1000000000+(100-ROW())/1000000000000) -> 0.82005954 | L8: 4 | M8: =IF(L8>COUNT($J$5:$J$17),"",INDEX($B$5:$B$17,MATCH(LARGE($J$5:$J$17,L8),$J$5:$J$17,0))) -> Ejec. Zona Norte | N8: =IF(M8="","",INDEX($F$5:$F$17,MATCH(LARGE($J$5:$J$17,L8),$J$5:$J$17,0))) -> 0.55072124 | O8: =IF(M8="","",INDEX($D$5:$D$17,MATCH(LARGE($J$5:$J$17,L8),$J$5:$J$17,0))) -> 35201 | P8: =IF(M8="","",INDEX($E$5:$E$17,MATCH(LARGE($J$5:$J$17,L8),$J$5:$J$17,0))) -> 63918
A9: CANDELA HERNANDEZ YOLANDA | B9: Yolanda Candela | C9: 36716 | D9: 27897 | E9: 58259 | F9: =IF(A9="","",IF(E9=0,0,D9/E9)) -> 0.47884447 | G9: =IF(F9="","",IF(F9>=1,"Verde",IF(F9>=0.7,"Ámbar","Rojo"))) -> Rojo | H9: 22797 | I9: 18 | J9: =IF(A9="","",F9+D9/1000000000+(100-ROW())/1000000000000) -> 0.47887237 | L9: 5 | M9: =IF(L9>COUNT($J$5:$J$17),"",INDEX($B$5:$B$17,MATCH(LARGE($J$5:$J$17,L9),$J$5:$J$17,0))) -> Yolanda Candela | N9: =IF(M9="","",INDEX($F$5:$F$17,MATCH(LARGE($J$5:$J$17,L9),$J$5:$J$17,0))) -> 0.47884447 | O9: =IF(M9="","",INDEX($D$5:$D$17,MATCH(LARGE($J$5:$J$17,L9),$J$5:$J$17,0))) -> 27897 | P9: =IF(M9="","",INDEX($E$5:$E$17,MATCH(LARGE($J$5:$J$17,L9),$J$5:$J$17,0))) -> 58259
A10: EJECUTIVO VENTAS ZONA CUENTAS CLAVES | B10: Ejec. Cuentas Clave | C10: 10539 | D10: 2608 | E10: 31201.125 | F10: =IF(A10="","",IF(E10=0,0,D10/E10)) -> 0.08358673 | G10: =IF(F10="","",IF(F10>=1,"Verde",IF(F10>=0.7,"Ámbar","Rojo"))) -> Rojo | H10: 0 | I10: 0 | J10: =IF(A10="","",F10+D10/1000000000+(100-ROW())/1000000000000) -> 0.083589338 | L10: 7 | M10: =IF(L10>COUNT($J$5:$J$17),"",INDEX($B$5:$B$17,MATCH(LARGE($J$5:$J$17,L10),$J$5:$J$17,0))) -> León A. Naranjo | N10: =IF(M10="","",INDEX($F$5:$F$17,MATCH(LARGE($J$5:$J$17,L10),$J$5:$J$17,0))) -> 0.032811335 | O10: =IF(M10="","",INDEX($D$5:$D$17,MATCH(LARGE($J$5:$J$17,L10),$J$5:$J$17,0))) -> 924 | P10: =IF(M10="","",INDEX($E$5:$E$17,MATCH(LARGE($J$5:$J$17,L10),$J$5:$J$17,0))) -> 28161
A11: NARANJO VELEZ LEON ALEXIS | B11: León A. Naranjo | C11: 14965 | D11: 924 | E11: 28161 | F11: =IF(A11="","",IF(E11=0,0,D11/E11)) -> 0.032811335 | G11: =IF(F11="","",IF(F11>=1,"Verde",IF(F11>=0.7,"Ámbar","Rojo"))) -> Rojo | H11: 14041 | I11: 1895 | J11: =IF(A11="","",F11+D11/1000000000+(100-ROW())/1000000000000) -> 0.032812259 | L11: 9 | M11: =IF(L11>COUNT($J$5:$J$17),"",INDEX($B$5:$B$17,MATCH(LARGE($J$5:$J$17,L11),$J$5:$J$17,0))) -> Ejec. Zona Bogotá | N11: =IF(M11="","",INDEX($F$5:$F$17,MATCH(LARGE($J$5:$J$17,L11),$J$5:$J$17,0))) -> 0 | O11: =IF(M11="","",INDEX($D$5:$D$17,MATCH(LARGE($J$5:$J$17,L11),$J$5:$J$17,0))) -> 0 | P11: =IF(M11="","",INDEX($E$5:$E$17,MATCH(LARGE($J$5:$J$17,L11),$J$5:$J$17,0))) -> 50778.75
A12: FONTALVO MENDIETA ADRIANA MARCELA | B12: Adriana M. Fontalvo | C12: 22878 | D12: 99 | E12: 19175 | F12: =IF(A12="","",IF(E12=0,0,D12/E12)) -> 0.0051629726 | G12: =IF(F12="","",IF(F12>=1,"Verde",IF(F12>=0.7,"Ámbar","Rojo"))) -> Rojo | H12: 22779 | I12: 0 | J12: =IF(A12="","",F12+D12/1000000000+(100-ROW())/1000000000000) -> 0.0051630717 | L12: 10 | M12: =IF(L12>COUNT($J$5:$J$17),"",INDEX($B$5:$B$17,MATCH(LARGE($J$5:$J$17,L12),$J$5:$J$17,0))) | N12: =IF(M12="","",INDEX($F$5:$F$17,MATCH(LARGE($J$5:$J$17,L12),$J$5:$J$17,0))) | O12: =IF(M12="","",INDEX($D$5:$D$17,MATCH(LARGE($J$5:$J$17,L12),$J$5:$J$17,0))) | P12: =IF(M12="","",INDEX($E$5:$E$17,MATCH(LARGE($J$5:$J$17,L12),$J$5:$J$17,0)))
A13: EJECUTIVO VENTAS ZONA BOGOTA | B13: Ejec. Zona Bogotá | C13: 0 | D13: 0 | E13: 50778.75 | F13: =IF(A13="","",IF(E13=0,0,D13/E13)) -> 0 | G13: =IF(F13="","",IF(F13>=1,"Verde",IF(F13>=0.7,"Ámbar","Rojo"))) -> Rojo | H13: 0 | I13: 0 | J13: =IF(A13="","",F13+D13/1000000000+(100-ROW())/1000000000000) -> 8.7e-11 | L13: 11 | M13: =IF(L13>COUNT($J$5:$J$17),"",INDEX($B$5:$B$17,MATCH(LARGE($J$5:$J$17,L13),$J$5:$J$17,0))) | N13: =IF(M13="","",INDEX($F$5:$F$17,MATCH(LARGE($J$5:$J$17,L13),$J$5:$J$17,0))) | O13: =IF(M13="","",INDEX($D$5:$D$17,MATCH(LARGE($J$5:$J$17,L13),$J$5:$J$17,0))) | P13: =IF(M13="","",INDEX($E$5:$E$17,MATCH(LARGE($J$5:$J$17,L13),$J$5:$J$17,0)))
F14: =IF(A14="","",IF(E14=0,0,D14/E14)) | G14: =IF(F14="","",IF(F14>=1,"Verde",IF(F14>=0.7,"Ámbar","Rojo"))) | J14: =IF(A14="","",F14+D14/1000000000+(100-ROW())/1000000000000) | L14: 12 | M14: =IF(L14>COUNT($J$5:$J$17),"",INDEX($B$5:$B$17,MATCH(LARGE($J$5:$J$17,L14),$J$5:$J$17,0))) | N14: =IF(M14="","",INDEX($F$5:$F$17,MATCH(LARGE($J$5:$J$17,L14),$J$5:$J$17,0))) | O14: =IF(M14="","",INDEX($D$5:$D$17,MATCH(LARGE($J$5:$J$17,L14),$J$5:$J$17,0))) | P14: =IF(M14="","",INDEX($E$5:$E$17,MATCH(LARGE($J$5:$J$17,L14),$J$5:$J$17,0)))
F15: =IF(A15="","",IF(E15=0,0,D15/E15)) | G15: =IF(F15="","",IF(F15>=1,"Verde",IF(F15>=0.7,"Ámbar","Rojo"))) | J15: =IF(A15="","",F15+D15/1000000000+(100-ROW())/1000000000000) | L15: 13 | M15: =IF(L15>COUNT($J$5:$J$17),"",INDEX($B$5:$B$17,MATCH(LARGE($J$5:$J$17,L15),$J$5:$J$17,0))) | N15: =IF(M15="","",INDEX($F$5:$F$17,MATCH(LARGE($J$5:$J$17,L15),$J$5:$J$17,0))) | O15: =IF(M15="","",INDEX($D$5:$D$17,MATCH(LARGE($J$5:$J$17,L15),$J$5:$J$17,0))) | P15: =IF(M15="","",INDEX($E$5:$E$17,MATCH(LARGE($J$5:$J$17,L15),$J$5:$J$17,0)))
F16: =IF(A16="","",IF(E16=0,0,D16/E16)) | G16: =IF(F16="","",IF(F16>=1,"Verde",IF(F16>=0.7,"Ámbar","Rojo"))) | J16: =IF(A16="","",F16+D16/1000000000+(100-ROW())/1000000000000) | L16: 14 | M16: =IF(L16>COUNT($J$5:$J$17),"",INDEX($B$5:$B$17,MATCH(LARGE($J$5:$J$17,L16),$J$5:$J$17,0))) | N16: =IF(M16="","",INDEX($F$5:$F$17,MATCH(LARGE($J$5:$J$17,L16),$J$5:$J$17,0))) | O16: =IF(M16="","",INDEX($D$5:$D$17,MATCH(LARGE($J$5:$J$17,L16),$J$5:$J$17,0))) | P16: =IF(M16="","",INDEX($E$5:$E$17,MATCH(LARGE($J$5:$J$17,L16),$J$5:$J$17,0)))
F17: =IF(A17="","",IF(E17=0,0,D17/E17)) | G17: =IF(F17="","",IF(F17>=1,"Verde",IF(F17>=0.7,"Ámbar","Rojo"))) | J17: =IF(A17="","",F17+D17/1000000000+(100-ROW())/1000000000000) | L17: 15 | M17: =IF(L17>COUNT($J$5:$J$17),"",INDEX($B$5:$B$17,MATCH(LARGE($J$5:$J$17,L17),$J$5:$J$17,0))) | N17: =IF(M17="","",INDEX($F$5:$F$17,MATCH(LARGE($J$5:$J$17,L17),$J$5:$J$17,0))) | O17: =IF(M17="","",INDEX($D$5:$D$17,MATCH(LARGE($J$5:$J$17,L17),$J$5:$J$17,0))) | P17: =IF(M17="","",INDEX($E$5:$E$17,MATCH(LARGE($J$5:$J$17,L17),$J$5:$J$17,0)))
A18: TOTAL CANAL | B18: =COUNTA(A5:A17)&" RSM" -> 9 RSM | C18: =SUM(C5:C17) -> 430568 | D18: =SUM(D5:D17) -> 339588 | E18: =SUM(E5:E17) -> 443901.88 | F18: =IF(E18=0,0,D18/E18) -> 0.76500691 | G18: =IF(F18>=1,"Verde",IF(F18>=0.7,"Ámbar","Rojo")) -> Ámbar | H18: =SUM(H5:H17) -> 210755 | I18: =SUM(I5:I17) -> 1913
A20: KPIs canal
A21: RSM ≥100% budget | B21: =COUNTIF(F5:F17,">=1") -> 2
A22: RSM <70% budget | B22: =COUNTIFS(F5:F17,"<0.7",A5:A17,"<>") -> 0
A23: Brecha vs budget (m²) | B23: =D18-E18 -> -104313.88
A24: Backlog total (m²) | B24: =H18+I18 -> 212668
A25: Book-to-bill (OI/Ventas) | B25: =IFERROR(C18/D18,"") -> 1.2679129

Sheet 10_RSM_Distribucion
A1: 10 · RSM Distribución – Cumplimiento y Backlog (YTD) [detalle interno – no se presenta en el deck]
A2: Diligencie la tabla izquierda; el ranking (derecha), totales y semáforos se calculan solos
A4: RSM (nombre completo) | B4: Nombre corto (slide) | C4: Order Intake m² | D4: Ventas Total m² | E4: Budget m² (paneles) | F4: % Cumpl. Budget | G4: Semáforo | H4: Backlog paneles m² | I4: Backlog otros m² | J4: Clave orden (aux) | L4: # | M4: Ranking – Fuente gráfico (mayor → menor cumplimiento) | N4: % Cumpl. | O4: Ventas m² | P4: Budget m²
A5: EJECUTIVO DE VENTAS SUR | B5: Ejec. Ventas Sur | C5: 4476 | D5: 10800 | E5: 5611 | F5: =IF(A5="","",IF(E5=0,0,D5/E5)) -> 1.9247906 | G5: =IF(F5="","",IF(F5>=1,"Verde",IF(F5>=0.7,"Ámbar","Rojo"))) -> Verde | H5: 0 | I5: 0 | J5: =IF(A5="","",F5+D5/1000000000+(100-ROW())/1000000000000) -> 1.9248014 | L5: 1 | M5: =IF(L5>COUNT($J$5:$J$19),"",INDEX($B$5:$B$19,MATCH(LARGE($J$5:$J$19,L5),$J$5:$J$19,0))) -> Ejec. Eje Cafetero | N5: =IF(M5="","",INDEX($F$5:$F$19,MATCH(LARGE($J$5:$J$19,L5),$J$5:$J$19,0))) -> 1.9834254 | O5: =IF(M5="","",INDEX($D$5:$D$19,MATCH(LARGE($J$5:$J$19,L5),$J$5:$J$19,0))) -> 11129 | P5: =IF(M5="","",INDEX($E$5:$E$19,MATCH(LARGE($J$5:$J$19,L5),$J$5:$J$19,0))) -> 5611
A6: EJECUTIVO DE VENTAS EJE CAFETERO | B6: Ejec. Eje Cafetero | C6: 7780 | D6: 11129 | E6: 5611 | F6: =IF(A6="","",IF(E6=0,0,D6/E6)) -> 1.9834254 | G6: =IF(F6="","",IF(F6>=1,"Verde",IF(F6>=0.7,"Ámbar","Rojo"))) -> Verde | H6: 0 | I6: 0 | J6: =IF(A6="","",F6+D6/1000000000+(100-ROW())/1000000000000) -> 1.9834365 | L6: 2 | M6: =IF(L6>COUNT($J$5:$J$19),"",INDEX($B$5:$B$19,MATCH(LARGE($J$5:$J$19,L6),$J$5:$J$19,0))) -> Ejec. Ventas Sur | N6: =IF(M6="","",INDEX($F$5:$F$19,MATCH(LARGE($J$5:$J$19,L6),$J$5:$J$19,0))) -> 1.9247906 | O6: =IF(M6="","",INDEX($D$5:$D$19,MATCH(LARGE($J$5:$J$19,L6),$J$5:$J$19,0))) -> 10800 | P6: =IF(M6="","",INDEX($E$5:$E$19,MATCH(LARGE($J$5:$J$19,L6),$J$5:$J$19,0))) -> 5611
A7: CANDELA HERNANDEZ YOLANDA | B7: Yolanda Candela | C7: 38269 | D7: 39934 | E7: 22361 | F7: =IF(A7="","",IF(E7=0,0,D7/E7)) -> 1.7858772 | G7: =IF(F7="","",IF(F7>=1,"Verde",IF(F7>=0.7,"Ámbar","Rojo"))) -> Verde | H7: 7750 | I7: 0 | J7: =IF(A7="","",F7+D7/1000000000+(100-ROW())/1000000000000) -> 1.7859171 | L7: 3 | M7: =IF(L7>COUNT($J$5:$J$19),"",INDEX($B$5:$B$19,MATCH(LARGE($J$5:$J$19,L7),$J$5:$J$19,0))) -> Yolanda Candela | N7: =IF(M7="","",INDEX($F$5:$F$19,MATCH(LARGE($J$5:$J$19,L7),$J$5:$J$19,0))) -> 1.7858772 | O7: =IF(M7="","",INDEX($D$5:$D$19,MATCH(LARGE($J$5:$J$19,L7),$J$5:$J$19,0))) -> 39934 | P7: =IF(M7="","",INDEX($E$5:$E$19,MATCH(LARGE($J$5:$J$19,L7),$J$5:$J$19,0))) -> 22361
A8: GARCIA RUIZ MONICA ALEXANDRA | B8: Mónica A. García | C8: 25763 | D8: 20362 | E8: 12000 | F8: =IF(A8="","",IF(E8=0,0,D8/E8)) -> 1.6968333 | G8: =IF(F8="","",IF(F8>=1,"Verde",IF(F8>=0.7,"Ámbar","Rojo"))) -> Verde | H8: 8016 | I8: 0 | J8: =IF(A8="","",F8+D8/1000000000+(100-ROW())/1000000000000) -> 1.6968537 | L8: 4 | M8: =IF(L8>COUNT($J$5:$J$19),"",INDEX($B$5:$B$19,MATCH(LARGE($J$5:$J$19,L8),$J$5:$J$19,0))) -> Mónica A. García | N8: =IF(M8="","",INDEX($F$5:$F$19,MATCH(LARGE($J$5:$J$19,L8),$J$5:$J$19,0))) -> 1.6968333 | O8: =IF(M8="","",INDEX($D$5:$D$19,MATCH(LARGE($J$5:$J$19,L8),$J$5:$J$19,0))) -> 20362 | P8: =IF(M8="","",INDEX($E$5:$E$19,MATCH(LARGE($J$5:$J$19,L8),$J$5:$J$19,0))) -> 12000
A9: PEREZ RESTREPO EIDY JOANA | B9: Eidy J. Pérez | C9: 76135 | D9: 80285 | E9: 70977 | F9: =IF(A9="","",IF(E9=0,0,D9/E9)) -> 1.1311411 | G9: =IF(F9="","",IF(F9>=1,"Verde",IF(F9>=0.7,"Ámbar","Rojo"))) -> Verde | H9: 14515 | I9: 1979 | J9: =IF(A9="","",F9+D9/1000000000+(100-ROW())/1000000000000) -> 1.1312214 | L9: 5 | M9: =IF(L9>COUNT($J$5:$J$19),"",INDEX($B$5:$B$19,MATCH(LARGE($J$5:$J$19,L9),$J$5:$J$19,0))) -> Eidy J. Pérez | N9: =IF(M9="","",INDEX($F$5:$F$19,MATCH(LARGE($J$5:$J$19,L9),$J$5:$J$19,0))) -> 1.1311411 | O9: =IF(M9="","",INDEX($D$5:$D$19,MATCH(LARGE($J$5:$J$19,L9),$J$5:$J$19,0))) -> 80285 | P9: =IF(M9="","",INDEX($E$5:$E$19,MATCH(LARGE($J$5:$J$19,L9),$J$5:$J$19,0))) -> 70977
A10: SALAZAR LOPEZ EDWAR ANDRES | B10: Edwar A. Salazar | C10: 21078 | D10: 14678 | E10: 21500 | F10: =IF(A10="","",IF(E10=0,0,D10/E10)) -> 0.68269767 | G10: =IF(F10="","",IF(F10>=1,"Verde",IF(F10>=0.7,"Ámbar","Rojo"))) -> Rojo | H10: 6400 | I10: 0 | J10: =IF(A10="","",F10+D10/1000000000+(100-ROW())/1000000000000) -> 0.68271235 | L10: 6 | M10: =IF(L10>COUNT($J$5:$J$19),"",INDEX($B$5:$B$19,MATCH(LARGE($J$5:$J$19,L10),$J$5:$J$19,0))) -> Edwar A. Salazar | N10: =IF(M10="","",INDEX($F$5:$F$19,MATCH(LARGE($J$5:$J$19,L10),$J$5:$J$19,0))) -> 0.68269767 | O10: =IF(M10="","",INDEX($D$5:$D$19,MATCH(LARGE($J$5:$J$19,L10),$J$5:$J$19,0))) -> 14678 | P10: =IF(M10="","",INDEX($E$5:$E$19,MATCH(LARGE($J$5:$J$19,L10),$J$5:$J$19,0))) -> 21500
A11: ACOSTA HERNANDEZ HENRY ALEJANDRO | B11: Henry A. Acosta | C11: 14822 | D11: 6805 | E11: 11596 | F11: =IF(A11="","",IF(E11=0,0,D11/E11)) -> 0.58684029 | G11: =IF(F11="","",IF(F11>=1,"Verde",IF(F11>=0.7,"Ámbar","Rojo"))) -> Rojo | H11: 8016 | I11: 0 | J11: =IF(A11="","",F11+D11/1000000000+(100-ROW())/1000000000000) -> 0.58684709 | L11: 7 | M11: =IF(L11>COUNT($J$5:$J$19),"",INDEX($B$5:$B$19,MATCH(LARGE($J$5:$J$19,L11),$J$5:$J$19,0))) -> Henry A. Acosta | N11: =IF(M11="","",INDEX($F$5:$F$19,MATCH(LARGE($J$5:$J$19,L11),$J$5:$J$19,0))) -> 0.58684029 | O11: =IF(M11="","",INDEX($D$5:$D$19,MATCH(LARGE($J$5:$J$19,L11),$J$5:$J$19,0))) -> 6805 | P11: =IF(M11="","",INDEX($E$5:$E$19,MATCH(LARGE($J$5:$J$19,L11),$J$5:$J$19,0))) -> 11596
A12: VALENZUELA TORRES RONALD | B12: Ronald Valenzuela | C12: 15745 | D12: 17303 | E12: 38653 | F12: =IF(A12="","",IF(E12=0,0,D12/E12)) -> 0.4476496 | G12: =IF(F12="","",IF(F12>=1,"Verde",IF(F12>=0.7,"Ámbar","Rojo"))) -> Rojo | H12: 0 | I12: 0 | J12: =IF(A12="","",F12+D12/1000000000+(100-ROW())/1000000000000) -> 0.4476669 | L12: 8 | M12: =IF(L12>COUNT($J$5:$J$19),"",INDEX($B$5:$B$19,MATCH(LARGE($J$5:$J$19,L12),$J$5:$J$19,0))) -> Erwin A. Ríos | N12: =IF(M12="","",INDEX($F$5:$F$19,MATCH(LARGE($J$5:$J$19,L12),$J$5:$J$19,0))) -> 0.46140048 | O12: =IF(M12="","",INDEX($D$5:$D$19,MATCH(LARGE($J$5:$J$19,L12),$J$5:$J$19,0))) -> 6688 | P12: =IF(M12="","",INDEX($E$5:$E$19,MATCH(LARGE($J$5:$J$19,L12),$J$5:$J$19,0))) -> 14495
A13: MENDEZ GONZALEZ RONALD ENRIQUE | B13: Ronald E. Méndez | C13: 13157 | D13: 19032 | E13: 45720 | F13: =IF(A13="","",IF(E13=0,0,D13/E13)) -> 0.41627297 | G13: =IF(F13="","",IF(F13>=1,"Verde",IF(F13>=0.7,"Ámbar","Rojo"))) -> Rojo | H13: 0 | I13: 0 | J13: =IF(A13="","",F13+D13/1000000000+(100-ROW())/1000000000000) -> 0.416292 | L13: 9 | M13: =IF(L13>COUNT($J$5:$J$19),"",INDEX($B$5:$B$19,MATCH(LARGE($J$5:$J$19,L13),$J$5:$J$19,0))) -> Ronald Valenzuela | N13: =IF(M13="","",INDEX($F$5:$F$19,MATCH(LARGE($J$5:$J$19,L13),$J$5:$J$19,0))) -> 0.4476496 | O13: =IF(M13="","",INDEX($D$5:$D$19,MATCH(LARGE($J$5:$J$19,L13),$J$5:$J$19,0))) -> 17303 | P13: =IF(M13="","",INDEX($E$5:$E$19,MATCH(LARGE($J$5:$J$19,L13),$J$5:$J$19,0))) -> 38653
A14: RIOS NUÑEZ ERWIN ANTONIO | B14: Erwin A. Ríos | C14: 19126 | D14: 6688 | E14: 14495 | F14: =IF(A14="","",IF(E14=0,0,D14/E14)) -> 0.46140048 | G14: =IF(F14="","",IF(F14>=1,"Verde",IF(F14>=0.7,"Ámbar","Rojo"))) -> Rojo | H14: 17840 | I14: 0 | J14: =IF(A14="","",F14+D14/1000000000+(100-ROW())/1000000000000) -> 0.46140717 | L14: 10 | M14: =IF(L14>COUNT($J$5:$J$19),"",INDEX($B$5:$B$19,MATCH(LARGE($J$5:$J$19,L14),$J$5:$J$19,0))) -> Ronald E. Méndez | N14: =IF(M14="","",INDEX($F$5:$F$19,MATCH(LARGE($J$5:$J$19,L14),$J$5:$J$19,0))) -> 0.41627297 | O14: =IF(M14="","",INDEX($D$5:$D$19,MATCH(LARGE($J$5:$J$19,L14),$J$5:$J$19,0))) -> 19032 | P14: =IF(M14="","",INDEX($E$5:$E$19,MATCH(LARGE($J$5:$J$19,L14),$J$5:$J$19,0))) -> 45720
F15: =IF(A15="","",IF(E15=0,0,D15/E15)) | G15: =IF(F15="","",IF(F15>=1,"Verde",IF(F15>=0.7,"Ámbar","Rojo"))) | J15: =IF(A15="","",F15+D15/1000000000+(100-ROW())/1000000000000) | L15: 11 | M15: =IF(L15>COUNT($J$5:$J$19),"",INDEX($B$5:$B$19,MATCH(LARGE($J$5:$J$19,L15),$J$5:$J$19,0))) | N15: =IF(M15="","",INDEX($F$5:$F$19,MATCH(LARGE($J$5:$J$19,L15),$J$5:$J$19,0))) | O15: =IF(M15="","",INDEX($D$5:$D$19,MATCH(LARGE($J$5:$J$19,L15),$J$5:$J$19,0))) | P15: =IF(M15="","",INDEX($E$5:$E$19,MATCH(LARGE($J$5:$J$19,L15),$J$5:$J$19,0)))
F16: =IF(A16="","",IF(E16=0,0,D16/E16)) | G16: =IF(F16="","",IF(F16>=1,"Verde",IF(F16>=0.7,"Ámbar","Rojo"))) | J16: =IF(A16="","",F16+D16/1000000000+(100-ROW())/1000000000000) | L16: 12 | M16: =IF(L16>COUNT($J$5:$J$19),"",INDEX($B$5:$B$19,MATCH(LARGE($J$5:$J$19,L16),$J$5:$J$19,0))) | N16: =IF(M16="","",INDEX($F$5:$F$19,MATCH(LARGE($J$5:$J$19,L16),$J$5:$J$19,0))) | O16: =IF(M16="","",INDEX($D$5:$D$19,MATCH(LARGE($J$5:$J$19,L16),$J$5:$J$19,0))) | P16: =IF(M16="","",INDEX($E$5:$E$19,MATCH(LARGE($J$5:$J$19,L16),$J$5:$J$19,0)))
F17: =IF(A17="","",IF(E17=0,0,D17/E17)) | G17: =IF(F17="","",IF(F17>=1,"Verde",IF(F17>=0.7,"Ámbar","Rojo"))) | J17: =IF(A17="","",F17+D17/1000000000+(100-ROW())/1000000000000) | L17: 13 | M17: =IF(L17>COUNT($J$5:$J$19),"",INDEX($B$5:$B$19,MATCH(LARGE($J$5:$J$19,L17),$J$5:$J$19,0))) | N17: =IF(M17="","",INDEX($F$5:$F$19,MATCH(LARGE($J$5:$J$19,L17),$J$5:$J$19,0))) | O17: =IF(M17="","",INDEX($D$5:$D$19,MATCH(LARGE($J$5:$J$19,L17),$J$5:$J$19,0))) | P17: =IF(M17="","",INDEX($E$5:$E$19,MATCH(LARGE($J$5:$J$19,L17),$J$5:$J$19,0)))
F18: =IF(A18="","",IF(E18=0,0,D18/E18)) | G18: =IF(F18="","",IF(F18>=1,"Verde",IF(F18>=0.7,"Ámbar","Rojo"))) | J18: =IF(A18="","",F18+D18/1000000000+(100-ROW())/1000000000000) | L18: 14 | M18: =IF(L18>COUNT($J$5:$J$19),"",INDEX($B$5:$B$19,MATCH(LARGE($J$5:$J$19,L18),$J$5:$J$19,0))) | N18: =IF(M18="","",INDEX($F$5:$F$19,MATCH(LARGE($J$5:$J$19,L18),$J$5:$J$19,0))) | O18: =IF(M18="","",INDEX($D$5:$D$19,MATCH(LARGE($J$5:$J$19,L18),$J$5:$J$19,0))) | P18: =IF(M18="","",INDEX($E$5:$E$19,MATCH(LARGE($J$5:$J$19,L18),$J$5:$J$19,0)))
F19: =IF(A19="","",IF(E19=0,0,D19/E19)) | G19: =IF(F19="","",IF(F19>=1,"Verde",IF(F19>=0.7,"Ámbar","Rojo"))) | J19: =IF(A19="","",F19+D19/1000000000+(100-ROW())/1000000000000) | L19: 15 | M19: =IF(L19>COUNT($J$5:$J$19),"",INDEX($B$5:$B$19,MATCH(LARGE($J$5:$J$19,L19),$J$5:$J$19,0))) | N19: =IF(M19="","",INDEX($F$5:$F$19,MATCH(LARGE($J$5:$J$19,L19),$J$5:$J$19,0))) | O19: =IF(M19="","",INDEX($D$5:$D$19,MATCH(LARGE($J$5:$J$19,L19),$J$5:$J$19,0))) | P19: =IF(M19="","",INDEX($E$5:$E$19,MATCH(LARGE($J$5:$J$19,L19),$J$5:$J$19,0)))
A20: TOTAL CANAL | B20: =COUNTA(A5:A19)&" RSM" -> 10 RSM | C20: =SUM(C5:C19) -> 236351 | D20: =SUM(D5:D19) -> 227016 | E20: =SUM(E5:E19) -> 248524 | F20: =IF(E20=0,0,D20/E20) -> 0.91345705 | G20: =IF(F20>=1,"Verde",IF(F20>=0.7,"Ámbar","Rojo")) -> Ámbar | H20: =SUM(H5:H19) -> 62537 | I20: =SUM(I5:I19) -> 1979
A22: KPIs canal
A23: RSM ≥100% budget | B23: =COUNTIF(F5:F19,">=1") -> 5
A24: RSM <70% budget | B24: =COUNTIFS(F5:F19,"<0.7",A5:A19,"<>") -> 0
A25: Brecha vs budget (m²) | B25: =D20-E20 -> -21508
A26: Backlog total (m²) | B26: =H20+I20 -> 64516
A27: Book-to-bill (OI/Ventas) | B27: =IFERROR(C20/D20,"") -> 1.0411204

Sheet 11_RSM_Otras_Geo
A1: 11 · RSM Otras Geografías (Exportación) – Cumplimiento y Backlog (YTD) [detalle interno – no se presenta en el deck]
A2: Diligencie la tabla izquierda; el ranking (derecha), totales y semáforos se calculan solos
A4: RSM (nombre completo) | B4: Nombre corto (slide) | C4: Order Intake m² | D4: Ventas Total m² | E4: Budget m² (paneles) | F4: % Cumpl. Budget | G4: Semáforo | H4: Backlog paneles m² | I4: Backlog otros m² | J4: Clave orden (aux) | L4: # | M4: Ranking – Fuente gráfico (mayor → menor cumplimiento) | N4: % Cumpl. | O4: Ventas m² | P4: Budget m²
A5: KAM ACOUNT MANAGER ECUADOR | B5: KAM 2 - Ecuador | C5: 0 | D5: 7006 | E5: 59844 | F5: =IF(A5="","",IF(E5=0,0,D5/E5)) -> 0.11707105 | G5: =IF(F5="","",IF(F5>=1,"Verde",IF(F5>=0.7,"Ámbar","Rojo"))) -> Rojo | H5: 0 | I5: 0 | J5: =IF(A5="","",F5+D5/1000000000+(100-ROW())/1000000000000) -> 0.11707806 | L5: 1 | M5: =IF(L5>COUNT($J$5:$J$19),"",INDEX($B$5:$B$19,MATCH(LARGE($J$5:$J$19,L5),$J$5:$J$19,0))) -> Laura M. Torres | N5: =IF(M5="","",INDEX($F$5:$F$19,MATCH(LARGE($J$5:$J$19,L5),$J$5:$J$19,0))) -> 1.3896956 | O5: =IF(M5="","",INDEX($D$5:$D$19,MATCH(LARGE($J$5:$J$19,L5),$J$5:$J$19,0))) -> 91114 | P5: =IF(M5="","",INDEX($E$5:$E$19,MATCH(LARGE($J$5:$J$19,L5),$J$5:$J$19,0))) -> 65564
A6: TORRES AREVALO LAURA MARCELA | B6: Laura M. Torres | C6: 127061 | D6: 91114 | E6: 65564 | F6: =IF(A6="","",IF(E6=0,0,D6/E6)) -> 1.3896956 | G6: =IF(F6="","",IF(F6>=1,"Verde",IF(F6>=0.7,"Ámbar","Rojo"))) -> Verde | H6: 40920 | I6: 0 | J6: =IF(A6="","",F6+D6/1000000000+(100-ROW())/1000000000000) -> 1.3897867 | L6: 2 | M6: =IF(L6>COUNT($J$5:$J$19),"",INDEX($B$5:$B$19,MATCH(LARGE($J$5:$J$19,L6),$J$5:$J$19,0))) -> María Y. Calderón | N6: =IF(M6="","",INDEX($F$5:$F$19,MATCH(LARGE($J$5:$J$19,L6),$J$5:$J$19,0))) -> 1.3598333 | O6: =IF(M6="","",INDEX($D$5:$D$19,MATCH(LARGE($J$5:$J$19,L6),$J$5:$J$19,0))) -> 26427 | P6: =IF(M6="","",INDEX($E$5:$E$19,MATCH(LARGE($J$5:$J$19,L6),$J$5:$J$19,0))) -> 19434
A7: CALDERON DURAN MARIA YELITZA | B7: María Y. Calderón | C7: 46249 | D7: 26427 | E7: 19434 | F7: =IF(A7="","",IF(E7=0,0,D7/E7)) -> 1.3598333 | G7: =IF(F7="","",IF(F7>=1,"Verde",IF(F7>=0.7,"Ámbar","Rojo"))) -> Verde | H7: 21052 | I7: 247 | J7: =IF(A7="","",F7+D7/1000000000+(100-ROW())/1000000000000) -> 1.3598597 | L7: 3 | M7: =IF(L7>COUNT($J$5:$J$19),"",INDEX($B$5:$B$19,MATCH(LARGE($J$5:$J$19,L7),$J$5:$J$19,0))) -> Carlos A. Rodríguez | N7: =IF(M7="","",INDEX($F$5:$F$19,MATCH(LARGE($J$5:$J$19,L7),$J$5:$J$19,0))) -> 1.0145874 | O7: =IF(M7="","",INDEX($D$5:$D$19,MATCH(LARGE($J$5:$J$19,L7),$J$5:$J$19,0))) -> 112953 | P7: =IF(M7="","",INDEX($E$5:$E$19,MATCH(LARGE($J$5:$J$19,L7),$J$5:$J$19,0))) -> 111329
A8: HINOSTROZA GAMBOA ERICK | B8: Erick Hinostroza | C8: 22789 | D8: 23798 | E8: 23613 | F8: =IF(A8="","",IF(E8=0,0,D8/E8)) -> 1.0078347 | G8: =IF(F8="","",IF(F8>=1,"Verde",IF(F8>=0.7,"Ámbar","Rojo"))) -> Verde | H8: 1061 | I8: 0 | J8: =IF(A8="","",F8+D8/1000000000+(100-ROW())/1000000000000) -> 1.0078585 | L8: 4 | M8: =IF(L8>COUNT($J$5:$J$19),"",INDEX($B$5:$B$19,MATCH(LARGE($J$5:$J$19,L8),$J$5:$J$19,0))) -> Erick Hinostroza | N8: =IF(M8="","",INDEX($F$5:$F$19,MATCH(LARGE($J$5:$J$19,L8),$J$5:$J$19,0))) -> 1.0078347 | O8: =IF(M8="","",INDEX($D$5:$D$19,MATCH(LARGE($J$5:$J$19,L8),$J$5:$J$19,0))) -> 23798 | P8: =IF(M8="","",INDEX($E$5:$E$19,MATCH(LARGE($J$5:$J$19,L8),$J$5:$J$19,0))) -> 23613
A9: RODRIGUEZ GONZALEZ CARLOS ALFREDO | B9: Carlos A. Rodríguez | C9: 119514 | D9: 112953 | E9: 111329 | F9: =IF(A9="","",IF(E9=0,0,D9/E9)) -> 1.0145874 | G9: =IF(F9="","",IF(F9>=1,"Verde",IF(F9>=0.7,"Ámbar","Rojo"))) -> Verde | H9: 54879 | I9: 0 | J9: =IF(A9="","",F9+D9/1000000000+(100-ROW())/1000000000000) -> 1.0147003 | L9: 5 | M9: =IF(L9>COUNT($J$5:$J$19),"",INDEX($B$5:$B$19,MATCH(LARGE($J$5:$J$19,L9),$J$5:$J$19,0))) -> Mayra A. Navas | N9: =IF(M9="","",INDEX($F$5:$F$19,MATCH(LARGE($J$5:$J$19,L9),$J$5:$J$19,0))) -> 0.62350837 | O9: =IF(M9="","",INDEX($D$5:$D$19,MATCH(LARGE($J$5:$J$19,L9),$J$5:$J$19,0))) -> 37307 | P9: =IF(M9="","",INDEX($E$5:$E$19,MATCH(LARGE($J$5:$J$19,L9),$J$5:$J$19,0))) -> 59834
A10: KAM ACOUNT MANAGER COSTA RICA | B10: KAM - Costa Rica | C10: 6245 | D10: 7471 | E10: 46495 | F10: =IF(A10="","",IF(E10=0,0,D10/E10)) -> 0.16068394 | G10: =IF(F10="","",IF(F10>=1,"Verde",IF(F10>=0.7,"Ámbar","Rojo"))) -> Rojo | H10: 0 | I10: 0 | J10: =IF(A10="","",F10+D10/1000000000+(100-ROW())/1000000000000) -> 0.16069142 | L10: 6 | M10: =IF(L10>COUNT($J$5:$J$19),"",INDEX($B$5:$B$19,MATCH(LARGE($J$5:$J$19,L10),$J$5:$J$19,0))) -> KAM - Costa Rica | N10: =IF(M10="","",INDEX($F$5:$F$19,MATCH(LARGE($J$5:$J$19,L10),$J$5:$J$19,0))) -> 0.16068394 | O10: =IF(M10="","",INDEX($D$5:$D$19,MATCH(LARGE($J$5:$J$19,L10),$J$5:$J$19,0))) -> 7471 | P10: =IF(M10="","",INDEX($E$5:$E$19,MATCH(LARGE($J$5:$J$19,L10),$J$5:$J$19,0))) -> 46495
A11: NAVAS ESCOBAR MAYRA ALEJANDRA | B11: Mayra A. Navas | C11: =45379 -> 45379 | D11: =37307 -> 37307 | E11: =59834 -> 59834 | F11: =IF(A11="","",IF(E11=0,0,D11/E11)) -> 0.62350837 | G11: =IF(F11="","",IF(F11>=1,"Verde",IF(F11>=0.7,"Ámbar","Rojo"))) -> Rojo | H11: 18220 | I11: 333 | J11: =IF(A11="","",F11+D11/1000000000+(100-ROW())/1000000000000) -> 0.62354568 | L11: 7 | M11: =IF(L11>COUNT($J$5:$J$19),"",INDEX($B$5:$B$19,MATCH(LARGE($J$5:$J$19,L11),$J$5:$J$19,0))) -> KAM 2 - Ecuador | N11: =IF(M11="","",INDEX($F$5:$F$19,MATCH(LARGE($J$5:$J$19,L11),$J$5:$J$19,0))) -> 0.11707105 | O11: =IF(M11="","",INDEX($D$5:$D$19,MATCH(LARGE($J$5:$J$19,L11),$J$5:$J$19,0))) -> 7006 | P11: =IF(M11="","",INDEX($E$5:$E$19,MATCH(LARGE($J$5:$J$19,L11),$J$5:$J$19,0))) -> 59844
A12: FERNANDINI MOLINA ANGIE PAOLA | B12: Angie P. Fernandini | C12: 0 | D12: 0 | E12: 2000 | F12: =IF(A12="","",IF(E12=0,0,D12/E12)) -> 0 | G12: =IF(F12="","",IF(F12>=1,"Verde",IF(F12>=0.7,"Ámbar","Rojo"))) -> Rojo | H12: 0 | I12: 0 | J12: =IF(A12="","",F12+D12/1000000000+(100-ROW())/1000000000000) -> 8.8e-11 | L12: 8 | M12: =IF(L12>COUNT($J$5:$J$19),"",INDEX($B$5:$B$19,MATCH(LARGE($J$5:$J$19,L12),$J$5:$J$19,0))) -> Angie P. Fernandini | N12: =IF(M12="","",INDEX($F$5:$F$19,MATCH(LARGE($J$5:$J$19,L12),$J$5:$J$19,0))) -> 0 | O12: =IF(M12="","",INDEX($D$5:$D$19,MATCH(LARGE($J$5:$J$19,L12),$J$5:$J$19,0))) -> 0 | P12: =IF(M12="","",INDEX($E$5:$E$19,MATCH(LARGE($J$5:$J$19,L12),$J$5:$J$19,0))) -> 2000
F13: =IF(A13="","",IF(E13=0,0,D13/E13)) | G13: =IF(F13="","",IF(F13>=1,"Verde",IF(F13>=0.7,"Ámbar","Rojo"))) | J13: =IF(A13="","",F13+D13/1000000000+(100-ROW())/1000000000000) | L13: 9 | M13: =IF(L13>COUNT($J$5:$J$19),"",INDEX($B$5:$B$19,MATCH(LARGE($J$5:$J$19,L13),$J$5:$J$19,0))) | N13: =IF(M13="","",INDEX($F$5:$F$19,MATCH(LARGE($J$5:$J$19,L13),$J$5:$J$19,0))) | O13: =IF(M13="","",INDEX($D$5:$D$19,MATCH(LARGE($J$5:$J$19,L13),$J$5:$J$19,0))) | P13: =IF(M13="","",INDEX($E$5:$E$19,MATCH(LARGE($J$5:$J$19,L13),$J$5:$J$19,0)))
F14: =IF(A14="","",IF(E14=0,0,D14/E14)) | G14: =IF(F14="","",IF(F14>=1,"Verde",IF(F14>=0.7,"Ámbar","Rojo"))) | J14: =IF(A14="","",F14+D14/1000000000+(100-ROW())/1000000000000) | L14: 10 | M14: =IF(L14>COUNT($J$5:$J$19),"",INDEX($B$5:$B$19,MATCH(LARGE($J$5:$J$19,L14),$J$5:$J$19,0))) | N14: =IF(M14="","",INDEX($F$5:$F$19,MATCH(LARGE($J$5:$J$19,L14),$J$5:$J$19,0))) | O14: =IF(M14="","",INDEX($D$5:$D$19,MATCH(LARGE($J$5:$J$19,L14),$J$5:$J$19,0))) | P14: =IF(M14="","",INDEX($E$5:$E$19,MATCH(LARGE($J$5:$J$19,L14),$J$5:$J$19,0)))
F15: =IF(A15="","",IF(E15=0,0,D15/E15)) | G15: =IF(F15="","",IF(F15>=1,"Verde",IF(F15>=0.7,"Ámbar","Rojo"))) | J15: =IF(A15="","",F15+D15/1000000000+(100-ROW())/1000000000000) | L15: 11 | M15: =IF(L15>COUNT($J$5:$J$19),"",INDEX($B$5:$B$19,MATCH(LARGE($J$5:$J$19,L15),$J$5:$J$19,0))) | N15: =IF(M15="","",INDEX($F$5:$F$19,MATCH(LARGE($J$5:$J$19,L15),$J$5:$J$19,0))) | O15: =IF(M15="","",INDEX($D$5:$D$19,MATCH(LARGE($J$5:$J$19,L15),$J$5:$J$19,0))) | P15: =IF(M15="","",INDEX($E$5:$E$19,MATCH(LARGE($J$5:$J$19,L15),$J$5:$J$19,0)))
F16: =IF(A16="","",IF(E16=0,0,D16/E16)) | G16: =IF(F16="","",IF(F16>=1,"Verde",IF(F16>=0.7,"Ámbar","Rojo"))) | J16: =IF(A16="","",F16+D16/1000000000+(100-ROW())/1000000000000) | L16: 12 | M16: =IF(L16>COUNT($J$5:$J$19),"",INDEX($B$5:$B$19,MATCH(LARGE($J$5:$J$19,L16),$J$5:$J$19,0))) | N16: =IF(M16="","",INDEX($F$5:$F$19,MATCH(LARGE($J$5:$J$19,L16),$J$5:$J$19,0))) | O16: =IF(M16="","",INDEX($D$5:$D$19,MATCH(LARGE($J$5:$J$19,L16),$J$5:$J$19,0))) | P16: =IF(M16="","",INDEX($E$5:$E$19,MATCH(LARGE($J$5:$J$19,L16),$J$5:$J$19,0)))
F17: =IF(A17="","",IF(E17=0,0,D17/E17)) | G17: =IF(F17="","",IF(F17>=1,"Verde",IF(F17>=0.7,"Ámbar","Rojo"))) | J17: =IF(A17="","",F17+D17/1000000000+(100-ROW())/1000000000000) | L17: 13 | M17: =IF(L17>COUNT($J$5:$J$19),"",INDEX($B$5:$B$19,MATCH(LARGE($J$5:$J$19,L17),$J$5:$J$19,0))) | N17: =IF(M17="","",INDEX($F$5:$F$19,MATCH(LARGE($J$5:$J$19,L17),$J$5:$J$19,0))) | O17: =IF(M17="","",INDEX($D$5:$D$19,MATCH(LARGE($J$5:$J$19,L17),$J$5:$J$19,0))) | P17: =IF(M17="","",INDEX($E$5:$E$19,MATCH(LARGE($J$5:$J$19,L17),$J$5:$J$19,0)))
F18: =IF(A18="","",IF(E18=0,0,D18/E18)) | G18: =IF(F18="","",IF(F18>=1,"Verde",IF(F18>=0.7,"Ámbar","Rojo"))) | J18: =IF(A18="","",F18+D18/1000000000+(100-ROW())/1000000000000) | L18: 14 | M18: =IF(L18>COUNT($J$5:$J$19),"",INDEX($B$5:$B$19,MATCH(LARGE($J$5:$J$19,L18),$J$5:$J$19,0))) | N18: =IF(M18="","",INDEX($F$5:$F$19,MATCH(LARGE($J$5:$J$19,L18),$J$5:$J$19,0))) | O18: =IF(M18="","",INDEX($D$5:$D$19,MATCH(LARGE($J$5:$J$19,L18),$J$5:$J$19,0))) | P18: =IF(M18="","",INDEX($E$5:$E$19,MATCH(LARGE($J$5:$J$19,L18),$J$5:$J$19,0)))
F19: =IF(A19="","",IF(E19=0,0,D19/E19)) | G19: =IF(F19="","",IF(F19>=1,"Verde",IF(F19>=0.7,"Ámbar","Rojo"))) | J19: =IF(A19="","",F19+D19/1000000000+(100-ROW())/1000000000000) | L19: 15 | M19: =IF(L19>COUNT($J$5:$J$19),"",INDEX($B$5:$B$19,MATCH(LARGE($J$5:$J$19,L19),$J$5:$J$19,0))) | N19: =IF(M19="","",INDEX($F$5:$F$19,MATCH(LARGE($J$5:$J$19,L19),$J$5:$J$19,0))) | O19: =IF(M19="","",INDEX($D$5:$D$19,MATCH(LARGE($J$5:$J$19,L19),$J$5:$J$19,0))) | P19: =IF(M19="","",INDEX($E$5:$E$19,MATCH(LARGE($J$5:$J$19,L19),$J$5:$J$19,0)))
A20: TOTAL CANAL | B20: =COUNTA(A5:A19)&" RSM" -> 8 RSM | C20: =SUM(C5:C19) -> 367237 | D20: =SUM(D5:D19) -> 306076 | E20: =SUM(E5:E19) -> 388113 | F20: =IF(E20=0,0,D20/E20) -> 0.78862599 | G20: =IF(F20>=1,"Verde",IF(F20>=0.7,"Ámbar","Rojo")) -> Ámbar | H20: =SUM(H5:H19) -> 136132 | I20: =SUM(I5:I19) -> 580
A22: KPIs canal
A23: RSM ≥100% budget | B23: =COUNTIF(F5:F19,">=1") -> 4
A24: RSM <70% budget | B24: =COUNTIFS(F5:F19,"<0.7",A5:A19,"<>") -> 0
A25: Brecha vs budget (m²) | B25: =D20-E20 -> -82037
A26: Backlog total (m²) | B26: =H20+I20 -> 136712
A27: Book-to-bill (OI/Ventas) | B27: =IFERROR(C20/D20,"") -> 1.1998229

Sheet 12_RSM_Cold_Storage
A1: 12 · RSM Refrigeración (Cold Storage) – Cumplimiento y Backlog (YTD) [detalle interno – no se presenta en el deck]
A2: Diligencie la tabla izquierda; el ranking (derecha), totales y semáforos se calculan solos
A4: RSM (nombre completo) | B4: Nombre corto (slide) | C4: Order Intake m² | D4: Ventas Total m² | E4: Budget m² (paneles) | F4: % Cumpl. Budget | G4: Semáforo | H4: Backlog paneles m² | I4: Backlog otros m² | J4: Clave orden (aux) | L4: # | M4: Ranking – Fuente gráfico (mayor → menor cumplimiento) | N4: % Cumpl. | O4: Ventas m² | P4: Budget m²
A5: RODRIGUEZ HENAO LAURA MARCELA | B5: Laura M. Rodríguez | C5: 20966 | D5: 5303 | E5: 4500 | F5: =IF(A5="","",IF(E5=0,0,D5/E5)) -> 1.1784444 | G5: =IF(F5="","",IF(F5>=1,"Verde",IF(F5>=0.7,"Ámbar","Rojo"))) -> Verde | H5: 15042 | I5: 468 | J5: =IF(A5="","",F5+D5/1000000000+(100-ROW())/1000000000000) -> 1.1784497 | L5: 1 | M5: =IF(L5>COUNT($J$5:$J$19),"",INDEX($B$5:$B$19,MATCH(LARGE($J$5:$J$19,L5),$J$5:$J$19,0))) -> Sandra M. Uribe | N5: =IF(M5="","",INDEX($F$5:$F$19,MATCH(LARGE($J$5:$J$19,L5),$J$5:$J$19,0))) -> 1.5552 | O5: =IF(M5="","",INDEX($D$5:$D$19,MATCH(LARGE($J$5:$J$19,L5),$J$5:$J$19,0))) -> 3888 | P5: =IF(M5="","",INDEX($E$5:$E$19,MATCH(LARGE($J$5:$J$19,L5),$J$5:$J$19,0))) -> 2500
A6: MENENDEZ ICABALCETA JUAN CARLOS | B6: Juan C. Menéndez | C6: 0 | D6: 0 | E6: 3000 | F6: =IF(A6="","",IF(E6=0,0,D6/E6)) -> 0 | G6: =IF(F6="","",IF(F6>=1,"Verde",IF(F6>=0.7,"Ámbar","Rojo"))) -> Rojo | H6: 0 | I6: 0 | J6: =IF(A6="","",F6+D6/1000000000+(100-ROW())/1000000000000) -> 9.4e-11 | L6: 2 | M6: =IF(L6>COUNT($J$5:$J$19),"",INDEX($B$5:$B$19,MATCH(LARGE($J$5:$J$19,L6),$J$5:$J$19,0))) -> Laura M. Rodríguez | N6: =IF(M6="","",INDEX($F$5:$F$19,MATCH(LARGE($J$5:$J$19,L6),$J$5:$J$19,0))) -> 1.1784444 | O6: =IF(M6="","",INDEX($D$5:$D$19,MATCH(LARGE($J$5:$J$19,L6),$J$5:$J$19,0))) -> 5303 | P6: =IF(M6="","",INDEX($E$5:$E$19,MATCH(LARGE($J$5:$J$19,L6),$J$5:$J$19,0))) -> 4500
A7: URIBE JIMENEZ SANDRA MILENA | B7: Sandra M. Uribe | C7: 15459 | D7: 3888 | E7: 2500 | F7: =IF(A7="","",IF(E7=0,0,D7/E7)) -> 1.5552 | G7: =IF(F7="","",IF(F7>=1,"Verde",IF(F7>=0.7,"Ámbar","Rojo"))) -> Verde | H7: 12191 | I7: 2734 | J7: =IF(A7="","",F7+D7/1000000000+(100-ROW())/1000000000000) -> 1.5552039 | L7: 3 | M7: =IF(L7>COUNT($J$5:$J$19),"",INDEX($B$5:$B$19,MATCH(LARGE($J$5:$J$19,L7),$J$5:$J$19,0))) -> Juan C. Menéndez | N7: =IF(M7="","",INDEX($F$5:$F$19,MATCH(LARGE($J$5:$J$19,L7),$J$5:$J$19,0))) -> 0 | O7: =IF(M7="","",INDEX($D$5:$D$19,MATCH(LARGE($J$5:$J$19,L7),$J$5:$J$19,0))) -> 0 | P7: =IF(M7="","",INDEX($E$5:$E$19,MATCH(LARGE($J$5:$J$19,L7),$J$5:$J$19,0))) -> 3000
F8: =IF(A8="","",IF(E8=0,0,D8/E8)) | G8: =IF(F8="","",IF(F8>=1,"Verde",IF(F8>=0.7,"Ámbar","Rojo"))) | J8: =IF(A8="","",F8+D8/1000000000+(100-ROW())/1000000000000) | L8: 4 | M8: =IF(L8>COUNT($J$5:$J$19),"",INDEX($B$5:$B$19,MATCH(LARGE($J$5:$J$19,L8),$J$5:$J$19,0))) | N8: =IF(M8="","",INDEX($F$5:$F$19,MATCH(LARGE($J$5:$J$19,L8),$J$5:$J$19,0))) | O8: =IF(M8="","",INDEX($D$5:$D$19,MATCH(LARGE($J$5:$J$19,L8),$J$5:$J$19,0))) | P8: =IF(M8="","",INDEX($E$5:$E$19,MATCH(LARGE($J$5:$J$19,L8),$J$5:$J$19,0)))
F9: =IF(A9="","",IF(E9=0,0,D9/E9)) | G9: =IF(F9="","",IF(F9>=1,"Verde",IF(F9>=0.7,"Ámbar","Rojo"))) | J9: =IF(A9="","",F9+D9/1000000000+(100-ROW())/1000000000000) | L9: 5 | M9: =IF(L9>COUNT($J$5:$J$19),"",INDEX($B$5:$B$19,MATCH(LARGE($J$5:$J$19,L9),$J$5:$J$19,0))) | N9: =IF(M9="","",INDEX($F$5:$F$19,MATCH(LARGE($J$5:$J$19,L9),$J$5:$J$19,0))) | O9: =IF(M9="","",INDEX($D$5:$D$19,MATCH(LARGE($J$5:$J$19,L9),$J$5:$J$19,0))) | P9: =IF(M9="","",INDEX($E$5:$E$19,MATCH(LARGE($J$5:$J$19,L9),$J$5:$J$19,0)))
F10: =IF(A10="","",IF(E10=0,0,D10/E10)) | G10: =IF(F10="","",IF(F10>=1,"Verde",IF(F10>=0.7,"Ámbar","Rojo"))) | J10: =IF(A10="","",F10+D10/1000000000+(100-ROW())/1000000000000) | L10: 6 | M10: =IF(L10>COUNT($J$5:$J$19),"",INDEX($B$5:$B$19,MATCH(LARGE($J$5:$J$19,L10),$J$5:$J$19,0))) | N10: =IF(M10="","",INDEX($F$5:$F$19,MATCH(LARGE($J$5:$J$19,L10),$J$5:$J$19,0))) | O10: =IF(M10="","",INDEX($D$5:$D$19,MATCH(LARGE($J$5:$J$19,L10),$J$5:$J$19,0))) | P10: =IF(M10="","",INDEX($E$5:$E$19,MATCH(LARGE($J$5:$J$19,L10),$J$5:$J$19,0)))
F11: =IF(A11="","",IF(E11=0,0,D11/E11)) | G11: =IF(F11="","",IF(F11>=1,"Verde",IF(F11>=0.7,"Ámbar","Rojo"))) | J11: =IF(A11="","",F11+D11/1000000000+(100-ROW())/1000000000000) | L11: 7 | M11: =IF(L11>COUNT($J$5:$J$19),"",INDEX($B$5:$B$19,MATCH(LARGE($J$5:$J$19,L11),$J$5:$J$19,0))) | N11: =IF(M11="","",INDEX($F$5:$F$19,MATCH(LARGE($J$5:$J$19,L11),$J$5:$J$19,0))) | O11: =IF(M11="","",INDEX($D$5:$D$19,MATCH(LARGE($J$5:$J$19,L11),$J$5:$J$19,0))) | P11: =IF(M11="","",INDEX($E$5:$E$19,MATCH(LARGE($J$5:$J$19,L11),$J$5:$J$19,0)))
F12: =IF(A12="","",IF(E12=0,0,D12/E12)) | G12: =IF(F12="","",IF(F12>=1,"Verde",IF(F12>=0.7,"Ámbar","Rojo"))) | J12: =IF(A12="","",F12+D12/1000000000+(100-ROW())/1000000000000) | L12: 8 | M12: =IF(L12>COUNT($J$5:$J$19),"",INDEX($B$5:$B$19,MATCH(LARGE($J$5:$J$19,L12),$J$5:$J$19,0))) | N12: =IF(M12="","",INDEX($F$5:$F$19,MATCH(LARGE($J$5:$J$19,L12),$J$5:$J$19,0))) | O12: =IF(M12="","",INDEX($D$5:$D$19,MATCH(LARGE($J$5:$J$19,L12),$J$5:$J$19,0))) | P12: =IF(M12="","",INDEX($E$5:$E$19,MATCH(LARGE($J$5:$J$19,L12),$J$5:$J$19,0)))
F13: =IF(A13="","",IF(E13=0,0,D13/E13)) | G13: =IF(F13="","",IF(F13>=1,"Verde",IF(F13>=0.7,"Ámbar","Rojo"))) | J13: =IF(A13="","",F13+D13/1000000000+(100-ROW())/1000000000000) | L13: 9 | M13: =IF(L13>COUNT($J$5:$J$19),"",INDEX($B$5:$B$19,MATCH(LARGE($J$5:$J$19,L13),$J$5:$J$19,0))) | N13: =IF(M13="","",INDEX($F$5:$F$19,MATCH(LARGE($J$5:$J$19,L13),$J$5:$J$19,0))) | O13: =IF(M13="","",INDEX($D$5:$D$19,MATCH(LARGE($J$5:$J$19,L13),$J$5:$J$19,0))) | P13: =IF(M13="","",INDEX($E$5:$E$19,MATCH(LARGE($J$5:$J$19,L13),$J$5:$J$19,0)))
F14: =IF(A14="","",IF(E14=0,0,D14/E14)) | G14: =IF(F14="","",IF(F14>=1,"Verde",IF(F14>=0.7,"Ámbar","Rojo"))) | J14: =IF(A14="","",F14+D14/1000000000+(100-ROW())/1000000000000) | L14: 10 | M14: =IF(L14>COUNT($J$5:$J$19),"",INDEX($B$5:$B$19,MATCH(LARGE($J$5:$J$19,L14),$J$5:$J$19,0))) | N14: =IF(M14="","",INDEX($F$5:$F$19,MATCH(LARGE($J$5:$J$19,L14),$J$5:$J$19,0))) | O14: =IF(M14="","",INDEX($D$5:$D$19,MATCH(LARGE($J$5:$J$19,L14),$J$5:$J$19,0))) | P14: =IF(M14="","",INDEX($E$5:$E$19,MATCH(LARGE($J$5:$J$19,L14),$J$5:$J$19,0)))
F15: =IF(A15="","",IF(E15=0,0,D15/E15)) | G15: =IF(F15="","",IF(F15>=1,"Verde",IF(F15>=0.7,"Ámbar","Rojo"))) | J15: =IF(A15="","",F15+D15/1000000000+(100-ROW())/1000000000000) | L15: 11 | M15: =IF(L15>COUNT($J$5:$J$19),"",INDEX($B$5:$B$19,MATCH(LARGE($J$5:$J$19,L15),$J$5:$J$19,0))) | N15: =IF(M15="","",INDEX($F$5:$F$19,MATCH(LARGE($J$5:$J$19,L15),$J$5:$J$19,0))) | O15: =IF(M15="","",INDEX($D$5:$D$19,MATCH(LARGE($J$5:$J$19,L15),$J$5:$J$19,0))) | P15: =IF(M15="","",INDEX($E$5:$E$19,MATCH(LARGE($J$5:$J$19,L15),$J$5:$J$19,0)))
F16: =IF(A16="","",IF(E16=0,0,D16/E16)) | G16: =IF(F16="","",IF(F16>=1,"Verde",IF(F16>=0.7,"Ámbar","Rojo"))) | J16: =IF(A16="","",F16+D16/1000000000+(100-ROW())/1000000000000) | L16: 12 | M16: =IF(L16>COUNT($J$5:$J$19),"",INDEX($B$5:$B$19,MATCH(LARGE($J$5:$J$19,L16),$J$5:$J$19,0))) | N16: =IF(M16="","",INDEX($F$5:$F$19,MATCH(LARGE($J$5:$J$19,L16),$J$5:$J$19,0))) | O16: =IF(M16="","",INDEX($D$5:$D$19,MATCH(LARGE($J$5:$J$19,L16),$J$5:$J$19,0))) | P16: =IF(M16="","",INDEX($E$5:$E$19,MATCH(LARGE($J$5:$J$19,L16),$J$5:$J$19,0)))
F17: =IF(A17="","",IF(E17=0,0,D17/E17)) | G17: =IF(F17="","",IF(F17>=1,"Verde",IF(F17>=0.7,"Ámbar","Rojo"))) | J17: =IF(A17="","",F17+D17/1000000000+(100-ROW())/1000000000000) | L17: 13 | M17: =IF(L17>COUNT($J$5:$J$19),"",INDEX($B$5:$B$19,MATCH(LARGE($J$5:$J$19,L17),$J$5:$J$19,0))) | N17: =IF(M17="","",INDEX($F$5:$F$19,MATCH(LARGE($J$5:$J$19,L17),$J$5:$J$19,0))) | O17: =IF(M17="","",INDEX($D$5:$D$19,MATCH(LARGE($J$5:$J$19,L17),$J$5:$J$19,0))) | P17: =IF(M17="","",INDEX($E$5:$E$19,MATCH(LARGE($J$5:$J$19,L17),$J$5:$J$19,0)))
F18: =IF(A18="","",IF(E18=0,0,D18/E18)) | G18: =IF(F18="","",IF(F18>=1,"Verde",IF(F18>=0.7,"Ámbar","Rojo"))) | J18: =IF(A18="","",F18+D18/1000000000+(100-ROW())/1000000000000) | L18: 14 | M18: =IF(L18>COUNT($J$5:$J$19),"",INDEX($B$5:$B$19,MATCH(LARGE($J$5:$J$19,L18),$J$5:$J$19,0))) | N18: =IF(M18="","",INDEX($F$5:$F$19,MATCH(LARGE($J$5:$J$19,L18),$J$5:$J$19,0))) | O18: =IF(M18="","",INDEX($D$5:$D$19,MATCH(LARGE($J$5:$J$19,L18),$J$5:$J$19,0))) | P18: =IF(M18="","",INDEX($E$5:$E$19,MATCH(LARGE($J$5:$J$19,L18),$J$5:$J$19,0)))
F19: =IF(A19="","",IF(E19=0,0,D19/E19)) | G19: =IF(F19="","",IF(F19>=1,"Verde",IF(F19>=0.7,"Ámbar","Rojo"))) | J19: =IF(A19="","",F19+D19/1000000000+(100-ROW())/1000000000000) | L19: 15 | M19: =IF(L19>COUNT($J$5:$J$19),"",INDEX($B$5:$B$19,MATCH(LARGE($J$5:$J$19,L19),$J$5:$J$19,0))) | N19: =IF(M19="","",INDEX($F$5:$F$19,MATCH(LARGE($J$5:$J$19,L19),$J$5:$J$19,0))) | O19: =IF(M19="","",INDEX($D$5:$D$19,MATCH(LARGE($J$5:$J$19,L19),$J$5:$J$19,0))) | P19: =IF(M19="","",INDEX($E$5:$E$19,MATCH(LARGE($J$5:$J$19,L19),$J$5:$J$19,0)))
A20: TOTAL CANAL | B20: =COUNTA(A5:A19)&" RSM" -> 3 RSM | C20: =SUM(C5:C19) -> 36425 | D20: =SUM(D5:D19) -> 9191 | E20: =SUM(E5:E19) -> 10000 | F20: =IF(E20=0,0,D20/E20) -> 0.9191 | G20: =IF(F20>=1,"Verde",IF(F20>=0.7,"Ámbar","Rojo")) -> Ámbar | H20: =SUM(H5:H19) -> 27233 | I20: =SUM(I5:I19) -> 3202
A22: KPIs canal
A23: RSM ≥100% budget | B23: =COUNTIF(F5:F19,">=1") -> 2
A24: RSM <70% budget | B24: =COUNTIFS(F5:F19,"<0.7",A5:A19,"<>") -> 0
A25: Brecha vs budget (m²) | B25: =D20-E20 -> -809
A26: Backlog total (m²) | B26: =H20+I20 -> 30435
A27: Book-to-bill (OI/Ventas) | B27: =IFERROR(C20/D20,"") -> 3.9631161

Sheet 13_RSM_Site_Cali
A1: 13 · RSM Site Cali – Cumplimiento y Backlog (YTD) [detalle interno – no se presenta en el deck]
A2: Diligencie la tabla izquierda; el ranking (derecha), totales y semáforos se calculan solos
A4: RSM (nombre completo) | B4: Nombre corto (slide) | C4: Order Intake m² | D4: Ventas Total m² | E4: Budget m² (paneles) | F4: % Cumpl. Budget | G4: Semáforo | H4: Backlog paneles m² | I4: Backlog otros m² | J4: Clave orden (aux) | L4: # | M4: Ranking – Fuente gráfico (mayor → menor cumplimiento) | N4: % Cumpl. | O4: Ventas m² | P4: Budget m²
A5: ALTAMIRANO PUENTES YAZMIN | B5: Yazmín Altamirano | C5: 52792 | D5: 42195 | E5: 23401 | F5: =IF(A5="","",IF(E5=0,0,D5/E5)) -> 1.8031281 | G5: =IF(F5="","",IF(F5>=1,"Verde",IF(F5>=0.7,"Ámbar","Rojo"))) -> Verde | H5: 8580 | I5: 456 | J5: =IF(A5="","",F5+D5/1000000000+(100-ROW())/1000000000000) -> 1.8031703 | L5: 1 | M5: =IF(L5>COUNT($J$5:$J$19),"",INDEX($B$5:$B$19,MATCH(LARGE($J$5:$J$19,L5),$J$5:$J$19,0))) -> Yazmín Altamirano | N5: =IF(M5="","",INDEX($F$5:$F$19,MATCH(LARGE($J$5:$J$19,L5),$J$5:$J$19,0))) -> 1.8031281 | O5: =IF(M5="","",INDEX($D$5:$D$19,MATCH(LARGE($J$5:$J$19,L5),$J$5:$J$19,0))) -> 42195 | P5: =IF(M5="","",INDEX($E$5:$E$19,MATCH(LARGE($J$5:$J$19,L5),$J$5:$J$19,0))) -> 23401
A6: CALDERON CHANTRE DIEGO ALFONSO | B6: Diego A. Calderón | C6: =81941+5399 -> 87340 | D6: =54854+9666 -> 64520 | E6: =50460+37595 -> 88055 | F6: =IF(A6="","",IF(E6=0,0,D6/E6)) -> 0.73272387 | G6: =IF(F6="","",IF(F6>=1,"Verde",IF(F6>=0.7,"Ámbar","Rojo"))) -> Ámbar | H6: 25839 | I6: 14490 | J6: =IF(A6="","",F6+D6/1000000000+(100-ROW())/1000000000000) -> 0.73278839 | L6: 2 | M6: =IF(L6>COUNT($J$5:$J$19),"",INDEX($B$5:$B$19,MATCH(LARGE($J$5:$J$19,L6),$J$5:$J$19,0))) -> Diego A. Calderón | N6: =IF(M6="","",INDEX($F$5:$F$19,MATCH(LARGE($J$5:$J$19,L6),$J$5:$J$19,0))) -> 0.73272387 | O6: =IF(M6="","",INDEX($D$5:$D$19,MATCH(LARGE($J$5:$J$19,L6),$J$5:$J$19,0))) -> 64520 | P6: =IF(M6="","",INDEX($E$5:$E$19,MATCH(LARGE($J$5:$J$19,L6),$J$5:$J$19,0))) -> 88055
F7: =IF(A7="","",IF(E7=0,0,D7/E7)) | G7: =IF(F7="","",IF(F7>=1,"Verde",IF(F7>=0.7,"Ámbar","Rojo"))) | J7: =IF(A7="","",F7+D7/1000000000+(100-ROW())/1000000000000) | L7: 3 | M7: =IF(L7>COUNT($J$5:$J$19),"",INDEX($B$5:$B$19,MATCH(LARGE($J$5:$J$19,L7),$J$5:$J$19,0))) | N7: =IF(M7="","",INDEX($F$5:$F$19,MATCH(LARGE($J$5:$J$19,L7),$J$5:$J$19,0))) | O7: =IF(M7="","",INDEX($D$5:$D$19,MATCH(LARGE($J$5:$J$19,L7),$J$5:$J$19,0))) | P7: =IF(M7="","",INDEX($E$5:$E$19,MATCH(LARGE($J$5:$J$19,L7),$J$5:$J$19,0)))
F8: =IF(A8="","",IF(E8=0,0,D8/E8)) | G8: =IF(F8="","",IF(F8>=1,"Verde",IF(F8>=0.7,"Ámbar","Rojo"))) | J8: =IF(A8="","",F8+D8/1000000000+(100-ROW())/1000000000000) | L8: 4 | M8: =IF(L8>COUNT($J$5:$J$19),"",INDEX($B$5:$B$19,MATCH(LARGE($J$5:$J$19,L8),$J$5:$J$19,0))) | N8: =IF(M8="","",INDEX($F$5:$F$19,MATCH(LARGE($J$5:$J$19,L8),$J$5:$J$19,0))) | O8: =IF(M8="","",INDEX($D$5:$D$19,MATCH(LARGE($J$5:$J$19,L8),$J$5:$J$19,0))) | P8: =IF(M8="","",INDEX($E$5:$E$19,MATCH(LARGE($J$5:$J$19,L8),$J$5:$J$19,0)))
F9: =IF(A9="","",IF(E9=0,0,D9/E9)) | G9: =IF(F9="","",IF(F9>=1,"Verde",IF(F9>=0.7,"Ámbar","Rojo"))) | J9: =IF(A9="","",F9+D9/1000000000+(100-ROW())/1000000000000) | L9: 5 | M9: =IF(L9>COUNT($J$5:$J$19),"",INDEX($B$5:$B$19,MATCH(LARGE($J$5:$J$19,L9),$J$5:$J$19,0))) | N9: =IF(M9="","",INDEX($F$5:$F$19,MATCH(LARGE($J$5:$J$19,L9),$J$5:$J$19,0))) | O9: =IF(M9="","",INDEX($D$5:$D$19,MATCH(LARGE($J$5:$J$19,L9),$J$5:$J$19,0))) | P9: =IF(M9="","",INDEX($E$5:$E$19,MATCH(LARGE($J$5:$J$19,L9),$J$5:$J$19,0)))
F10: =IF(A10="","",IF(E10=0,0,D10/E10)) | G10: =IF(F10="","",IF(F10>=1,"Verde",IF(F10>=0.7,"Ámbar","Rojo"))) | J10: =IF(A10="","",F10+D10/1000000000+(100-ROW())/1000000000000) | L10: 6 | M10: =IF(L10>COUNT($J$5:$J$19),"",INDEX($B$5:$B$19,MATCH(LARGE($J$5:$J$19,L10),$J$5:$J$19,0))) | N10: =IF(M10="","",INDEX($F$5:$F$19,MATCH(LARGE($J$5:$J$19,L10),$J$5:$J$19,0))) | O10: =IF(M10="","",INDEX($D$5:$D$19,MATCH(LARGE($J$5:$J$19,L10),$J$5:$J$19,0))) | P10: =IF(M10="","",INDEX($E$5:$E$19,MATCH(LARGE($J$5:$J$19,L10),$J$5:$J$19,0)))
F11: =IF(A11="","",IF(E11=0,0,D11/E11)) | G11: =IF(F11="","",IF(F11>=1,"Verde",IF(F11>=0.7,"Ámbar","Rojo"))) | J11: =IF(A11="","",F11+D11/1000000000+(100-ROW())/1000000000000) | L11: 7 | M11: =IF(L11>COUNT($J$5:$J$19),"",INDEX($B$5:$B$19,MATCH(LARGE($J$5:$J$19,L11),$J$5:$J$19,0))) | N11: =IF(M11="","",INDEX($F$5:$F$19,MATCH(LARGE($J$5:$J$19,L11),$J$5:$J$19,0))) | O11: =IF(M11="","",INDEX($D$5:$D$19,MATCH(LARGE($J$5:$J$19,L11),$J$5:$J$19,0))) | P11: =IF(M11="","",INDEX($E$5:$E$19,MATCH(LARGE($J$5:$J$19,L11),$J$5:$J$19,0)))
F12: =IF(A12="","",IF(E12=0,0,D12/E12)) | G12: =IF(F12="","",IF(F12>=1,"Verde",IF(F12>=0.7,"Ámbar","Rojo"))) | J12: =IF(A12="","",F12+D12/1000000000+(100-ROW())/1000000000000) | L12: 8 | M12: =IF(L12>COUNT($J$5:$J$19),"",INDEX($B$5:$B$19,MATCH(LARGE($J$5:$J$19,L12),$J$5:$J$19,0))) | N12: =IF(M12="","",INDEX($F$5:$F$19,MATCH(LARGE($J$5:$J$19,L12),$J$5:$J$19,0))) | O12: =IF(M12="","",INDEX($D$5:$D$19,MATCH(LARGE($J$5:$J$19,L12),$J$5:$J$19,0))) | P12: =IF(M12="","",INDEX($E$5:$E$19,MATCH(LARGE($J$5:$J$19,L12),$J$5:$J$19,0)))
F13: =IF(A13="","",IF(E13=0,0,D13/E13)) | G13: =IF(F13="","",IF(F13>=1,"Verde",IF(F13>=0.7,"Ámbar","Rojo"))) | J13: =IF(A13="","",F13+D13/1000000000+(100-ROW())/1000000000000) | L13: 9 | M13: =IF(L13>COUNT($J$5:$J$19),"",INDEX($B$5:$B$19,MATCH(LARGE($J$5:$J$19,L13),$J$5:$J$19,0))) | N13: =IF(M13="","",INDEX($F$5:$F$19,MATCH(LARGE($J$5:$J$19,L13),$J$5:$J$19,0))) | O13: =IF(M13="","",INDEX($D$5:$D$19,MATCH(LARGE($J$5:$J$19,L13),$J$5:$J$19,0))) | P13: =IF(M13="","",INDEX($E$5:$E$19,MATCH(LARGE($J$5:$J$19,L13),$J$5:$J$19,0)))
F14: =IF(A14="","",IF(E14=0,0,D14/E14)) | G14: =IF(F14="","",IF(F14>=1,"Verde",IF(F14>=0.7,"Ámbar","Rojo"))) | J14: =IF(A14="","",F14+D14/1000000000+(100-ROW())/1000000000000) | L14: 10 | M14: =IF(L14>COUNT($J$5:$J$19),"",INDEX($B$5:$B$19,MATCH(LARGE($J$5:$J$19,L14),$J$5:$J$19,0))) | N14: =IF(M14="","",INDEX($F$5:$F$19,MATCH(LARGE($J$5:$J$19,L14),$J$5:$J$19,0))) | O14: =IF(M14="","",INDEX($D$5:$D$19,MATCH(LARGE($J$5:$J$19,L14),$J$5:$J$19,0))) | P14: =IF(M14="","",INDEX($E$5:$E$19,MATCH(LARGE($J$5:$J$19,L14),$J$5:$J$19,0)))
F15: =IF(A15="","",IF(E15=0,0,D15/E15)) | G15: =IF(F15="","",IF(F15>=1,"Verde",IF(F15>=0.7,"Ámbar","Rojo"))) | J15: =IF(A15="","",F15+D15/1000000000+(100-ROW())/1000000000000) | L15: 11 | M15: =IF(L15>COUNT($J$5:$J$19),"",INDEX($B$5:$B$19,MATCH(LARGE($J$5:$J$19,L15),$J$5:$J$19,0))) | N15: =IF(M15="","",INDEX($F$5:$F$19,MATCH(LARGE($J$5:$J$19,L15),$J$5:$J$19,0))) | O15: =IF(M15="","",INDEX($D$5:$D$19,MATCH(LARGE($J$5:$J$19,L15),$J$5:$J$19,0))) | P15: =IF(M15="","",INDEX($E$5:$E$19,MATCH(LARGE($J$5:$J$19,L15),$J$5:$J$19,0)))
F16: =IF(A16="","",IF(E16=0,0,D16/E16)) | G16: =IF(F16="","",IF(F16>=1,"Verde",IF(F16>=0.7,"Ámbar","Rojo"))) | J16: =IF(A16="","",F16+D16/1000000000+(100-ROW())/1000000000000) | L16: 12 | M16: =IF(L16>COUNT($J$5:$J$19),"",INDEX($B$5:$B$19,MATCH(LARGE($J$5:$J$19,L16),$J$5:$J$19,0))) | N16: =IF(M16="","",INDEX($F$5:$F$19,MATCH(LARGE($J$5:$J$19,L16),$J$5:$J$19,0))) | O16: =IF(M16="","",INDEX($D$5:$D$19,MATCH(LARGE($J$5:$J$19,L16),$J$5:$J$19,0))) | P16: =IF(M16="","",INDEX($E$5:$E$19,MATCH(LARGE($J$5:$J$19,L16),$J$5:$J$19,0)))
F17: =IF(A17="","",IF(E17=0,0,D17/E17)) | G17: =IF(F17="","",IF(F17>=1,"Verde",IF(F17>=0.7,"Ámbar","Rojo"))) | J17: =IF(A17="","",F17+D17/1000000000+(100-ROW())/1000000000000) | L17: 13 | M17: =IF(L17>COUNT($J$5:$J$19),"",INDEX($B$5:$B$19,MATCH(LARGE($J$5:$J$19,L17),$J$5:$J$19,0))) | N17: =IF(M17="","",INDEX($F$5:$F$19,MATCH(LARGE($J$5:$J$19,L17),$J$5:$J$19,0))) | O17: =IF(M17="","",INDEX($D$5:$D$19,MATCH(LARGE($J$5:$J$19,L17),$J$5:$J$19,0))) | P17: =IF(M17="","",INDEX($E$5:$E$19,MATCH(LARGE($J$5:$J$19,L17),$J$5:$J$19,0)))
F18: =IF(A18="","",IF(E18=0,0,D18/E18)) | G18: =IF(F18="","",IF(F18>=1,"Verde",IF(F18>=0.7,"Ámbar","Rojo"))) | J18: =IF(A18="","",F18+D18/1000000000+(100-ROW())/1000000000000) | L18: 14 | M18: =IF(L18>COUNT($J$5:$J$19),"",INDEX($B$5:$B$19,MATCH(LARGE($J$5:$J$19,L18),$J$5:$J$19,0))) | N18: =IF(M18="","",INDEX($F$5:$F$19,MATCH(LARGE($J$5:$J$19,L18),$J$5:$J$19,0))) | O18: =IF(M18="","",INDEX($D$5:$D$19,MATCH(LARGE($J$5:$J$19,L18),$J$5:$J$19,0))) | P18: =IF(M18="","",INDEX($E$5:$E$19,MATCH(LARGE($J$5:$J$19,L18),$J$5:$J$19,0)))
F19: =IF(A19="","",IF(E19=0,0,D19/E19)) | G19: =IF(F19="","",IF(F19>=1,"Verde",IF(F19>=0.7,"Ámbar","Rojo"))) | J19: =IF(A19="","",F19+D19/1000000000+(100-ROW())/1000000000000) | L19: 15 | M19: =IF(L19>COUNT($J$5:$J$19),"",INDEX($B$5:$B$19,MATCH(LARGE($J$5:$J$19,L19),$J$5:$J$19,0))) | N19: =IF(M19="","",INDEX($F$5:$F$19,MATCH(LARGE($J$5:$J$19,L19),$J$5:$J$19,0))) | O19: =IF(M19="","",INDEX($D$5:$D$19,MATCH(LARGE($J$5:$J$19,L19),$J$5:$J$19,0))) | P19: =IF(M19="","",INDEX($E$5:$E$19,MATCH(LARGE($J$5:$J$19,L19),$J$5:$J$19,0)))
A20: TOTAL CANAL | B20: =COUNTA(A5:A19)&" RSM" -> 2 RSM | C20: =SUM(C5:C19) -> 140132 | D20: =SUM(D5:D19) -> 106715 | E20: =SUM(E5:E19) -> 111456 | F20: =IF(E20=0,0,D20/E20) -> 0.95746303 | G20: =IF(F20>=1,"Verde",IF(F20>=0.7,"Ámbar","Rojo")) -> Ámbar | H20: =SUM(H5:H19) -> 34419 | I20: =SUM(I5:I19) -> 14946
A22: KPIs canal
A23: RSM ≥100% budget | B23: =COUNTIF(F5:F19,">=1") -> 1
A24: RSM <70% budget | B24: =COUNTIFS(F5:F19,"<0.7",A5:A19,"<>") -> 0
A25: Brecha vs budget (m²) | B25: =D20-E20 -> -4741
A26: Backlog total (m²) | B26: =H20+I20 -> 49365
A27: Book-to-bill (OI/Ventas) | B27: =IFERROR(C20/D20,"") -> 1.3131425

Sheet 14_RSM_Vtas_Alt
A1: 14 · RSM Ventas Alternativas – Cumplimiento y Backlog (YTD) [detalle interno – no se presenta en el deck]
A2: Diligencie la tabla izquierda; el ranking (derecha), totales y semáforos se calculan solos
A4: RSM (nombre completo) | B4: Nombre corto (slide) | C4: Order Intake m² | D4: Ventas Total m² | E4: Budget m² (paneles) | F4: % Cumpl. Budget | G4: Semáforo | H4: Backlog paneles m² | I4: Backlog otros m² | J4: Clave orden (aux) | L4: # | M4: Ranking – Fuente gráfico (mayor → menor cumplimiento) | N4: % Cumpl. | O4: Ventas m² | P4: Budget m²
A5: ALTAMIRANO PUENTES YAZMIN | B5: Yazmín Altamirano | C5: 850 | D5: 1752 | E5: 1118 | F5: =IF(A5="","",IF(E5=0,0,D5/E5)) -> 1.5670841 | G5: =IF(F5="","",IF(F5>=1,"Verde",IF(F5>=0.7,"Ámbar","Rojo"))) -> Verde | H5: 0 | I5: 0 | J5: =IF(A5="","",F5+D5/1000000000+(100-ROW())/1000000000000) -> 1.5670858 | L5: 1 | M5: =IF(L5>COUNT($J$5:$J$19),"",INDEX($B$5:$B$19,MATCH(LARGE($J$5:$J$19,L5),$J$5:$J$19,0))) -> Yazmín Altamirano | N5: =IF(M5="","",INDEX($F$5:$F$19,MATCH(LARGE($J$5:$J$19,L5),$J$5:$J$19,0))) -> 1.5670841 | O5: =IF(M5="","",INDEX($D$5:$D$19,MATCH(LARGE($J$5:$J$19,L5),$J$5:$J$19,0))) -> 1752 | P5: =IF(M5="","",INDEX($E$5:$E$19,MATCH(LARGE($J$5:$J$19,L5),$J$5:$J$19,0))) -> 1118
A6: QUINTANA BARRIOS JAIRO ALONSO | B6: Jairo A. Quintana | C6: 57561 | D6: 67678 | E6: 44250 | F6: =IF(A6="","",IF(E6=0,0,D6/E6)) -> 1.5294463 | G6: =IF(F6="","",IF(F6>=1,"Verde",IF(F6>=0.7,"Ámbar","Rojo"))) -> Verde | H6: 6066 | I6: 0 | J6: =IF(A6="","",F6+D6/1000000000+(100-ROW())/1000000000000) -> 1.529514 | L6: 2 | M6: =IF(L6>COUNT($J$5:$J$19),"",INDEX($B$5:$B$19,MATCH(LARGE($J$5:$J$19,L6),$J$5:$J$19,0))) -> Jairo A. Quintana | N6: =IF(M6="","",INDEX($F$5:$F$19,MATCH(LARGE($J$5:$J$19,L6),$J$5:$J$19,0))) -> 1.5294463 | O6: =IF(M6="","",INDEX($D$5:$D$19,MATCH(LARGE($J$5:$J$19,L6),$J$5:$J$19,0))) -> 67678 | P6: =IF(M6="","",INDEX($E$5:$E$19,MATCH(LARGE($J$5:$J$19,L6),$J$5:$J$19,0))) -> 44250
F7: =IF(A7="","",IF(E7=0,0,D7/E7)) | G7: =IF(F7="","",IF(F7>=1,"Verde",IF(F7>=0.7,"Ámbar","Rojo"))) | J7: =IF(A7="","",F7+D7/1000000000+(100-ROW())/1000000000000) | L7: 3 | M7: =IF(L7>COUNT($J$5:$J$19),"",INDEX($B$5:$B$19,MATCH(LARGE($J$5:$J$19,L7),$J$5:$J$19,0))) | N7: =IF(M7="","",INDEX($F$5:$F$19,MATCH(LARGE($J$5:$J$19,L7),$J$5:$J$19,0))) | O7: =IF(M7="","",INDEX($D$5:$D$19,MATCH(LARGE($J$5:$J$19,L7),$J$5:$J$19,0))) | P7: =IF(M7="","",INDEX($E$5:$E$19,MATCH(LARGE($J$5:$J$19,L7),$J$5:$J$19,0)))
F8: =IF(A8="","",IF(E8=0,0,D8/E8)) | G8: =IF(F8="","",IF(F8>=1,"Verde",IF(F8>=0.7,"Ámbar","Rojo"))) | J8: =IF(A8="","",F8+D8/1000000000+(100-ROW())/1000000000000) | L8: 4 | M8: =IF(L8>COUNT($J$5:$J$19),"",INDEX($B$5:$B$19,MATCH(LARGE($J$5:$J$19,L8),$J$5:$J$19,0))) | N8: =IF(M8="","",INDEX($F$5:$F$19,MATCH(LARGE($J$5:$J$19,L8),$J$5:$J$19,0))) | O8: =IF(M8="","",INDEX($D$5:$D$19,MATCH(LARGE($J$5:$J$19,L8),$J$5:$J$19,0))) | P8: =IF(M8="","",INDEX($E$5:$E$19,MATCH(LARGE($J$5:$J$19,L8),$J$5:$J$19,0)))
F9: =IF(A9="","",IF(E9=0,0,D9/E9)) | G9: =IF(F9="","",IF(F9>=1,"Verde",IF(F9>=0.7,"Ámbar","Rojo"))) | J9: =IF(A9="","",F9+D9/1000000000+(100-ROW())/1000000000000) | L9: 5 | M9: =IF(L9>COUNT($J$5:$J$19),"",INDEX($B$5:$B$19,MATCH(LARGE($J$5:$J$19,L9),$J$5:$J$19,0))) | N9: =IF(M9="","",INDEX($F$5:$F$19,MATCH(LARGE($J$5:$J$19,L9),$J$5:$J$19,0))) | O9: =IF(M9="","",INDEX($D$5:$D$19,MATCH(LARGE($J$5:$J$19,L9),$J$5:$J$19,0))) | P9: =IF(M9="","",INDEX($E$5:$E$19,MATCH(LARGE($J$5:$J$19,L9),$J$5:$J$19,0)))
F10: =IF(A10="","",IF(E10=0,0,D10/E10)) | G10: =IF(F10="","",IF(F10>=1,"Verde",IF(F10>=0.7,"Ámbar","Rojo"))) | J10: =IF(A10="","",F10+D10/1000000000+(100-ROW())/1000000000000) | L10: 6 | M10: =IF(L10>COUNT($J$5:$J$19),"",INDEX($B$5:$B$19,MATCH(LARGE($J$5:$J$19,L10),$J$5:$J$19,0))) | N10: =IF(M10="","",INDEX($F$5:$F$19,MATCH(LARGE($J$5:$J$19,L10),$J$5:$J$19,0))) | O10: =IF(M10="","",INDEX($D$5:$D$19,MATCH(LARGE($J$5:$J$19,L10),$J$5:$J$19,0))) | P10: =IF(M10="","",INDEX($E$5:$E$19,MATCH(LARGE($J$5:$J$19,L10),$J$5:$J$19,0)))
F11: =IF(A11="","",IF(E11=0,0,D11/E11)) | G11: =IF(F11="","",IF(F11>=1,"Verde",IF(F11>=0.7,"Ámbar","Rojo"))) | J11: =IF(A11="","",F11+D11/1000000000+(100-ROW())/1000000000000) | L11: 7 | M11: =IF(L11>COUNT($J$5:$J$19),"",INDEX($B$5:$B$19,MATCH(LARGE($J$5:$J$19,L11),$J$5:$J$19,0))) | N11: =IF(M11="","",INDEX($F$5:$F$19,MATCH(LARGE($J$5:$J$19,L11),$J$5:$J$19,0))) | O11: =IF(M11="","",INDEX($D$5:$D$19,MATCH(LARGE($J$5:$J$19,L11),$J$5:$J$19,0))) | P11: =IF(M11="","",INDEX($E$5:$E$19,MATCH(LARGE($J$5:$J$19,L11),$J$5:$J$19,0)))
F12: =IF(A12="","",IF(E12=0,0,D12/E12)) | G12: =IF(F12="","",IF(F12>=1,"Verde",IF(F12>=0.7,"Ámbar","Rojo"))) | J12: =IF(A12="","",F12+D12/1000000000+(100-ROW())/1000000000000) | L12: 8 | M12: =IF(L12>COUNT($J$5:$J$19),"",INDEX($B$5:$B$19,MATCH(LARGE($J$5:$J$19,L12),$J$5:$J$19,0))) | N12: =IF(M12="","",INDEX($F$5:$F$19,MATCH(LARGE($J$5:$J$19,L12),$J$5:$J$19,0))) | O12: =IF(M12="","",INDEX($D$5:$D$19,MATCH(LARGE($J$5:$J$19,L12),$J$5:$J$19,0))) | P12: =IF(M12="","",INDEX($E$5:$E$19,MATCH(LARGE($J$5:$J$19,L12),$J$5:$J$19,0)))
F13: =IF(A13="","",IF(E13=0,0,D13/E13)) | G13: =IF(F13="","",IF(F13>=1,"Verde",IF(F13>=0.7,"Ámbar","Rojo"))) | J13: =IF(A13="","",F13+D13/1000000000+(100-ROW())/1000000000000) | L13: 9 | M13: =IF(L13>COUNT($J$5:$J$19),"",INDEX($B$5:$B$19,MATCH(LARGE($J$5:$J$19,L13),$J$5:$J$19,0))) | N13: =IF(M13="","",INDEX($F$5:$F$19,MATCH(LARGE($J$5:$J$19,L13),$J$5:$J$19,0))) | O13: =IF(M13="","",INDEX($D$5:$D$19,MATCH(LARGE($J$5:$J$19,L13),$J$5:$J$19,0))) | P13: =IF(M13="","",INDEX($E$5:$E$19,MATCH(LARGE($J$5:$J$19,L13),$J$5:$J$19,0)))
F14: =IF(A14="","",IF(E14=0,0,D14/E14)) | G14: =IF(F14="","",IF(F14>=1,"Verde",IF(F14>=0.7,"Ámbar","Rojo"))) | J14: =IF(A14="","",F14+D14/1000000000+(100-ROW())/1000000000000) | L14: 10 | M14: =IF(L14>COUNT($J$5:$J$19),"",INDEX($B$5:$B$19,MATCH(LARGE($J$5:$J$19,L14),$J$5:$J$19,0))) | N14: =IF(M14="","",INDEX($F$5:$F$19,MATCH(LARGE($J$5:$J$19,L14),$J$5:$J$19,0))) | O14: =IF(M14="","",INDEX($D$5:$D$19,MATCH(LARGE($J$5:$J$19,L14),$J$5:$J$19,0))) | P14: =IF(M14="","",INDEX($E$5:$E$19,MATCH(LARGE($J$5:$J$19,L14),$J$5:$J$19,0)))
F15: =IF(A15="","",IF(E15=0,0,D15/E15)) | G15: =IF(F15="","",IF(F15>=1,"Verde",IF(F15>=0.7,"Ámbar","Rojo"))) | J15: =IF(A15="","",F15+D15/1000000000+(100-ROW())/1000000000000) | L15: 11 | M15: =IF(L15>COUNT($J$5:$J$19),"",INDEX($B$5:$B$19,MATCH(LARGE($J$5:$J$19,L15),$J$5:$J$19,0))) | N15: =IF(M15="","",INDEX($F$5:$F$19,MATCH(LARGE($J$5:$J$19,L15),$J$5:$J$19,0))) | O15: =IF(M15="","",INDEX($D$5:$D$19,MATCH(LARGE($J$5:$J$19,L15),$J$5:$J$19,0))) | P15: =IF(M15="","",INDEX($E$5:$E$19,MATCH(LARGE($J$5:$J$19,L15),$J$5:$J$19,0)))
F16: =IF(A16="","",IF(E16=0,0,D16/E16)) | G16: =IF(F16="","",IF(F16>=1,"Verde",IF(F16>=0.7,"Ámbar","Rojo"))) | J16: =IF(A16="","",F16+D16/1000000000+(100-ROW())/1000000000000) | L16: 12 | M16: =IF(L16>COUNT($J$5:$J$19),"",INDEX($B$5:$B$19,MATCH(LARGE($J$5:$J$19,L16),$J$5:$J$19,0))) | N16: =IF(M16="","",INDEX($F$5:$F$19,MATCH(LARGE($J$5:$J$19,L16),$J$5:$J$19,0))) | O16: =IF(M16="","",INDEX($D$5:$D$19,MATCH(LARGE($J$5:$J$19,L16),$J$5:$J$19,0))) | P16: =IF(M16="","",INDEX($E$5:$E$19,MATCH(LARGE($J$5:$J$19,L16),$J$5:$J$19,0)))
F17: =IF(A17="","",IF(E17=0,0,D17/E17)) | G17: =IF(F17="","",IF(F17>=1,"Verde",IF(F17>=0.7,"Ámbar","Rojo"))) | J17: =IF(A17="","",F17+D17/1000000000+(100-ROW())/1000000000000) | L17: 13 | M17: =IF(L17>COUNT($J$5:$J$19),"",INDEX($B$5:$B$19,MATCH(LARGE($J$5:$J$19,L17),$J$5:$J$19,0))) | N17: =IF(M17="","",INDEX($F$5:$F$19,MATCH(LARGE($J$5:$J$19,L17),$J$5:$J$19,0))) | O17: =IF(M17="","",INDEX($D$5:$D$19,MATCH(LARGE($J$5:$J$19,L17),$J$5:$J$19,0))) | P17: =IF(M17="","",INDEX($E$5:$E$19,MATCH(LARGE($J$5:$J$19,L17),$J$5:$J$19,0)))
F18: =IF(A18="","",IF(E18=0,0,D18/E18)) | G18: =IF(F18="","",IF(F18>=1,"Verde",IF(F18>=0.7,"Ámbar","Rojo"))) | J18: =IF(A18="","",F18+D18/1000000000+(100-ROW())/1000000000000) | L18: 14 | M18: =IF(L18>COUNT($J$5:$J$19),"",INDEX($B$5:$B$19,MATCH(LARGE($J$5:$J$19,L18),$J$5:$J$19,0))) | N18: =IF(M18="","",INDEX($F$5:$F$19,MATCH(LARGE($J$5:$J$19,L18),$J$5:$J$19,0))) | O18: =IF(M18="","",INDEX($D$5:$D$19,MATCH(LARGE($J$5:$J$19,L18),$J$5:$J$19,0))) | P18: =IF(M18="","",INDEX($E$5:$E$19,MATCH(LARGE($J$5:$J$19,L18),$J$5:$J$19,0)))
F19: =IF(A19="","",IF(E19=0,0,D19/E19)) | G19: =IF(F19="","",IF(F19>=1,"Verde",IF(F19>=0.7,"Ámbar","Rojo"))) | J19: =IF(A19="","",F19+D19/1000000000+(100-ROW())/1000000000000) | L19: 15 | M19: =IF(L19>COUNT($J$5:$J$19),"",INDEX($B$5:$B$19,MATCH(LARGE($J$5:$J$19,L19),$J$5:$J$19,0))) | N19: =IF(M19="","",INDEX($F$5:$F$19,MATCH(LARGE($J$5:$J$19,L19),$J$5:$J$19,0))) | O19: =IF(M19="","",INDEX($D$5:$D$19,MATCH(LARGE($J$5:$J$19,L19),$J$5:$J$19,0))) | P19: =IF(M19="","",INDEX($E$5:$E$19,MATCH(LARGE($J$5:$J$19,L19),$J$5:$J$19,0)))
A20: TOTAL CANAL | B20: =COUNTA(A5:A19)&" RSM" -> 2 RSM | C20: =SUM(C5:C19) -> 58411 | D20: =SUM(D5:D19) -> 69430 | E20: =SUM(E5:E19) -> 45368 | F20: =IF(E20=0,0,D20/E20) -> 1.5303738 | G20: =IF(F20>=1,"Verde",IF(F20>=0.7,"Ámbar","Rojo")) -> Verde | H20: =SUM(H5:H19) -> 6066 | I20: =SUM(I5:I19) -> 0
A22: KPIs canal
A23: RSM ≥100% budget | B23: =COUNTIF(F5:F19,">=1") -> 2
A24: RSM <70% budget | B24: =COUNTIFS(F5:F19,"<0.7",A5:A19,"<>") -> 0
A25: Brecha vs budget (m²) | B25: =D20-E20 -> 24062
A26: Backlog total (m²) | B26: =H20+I20 -> 6066
A27: Book-to-bill (OI/Ventas) | B27: =IFERROR(C20/D20,"") -> 0.84129339

Sheet 15_Highlights
A1: 15 · Highlights septiembre – Comercial
A2: KPIs de gestión comercial e hitos del mes
A4: KPI | B4: Valor | C4: Unidad / detalle
A5: Visitas a clientes | B5: 218 | C5: visitas
A6: Clientes nuevos | B6: 26 | C6: clientes
A7: m² clientes nuevos | B7: 7400 | C7: m²
A8: USD clientes nuevos | B8: 197235 | C8: USD
A9: Personas capacitadas | B9: 122 | C9: personas (clientes + portafolio cold storage)
A10: Ferias / eventos | B10: 2 | C10: eventos
A11: m² especificados en paneles | B11: 163801 | C11: m²
A12: m² especificados línea arquitectónica | B12: 49626 | C12: m²
A13: USD promedio por cliente nuevo | B13: =IFERROR(B8/B6,0) -> 7585.9615
A14: m² especificados – total | B14: =B11+B12 -> 213427
A16: Hito | B16: Qué se hizo | C16: Impacto / siguiente paso
A17: Evento Binacional – Cúcuta | B17: Participación en rueda de negocios conectando empresas colombianas con compradores venezolanos | C17: Pipeline de nuevas oportunidades en Venezuela; seguimiento a contactos
A18: Formación de clientes | B18: Capacitaciones a clientes y portafolio general / cold storage (122 personas); portafolio cold storage para Grupo Nutresa | C18: Especificación temprana y fidelización de cuentas clave
A19: Proyecto destacado – Smartfit | B19: Fachada Smartfit 599 m² | C19: Referencia arquitectónica para retail / fitness
A20: Proyecto destacado – Dollarcity Mamatoco | B20: Suministro de solución de cubierta para nueva tienda | C20: Replicable al plan de expansión de la cadena

Sheet Pipeline
A1: Pipeline de proyectos – Industrial y Distribución (input)
A2: Una fila por proyecto. Las columnas grises son auxiliares (no editar).
A4: Criterio Top Opportunities (USD o m2) | C4: USD
A6: Segmento | B6: Cliente | C6: Proyecto | D6: Responsable | E6: País | F6: Portafolio | G6: m² | H6: USD | I6: Estado | J6: % Cierre | K6: Fecha cierre proy. | L6: Valor ponderado USD | M6: Clave Top Opps Ind | N6: Clave Top Opps Dis | O6: Clave m² Ind | P6: Clave m² Dis
A7: Industrial | B7: Construplan | C7: Walmart | D7: Carlos Rodriguez | E7: Guatemala | F7: King Wall / King Frio / King Roof | G7: 100000 | H7: 2787794 | I7: Specification | J7: 0.75 | K7: Noviembre | L7: =IF(J7="","",H7*J7) -> 2090845.5 | M7: =IF(AND(A7="Industrial",I7<>"Closed Won",B7<>"Others"),IF($C$4="m2",G7,H7)+(1000-ROW())/1000000,"") -> 2787794 | N7: =IF(AND(A7="Distribución",I7<>"Closed Won",B7<>"Others"),IF($C$4="m2",G7,H7)+(1000-ROW())/1000000,"") | O7: =IF(AND(A7="Industrial",B7<>"Others"),G7+(1000-ROW())/1000000,"") -> 100000 | P7: =IF(AND(A7="Distribución",B7<>"Others"),G7+(1000-ROW())/1000000,"")
A8: Industrial | B8: Haceb | C8: Recambio | D8: Ana Arias | E8: Colombia | F8: KingWall / KingRoof | G8: 61000 | H8: 1700505 | I8: Pending | J8: 0.8 | K8: Noviembre | L8: =IF(J8="","",H8*J8) -> 1360404 | M8: =IF(AND(A8="Industrial",I8<>"Closed Won",B8<>"Others"),IF($C$4="m2",G8,H8)+(1000-ROW())/1000000,"") -> 1700505 | N8: =IF(AND(A8="Distribución",I8<>"Closed Won",B8<>"Others"),IF($C$4="m2",G8,H8)+(1000-ROW())/1000000,"") | O8: =IF(AND(A8="Industrial",B8<>"Others"),G8+(1000-ROW())/1000000,"") -> 61000.001 | P8: =IF(AND(A8="Distribución",B8<>"Others"),G8+(1000-ROW())/1000000,"")
A9: Industrial | B9: Conmetal | C9: Bodegas AMT | D9: Carlos Rodriguez | E9: Guatemala | F9: KingRoof / KingWall | G9: 50000 | H9: 1200000 | I9: Pending | J9: 0.6 | K9: Diciembre | L9: =IF(J9="","",H9*J9) -> 720000 | M9: =IF(AND(A9="Industrial",I9<>"Closed Won",B9<>"Others"),IF($C$4="m2",G9,H9)+(1000-ROW())/1000000,"") -> 1200000 | N9: =IF(AND(A9="Distribución",I9<>"Closed Won",B9<>"Others"),IF($C$4="m2",G9,H9)+(1000-ROW())/1000000,"") | O9: =IF(AND(A9="Industrial",B9<>"Others"),G9+(1000-ROW())/1000000,"") -> 50000.001 | P9: =IF(AND(A9="Distribución",B9<>"Others"),G9+(1000-ROW())/1000000,"")
A10: Industrial | B10: Imbert Dominguez | C10: INDAL-IDA | D10: Laura Torres | E10: Dominicana | F10: KingRoof / KingWall / KingFrigo | G10: 50000 | H10: 1550000 | I10: Pending | J10: 0.75 | K10: Noviembre | L10: =IF(J10="","",H10*J10) -> 1162500 | M10: =IF(AND(A10="Industrial",I10<>"Closed Won",B10<>"Others"),IF($C$4="m2",G10,H10)+(1000-ROW())/1000000,"") -> 1550000 | N10: =IF(AND(A10="Distribución",I10<>"Closed Won",B10<>"Others"),IF($C$4="m2",G10,H10)+(1000-ROW())/1000000,"") | O10: =IF(AND(A10="Industrial",B10<>"Others"),G10+(1000-ROW())/1000000,"") -> 50000.001 | P10: =IF(AND(A10="Distribución",B10<>"Others"),G10+(1000-ROW())/1000000,"")
A11: Industrial | B11: Magnetron | C11: — | D11: Julio Guerrero | E11: Colombia | F11: KingRoof, KingMetalRoof, KingWall | G11: 45000 | H11: 892114 | I11: Pending | L11: =IF(J11="","",H11*J11) | M11: =IF(AND(A11="Industrial",I11<>"Closed Won",B11<>"Others"),IF($C$4="m2",G11,H11)+(1000-ROW())/1000000,"") -> 892114 | N11: =IF(AND(A11="Distribución",I11<>"Closed Won",B11<>"Others"),IF($C$4="m2",G11,H11)+(1000-ROW())/1000000,"") | O11: =IF(AND(A11="Industrial",B11<>"Others"),G11+(1000-ROW())/1000000,"") -> 45000.001 | P11: =IF(AND(A11="Distribución",B11<>"Others"),G11+(1000-ROW())/1000000,"")
A12: Industrial | B12: Amo Contratistas | C12: Nave Lima | D12: Erick Hinestroza | E12: Perú | F12: KingRoof / KingWall | G12: 38000 | H12: 890000 | I12: Pending | L12: =IF(J12="","",H12*J12) | M12: =IF(AND(A12="Industrial",I12<>"Closed Won",B12<>"Others"),IF($C$4="m2",G12,H12)+(1000-ROW())/1000000,"") -> 890000 | N12: =IF(AND(A12="Distribución",I12<>"Closed Won",B12<>"Others"),IF($C$4="m2",G12,H12)+(1000-ROW())/1000000,"") | O12: =IF(AND(A12="Industrial",B12<>"Others"),G12+(1000-ROW())/1000000,"") -> 38000.001 | P12: =IF(AND(A12="Distribución",B12<>"Others"),G12+(1000-ROW())/1000000,"")
A13: Industrial | B13: Super Alimentos Zona Franca | C13: Fábrica | D13: Diego Calderón | E13: Colombia | F13: KingRoof / KingWall / KingFrigo | G13: 35000 | H13: 875000 | I13: Pending | L13: =IF(J13="","",H13*J13) | M13: =IF(AND(A13="Industrial",I13<>"Closed Won",B13<>"Others"),IF($C$4="m2",G13,H13)+(1000-ROW())/1000000,"") -> 875000 | N13: =IF(AND(A13="Distribución",I13<>"Closed Won",B13<>"Others"),IF($C$4="m2",G13,H13)+(1000-ROW())/1000000,"") | O13: =IF(AND(A13="Industrial",B13<>"Others"),G13+(1000-ROW())/1000000,"") -> 35000.001 | P13: =IF(AND(A13="Distribución",B13<>"Others"),G13+(1000-ROW())/1000000,"")
A14: Industrial | B14: Ministerio de Vivienda SV | C14: Casas El Salvador | D14: Carlos Rodriguez | E14: El Salvador | F14: KingRoof / KingWall | G14: 30000 | H14: 900000 | I14: Pending | L14: =IF(J14="","",H14*J14) | M14: =IF(AND(A14="Industrial",I14<>"Closed Won",B14<>"Others"),IF($C$4="m2",G14,H14)+(1000-ROW())/1000000,"") -> 900000 | N14: =IF(AND(A14="Distribución",I14<>"Closed Won",B14<>"Others"),IF($C$4="m2",G14,H14)+(1000-ROW())/1000000,"") | O14: =IF(AND(A14="Industrial",B14<>"Others"),G14+(1000-ROW())/1000000,"") -> 30000.001 | P14: =IF(AND(A14="Distribución",B14<>"Others"),G14+(1000-ROW())/1000000,"")
A15: Industrial | B15: Haceb | C15: Recambio | D15: Ana Arias | E15: Colombia | F15: KingWall / KingRoof | G15: 24000 | H15: 669120 | I15: Closed Won | L15: =IF(J15="","",H15*J15) | O15: =IF(AND(A15="Industrial",B15<>"Others"),G15+(1000-ROW())/1000000,"") -> 24000.001 | P15: =IF(AND(A15="Distribución",B15<>"Others"),G15+(1000-ROW())/1000000,"")
A16: Industrial | B16: Prosein | C16: Casa Venezuela | D16: María Yelitza Calderón | E16: Venezuela | F16: KingFrigo / KingRoof | G16: 22000 | H16: 891749 | I16: Pending | L16: =IF(J16="","",H16*J16) | M16: =IF(AND(A16="Industrial",I16<>"Closed Won",B16<>"Others"),IF($C$4="m2",G16,H16)+(1000-ROW())/1000000,"") -> 891749 | N16: =IF(AND(A16="Distribución",I16<>"Closed Won",B16<>"Others"),IF($C$4="m2",G16,H16)+(1000-ROW())/1000000,"") | O16: =IF(AND(A16="Industrial",B16<>"Others"),G16+(1000-ROW())/1000000,"") -> 22000.001 | P16: =IF(AND(A16="Distribución",B16<>"Others"),G16+(1000-ROW())/1000000,"")
A17: Industrial | B17: Remar | C17: Casa Venezuela | D17: María Yelitza Calderón | E17: Venezuela | F17: KingFrigo / KingRoof | G17: 20000 | H17: 577429 | I17: Pending | L17: =IF(J17="","",H17*J17) | M17: =IF(AND(A17="Industrial",I17<>"Closed Won",B17<>"Others"),IF($C$4="m2",G17,H17)+(1000-ROW())/1000000,"") -> 577429 | N17: =IF(AND(A17="Distribución",I17<>"Closed Won",B17<>"Others"),IF($C$4="m2",G17,H17)+(1000-ROW())/1000000,"") | O17: =IF(AND(A17="Industrial",B17<>"Others"),G17+(1000-ROW())/1000000,"") -> 20000.001 | P17: =IF(AND(A17="Distribución",B17<>"Others"),G17+(1000-ROW())/1000000,"")
A18: Industrial | B18: Cubic 33 | C18: Mapei | D18: Erick Hinestroza | E18: Perú | F18: King Wall / King Frio / King Roof | G18: 18000 | H18: 360000 | I18: Pending | L18: =IF(J18="","",H18*J18) | M18: =IF(AND(A18="Industrial",I18<>"Closed Won",B18<>"Others"),IF($C$4="m2",G18,H18)+(1000-ROW())/1000000,"") -> 360000 | N18: =IF(AND(A18="Distribución",I18<>"Closed Won",B18<>"Others"),IF($C$4="m2",G18,H18)+(1000-ROW())/1000000,"") | O18: =IF(AND(A18="Industrial",B18<>"Others"),G18+(1000-ROW())/1000000,"") -> 18000.001 | P18: =IF(AND(A18="Distribución",B18<>"Others"),G18+(1000-ROW())/1000000,"")
A19: Industrial | B19: Mecalfab | C19: Trinidad Sea Food | D19: Laura Torres | E19: Trinidad | F19: King Frio | G19: 16000 | H19: 550000 | I19: Closed Won | L19: =IF(J19="","",H19*J19) | M19: =IF(AND(A19="Industrial",I19<>"Closed Won",B19<>"Others"),IF($C$4="m2",G19,H19)+(1000-ROW())/1000000,"") | N19: =IF(AND(A19="Distribución",I19<>"Closed Won",B19<>"Others"),IF($C$4="m2",G19,H19)+(1000-ROW())/1000000,"") | O19: =IF(AND(A19="Industrial",B19<>"Others"),G19+(1000-ROW())/1000000,"") -> 16000.001 | P19: =IF(AND(A19="Distribución",B19<>"Others"),G19+(1000-ROW())/1000000,"")
A20: Industrial | B20: Conconcreto | C20: Planta Arroz Diana B/quilla | D20: Ana Arias | E20: Colombia | F20: KingWall / KingRoof | G20: 13000 | H20: 481132 | I20: Pending | L20: =IF(J20="","",H20*J20) | M20: =IF(AND(A20="Industrial",I20<>"Closed Won",B20<>"Others"),IF($C$4="m2",G20,H20)+(1000-ROW())/1000000,"") -> 481132 | N20: =IF(AND(A20="Distribución",I20<>"Closed Won",B20<>"Others"),IF($C$4="m2",G20,H20)+(1000-ROW())/1000000,"") | O20: =IF(AND(A20="Industrial",B20<>"Others"),G20+(1000-ROW())/1000000,"") -> 13000.001 | P20: =IF(AND(A20="Distribución",B20<>"Others"),G20+(1000-ROW())/1000000,"")
A21: Industrial | B21: Scadia | C21: Angar Avianca (Bogotá) | D21: Julio Guerrero | E21: Colombia | F21: KingWall / KingRoof o SS | G21: 13000 | H21: 1203774 | I21: Pending | J21: 0.6 | K21: Diciembre | L21: =IF(J21="","",H21*J21) -> 722264.4 | M21: =IF(AND(A21="Industrial",I21<>"Closed Won",B21<>"Others"),IF($C$4="m2",G21,H21)+(1000-ROW())/1000000,"") -> 1203774 | N21: =IF(AND(A21="Distribución",I21<>"Closed Won",B21<>"Others"),IF($C$4="m2",G21,H21)+(1000-ROW())/1000000,"") | O21: =IF(AND(A21="Industrial",B21<>"Others"),G21+(1000-ROW())/1000000,"") -> 13000.001 | P21: =IF(AND(A21="Distribución",B21<>"Others"),G21+(1000-ROW())/1000000,"")
A22: Industrial | B22: Dolarcity | C22: Dolarcity | D22: Julio Guerrero | E22: Colombia | F22: KingWall | G22: 12000 | H22: 408282 | I22: Pending | L22: =IF(J22="","",H22*J22) | M22: =IF(AND(A22="Industrial",I22<>"Closed Won",B22<>"Others"),IF($C$4="m2",G22,H22)+(1000-ROW())/1000000,"") -> 408282 | N22: =IF(AND(A22="Distribución",I22<>"Closed Won",B22<>"Others"),IF($C$4="m2",G22,H22)+(1000-ROW())/1000000,"") | O22: =IF(AND(A22="Industrial",B22<>"Others"),G22+(1000-ROW())/1000000,"") -> 12000.001 | P22: =IF(AND(A22="Distribución",B22<>"Others"),G22+(1000-ROW())/1000000,"")
A23: Industrial | B23: Nestlé | C23: Planta Bugalagrande | D23: Diego Calderón | E23: Colombia | F23: KingFrigo | G23: 12000 | H23: 617547 | I23: Pending | L23: =IF(J23="","",H23*J23) | M23: =IF(AND(A23="Industrial",I23<>"Closed Won",B23<>"Others"),IF($C$4="m2",G23,H23)+(1000-ROW())/1000000,"") -> 617547 | N23: =IF(AND(A23="Distribución",I23<>"Closed Won",B23<>"Others"),IF($C$4="m2",G23,H23)+(1000-ROW())/1000000,"") | O23: =IF(AND(A23="Industrial",B23<>"Others"),G23+(1000-ROW())/1000000,"") -> 12000.001 | P23: =IF(AND(A23="Distribución",B23<>"Others"),G23+(1000-ROW())/1000000,"")
A24: Industrial | B24: Metalmecánica | C24: Indulogix | D24: Carlos Rodriguez | E24: Guatemala | F24: KingWall / KingRoof | G24: 11500 | H24: 310000 | I24: Closed Won | L24: =IF(J24="","",H24*J24) | M24: =IF(AND(A24="Industrial",I24<>"Closed Won",B24<>"Others"),IF($C$4="m2",G24,H24)+(1000-ROW())/1000000,"") | N24: =IF(AND(A24="Distribución",I24<>"Closed Won",B24<>"Others"),IF($C$4="m2",G24,H24)+(1000-ROW())/1000000,"") | O24: =IF(AND(A24="Industrial",B24<>"Others"),G24+(1000-ROW())/1000000,"") -> 11500.001 | P24: =IF(AND(A24="Distribución",B24<>"Others"),G24+(1000-ROW())/1000000,"")
A25: Industrial | B25: Fluitec | C25: Nave Sein | D25: Laura Torres | E25: Dominicana | F25: KingRoof / KingWall | G25: 11000 | H25: 307000 | I25: Closed Won | L25: =IF(J25="","",H25*J25) | M25: =IF(AND(A25="Industrial",I25<>"Closed Won",B25<>"Others"),IF($C$4="m2",G25,H25)+(1000-ROW())/1000000,"") | N25: =IF(AND(A25="Distribución",I25<>"Closed Won",B25<>"Others"),IF($C$4="m2",G25,H25)+(1000-ROW())/1000000,"") | O25: =IF(AND(A25="Industrial",B25<>"Others"),G25+(1000-ROW())/1000000,"") -> 11000.001 | P25: =IF(AND(A25="Distribución",B25<>"Others"),G25+(1000-ROW())/1000000,"")
A26: Industrial | B26: Ménsula / Conconcreto | C26: Viva Suba / Claro | D26: Ana Arias | E26: Colombia | F26: KingRoof / Benchmark | G26: 10289 | H26: 1600000 | I26: Pending | L26: =IF(J26="","",H26*J26) | M26: =IF(AND(A26="Industrial",I26<>"Closed Won",B26<>"Others"),IF($C$4="m2",G26,H26)+(1000-ROW())/1000000,"") -> 1600000 | N26: =IF(AND(A26="Distribución",I26<>"Closed Won",B26<>"Others"),IF($C$4="m2",G26,H26)+(1000-ROW())/1000000,"") | O26: =IF(AND(A26="Industrial",B26<>"Others"),G26+(1000-ROW())/1000000,"") -> 10289.001 | P26: =IF(AND(A26="Distribución",B26<>"Others"),G26+(1000-ROW())/1000000,"")
A27: Industrial | B27: COPREFA | C27: Campamento Modular | D27: Erick Hinestroza | E27: Perú | F27: KingFrigo / KingRoof | G27: 8000 | H27: 290000 | I27: Pending | L27: =IF(J27="","",H27*J27) | M27: =IF(AND(A27="Industrial",I27<>"Closed Won",B27<>"Others"),IF($C$4="m2",G27,H27)+(1000-ROW())/1000000,"") -> 290000 | N27: =IF(AND(A27="Distribución",I27<>"Closed Won",B27<>"Others"),IF($C$4="m2",G27,H27)+(1000-ROW())/1000000,"") | O27: =IF(AND(A27="Industrial",B27<>"Others"),G27+(1000-ROW())/1000000,"") -> 8000.001 | P27: =IF(AND(A27="Distribución",B27<>"Others"),G27+(1000-ROW())/1000000,"")
A28: Industrial | B28: Tronex Fachada | C28: Proyecto Itagüí | D28: Ana Arias | E28: Colombia | F28: KingWall / KingRoof | G28: 6000 | H28: 94118 | I28: Pending | L28: =IF(J28="","",H28*J28) | M28: =IF(AND(A28="Industrial",I28<>"Closed Won",B28<>"Others"),IF($C$4="m2",G28,H28)+(1000-ROW())/1000000,"") -> 94118.001 | N28: =IF(AND(A28="Distribución",I28<>"Closed Won",B28<>"Others"),IF($C$4="m2",G28,H28)+(1000-ROW())/1000000,"") | O28: =IF(AND(A28="Industrial",B28<>"Others"),G28+(1000-ROW())/1000000,"") -> 6000.001 | P28: =IF(AND(A28="Distribución",B28<>"Others"),G28+(1000-ROW())/1000000,"")
A29: Industrial | B29: Xperto | C29: Xperto | D29: Alejandra Navas | E29: Ecuador | F29: KingFrigo | G29: 5500 | H29: 288750 | I29: Pending | L29: =IF(J29="","",H29*J29) | M29: =IF(AND(A29="Industrial",I29<>"Closed Won",B29<>"Others"),IF($C$4="m2",G29,H29)+(1000-ROW())/1000000,"") -> 288750 | N29: =IF(AND(A29="Distribución",I29<>"Closed Won",B29<>"Others"),IF($C$4="m2",G29,H29)+(1000-ROW())/1000000,"") | O29: =IF(AND(A29="Industrial",B29<>"Others"),G29+(1000-ROW())/1000000,"") -> 5500.001 | P29: =IF(AND(A29="Distribución",B29<>"Others"),G29+(1000-ROW())/1000000,"")
A30: Industrial | B30: JT Allum | C30: JT Allum | D30: Laura Torres | E30: Trinidad | F30: KingRoof | G30: 5000 | H30: 170000 | I30: Pending | L30: =IF(J30="","",H30*J30) | M30: =IF(AND(A30="Industrial",I30<>"Closed Won",B30<>"Others"),IF($C$4="m2",G30,H30)+(1000-ROW())/1000000,"") -> 170000 | N30: =IF(AND(A30="Distribución",I30<>"Closed Won",B30<>"Others"),IF($C$4="m2",G30,H30)+(1000-ROW())/1000000,"") | O30: =IF(AND(A30="Industrial",B30<>"Others"),G30+(1000-ROW())/1000000,"") -> 5000.001 | P30: =IF(AND(A30="Distribución",B30<>"Others"),G30+(1000-ROW())/1000000,"")
A31: Industrial | B31: Inversiones Cold | C31: Proyecto | D31: María Yelitza Calderón | E31: Venezuela | F31: KingRoof / KingFrigo | G31: 5000 | H31: 120000 | I31: Closed Won | L31: =IF(J31="","",H31*J31) | M31: =IF(AND(A31="Industrial",I31<>"Closed Won",B31<>"Others"),IF($C$4="m2",G31,H31)+(1000-ROW())/1000000,"") | N31: =IF(AND(A31="Distribución",I31<>"Closed Won",B31<>"Others"),IF($C$4="m2",G31,H31)+(1000-ROW())/1000000,"") | O31: =IF(AND(A31="Industrial",B31<>"Others"),G31+(1000-ROW())/1000000,"") -> 5000.001 | P31: =IF(AND(A31="Distribución",B31<>"Others"),G31+(1000-ROW())/1000000,"")
A32: Industrial | B32: Grupo Constructor Industrial | C32: Planta de líquidos Hada | D32: Ana Arias | E32: Colombia | F32: KingWall / King Frio | G32: 4600 | H32: 226730 | I32: Pending | L32: =IF(J32="","",H32*J32) | M32: =IF(AND(A32="Industrial",I32<>"Closed Won",B32<>"Others"),IF($C$4="m2",G32,H32)+(1000-ROW())/1000000,"") -> 226730 | N32: =IF(AND(A32="Distribución",I32<>"Closed Won",B32<>"Others"),IF($C$4="m2",G32,H32)+(1000-ROW())/1000000,"") | O32: =IF(AND(A32="Industrial",B32<>"Others"),G32+(1000-ROW())/1000000,"") -> 4600.001 | P32: =IF(AND(A32="Distribución",B32<>"Others"),G32+(1000-ROW())/1000000,"")
A33: Industrial | B33: Arklit | C33: Proyecto Hiper Santo Domingo | D33: Alejandra Navas | E33: Ecuador | F33: KingWall | G33: 4300 | H33: 90300 | I33: Pending | L33: =IF(J33="","",H33*J33) | M33: =IF(AND(A33="Industrial",I33<>"Closed Won",B33<>"Others"),IF($C$4="m2",G33,H33)+(1000-ROW())/1000000,"") -> 90300.001 | N33: =IF(AND(A33="Distribución",I33<>"Closed Won",B33<>"Others"),IF($C$4="m2",G33,H33)+(1000-ROW())/1000000,"") | O33: =IF(AND(A33="Industrial",B33<>"Others"),G33+(1000-ROW())/1000000,"") -> 4300.001 | P33: =IF(AND(A33="Distribución",B33<>"Others"),G33+(1000-ROW())/1000000,"")
A34: Industrial | B34: Others | C34: Different projects | D34: — | E34: Others | F34: King Wall / King Frio / King Roof | G34: 32582 | H34: 986673 | I34: Pending | L34: =IF(J34="","",H34*J34) | M34: =IF(AND(A34="Industrial",I34<>"Closed Won",B34<>"Others"),IF($C$4="m2",G34,H34)+(1000-ROW())/1000000,"") | N34: =IF(AND(A34="Distribución",I34<>"Closed Won",B34<>"Others"),IF($C$4="m2",G34,H34)+(1000-ROW())/1000000,"") | O34: =IF(AND(A34="Industrial",B34<>"Others"),G34+(1000-ROW())/1000000,"") | P34: =IF(AND(A34="Distribución",B34<>"Others"),G34+(1000-ROW())/1000000,"")
A35: Distribución | B35: Colcover | C35: Proyecto | D35: Henry Acosta | E35: Colombia | F35: KingRoof | G35: 21528 | H35: 411564.71 | I35: Pending | J35: 0.8 | K35: Noviembre | L35: =IF(J35="","",H35*J35) -> 329251.77 | M35: =IF(AND(A35="Industrial",I35<>"Closed Won",B35<>"Others"),IF($C$4="m2",G35,H35)+(1000-ROW())/1000000,"") | N35: =IF(AND(A35="Distribución",I35<>"Closed Won",B35<>"Others"),IF($C$4="m2",G35,H35)+(1000-ROW())/1000000,"") -> 411564.71 | O35: =IF(AND(A35="Industrial",B35<>"Others"),G35+(1000-ROW())/1000000,"") | P35: =IF(AND(A35="Distribución",B35<>"Others"),G35+(1000-ROW())/1000000,"") -> 21528.001
A36: Distribución | B36: Galvaceros | C36: Colegios Sucre | D36: Joana Perez | E36: Colombia | F36: KingRoof | G36: 14000 | H36: 333529 | I36: Pending | J36: 0.82 | K36: Noviembre | L36: =IF(J36="","",H36*J36) -> 273493.78 | M36: =IF(AND(A36="Industrial",I36<>"Closed Won",B36<>"Others"),IF($C$4="m2",G36,H36)+(1000-ROW())/1000000,"") | N36: =IF(AND(A36="Distribución",I36<>"Closed Won",B36<>"Others"),IF($C$4="m2",G36,H36)+(1000-ROW())/1000000,"") -> 333529 | O36: =IF(AND(A36="Industrial",B36<>"Others"),G36+(1000-ROW())/1000000,"") | P36: =IF(AND(A36="Distribución",B36<>"Others"),G36+(1000-ROW())/1000000,"") -> 14000.001
A37: Distribución | B37: RFS | C37: Cold Storage | D37: Juan Carlos Menendez | E37: Costa Rica | F37: KingFrigo | G37: 12500 | H37: 312500 | I37: Closed Won | L37: =IF(J37="","",H37*J37) | M37: =IF(AND(A37="Industrial",I37<>"Closed Won",B37<>"Others"),IF($C$4="m2",G37,H37)+(1000-ROW())/1000000,"") | N37: =IF(AND(A37="Distribución",I37<>"Closed Won",B37<>"Others"),IF($C$4="m2",G37,H37)+(1000-ROW())/1000000,"") | O37: =IF(AND(A37="Industrial",B37<>"Others"),G37+(1000-ROW())/1000000,"") | P37: =IF(AND(A37="Distribución",B37<>"Others"),G37+(1000-ROW())/1000000,"") -> 12500.001
A38: Distribución | B38: CIA Caribe Mar | C38: Antártica | D38: María Yelitza Calderón | E38: Venezuela | F38: KingFrigo | G38: 12000 | H38: 360000 | I38: Specification | J38: 0.9 | K38: Noviembre | L38: =IF(J38="","",H38*J38) -> 324000 | M38: =IF(AND(A38="Industrial",I38<>"Closed Won",B38<>"Others"),IF($C$4="m2",G38,H38)+(1000-ROW())/1000000,"") | N38: =IF(AND(A38="Distribución",I38<>"Closed Won",B38<>"Others"),IF($C$4="m2",G38,H38)+(1000-ROW())/1000000,"") -> 360000 | O38: =IF(AND(A38="Industrial",B38<>"Others"),G38+(1000-ROW())/1000000,"") | P38: =IF(AND(A38="Distribución",B38<>"Others"),G38+(1000-ROW())/1000000,"") -> 12000.001
A39: Distribución | B39: Galvaceros | C39: Panandina Data Center | D39: Joana Perez | E39: Colombia | F39: KingRoof / KingWall LMR | G39: 4106 | H39: 494712 | I39: Pending | J39: 0.85 | K39: Diciembre | L39: =IF(J39="","",H39*J39) -> 420505.2 | M39: =IF(AND(A39="Industrial",I39<>"Closed Won",B39<>"Others"),IF($C$4="m2",G39,H39)+(1000-ROW())/1000000,"") | N39: =IF(AND(A39="Distribución",I39<>"Closed Won",B39<>"Others"),IF($C$4="m2",G39,H39)+(1000-ROW())/1000000,"") -> 494712 | O39: =IF(AND(A39="Industrial",B39<>"Others"),G39+(1000-ROW())/1000000,"") | P39: =IF(AND(A39="Distribución",B39<>"Others"),G39+(1000-ROW())/1000000,"") -> 4106.001
A40: Distribución | B40: Espuma SantaFe | C40: Recambio | D40: Henry Acosta | E40: Colombia | F40: KingRoof / KingWall | G40: 4000 | H40: 152072 | I40: Pending | J40: 0.8 | K40: Diciembre | L40: =IF(J40="","",H40*J40) -> 121657.6 | M40: =IF(AND(A40="Industrial",I40<>"Closed Won",B40<>"Others"),IF($C$4="m2",G40,H40)+(1000-ROW())/1000000,"") | N40: =IF(AND(A40="Distribución",I40<>"Closed Won",B40<>"Others"),IF($C$4="m2",G40,H40)+(1000-ROW())/1000000,"") -> 152072 | O40: =IF(AND(A40="Industrial",B40<>"Others"),G40+(1000-ROW())/1000000,"") | P40: =IF(AND(A40="Distribución",B40<>"Others"),G40+(1000-ROW())/1000000,"") -> 4000.001
A41: Distribución | B41: Galvaceros | C41: Bodega Amazon etapa 2 | D41: Joana Perez | E41: Colombia | F41: KingRoof | G41: 4000 | H41: 136094 | I41: Pending | L41: =IF(J41="","",H41*J41) | M41: =IF(AND(A41="Industrial",I41<>"Closed Won",B41<>"Others"),IF($C$4="m2",G41,H41)+(1000-ROW())/1000000,"") | N41: =IF(AND(A41="Distribución",I41<>"Closed Won",B41<>"Others"),IF($C$4="m2",G41,H41)+(1000-ROW())/1000000,"") -> 136094 | O41: =IF(AND(A41="Industrial",B41<>"Others"),G41+(1000-ROW())/1000000,"") | P41: =IF(AND(A41="Distribución",B41<>"Others"),G41+(1000-ROW())/1000000,"") -> 4000.001
A42: Distribución | B42: Agropecuaria SantaCruz | C42: Cuarto Frío | D42: Erwin Ríos | E42: Colombia | F42: KingFrigo | G42: 2715 | H42: 119437 | I42: Closed Won | L42: =IF(J42="","",H42*J42) | M42: =IF(AND(A42="Industrial",I42<>"Closed Won",B42<>"Others"),IF($C$4="m2",G42,H42)+(1000-ROW())/1000000,"") | N42: =IF(AND(A42="Distribución",I42<>"Closed Won",B42<>"Others"),IF($C$4="m2",G42,H42)+(1000-ROW())/1000000,"") | O42: =IF(AND(A42="Industrial",B42<>"Others"),G42+(1000-ROW())/1000000,"") | P42: =IF(AND(A42="Distribución",B42<>"Others"),G42+(1000-ROW())/1000000,"") -> 2715.001
A43: Distribución | B43: Tejas Cubiertas e Ingeniería | C43: Recambio | D43: Edwar Salazar | E43: Colombia | F43: KingWall | G43: 2405 | H43: 79598 | I43: Pending | L43: =IF(J43="","",H43*J43) | M43: =IF(AND(A43="Industrial",I43<>"Closed Won",B43<>"Others"),IF($C$4="m2",G43,H43)+(1000-ROW())/1000000,"") | N43: =IF(AND(A43="Distribución",I43<>"Closed Won",B43<>"Others"),IF($C$4="m2",G43,H43)+(1000-ROW())/1000000,"") -> 79598.001 | O43: =IF(AND(A43="Industrial",B43<>"Others"),G43+(1000-ROW())/1000000,"") | P43: =IF(AND(A43="Distribución",B43<>"Others"),G43+(1000-ROW())/1000000,"") -> 2405.001
A44: Distribución | B44: Técnica Industrial Duarte | C44: Stock | D44: María Yelitza Calderón | E44: Venezuela | F44: KingFrigo | G44: 2000 | H44: 60000 | I44: Closed Won | L44: =IF(J44="","",H44*J44) | M44: =IF(AND(A44="Industrial",I44<>"Closed Won",B44<>"Others"),IF($C$4="m2",G44,H44)+(1000-ROW())/1000000,"") | N44: =IF(AND(A44="Distribución",I44<>"Closed Won",B44<>"Others"),IF($C$4="m2",G44,H44)+(1000-ROW())/1000000,"") | O44: =IF(AND(A44="Industrial",B44<>"Others"),G44+(1000-ROW())/1000000,"") | P44: =IF(AND(A44="Distribución",B44<>"Others"),G44+(1000-ROW())/1000000,"") -> 2000.001
L45: =IF(J45="","",H45*J45) | M45: =IF(AND(A45="Industrial",I45<>"Closed Won",B45<>"Others"),IF($C$4="m2",G45,H45)+(1000-ROW())/1000000,"") | N45: =IF(AND(A45="Distribución",I45<>"Closed Won",B45<>"Others"),IF($C$4="m2",G45,H45)+(1000-ROW())/1000000,"") | O45: =IF(AND(A45="Industrial",B45<>"Others"),G45+(1000-ROW())/1000000,"") | P45: =IF(AND(A45="Distribución",B45<>"Others"),G45+(1000-ROW())/1000000,"")
L46: =IF(J46="","",H46*J46) | M46: =IF(AND(A46="Industrial",I46<>"Closed Won",B46<>"Others"),IF($C$4="m2",G46,H46)+(1000-ROW())/1000000,"") | N46: =IF(AND(A46="Distribución",I46<>"Closed Won",B46<>"Others"),IF($C$4="m2",G46,H46)+(1000-ROW())/1000000,"") | O46: =IF(AND(A46="Industrial",B46<>"Others"),G46+(1000-ROW())/1000000,"") | P46: =IF(AND(A46="Distribución",B46<>"Others"),G46+(1000-ROW())/1000000,"")
L47: =IF(J47="","",H47*J47) | M47: =IF(AND(A47="Industrial",I47<>"Closed Won",B47<>"Others"),IF($C$4="m2",G47,H47)+(1000-ROW())/1000000,"") | N47: =IF(AND(A47="Distribución",I47<>"Closed Won",B47<>"Others"),IF($C$4="m2",G47,H47)+(1000-ROW())/1000000,"") | O47: =IF(AND(A47="Industrial",B47<>"Others"),G47+(1000-ROW())/1000000,"") | P47: =IF(AND(A47="Distribución",B47<>"Others"),G47+(1000-ROW())/1000000,"")
L48: =IF(J48="","",H48*J48) | M48: =IF(AND(A48="Industrial",I48<>"Closed Won",B48<>"Others"),IF($C$4="m2",G48,H48)+(1000-ROW())/1000000,"") | N48: =IF(AND(A48="Distribución",I48<>"Closed Won",B48<>"Others"),IF($C$4="m2",G48,H48)+(1000-ROW())/1000000,"") | O48: =IF(AND(A48="Industrial",B48<>"Others"),G48+(1000-ROW())/1000000,"") | P48: =IF(AND(A48="Distribución",B48<>"Others"),G48+(1000-ROW())/1000000,"")
L49: =IF(J49="","",H49*J49) | M49: =IF(AND(A49="Industrial",I49<>"Closed Won",B49<>"Others"),IF($C$4="m2",G49,H49)+(1000-ROW())/1000000,"") | N49: =IF(AND(A49="Distribución",I49<>"Closed Won",B49<>"Others"),IF($C$4="m2",G49,H49)+(1000-ROW())/1000000,"") | O49: =IF(AND(A49="Industrial",B49<>"Others"),G49+(1000-ROW())/1000000,"") | P49: =IF(AND(A49="Distribución",B49<>"Others"),G49+(1000-ROW())/1000000,"")
L50: =IF(J50="","",H50*J50) | M50: =IF(AND(A50="Industrial",I50<>"Closed Won",B50<>"Others"),IF($C$4="m2",G50,H50)+(1000-ROW())/1000000,"") | N50: =IF(AND(A50="Distribución",I50<>"Closed Won",B50<>"Others"),IF($C$4="m2",G50,H50)+(1000-ROW())/1000000,"") | O50: =IF(AND(A50="Industrial",B50<>"Others"),G50+(1000-ROW())/1000000,"") | P50: =IF(AND(A50="Distribución",B50<>"Others"),G50+(1000-ROW())/1000000,"")
L51: =IF(J51="","",H51*J51) | M51: =IF(AND(A51="Industrial",I51<>"Closed Won",B51<>"Others"),IF($C$4="m2",G51,H51)+(1000-ROW())/1000000,"") | N51: =IF(AND(A51="Distribución",I51<>"Closed Won",B51<>"Others"),IF($C$4="m2",G51,H51)+(1000-ROW())/1000000,"") | O51: =IF(AND(A51="Industrial",B51<>"Others"),G51+(1000-ROW())/1000000,"") | P51: =IF(AND(A51="Distribución",B51<>"Others"),G51+(1000-ROW())/1000000,"")
L52: =IF(J52="","",H52*J52) | M52: =IF(AND(A52="Industrial",I52<>"Closed Won",B52<>"Others"),IF($C$4="m2",G52,H52)+(1000-ROW())/1000000,"") | N52: =IF(AND(A52="Distribución",I52<>"Closed Won",B52<>"Others"),IF($C$4="m2",G52,H52)+(1000-ROW())/1000000,"") | O52: =IF(AND(A52="Industrial",B52<>"Others"),G52+(1000-ROW())/1000000,"") | P52: =IF(AND(A52="Distribución",B52<>"Others"),G52+(1000-ROW())/1000000,"")
L53: =IF(J53="","",H53*J53) | M53: =IF(AND(A53="Industrial",I53<>"Closed Won",B53<>"Others"),IF($C$4="m2",G53,H53)+(1000-ROW())/1000000,"") | N53: =IF(AND(A53="Distribución",I53<>"Closed Won",B53<>"Others"),IF($C$4="m2",G53,H53)+(1000-ROW())/1000000,"") | O53: =IF(AND(A53="Industrial",B53<>"Others"),G53+(1000-ROW())/1000000,"") | P53: =IF(AND(A53="Distribución",B53<>"Others"),G53+(1000-ROW())/1000000,"")
L54: =IF(J54="","",H54*J54) | M54: =IF(AND(A54="Industrial",I54<>"Closed Won",B54<>"Others"),IF($C$4="m2",G54,H54)+(1000-ROW())/1000000,"") | N54: =IF(AND(A54="Distribución",I54<>"Closed Won",B54<>"Others"),IF($C$4="m2",G54,H54)+(1000-ROW())/1000000,"") | O54: =IF(AND(A54="Industrial",B54<>"Others"),G54+(1000-ROW())/1000000,"") | P54: =IF(AND(A54="Distribución",B54<>"Others"),G54+(1000-ROW())/1000000,"")
L55: =IF(J55="","",H55*J55) | M55: =IF(AND(A55="Industrial",I55<>"Closed Won",B55<>"Others"),IF($C$4="m2",G55,H55)+(1000-ROW())/1000000,"") | N55: =IF(AND(A55="Distribución",I55<>"Closed Won",B55<>"Others"),IF($C$4="m2",G55,H55)+(1000-ROW())/1000000,"") | O55: =IF(AND(A55="Industrial",B55<>"Others"),G55+(1000-ROW())/1000000,"") | P55: =IF(AND(A55="Distribución",B55<>"Others"),G55+(1000-ROW())/1000000,"")
L56: =IF(J56="","",H56*J56) | M56: =IF(AND(A56="Industrial",I56<>"Closed Won",B56<>"Others"),IF($C$4="m2",G56,H56)+(1000-ROW())/1000000,"") | N56: =IF(AND(A56="Distribución",I56<>"Closed Won",B56<>"Others"),IF($C$4="m2",G56,H56)+(1000-ROW())/1000000,"") | O56: =IF(AND(A56="Industrial",B56<>"Others"),G56+(1000-ROW())/1000000,"") | P56: =IF(AND(A56="Distribución",B56<>"Others"),G56+(1000-ROW())/1000000,"")
... L67: =IF(J67="","",H67*J67) | M67: =IF(AND(A67="Industrial",I67<>"Closed Won",B67<>"Others"),IF($C$4="m2",G67,H67)+(1000-ROW())/1000000,"") | N67: =IF(AND(A67="Distribución",I67<>"Closed Won",B67<>"Others"),IF($C$4="m2",G67,H67)+(1000-ROW())/1000000,"") | O67: =IF(AND(A67="Industrial",B67<>"Others"),G67+(1000-ROW())/1000000,"") | P67: =IF(AND(A67="Distribución",B67<>"Others"),G67+(1000-ROW())/1000000,"")

Sheet Validaciones
A1: Validaciones de datos – deck original vs motor
A2: Inconsistencias detectadas al reconstruir el reporte (revisar con la fuente)
A3: Puntos abiertos (deben ser 0 antes del deck final): | E3: =COUNTIF(E5:E21,"Abierto") -> 6
A4: # | B4: Slide | C4: Hallazgo | D4: Tratamiento en esta versión | E4: Estado | F4: Cifra validada / responsable
A5: 1 | B5: Commercial Overview | C5: Order Intake rotulado "August" y YTD "1,293,5K m²"; la tabla OI muestra Sep = 146.446 y YTD = 1.239.541. | D5: Se rotula Sep-26 y se usa 1.239.541 (YoY +25,4%). | E5: Cerrado
A6: 2 | B6: Commercial Overview | C6: Ventas: solo se reportan % (YoY, MoM); no hay PY ni mes anterior absolutos. | D6: PY y Ago derivados del %; marcados como input a reemplazar. | E6: Cerrado
A7: 3 | B7: Order Intake / Backlog | C7: Tarjetas de margen dicen "August 2026". | D7: Se rotulan Sep-26. | E7: Cerrado
A8: 4 | B8: Performed / Forecast | C8: Ingreso Jul = 13.652.194 (duplica Jun). Con el valor del gráfico (11.718.909) el acumulado YTD cuadra con 130.176 COP MM. | D8: Jul corregido → cierre forecast 172.899 COP MM (+31,8% YoY) en lugar de 174.832 (+33%). | E8: Cerrado
A9: 5 | B9: Performed / Forecast | C9: Acumulado volumen Ene = 86.671 (debe ser 104.582) y acumulado ingreso Ene = 7.958.800 (es el PY). | D9: Acumulados recalculados por fórmula. | E9: Cerrado
A10: 6 | B10: Order Intake | C10: Gráfico OI Abr = 13.170 COP MM vs tabla Performed 12.270. | D10: Se usa 12.270 (cuadra con YTD 130.176). Validar. | E10: Cerrado
A11: 7 | B11: Backlog | C11: Ingreso PY = 10.617 (duplica Single Skin PY). | D11: Se usa 33.248 COP MM (gráfico de progresión Sep-25). | E11: Cerrado
A12: 8 | B12: Key Projects Industrial | C12: Suma de filas m² = 662.771 vs total reportado 658.771 (USD cuadra: 21.038.017). | D12: Se usa suma por fórmula; validar m² de alguna fila. | E12: Cerrado
A13: 9 | B13: Key Projects Industrial | C13: Se reportan 38 proyectos; la tabla tiene 26 filas + "Others". | D13: Se asume que "Others" agrupa 12 proyectos. | E13: Cerrado
A14: 10 | B14: Commercial Overview | C14: Top pedidos con encabezado "USD (mm)" y valores $306/$236/$173. | D14: Se conserva la unidad del deck; validar (¿USD miles?). | E14: Cerrado
A15: 11 | B15: Por canal (03 y 05) | C15: No hay OI/backlog mensual por canal ni PY/GM por canal en el deck. | D15: YTD y backlog por canal se toman de las tablas RSM; CM/PY/GM quedan como input. | E15: Cerrado
A16: 12 | B16: Overview / OI / Performed | C16: OI YTD: 1.239.541 m² (tabla OI) vs 1.228.503 m² (Performed, junio corregido). | D16: Definir una sola cifra y alinear slides 3–4 y 8. | E16: Abierto
... A21: 17 | B21: Overview | C21: Insight "OI YoY 18%": cierre año hoy +20%. | D21: Ajustar texto. | E21: Abierto

Sheet 16_Iniciativas
A1: 16 · Iniciativas estratégicas (agosto) – semáforo de seguimiento
A2: Slides 15–16. Una fila por iniciativa. Diligenciar meta y resultado numérico para que el % de avance y el estado sugerido se calculen; el estado final se elige en la lista.
A4: # | B4: Iniciativa | C4: Compromiso / meta (presentado en agosto) | D4: KPI de medición | E4: Meta (número) | F4: Resultado sep (número) | G4: % avance | H4: Resultado sep (texto para slide) | I4: Estado sugerido | J4: Estado final | K4: Responsable | L4: Próximo paso | M4: Fecha | N4: Comentarios
A5: 1 | B5: Inteligencia competitiva / market share | G5: =IF(OR(E5="",F5="",E5=0),"",F5/E5) | I5: =IF(G5="","Definir",IF(G5>=0.9,"Verde",IF(G5>=0.7,"Amarillo","Rojo"))) -> Definir
A6: 2 | B6: Nuevos productos | G6: =IF(OR(E6="",F6="",E6=0),"",F6/E6) | I6: =IF(G6="","Definir",IF(G6>=0.9,"Verde",IF(G6>=0.7,"Amarillo","Rojo"))) -> Definir
A7: 3 | B7: Venezuela y Ecuador | G7: =IF(OR(E7="",F7="",E7=0),"",F7/E7) | H7: Evento Binacional Cúcuta; pipeline VE: CIA Caribe Mar USD 360k (especificación), Prosein + Remar USD 1,47 M; 1 proyecto VE ganado. Cuenta Ecuador por debajo de budget | I7: =IF(G7="","Definir",IF(G7>=0.9,"Verde",IF(G7>=0.7,"Amarillo","Rojo"))) -> Definir
A8: 4 | B8: Distribución | G8: =IF(OR(E8="",F8="",E8=0),"",F8/E8) | H8: 91% del budget de ventas YTD; backlog 64,5k m² (+27% YoY) con margen 30% (+3 pp) | I8: =IF(G8="","Definir",IF(G8>=0.9,"Verde",IF(G8>=0.7,"Amarillo","Rojo"))) -> Definir
A9: 5 | B9: Single Skin | G9: =IF(OR(E9="",F9="",E9=0),"",F9/E9) | H9: OI YTD 106k m² (2,8x PY); sep −4% YoY; backlog 40k m² (3,8x PY) | I9: =IF(G9="","Definir",IF(G9>=0.9,"Verde",IF(G9>=0.7,"Amarillo","Rojo"))) -> Definir
A10: 6 | B10: Benchmark / línea arquitectónica | G10: =IF(OR(E10="",F10="",E10=0),"",F10/E10) | H10: Benchmark OI YTD 5,8k m² (vs 0,4k PY); backlog 4,7k m²; 49,6k m² especificados línea arquitectónica; fachada Smartfit 599 m² | I10: =IF(G10="","Definir",IF(G10>=0.9,"Verde",IF(G10>=0.7,"Amarillo","Rojo"))) -> Definir
A11: 7 | B11: Top 20 proyectos | G11: =IF(OR(E11="",F11="",E11=0),"",F11/E11) | H11: Top 20 abiertos = USD 19,2 M (605k m²), 93% del pipeline abierto; Top 10 ponderado USD 8,3 M | I11: =IF(G11="","Definir",IF(G11>=0.9,"Verde",IF(G11>=0.7,"Amarillo","Rojo"))) -> Definir
A12: 8 | B12: Cali-Site | G12: =IF(OR(E12="",F12="",E12=0),"",F12/E12) | H12: 96% del budget de ventas YTD; OI YTD 140k m²; backlog 49k m² (margen 37%) | I12: =IF(G12="","Definir",IF(G12>=0.9,"Verde",IF(G12>=0.7,"Amarillo","Rojo"))) -> Definir
A14: Resumen
B15: Verde | C15: =COUNTIF(J5:J12,"Verde") -> 0
B16: Amarillo | C16: =COUNTIF(J5:J12,"Amarillo") -> 0
B17: Rojo | C17: =COUNTIF(J5:J12,"Rojo") -> 0
B18: Sin definir | C18: =8-COUNTIF(J5:J12,"Verde")-COUNTIF(J5:J12,"Amarillo")-COUNTIF(J5:J12,"Rojo") -> 8
A20: Regla estado sugerido: avance ≥90% = Verde · 70–89% = Amarillo · <70% = Rojo. Estado final (lista) prevalece en el slide.

Sheet 17_Actividad_Impacto
A1: 17 · De la actividad al impacto
A2: Slide 17. Indicadores de actividad (input) conectados con indicadores de impacto (fórmula cuando existe la fuente; input cuando no).
A4: Bloque | B4: Indicador | C4: Valor | D4: Unidad | E4: Fuente / nota
A5: Actividad | B5: Visitas a clientes | C5: ='15_Highlights'!B5 -> 218 | D5: visitas | E5: 15_Highlights
A6: Actividad | B6: Personas capacitadas | C6: ='15_Highlights'!B9 -> 122 | D6: personas | E6: 15_Highlights
A7: Actividad | B7: Clientes nuevos | C7: ='15_Highlights'!B6 -> 26 | D7: clientes | E7: 15_Highlights
A8: Actividad | B8: m² especificados (paneles + arquitectónica) | C8: ='15_Highlights'!B14 -> 213427 | D8: m² | E8: 15_Highlights
A9: Impacto | B9: Oportunidades generadas por la actividad del mes (#) | D9: # | E9: INPUT – CRM: oportunidades creadas en el mes con origen visita/capacitación/especificación
A10: Impacto | B10: Valor de oportunidades generadas (USD) | D10: USD | E10: INPUT – CRM
A11: Impacto | B11: Valor pipeline total (USD) | C11: =SUM(Pipeline!H7:H67) -> 23497524 | D11: USD | E11: Pipeline
A12: Impacto | B12: Closed won (USD) | C12: =SUMIFS(Pipeline!H7:H67,Pipeline!I7:I67,"Closed Won") -> 2448057 | D12: USD | E12: Pipeline
A13: Impacto | B13: Conversión (closed won / pipeline) | C13: =IFERROR(C12/C11,0) -> 0.10418362 | D13: % | E13: Calculado
A14: Impacto | B14: m² especificados convertidos en pedidos | D14: m² | E14: INPUT
A15: Impacto | B15: Conversión especificación → pedido | C15: =IF(C14="","",IFERROR(C14/C8,"")) | D15: % | E15: Calculado
A16: Impacto | B16: Pedidos clientes nuevos (m²) | C16: ='15_Highlights'!B7 -> 7400 | D16: m² | E16: 15_Highlights
A17: Impacto | B17: Pedidos clientes nuevos (USD) | C17: ='15_Highlights'!B8 -> 197235 | D17: USD | E17: 15_Highlights
A18: Impacto | B18: Order Intake del mes (m²) | C18: ='02_OI'!B7 -> 160547 | D18: m² | E18: 02_OI
A19: Impacto | B19: Ventas YTD (m²) | C19: =RSM_Resumen_Canales!D11 -> 1058016 | D19: m² | E19: RSM_Resumen_Canales
A20: Impacto | B20: Margen OI del mes | C20: ='02_OI'!B12 -> 0.27 | D20: % | E20: 02_OI
A21: Ratio | B21: USD de pipeline por visita | C21: =IFERROR(C11/C5,0) -> 107786.81 | D21: USD/visita | E21: Calculado
A22: Ratio | B22: Oportunidades generadas por cada 10 visitas | C22: =IF(C9="","",IFERROR(C9/C5*10,"")) | D22: # | E22: Calculado

Sheet 18_Acciones_Decisiones
A1: 18 · Decisiones y próximos pasos
A2: Slide 19. Filas 1–5 son propuestas derivadas del análisis: confirmar, editar o eliminar. Estado en lista.
A4: # | B4: Decisión / acción requerida | C4: Tipo | D4: Impacto esperado | E4: Responsable | F4: Fecha | G4: Estado | H4: Seguimiento / comentario
A5: 1 | B5: Cubrir territorios Industrial abiertos (Bogotá, cuentas clave) – contratar / reasignar cobertura | C5: Decisión | D5: ~82k m² de budget hoy sin ventas | G5: Abierta
A6: 2 | B6: Plan de recuperación cuentas Ecuador y Costa Rica | C6: Acción | D6: Cerrar parte de la brecha de −92k m² vs budget | G6: Abierta
A7: 3 | B7: Asegurar cierre Top 10 oportunidades (USD 9,4 M esperados en noviembre) | C7: Acción | D7: USD 8,3 M pipeline ponderado | G7: Abierta
A8: 4 | B8: Revisar pricing / mix del backlog Cold Storage | C8: Acción | D8: Recuperar margen −10,6 pp vs PY | G8: Abierta
A9: 5 | B9: Validar cifra única de OI YTD y cerrar notas pendientes antes del deck final | C9: Acción | D9: Una sola cifra validada para la junta | G9: Abierta
A10: 6
A11: 7
A12: 8
A13: 9
A14: 10
B16: Abiertas / en curso | C16: =COUNTIF(G5:G14,"Abierta")+COUNTIF(G5:G14,"En curso") -> 5
