Workbook

Sheet LEEME
A1: Kingspan Middle Americas · Commercial Review – Motor de datos (Data Engine)
A3: Cómo usar este archivo
A4: 1. Diligencie SOLO las celdas amarillas con texto azul (inputs). Todo lo demás (%, YoY, MoM, totales, mix, rankings, semáforos, Top 5) se calcula solo.
A5: 2. Cada hoja corresponde a un slide del deck (01 = Commercial Overview … 15 = Highlights). El número de la hoja = número del slide de contenido.
A6: 3. Los rankings de consultores (hojas 09–14) y los Top 5 (hojas 07–08) se reordenan automáticamente al cambiar los datos.
A7: 4. Para actualizar el PowerPoint: en cada gráfico clic derecho › "Editar datos" y pegue los valores de la tabla "Fuente gráfico" de la hoja correspondiente; en las tablas, pegue valores (Pegado especial › Valores) desde el bloque "Tabla slide".
A8: Alternativa: copie el bloque de la hoja y en PowerPoint use Pegado especial › "Pegar vínculo" (Hoja de Microsoft Excel) para dejar la tabla vinculada a este archivo.
A9: 5. Mes de corte: hoja 02_OI celda B4 y 06_Perf_Forecast celda B4 (número de mes, 9 = septiembre).
A10: 6. Revise la hoja "Validaciones": lista inconsistencias detectadas en el deck original y cómo se corrigieron.
A12: Convenciones
A13: Amarillo + azul = input · Negro = fórmula · Verde/Ámbar/Rojo = semáforo de cumplimiento (≥100% / 70–99% / <70%).
A14: Unidades: volumen en m²; ingresos en COP MM (millones de pesos); pipeline en USD.
... A34: • Para regenerar el deck: python scripts/actualizar_deck_comercial.py <este Excel> <deck base> <salida>.

Sheet 00_Resumen_Ejecutivo
A1: 00 · Resumen ejecutivo – 4 preguntas
A2: Slide 2: qué nos comprometimos (amarillo = input), qué logramos (fórmula), desviación y estado (automáticos), qué la explica y acción (input).
A4: Indicador | B4: Unidad | C4: Compromiso / meta | D4: Resultado | E4: Desviación (Res − Comp) | F4: % vs compromiso | G4: Estado sugerido | H4: Estado final (override) | I4: Qué la explica | J4: Acción / decisión | K4: Responsable | L4: Fecha
A5: Order Intake YTD | B5: m² | D5: ='02_OI'!E7 | E5: =IF(C5="","",D5-C5) | F5: =IF(OR(C5="",C5=0),"",D5/C5) | G5: =IF(F5="","Definir",IF(ROUND(F5,2)>=1,"Verde",IF(ROUND(F5,2)>=0.85,"Amarillo","Rojo")))
A6: Ventas YTD | B6: m² | C6: =RSM_Resumen_Canales!T11 | D6: =RSM_Resumen_Canales!D11 | E6: =IF(C6="","",D6-C6) | F6: =IF(OR(C6="",C6=0),"",D6/C6) | G6: =IF(F6="","Definir",IF(ROUND(F6,2)>=1,"Verde",IF(ROUND(F6,2)>=0.85,"Amarillo","Rojo"))) | I6: Industrial y Otras Geografías = 98% de la brecha | J6: Plan de cobertura territorios Industrial + plan de recuperación cuentas Ecuador / Costa Rica
A7: Margen OI YTD (Gross-STD) | B7: % | D7: ='02_OI'!E12 | E7: =IF(C7="","",D7-C7) | F7: =IF(OR(C7="",C7=0),"",D7/C7) | G7: =IF(F7="","Definir",IF(ROUND(F7,2)>=1,"Verde",IF(ROUND(F7,2)>=0.85,"Amarillo","Rojo")))
A8: Backlog IMP | B8: m² | D8: ='04_Backlog'!B5 | E8: =IF(C8="","",D8-C8) | F8: =IF(OR(C8="",C8=0),"",D8/C8) | G8: =IF(F8="","Definir",IF(ROUND(F8,2)>=1,"Verde",IF(ROUND(F8,2)>=0.85,"Amarillo","Rojo")))
A9: Margen backlog (ponderado) | B9: % | D9: =RSM_Resumen_Canales!J11 | E9: =IF(C9="","",D9-C9) | F9: =IF(OR(C9="",C9=0),"",D9/C9) | G9: =IF(F9="","Definir",IF(ROUND(F9,2)>=1,"Verde",IF(ROUND(F9,2)>=0.85,"Amarillo","Rojo")))
A10: Cierre año OI (real + forecast) | B10: m² | D10: ='06_Perf_Forecast'!B30 | E10: =IF(C10="","",D10-C10) | F10: =IF(OR(C10="",C10=0),"",D10/C10) | G10: =IF(F10="","Definir",IF(ROUND(F10,2)>=1,"Verde",IF(ROUND(F10,2)>=0.85,"Amarillo","Rojo"))) | I10: Forecast Q4 400k m² (+7,6% vs Q4-25)
A11: Iniciativas estratégicas en verde | B11: # | C11: 8 | D11: =COUNTIF('16_Iniciativas'!J5:J12,"Verde") | E11: =IF(C11="","",D11-C11) | F11: =IF(OR(C11="",C11=0),"",D11/C11) | G11: =IF(COUNTA('16_Iniciativas'!J5:J12)=0,"Definir",IF(ROUND(F11,2)>=1,"Verde",IF(ROUND(F11,2)>=0.85,"Amarillo","Rojo")))
A13: Regla de estado sugerido: ≥100% del compromiso = Verde · 85–99% = Amarillo · <85% = Rojo. Si se diligencia "Estado final", ese prevalece en el slide.
A14: Mensaje clave del slide (1 línea): | C14: Estamos al 85% del budget de ventas YTD con OI y margen por encima del año anterior; la brecha está en territorios Industrial y dos cuentas de exportación.

Sheet 01_Overview
A1: 01 · Commercial Overview
A2: Ventas y Order Intake del mes, YTD, YoY y MoM · mix de ventas por canal y geografía
A4: Concepto (m²) | B4: Mes actual (Sep-26) | C4: Mismo mes PY (Sep-25) | D4: Mes anterior (Ago-26) | E4: YTD 2026 | F4: YTD 2025 | G4: YoY mes | H4: MoM | I4: YoY YTD
A5: Ventas (Sales) | B5: 141231 | C5: 99001 | D5: 125933 | E5: 1199504 | F5: 1120888 | G5: =IF(OR(B5="",C5=""),"",IF(C5=0,"n.a.",B5/C5-1)) | H5: =IF(OR(B5="",D5=""),"",IF(D5=0,"n.a.",B5/D5-1)) | I5: =IF(OR(E5="",F5=""),"",IF(F5=0,"n.a.",E5/F5-1))
A6: Order Intake | B6: 160547 | C6: 132769 | D6: 146446 | E6: 1400088 | F6: 1120898 | G6: =IF(OR(B6="",C6=""),"",IF(C6=0,"n.a.",B6/C6-1)) | H6: =IF(OR(B6="",D6=""),"",IF(D6=0,"n.a.",B6/D6-1)) | I6: =IF(OR(E6="",F6=""),"",IF(F6=0,"n.a.",E6/F6-1))
A7: Book-to-bill YTD (OI / Ventas) | E7: =IFERROR(E6/E5,"")
A8: Book-to-bill mes | B8: =IFERROR(B6/B5,"")
A10: Ventas del mes por canal | B10: m² | C10: Mix %
A11: Industrial | C11: =IFERROR(B11/SUM($B$11:$B$12),0)
A12: Distribution | C12: =IFERROR(B12/SUM($B$11:$B$12),0)
A14: Ventas del mes por geografía | B14: m² | C14: Mix %
A15: Colombia | C15: =IFERROR(B15/SUM($B$15:$B$16),0)
A16: Other Geographies | C16: =IFERROR(B16/SUM($B$15:$B$16),0)
A18: Otras geografías – país | B18: m² mes | C18: % del total OG | D18: Ranking
A19: Ecuador | B19: 8828 | C19: =IFERROR(B19/SUM($B$19:$B$23),0) | D19: =RANK(B19,$B$19:$B$23)
A20: Others | B20: 6421 | C20: =IFERROR(B20/SUM($B$19:$B$23),0) | D20: =RANK(B20,$B$19:$B$23)
A21: Republica Dominicana | B21: 15144 | C21: =IFERROR(B21/SUM($B$19:$B$23),0) | D21: =RANK(B21,$B$19:$B$23)
A22: Venezuela | B22: 9798 | C22: =IFERROR(B22/SUM($B$19:$B$23),0) | D22: =RANK(B22,$B$19:$B$23)
C23: =IFERROR(B23/SUM($B$19:$B$23),0) | D23: =RANK(B23,$B$19:$B$23)
A24: Total | B24: =SUM(B19:B23) | C24: =SUM(C19:C23)
A26: Top pedidos del mes – Cliente | B26: Proyecto | C26: Canal | D26: Valor (USD mm, según deck)
A27: Envases Tropicales | B27: Cubierta Envases Tropicales | LTORR-02071 | C27: Other Geographies | D27: 306
A28: Industrial Nutricional Avícola | B28: Industria Nutricional Avícola | C28: Cold Storage | D28: 236
A29: C.C. Chipichape P.H. | B29: Recambio cubierta Chipichape – Bodega 04 | C29: Industrial | D29: 173

Sheet 19_OI_Regiones
A1: 19 · Order Intake por región (slide Commercial Overview)
A2: Diligencie el OI del mes y el YTD por región (amarillo). Seleccione la vista en B4: el ranking y el gráfico se reordenan solos de mayor a menor volumen.
A4: Vista del gráfico | B4: Mes
A6: Región | B6: OI mes (m²) | C6: OI YTD (m²) | D6: Fuente / estado del dato | E6: Valor vista | F6: Clave orden (aux)
A7: Colombia | B7: 104987 | D7: Estimado: OI IMP mes − OI Otras Geografías (03_OI_Canal B7) | E7: =IF($B$4="YTD",C7,B7) | F7: =N(E7)+(100-ROW())/1000000000
A8: Centro América | B8: 6756 | D8: Estimado: Otras Geo × mix ventas 'Others' × peso pipeline CA | E8: =IF($B$4="YTD",C8,B8) | F8: =N(E8)+(100-ROW())/1000000000
A9: Caribe | B9: 20935 | D9: Estimado: Otras Geo × mix ventas Rep. Dominicana | E9: =IF($B$4="YTD",C9,B9) | F9: =N(E9)+(100-ROW())/1000000000
A10: Ecuador | B10: 12204 | D10: Estimado: Otras Geo × mix ventas Ecuador | E10: =IF($B$4="YTD",C10,B10) | F10: =N(E10)+(100-ROW())/1000000000
A11: Perú | B11: 2120 | D11: Estimado: Otras Geo × mix ventas 'Others' × peso pipeline Perú | E11: =IF($B$4="YTD",C11,B11) | F11: =N(E11)+(100-ROW())/1000000000
A12: Venezuela | B12: 13545 | D12: Estimado: Otras Geo × mix ventas Venezuela | E12: =IF($B$4="YTD",C12,B12) | F12: =N(E12)+(100-ROW())/1000000000
A13: TOTAL | B13: =SUM(B7:B12) | C13: =SUM(C7:C12) | E13: =SUM(E7:E12)
A14: Control: Σ regiones mes − OI IMP mes (02_OI B7) | B14: =B13-'02_OI'!B7
A15: Control: Σ regiones YTD − OI IMP YTD (02_OI E7) | C15: =IF(C13=0,"Pendiente",C13-'02_OI'!E7)
A17: RANKING – fuente del gráfico (se ordena solo)
A18: # | B18: Región | C18: m² | D18: % del total
A19: 1 | B19: =INDEX($A$7:$A$12,MATCH(LARGE($F$7:$F$12,A19),$F$7:$F$12,0)) | C19: =INDEX($E$7:$E$12,MATCH(LARGE($F$7:$F$12,A19),$F$7:$F$12,0)) | D19: =IFERROR(C19/$E$13,0)
A20: 2 | B20: =INDEX($A$7:$A$12,MATCH(LARGE($F$7:$F$12,A20),$F$7:$F$12,0)) | C20: =INDEX($E$7:$E$12,MATCH(LARGE($F$7:$F$12,A20),$F$7:$F$12,0)) | D20: =IFERROR(C20/$E$13,0)
A21: 3 | B21: =INDEX($A$7:$A$12,MATCH(LARGE($F$7:$F$12,A21),$F$7:$F$12,0)) | C21: =INDEX($E$7:$E$12,MATCH(LARGE($F$7:$F$12,A21),$F$7:$F$12,0)) | D21: =IFERROR(C21/$E$13,0)
A22: 4 | B22: =INDEX($A$7:$A$12,MATCH(LARGE($F$7:$F$12,A22),$F$7:$F$12,0)) | C22: =INDEX($E$7:$E$12,MATCH(LARGE($F$7:$F$12,A22),$F$7:$F$12,0)) | D22: =IFERROR(C22/$E$13,0)
A23: 5 | B23: =INDEX($A$7:$A$12,MATCH(LARGE($F$7:$F$12,A23),$F$7:$F$12,0)) | C23: =INDEX($E$7:$E$12,MATCH(LARGE($F$7:$F$12,A23),$F$7:$F$12,0)) | D23: =IFERROR(C23/$E$13,0)
A24: 6 | B24: =INDEX($A$7:$A$12,MATCH(LARGE($F$7:$F$12,A24),$F$7:$F$12,0)) | C24: =INDEX($E$7:$E$12,MATCH(LARGE($F$7:$F$12,A24),$F$7:$F$12,0)) | D24: =IFERROR(C24/$E$13,0)
A26: Las celdas en salmón son estimaciones iniciales: reemplácelas con el OI real por país.

Sheet 02_OI
A1: 02 · Order Intake – Octuber
A2: Tabla por producto + progresión mensual de ingresos y margen
A4: Mes de corte (1-12) | B4: 10
A6: Producto / métrica | B6: Mes actual | C6: PY | D6: YoY mes | E6: YTD | F6: Prior YTD | G6: YoY YTD
A7: IMP – Volume (m²) | B7: 160547 | C7: 132786 | D7: =IF(OR(B7="",C7=""),"",IF(C7=0,"n.a.",B7/C7-1)) | E7: 1400088 | F7: 1120898 | G7: =IF(OR(E7="",F7=""),"",IF(F7=0,"n.a.",E7/F7-1))
A8: Kingcore – Volume (m²) | B8: 20793 | C8: 10126 | D8: =IF(OR(B8="",C8=""),"",IF(C8=0,"n.a.",B8/C8-1)) | E8: 229903 | F8: 88736 | G8: =IF(OR(E8="",F8=""),"",IF(F8=0,"n.a.",E8/F8-1))
A9: Single Skin – Volume (m²) | B9: 16271 | C9: 13834 | D9: =IF(OR(B9="",C9=""),"",IF(C9=0,"n.a.",B9/C9-1)) | E9: 122613 | F9: 52330 | G9: =IF(OR(E9="",F9=""),"",IF(F9=0,"n.a.",E9/F9-1))
A10: Benchmark – Volume (m²) | B10: 7880 | C10: 0 | D10: =IF(OR(B10="",C10=""),"",IF(C10=0,"n.a.",B10/C10-1)) | E10: 5817 | F10: 563 | G10: =IF(OR(E10="",F10=""),"",IF(F10=0,"n.a.",E10/F10-1))
A11: IMP – Revenue (COP MM) | B11: 14484 | C11: 12723 | D11: =IF(OR(B11="",C11=""),"",IF(C11=0,"n.a.",B11/C11-1)) | E11: 144659 | F11: 108228 | G11: =IF(OR(E11="",F11=""),"",IF(F11=0,"n.a.",E11/F11-1))
A12: Margen (Gross-STD) | B12: 0.27 | C12: 0.24 | D12: =IF(OR(B12="",C12=""),"",(B12-C12)*100) | E12: 0.25 | F12: 0.24 | G12: =IF(OR(E12="",F12=""),"",(E12-F12)*100)
A14: N° mes | B14: Mes | C14: Ingresos CY (COP MM) | D14: Ingresos PY (COP MM) | E14: YoY | F14: Margen CY % | G14: Fuente gráfico: CY | H14: Fuente gráfico: PY | I14: Etiqueta barra 2026: OI m² | J14: Etiqueta barra 2025: OI m² (input)
A15: 1 | B15: Jan | C15: 9968.166 | D15: 7958.8 | E15: =IF(OR(C15="",D15=""),"",IF(D15=0,"n.a.",C15/D15-1)) | F15: 0.251 | G15: =IF(A15<=$B$4,C15,"") | H15: =D15 | I15: =IF(A15<=$B$4,'06_Perf_Forecast'!E7,"")
A16: 2 | B16: Feb | C16: 12767.714 | D16: 10536.7 | E16: =IF(OR(C16="",D16=""),"",IF(D16=0,"n.a.",C16/D16-1)) | F16: 0.254 | G16: =IF(A16<=$B$4,C16,"") | H16: =D16 | I16: =IF(A16<=$B$4,'06_Perf_Forecast'!E8,"")
A17: 3 | B17: Mar | C17: 14462.925 | D17: 12471.2 | E17: =IF(OR(C17="",D17=""),"",IF(D17=0,"n.a.",C17/D17-1)) | F17: 0.261 | G17: =IF(A17<=$B$4,C17,"") | H17: =D17 | I17: =IF(A17<=$B$4,'06_Perf_Forecast'!E9,"")
A18: 4 | B18: Apr | C18: 12270.448 | D18: 9577 | E18: =IF(OR(C18="",D18=""),"",IF(D18=0,"n.a.",C18/D18-1)) | F18: 0.257 | G18: =IF(A18<=$B$4,C18,"") | H18: =D18 | I18: =IF(A18<=$B$4,'06_Perf_Forecast'!E10,"")
A19: 5 | B19: May | C19: 27093.858 | D19: 8092 | E19: =IF(OR(C19="",D19=""),"",IF(D19=0,"n.a.",C19/D19-1)) | F19: 0.209 | G19: =IF(A19<=$B$4,C19,"") | H19: =D19 | I19: =IF(A19<=$B$4,'06_Perf_Forecast'!E11,"")
A20: 6 | B20: Jun | C20: 13652.194 | D20: 11810.8 | E20: =IF(OR(C20="",D20=""),"",IF(D20=0,"n.a.",C20/D20-1)) | F20: 0.285 | G20: =IF(A20<=$B$4,C20,"") | H20: =D20 | I20: =IF(A20<=$B$4,'06_Perf_Forecast'!E12,"")
A21: 7 | B21: Jul | C21: 11718.909 | D21: 7612.5 | E21: =IF(OR(C21="",D21=""),"",IF(D21=0,"n.a.",C21/D21-1)) | F21: 0.273 | G21: =IF(A21<=$B$4,C21,"") | H21: =D21 | I21: =IF(A21<=$B$4,'06_Perf_Forecast'!E13,"")
A22: 8 | B22: Aug | C22: 14500.72 | D22: 16772.6 | E22: =IF(OR(C22="",D22=""),"",IF(D22=0,"n.a.",C22/D22-1)) | F22: 0.268 | G22: =IF(A22<=$B$4,C22,"") | H22: =D22 | I22: =IF(A22<=$B$4,'06_Perf_Forecast'!E14,"")
A23: 9 | B23: Sep | C23: 13740.67 | D23: 10673.6 | E23: =IF(OR(C23="",D23=""),"",IF(D23=0,"n.a.",C23/D23-1)) | F23: 0.271 | G23: =IF(A23<=$B$4,C23,"") | H23: =D23 | I23: =IF(A23<=$B$4,'06_Perf_Forecast'!E15,"")
A24: 10 | B24: Oct | C24: 14484 | D24: 12723.1 | E24: =IF(OR(C24="",D24=""),"",IF(D24=0,"n.a.",C24/D24-1)) | F24: =B12 | G24: =IF(A24<=$B$4,C24,"") | H24: =D24 | I24: =IF(A24<=$B$4,'06_Perf_Forecast'!E16,"")
A25: 11 | B25: Nov | D25: 12445.1 | E25: =IF(OR(C25="",D25=""),"",IF(D25=0,"n.a.",C25/D25-1)) | G25: =IF(A25<=$B$4,C25,"") | H25: =D25 | I25: =IF(A25<=$B$4,'06_Perf_Forecast'!E17,"")
A26: 12 | B26: Dec | D26: 10462.4 | E26: =IF(OR(C26="",D26=""),"",IF(D26=0,"n.a.",C26/D26-1)) | G26: =IF(A26<=$B$4,C26,"") | H26: =D26 | I26: =IF(A26<=$B$4,'06_Perf_Forecast'!E18,"")
B27: YTD | C27: =SUMIFS(C15:C26,A15:A26,"<="&$B$4) | D27: =SUMIFS(D15:D26,A15:A26,"<="&$B$4) | E27: =IF(OR(C27="",D27=""),"",IF(D27=0,"n.a.",C27/D27-1))
B28: Control vs tabla | C28: =C27-E11

Sheet 03_OI_Canal
A1: 03 · Order Intake por canal (IMP)
A2: CM / PY / YoY / Gross Margin por canal · YTD y mix se alimentan de las hojas RSM (09–14) | G2: 157039 | H2: 160547 | I2: {=H2-G1:G2}
I3: 3508
A4: Canal | B4: OI mes CM (m²) | C4: OI mes PY (m²) | D4: YoY mes | E4: GM % CM | F4: GM % PY | G4: Δ GM (pp) | H4: OI YTD m² (RSM) | I4: Mix YTD % | J4: Ventas YTD m² | K4: Budget YTD m² | L4: % Cumpl. ventas
A5: Industrial | B5: =62296-13276+3508 | C5: 40646 | D5: =IF(OR(B5="",C5=""),"",IF(C5=0,"n.a.",B5/C5-1)) | E5: 0.3307481 | F5: 0.28692083 | G5: =IF(OR(E5="",F5=""),"",(E5-F5)*100) | H5: ='09_RSM_Industrial'!C18 | I5: =IFERROR(H5/$H$11,0) | J5: ='09_RSM_Industrial'!D18 | K5: ='09_RSM_Industrial'!E18 | L5: =IFERROR(J5/K5,0)
A6: Distribución | B6: 29274 | C6: 53212 | D6: =IF(OR(B6="",C6=""),"",IF(C6=0,"n.a.",B6/C6-1)) | E6: 0.3307481 | F6: 0.2701004 | G6: =IF(OR(E6="",F6=""),"",(E6-F6)*100) | H6: ='10_RSM_Distribucion'!C20 | I6: =IFERROR(H6/$H$11,0) | J6: ='10_RSM_Distribucion'!D20 | K6: ='10_RSM_Distribucion'!E20 | L6: =IFERROR(J6/K6,0)
A7: Otras Geografías | B7: 55560 | C7: 36701 | D7: =IF(OR(B7="",C7=""),"",IF(C7=0,"n.a.",B7/C7-1)) | E7: 0.16021742 | F7: 0.10427401 | G7: =IF(OR(E7="",F7=""),"",(E7-F7)*100) | H7: ='11_RSM_Otras_Geo'!C20 | I7: =IFERROR(H7/$H$11,0) | J7: ='11_RSM_Otras_Geo'!D20 | K7: ='11_RSM_Otras_Geo'!E20 | L7: =IFERROR(J7/K7,0)
A8: Cold Storage | B8: 10911 | C8: 0 | D8: =IF(OR(B8="",C8=""),"",IF(C8=0,"n.a.",B8/C8-1)) | E8: 0.28710517 | F8: 0.38680242 | G8: =IF(OR(E8="",F8=""),"",(E8-F8)*100) | H8: ='12_RSM_Cold_Storage'!C20 | I8: =IFERROR(H8/$H$11,0) | J8: ='12_RSM_Cold_Storage'!D20 | K8: ='12_RSM_Cold_Storage'!E20 | L8: =IFERROR(J8/K8,0)
A9: Site Cali | B9: 6625 | C9: 0 | D9: =IF(OR(B9="",C9=""),"",IF(C9=0,"n.a.",B9/C9-1)) | E9: 0.35059275 | F9: 0 | G9: =IF(OR(E9="",F9=""),"",(E9-F9)*100) | H9: ='13_RSM_Site_Cali'!C20 | I9: =IFERROR(H9/$H$11,0) | J9: ='13_RSM_Site_Cali'!D20 | K9: ='13_RSM_Site_Cali'!E20 | L9: =IFERROR(J9/K9,0)
A10: Ventas Alternativas | B10: 5649 | C10: 2669 | D10: =IF(OR(B10="",C10=""),"",IF(C10=0,"n.a.",B10/C10-1)) | E10: 0.41498837 | F10: 0.36956934 | G10: =IF(OR(E10="",F10=""),"",(E10-F10)*100) | H10: ='14_RSM_Vtas_Alt'!C20 | I10: =IFERROR(H10/$H$11,0) | J10: ='14_RSM_Vtas_Alt'!D20 | K10: ='14_RSM_Vtas_Alt'!E20 | L10: =IFERROR(J10/K10,0)
A11: TOTAL | B11: =IF(COUNT(B5:B10)=0,"",SUM(B5:B10)) | C11: =IF(COUNT(C5:C10)=0,"",SUM(C5:C10)) | D11: =IF(OR(B11="",C11=""),"",IF(C11=0,"n.a.",B11/C11-1)) | G11: =IF(OR(E11="",F11=""),"",(E11-F11)*100) | H11: =IF(COUNT(H5:H10)=0,"",SUM(H5:H10)) | I11: =SUM(I5:I10) | J11: =IF(COUNT(J5:J10)=0,"",SUM(J5:J10)) | K11: =IF(COUNT(K5:K10)=0,"",SUM(K5:K10)) | L11: =IFERROR(J11/K11,0)
A12: Control: Σ CM canales vs OI IMP mes (hoja 02) | B12: =IF(B11="","Pendiente",B11-'02_OI'!B7)
A13: Control: OI YTD RSM vs OI YTD IMP (hoja 02) | C13: 114611 | H13: =H11-'02_OI'!E7
C14: =+C13-C11

Sheet 22_Canales_Segmentos
A1: 22 · Motor de canales (Industrial · Distribución · Ventas Alternativas) y segmentos (Construcción · Refrigeración)
A2: Regla: Ventas Alternativas = valor del canal actual · Industrial + Distribución = total IMP − Alternativas, prorrateado con la participación Industrial/(Industrial+Distribución) del canal actual (o el % manual) · Segmentos = total de los 3 canales × % asignado manualmente.
A4: PARÁMETROS
A5: % Construcción por defecto (Refrigeración = 1 − Construcción) | B5: 0.7 | C5: Asigne el % real del mes. Se puede ajustar por métrica en la fila 24.
A8: Concepto (m²) | B8: OI mes CM | C8: OI mes PY | D8: OI YTD | E8: Ventas YTD | F8: Presupuesto YTD (Junta) | G8: Backlog CM | H8: Backlog PY | I8: OI YTD (RSM) | J8: Ventas YTD (RSM)
A9: Fuente del total | B9: 02_OI B7 | C9: 02_OI C7 | D9: 02_OI E7 | E9: 01_Overview E5 | F9: 21_Ppto_Junta N41 | G9: 04_Backlog B5 | H9: 04_Backlog C5 | I9: RSM C11 | J9: RSM D11
A10: Total IMP (m²) | B10: ='02_OI'!B7 | C10: ='02_OI'!C7 | D10: ='02_OI'!E7 | E10: ='01_Overview'!E5 | F10: ='21_Ppto_Junta'!N41 | G10: ='04_Backlog'!B5 | H10: ='04_Backlog'!C5 | I10: =RSM_Resumen_Canales!C11 | J10: =RSM_Resumen_Canales!D11
A11: Ventas Alternativas – canal actual | B11: ='03_OI_Canal'!B10 | C11: ='03_OI_Canal'!C10 | D11: ='03_OI_Canal'!H10 | E11: =RSM_Resumen_Canales!D10 | F11: ='21_Ppto_Junta'!N40 | G11: ='05_Backlog_Canal'!B10 | H11: ='05_Backlog_Canal'!C10 | I11: =RSM_Resumen_Canales!C10 | J11: =RSM_Resumen_Canales!D10
A12: Industrial + Distribución = Total − Alternativas | B12: =B10-B11 | C12: =C10-C11 | D12: =D10-D11 | E12: =E10-E11 | F12: =F10-F11 | G12: =G10-G11 | H12: =H10-H11 | I12: =I10-I11 | J12: =J10-J11
A13: Base prorrateo: Industrial (canal actual) | B13: ='03_OI_Canal'!B5 | C13: ='03_OI_Canal'!C5 | D13: ='03_OI_Canal'!H5 | E13: =RSM_Resumen_Canales!D5 | F13: ='21_Ppto_Junta'!N35 | G13: ='05_Backlog_Canal'!B5 | H13: ='05_Backlog_Canal'!C5 | I13: =RSM_Resumen_Canales!C5 | J13: =RSM_Resumen_Canales!D5
A14: Base prorrateo: Distribución (canal actual) | B14: ='03_OI_Canal'!B6 | C14: ='03_OI_Canal'!C6 | D14: ='03_OI_Canal'!H6 | E14: =RSM_Resumen_Canales!D6 | F14: ='21_Ppto_Junta'!N36 | G14: ='05_Backlog_Canal'!B6 | H14: ='05_Backlog_Canal'!C6 | I14: =RSM_Resumen_Canales!C6 | J14: =RSM_Resumen_Canales!D6
A15: % Industrial – prorrateo automático | B15: =IFERROR(B13/(B13+B14),0.5) | C15: =IFERROR(C13/(C13+C14),0.5) | D15: =IFERROR(D13/(D13+D14),0.5) | E15: =IFERROR(E13/(E13+E14),0.5) | F15: =IFERROR(F13/(F13+F14),0.5) | G15: =IFERROR(G13/(G13+G14),0.5) | H15: =IFERROR(H13/(H13+H14),0.5) | I15: =IFERROR(I13/(I13+I14),0.5) | J15: =IFERROR(J13/(J13+J14),0.5)
A16: % Industrial – ajuste manual (opcional)
A17: % Industrial aplicado | B17: =IF(B16="",B15,B16) | C17: =IF(C16="",C15,C16) | D17: =IF(D16="",D15,D16) | E17: =IF(E16="",E15,E16) | F17: =IF(F16="",F15,F16) | G17: =IF(G16="",G15,G16) | H17: =IF(H16="",H15,H16) | I17: =IF(I16="",I15,I16) | J17: =IF(J16="",J15,J16)
A18: % Distribución aplicado | B18: =1-B17 | C18: =1-C17 | D18: =1-D17 | E18: =1-E17 | F18: =1-F17 | G18: =1-G17 | H18: =1-H17 | I18: =1-I17 | J18: =1-J17
A19: INDUSTRIAL | B19: =B12*B17 | C19: =C12*C17 | D19: =D12*D17 | E19: =E12*E17 | F19: =F12*F17 | G19: =G12*G17 | H19: =H12*H17 | I19: =I12*I17 | J19: =J12*J17
A20: DISTRIBUCIÓN | B20: =B12*B18 | C20: =C12*C18 | D20: =D12*D18 | E20: =E12*E18 | F20: =F12*F18 | G20: =G12*G18 | H20: =H12*H18 | I20: =I12*I18 | J20: =J12*J18
A21: VENTAS ALTERNATIVAS | B21: =B11 | C21: =C11 | D21: =D11 | E21: =E11 | F21: =F11 | G21: =G11 | H21: =H11 | I21: =I11 | J21: =J11
A22: TOTAL CANALES | B22: =SUM(B19:B21) | C22: =SUM(C19:C21) | D22: =SUM(D19:D21) | E22: =SUM(E19:E21) | F22: =SUM(F19:F21) | G22: =SUM(G19:G21) | H22: =SUM(H19:H21) | I22: =SUM(I19:I21) | J22: =SUM(J19:J21)
A23: Control vs total IMP (debe ser 0) | B23: =ROUND(B22-B10,0) | C23: =ROUND(C22-C10,0) | D23: =ROUND(D22-D10,0) | E23: =ROUND(E22-E10,0) | F23: =ROUND(F22-F10,0) | G23: =ROUND(G22-G10,0) | H23: =ROUND(H22-H10,0) | I23: =ROUND(I22-I10,0) | J23: =ROUND(J22-J10,0)
A24: % Construcción – ajuste manual (opcional)
A25: % Construcción aplicado | B25: =IF(B24="",$B$5,B24) | C25: =IF(C24="",$B$5,C24) | D25: =IF(D24="",$B$5,D24) | E25: =IF(E24="",$B$5,E24) | F25: =IF(F24="",$B$5,F24) | G25: =IF(G24="",$B$5,G24) | H25: =IF(H24="",$B$5,H24) | I25: =IF(I24="",$B$5,I24) | J25: =IF(J24="",$B$5,J24)
A26: % Refrigeración aplicado | B26: =1-B25 | C26: =1-C25 | D26: =1-D25 | E26: =1-E25 | F26: =1-F25 | G26: =1-G25 | H26: =1-H25 | I26: =1-I25 | J26: =1-J25
A27: CONSTRUCCIÓN | B27: =B22*B25 | C27: =C22*C25 | D27: =D22*D25 | E27: =E22*E25 | F27: =F22*F25 | G27: =G22*G25 | H27: =H22*H25 | I27: =I22*I25 | J27: =J22*J25
A28: REFRIGERACIÓN | B28: =B22*B26 | C28: =C22*C26 | D28: =D22*D26 | E28: =E22*E26 | F28: =F22*F26 | G28: =G22*G26 | H28: =H22*H26 | I28: =I22*I26 | J28: =J22*J26
A29: TOTAL SEGMENTOS | B29: =B27+B28 | C29: =C27+C28 | D29: =D27+D28 | E29: =E27+E28 | F29: =F27+F28 | G29: =G27+G28 | H29: =H27+H28 | I29: =I27+I28 | J29: =J27+J28
A31: MARGEN BRUTO (GM %) POR CANAL NUEVO – ponderado por volumen
A32: Canal | B32: OI GM CM | C32: OI GM PY | D32: Backlog GM CM | E32: Backlog GM PY
A33: Industrial | B33: =IFERROR(('03_OI_Canal'!B5*'03_OI_Canal'!E5+$B$17*SUMPRODUCT('03_OI_Canal'!B7:B9,'03_OI_Canal'!E7:E9))/('03_OI_Canal'!B5+$B$17*SUM('03_OI_Canal'!B7:B9)),"") | C33: =IFERROR(('03_OI_Canal'!C5*'03_OI_Canal'!F5+$C$17*SUMPRODUCT('03_OI_Canal'!C7:C9,'03_OI_Canal'!F7:F9))/('03_OI_Canal'!C5+$C$17*SUM('03_OI_Canal'!C7:C9)),"") | D33: =IFERROR(('05_Backlog_Canal'!B5*'05_Backlog_Canal'!E5+$G$17*SUMPRODUCT('05_Backlog_Canal'!B7:B9,'05_Backlog_Canal'!E7:E9))/('05_Backlog_Canal'!B5+$G$17*SUM('05_Backlog_Canal'!B7:B9)),"") | E33: =IFERROR(('05_Backlog_Canal'!C5*'05_Backlog_Canal'!F5+$H$17*SUMPRODUCT('05_Backlog_Canal'!C7:C9,'05_Backlog_Canal'!F7:F9))/('05_Backlog_Canal'!C5+$H$17*SUM('05_Backlog_Canal'!C7:C9)),"")
A34: Distribución | B34: =IFERROR(('03_OI_Canal'!B6*'03_OI_Canal'!E6+(1-$B$17)*SUMPRODUCT('03_OI_Canal'!B7:B9,'03_OI_Canal'!E7:E9))/('03_OI_Canal'!B6+(1-$B$17)*SUM('03_OI_Canal'!B7:B9)),"") | C34: =IFERROR(('03_OI_Canal'!C6*'03_OI_Canal'!F6+(1-$C$17)*SUMPRODUCT('03_OI_Canal'!C7:C9,'03_OI_Canal'!F7:F9))/('03_OI_Canal'!C6+(1-$C$17)*SUM('03_OI_Canal'!C7:C9)),"") | D34: =IFERROR(('05_Backlog_Canal'!B6*'05_Backlog_Canal'!E6+(1-$G$17)*SUMPRODUCT('05_Backlog_Canal'!B7:B9,'05_Backlog_Canal'!E7:E9))/('05_Backlog_Canal'!B6+(1-$G$17)*SUM('05_Backlog_Canal'!B7:B9)),"") | E34: =IFERROR(('05_Backlog_Canal'!C6*'05_Backlog_Canal'!F6+(1-$H$17)*SUMPRODUCT('05_Backlog_Canal'!C7:C9,'05_Backlog_Canal'!F7:F9))/('05_Backlog_Canal'!C6+(1-$H$17)*SUM('05_Backlog_Canal'!C7:C9)),"")
A35: Ventas Alternativas | B35: =IFERROR('03_OI_Canal'!E10,"") | C35: =IFERROR('03_OI_Canal'!F10,"") | D35: =IFERROR('05_Backlog_Canal'!E10,"") | E35: =IFERROR('05_Backlog_Canal'!F10,"")
A36: TOTAL (ponderado) | B36: =IFERROR(SUMPRODUCT('03_OI_Canal'!B5:B10,'03_OI_Canal'!E5:E10)/SUM('03_OI_Canal'!B5:B10),"") | C36: =IFERROR(SUMPRODUCT('03_OI_Canal'!C5:C10,'03_OI_Canal'!F5:F10)/SUM('03_OI_Canal'!C5:C10),"") | D36: =IFERROR(SUMPRODUCT('05_Backlog_Canal'!B5:B10,'05_Backlog_Canal'!E5:E10)/SUM('05_Backlog_Canal'!B5:B10),"") | E36: =IFERROR(SUMPRODUCT('05_Backlog_Canal'!C5:C10,'05_Backlog_Canal'!F5:F10)/SUM('05_Backlog_Canal'!C5:C10),"")
A37: Construcción (input opcional)
A38: Refrigeración (input opcional)
A39: Si el GM por segmento queda en blanco, el slide muestra '—'.
A41: TABLA SLIDE · ORDER INTAKE BY CHANNEL – IMP
A42: Canal | B42: OI CM | C42: OI PY | D42: YoY | E42: GM CM | F42: GM PY | G42: Var GM (pp) | H42: OI YTD | I42: Mix YTD | J42: Ventas YTD | K42: Budget YTD | L42: % Budget
A43: Industrial | B43: =B19 | C43: =C19 | D43: =IF(OR(B43="",C43=""),"",IF(C43=0,"n.a.",B43/C43-1)) | E43: =B33 | F43: =C33 | G43: =IF(OR(E43="",F43=""),"",(E43-F43)*100) | H43: =D19 | I43: =IFERROR(H43/$H$46,0) | J43: =E19 | K43: =F19 | L43: =IFERROR(J43/K43,0)
A44: Distribución | B44: =B20 | C44: =C20 | D44: =IF(OR(B44="",C44=""),"",IF(C44=0,"n.a.",B44/C44-1)) | E44: =B34 | F44: =C34 | G44: =IF(OR(E44="",F44=""),"",(E44-F44)*100) | H44: =D20 | I44: =IFERROR(H44/$H$46,0) | J44: =E20 | K44: =F20 | L44: =IFERROR(J44/K44,0)
A45: Ventas Alternativas | B45: =B21 | C45: =C21 | D45: =IF(OR(B45="",C45=""),"",IF(C45=0,"n.a.",B45/C45-1)) | E45: =B35 | F45: =C35 | G45: =IF(OR(E45="",F45=""),"",(E45-F45)*100) | H45: =D21 | I45: =IFERROR(H45/$H$46,0) | J45: =E21 | K45: =F21 | L45: =IFERROR(J45/K45,0)
A46: TOTAL | B46: =B22 | C46: =C22 | D46: =IF(OR(B46="",C46=""),"",IF(C46=0,"n.a.",B46/C46-1)) | E46: =B36 | F46: =C36 | G46: =IF(OR(E46="",F46=""),"",(E46-F46)*100) | H46: =D22 | I46: =IFERROR(H46/$H$46,0) | J46: =E22 | K46: =F22 | L46: =IFERROR(J46/K46,0)
A48: Segmento | B48: OI CM | C48: OI PY | D48: YoY | E48: GM CM | F48: GM PY | G48: Var GM (pp) | H48: OI YTD | I48: Mix YTD | J48: Ventas YTD | K48: Budget YTD | L48: % Budget
A49: Construcción | B49: =B27 | C49: =C27 | D49: =IF(OR(B49="",C49=""),"",IF(C49=0,"n.a.",B49/C49-1)) | E49: =IF(B37="","",B37) | F49: =IF(C37="","",C37) | G49: =IF(OR(E49="",F49=""),"",(E49-F49)*100) | H49: =D27 | I49: =IFERROR(H49/$H$51,0) | J49: =E27 | K49: =F27 | L49: =IFERROR(J49/K49,0)
A50: Refrigeración | B50: =B28 | C50: =C28 | D50: =IF(OR(B50="",C50=""),"",IF(C50=0,"n.a.",B50/C50-1)) | E50: =IF(B38="","",B38) | F50: =IF(C38="","",C38) | G50: =IF(OR(E50="",F50=""),"",(E50-F50)*100) | H50: =D28 | I50: =IFERROR(H50/$H$51,0) | J50: =E28 | K50: =F28 | L50: =IFERROR(J50/K50,0)
A51: TOTAL | B51: =B29 | C51: =C29 | D51: =IF(OR(B51="",C51=""),"",IF(C51=0,"n.a.",B51/C51-1)) | E51: =IF(B36="","",B36) | F51: =IF(C36="","",C36) | G51: =IF(OR(E51="",F51=""),"",(E51-F51)*100) | H51: =D29 | I51: =IFERROR(H51/$H$51,0) | J51: =E29 | K51: =F29 | L51: =IFERROR(J51/K51,0)
A53: TABLA SLIDE · BACKLOG BY CHANNEL – IMP
A54: Canal | B54: Backlog CM | C54: Backlog PY | D54: YoY | E54: GM CM | F54: GM PY | G54: Δ GM (pp) | H54: Mix %
A55: Industrial | B55: =G19 | C55: =H19 | D55: =IF(OR(B55="",C55=""),"",IF(C55=0,"n.a.",B55/C55-1)) | E55: =D33 | F55: =E33 | G55: =IF(OR(E55="",F55=""),"",(E55-F55)*100) | H55: =IFERROR(B55/$B$58,0)
A56: Distribución | B56: =G20 | C56: =H20 | D56: =IF(OR(B56="",C56=""),"",IF(C56=0,"n.a.",B56/C56-1)) | E56: =D34 | F56: =E34 | G56: =IF(OR(E56="",F56=""),"",(E56-F56)*100) | H56: =IFERROR(B56/$B$58,0)
A57: Ventas Alternativas | B57: =G21 | C57: =H21 | D57: =IF(OR(B57="",C57=""),"",IF(C57=0,"n.a.",B57/C57-1)) | E57: =D35 | F57: =E35 | G57: =IF(OR(E57="",F57=""),"",(E57-F57)*100) | H57: =IFERROR(B57/$B$58,0)
A58: TOTAL | B58: =G22 | C58: =H22 | D58: =IF(OR(B58="",C58=""),"",IF(C58=0,"n.a.",B58/C58-1)) | E58: =D36 | F58: =E36 | G58: =IF(OR(E58="",F58=""),"",(E58-F58)*100) | H58: =IFERROR(B58/$B$58,0)
A60: Segmento | B60: Backlog CM | C60: Backlog PY | D60: YoY | E60: GM CM | F60: GM PY | G60: Δ GM (pp) | H60: Mix %
A61: Construcción | B61: =G27 | C61: =H27 | D61: =IF(OR(B61="",C61=""),"",IF(C61=0,"n.a.",B61/C61-1)) | E61: =IF(D37="","",D37) | F61: =IF(E37="","",E37) | G61: =IF(OR(E61="",F61=""),"",(E61-F61)*100) | H61: =IFERROR(B61/$B$63,0)
A62: Refrigeración | B62: =G28 | C62: =H28 | D62: =IF(OR(B62="",C62=""),"",IF(C62=0,"n.a.",B62/C62-1)) | E62: =IF(D38="","",D38) | F62: =IF(E38="","",E38) | G62: =IF(OR(E62="",F62=""),"",(E62-F62)*100) | H62: =IFERROR(B62/$B$63,0)
A63: TOTAL | B63: =G29 | C63: =H29 | D63: =IF(OR(B63="",C63=""),"",IF(C63=0,"n.a.",B63/C63-1)) | E63: =D36 | F63: =E36 | G63: =IF(OR(E63="",F63=""),"",(E63-F63)*100) | H63: =IFERROR(B63/$B$63,0)
A65: TABLA SLIDE · RSM PERFORMANCE – CANALES Y SEGMENTOS (YTD, resumen)
A66: Canal | B66: OI YTD | C66: Ventas YTD | D66: Budget YTD (Junta) | E66: Brecha | F66: % Budget | G66: Backlog | H66: Margen backlog | I66: Mix backlog
A67: Industrial | B67: =I19 | C67: =J19 | D67: =F19 | E67: =C67-D67 | F67: =IFERROR(C67/D67,0) | G67: =G19 | H67: =D33 | I67: =IFERROR(G67/$G$70,0)
A68: Distribución | B68: =I20 | C68: =J20 | D68: =F20 | E68: =C68-D68 | F68: =IFERROR(C68/D68,0) | G68: =G20 | H68: =D34 | I68: =IFERROR(G68/$G$70,0)
A69: Ventas Alternativas | B69: =I21 | C69: =J21 | D69: =F21 | E69: =C69-D69 | F69: =IFERROR(C69/D69,0) | G69: =G21 | H69: =D35 | I69: =IFERROR(G69/$G$70,0)
A70: TOTAL | B70: =I22 | C70: =J22 | D70: =F22 | E70: =C70-D70 | F70: =IFERROR(C70/D70,0) | G70: =G22 | H70: =D36 | I70: =IFERROR(G70/$G$70,0)
A72: Segmento | B72: OI YTD | C72: Ventas YTD | D72: Budget YTD (Junta) | E72: Brecha | F72: % Budget | G72: Backlog | H72: Margen backlog | I72: Mix backlog
A73: Construcción | B73: =I27 | C73: =J27 | D73: =F27 | E73: =C73-D73 | F73: =IFERROR(C73/D73,0) | G73: =G27 | H73: =IF(D37="","",D37) | I73: =IFERROR(G73/$G$75,0)
A74: Refrigeración | B74: =I28 | C74: =J28 | D74: =F28 | E74: =C74-D74 | F74: =IFERROR(C74/D74,0) | G74: =G28 | H74: =IF(D38="","",D38) | I74: =IFERROR(G74/$G$75,0)
A75: TOTAL | B75: =I29 | C75: =J29 | D75: =F29 | E75: =C75-D75 | F75: =IFERROR(C75/D75,0) | G75: =G29 | H75: =D36 | I75: =IFERROR(G75/$G$75,0)

Sheet 21_Ppto_Junta
A1: 21 · Presupuesto de Junta, metas y ventas reales (IMP, m²)
A2: Amarillo = input. Actualice el presupuesto mensual, los % por canal y las ventas reales; todo lo demás (YTD, asignación por canal y por segmento) es fórmula.
A4: Mes de corte (de 02_OI B4) | B4: ='02_OI'!B4
A5: Base de participación por canal | B5: Anterior | C5: Anterior = % de cada canal en el presupuesto previo (RSM). Junta = % mensuales del archivo de Junta (filas 17–21).
A7: Concepto | B7: Ene | C7: Feb | D7: Mar | E7: Abr | F7: May | G7: Jun | H7: Jul | I7: Ago | J7: Sep | K7: Oct | L7: Nov | M7: Dic | N7: YTD (≤ corte) | O7: Total año
A8: N° mes | B8: 1 | C8: 2 | D8: 3 | E8: 4 | F8: 5 | G8: 6 | H8: 7 | I8: 8 | J8: 9 | K8: 10 | L8: 11 | M8: 12
A9: Presupuesto Junta IMP (m²) | B9: 104628 | C9: 96362.693 | D9: 115099.08 | E9: 98564.602 | F9: 106108.77 | G9: 121966.05 | H9: 115931.37 | I9: 143000 | J9: 125010 | K9: 123189 | L9: 132443 | M9: 90000 | N9: =SUMIFS(B9:M9,$B$8:$M$8,"<="&$B$4) | O9: =SUM(B9:M9)
A10: Ventas reales IMP (m²) – mensual | J10: 125933 | K10: 141231 | N10: =SUMIFS(B10:M10,$B$8:$M$8,"<="&$B$4) | O10: =SUM(B10:M10)
A11: % cumplimiento mes | B11: =IF(OR(B10="",B9=0),"",B10/B9) | C11: =IF(OR(C10="",C9=0),"",C10/C9) | D11: =IF(OR(D10="",D9=0),"",D10/D9) | E11: =IF(OR(E10="",E9=0),"",E10/E9) | F11: =IF(OR(F10="",F9=0),"",F10/F9) | G11: =IF(OR(G10="",G9=0),"",G10/G9) | H11: =IF(OR(H10="",H9=0),"",H10/H9) | I11: =IF(OR(I10="",I9=0),"",I10/I9) | ... M11: =IF(OR(M10="",M9=0),"",M10/M9)
A12: Ventas YTD reales – cifra oficial (01_Overview E5) | B12: Si diligencia todos los meses de la fila 10, N10 debe igualar N12. | N12: ='01_Overview'!E5
A13: % cumplimiento YTD vs Presupuesto Junta | N13: =IFERROR(N12/N9,0)
A15: % participación – Presupuesto Junta | B15: Ene | C15: Feb | D15: Mar | E15: Abr | F15: May | G15: Jun | H15: Jul | I15: Ago | J15: Sep | K15: Oct | L15: Nov | M15: Dic | N15: YTD ponderado | O15: Año
A16: (los meses deben sumar 100%; ver control fila 22)
A17: Distribución | B17: 0.1979 | C17: 0.1913 | D17: 0.1937 | E17: 0.2055 | F17: 0.206 | G17: 0.2059 | H17: 0.2054 | I17: 0.2054 | J17: 0.1976 | K17: 0.1976 | L17: 0.2054 | M17: 0.2231 | N17: =IFERROR(SUMPRODUCT(B17:M17,$B$9:$M$9,--($B$8:$M$8<=$B$4))/$N$9,0) | O17: =IFERROR(SUMPRODUCT(B17:M17,$B$9:$M$9)/$O$9,0)
A18: Industrial | B18: 0.4055 | C18: 0.392 | D18: 0.3903 | E18: 0.3658 | F18: 0.3417 | G18: 0.3415 | H18: 0.3407 | I18: 0.3407 | J18: 0.3276 | K18: 0.3683 | L18: 0.384 | M18: 0.416 | N18: =IFERROR(SUMPRODUCT(B18:M18,$B$9:$M$9,--($B$8:$M$8<=$B$4))/$N$9,0) | O18: =IFERROR(SUMPRODUCT(B18:M18,$B$9:$M$9)/$O$9,0)
A19: Otras Geografías | B19: 0.2648 | C19: 0.2987 | D19: 0.3059 | E19: 0.3185 | F19: 0.3193 | G19: 0.3166 | H19: 0.3183 | I19: 0.3183 | J19: 0.3444 | K19: 0.3444 | L19: 0.3183 | M19: 0.2596 | N19: =IFERROR(SUMPRODUCT(B19:M19,$B$9:$M$9,--($B$8:$M$8<=$B$4))/$N$9,0) | O19: =IFERROR(SUMPRODUCT(B19:M19,$B$9:$M$9)/$O$9,0)
A20: SITES (Site Cali) | B20: 0.081 | C20: 0.0783 | D20: 0.078 | E20: 0.0731 | F20: 0.0979 | G20: 0.1008 | H20: 0.1006 | I20: 0.1006 | J20: 0.0967 | K20: 0.056 | L20: 0.0572 | M20: 0.0632 | N20: =IFERROR(SUMPRODUCT(B20:M20,$B$9:$M$9,--($B$8:$M$8<=$B$4))/$N$9,0) | O20: =IFERROR(SUMPRODUCT(B20:M20,$B$9:$M$9)/$O$9,0)
A21: Ventas Alternativas | B21: 0.0508 | C21: 0.0398 | D21: 0.0321 | E21: 0.0371 | F21: 0.0351 | G21: 0.0351 | H21: 0.035 | I21: 0.035 | J21: 0.0337 | K21: 0.0337 | L21: 0.035 | M21: 0.0381 | N21: =IFERROR(SUMPRODUCT(B21:M21,$B$9:$M$9,--($B$8:$M$8<=$B$4))/$N$9,0) | O21: =IFERROR(SUMPRODUCT(B21:M21,$B$9:$M$9)/$O$9,0)
A22: Control Σ % | B22: =SUM(B17:B21) | C22: =SUM(C17:C21) | D22: =SUM(D17:D21) | E22: =SUM(E17:E21) | F22: =SUM(F17:F21) | G22: =SUM(G17:G21) | H22: =SUM(H17:H21) | I22: =SUM(I17:I21) | ... O22: =SUM(O17:O21)
A24: Canal (estructura anterior) | B24: Budget anterior YTD (RSM) | C24: % part. anterior | D24: % part. Junta YTD | E24: % part. aplicada
A25: Industrial | B25: =RSM_Resumen_Canales!E5 | C25: =IFERROR(B25/$B$31,0) | D25: =N18 | E25: =IF($B$5="Junta",D25,C25)
A26: Distribution | B26: =RSM_Resumen_Canales!E6 | C26: =IFERROR(B26/$B$31,0) | D26: =N17 | E26: =IF($B$5="Junta",D26,C26)
A27: Other Geographies | B27: =RSM_Resumen_Canales!E7 | C27: =IFERROR(B27/$B$31,0) | D27: =N19 | E27: =IF($B$5="Junta",D27,C27)
A28: Cold Storage | B28: =RSM_Resumen_Canales!E8 | C28: =IFERROR(B28/$B$31,0) | D28: 0 | E28: =IF($B$5="Junta",D28,C28)
A29: Site Cali | B29: =RSM_Resumen_Canales!E9 | C29: =IFERROR(B29/$B$31,0) | D29: =N20 | E29: =IF($B$5="Junta",D29,C29)
A30: Alternative Sales | B30: =RSM_Resumen_Canales!E10 | C30: =IFERROR(B30/$B$31,0) | D30: =N21 | E30: =IF($B$5="Junta",D30,C30)
A31: TOTAL | B31: =SUM(B25:B30) | C31: =SUM(C25:C30) | D31: =SUM(D25:D30) | E31: =SUM(E25:E30)
A33: Presupuesto Junta por canal anterior (m²) | B33: Ene | C33: Feb | D33: Mar | E33: Abr | F33: May | G33: Jun | H33: Jul | I33: Ago | J33: Sep | K33: Oct | L33: Nov | M33: Dic | N33: YTD (≤ corte) | O33: Total año
A34: (base = selector B5)
A35: Industrial | B35: =IF($B$5="Junta",B$9*B18,B$9*$C25) | C35: =IF($B$5="Junta",C$9*C18,C$9*$C25) | D35: =IF($B$5="Junta",D$9*D18,D$9*$C25) | E35: =IF($B$5="Junta",E$9*E18,E$9*$C25) | F35: =IF($B$5="Junta",F$9*F18,F$9*$C25) | G35: =IF($B$5="Junta",G$9*G18,G$9*$C25) | H35: =IF($B$5="Junta",H$9*H18,H$9*$C25) | I35: =IF($B$5="Junta",I$9*I18,I$9*$C25) | ... M35: =IF($B$5="Junta",M$9*M18,M$9*$C25) | N35: =SUMIFS(B35:M35,$B$8:$M$8,"<="&$B$4) | O35: =SUM(B35:M35)
A36: Distribution | B36: =IF($B$5="Junta",B$9*B17,B$9*$C26) | C36: =IF($B$5="Junta",C$9*C17,C$9*$C26) | D36: =IF($B$5="Junta",D$9*D17,D$9*$C26) | E36: =IF($B$5="Junta",E$9*E17,E$9*$C26) | F36: =IF($B$5="Junta",F$9*F17,F$9*$C26) | G36: =IF($B$5="Junta",G$9*G17,G$9*$C26) | H36: =IF($B$5="Junta",H$9*H17,H$9*$C26) | I36: =IF($B$5="Junta",I$9*I17,I$9*$C26) | ... M36: =IF($B$5="Junta",M$9*M17,M$9*$C26) | N36: =SUMIFS(B36:M36,$B$8:$M$8,"<="&$B$4) | O36: =SUM(B36:M36)
A37: Other Geographies | B37: =IF($B$5="Junta",B$9*B19,B$9*$C27) | C37: =IF($B$5="Junta",C$9*C19,C$9*$C27) | D37: =IF($B$5="Junta",D$9*D19,D$9*$C27) | E37: =IF($B$5="Junta",E$9*E19,E$9*$C27) | F37: =IF($B$5="Junta",F$9*F19,F$9*$C27) | G37: =IF($B$5="Junta",G$9*G19,G$9*$C27) | H37: =IF($B$5="Junta",H$9*H19,H$9*$C27) | I37: =IF($B$5="Junta",I$9*I19,I$9*$C27) | ... M37: =IF($B$5="Junta",M$9*M19,M$9*$C27) | N37: =SUMIFS(B37:M37,$B$8:$M$8,"<="&$B$4) | O37: =SUM(B37:M37)
A38: Cold Storage | B38: =IF($B$5="Junta",0,B$9*$C28) | C38: =IF($B$5="Junta",0,C$9*$C28) | D38: =IF($B$5="Junta",0,D$9*$C28) | E38: =IF($B$5="Junta",0,E$9*$C28) | F38: =IF($B$5="Junta",0,F$9*$C28) | G38: =IF($B$5="Junta",0,G$9*$C28) | H38: =IF($B$5="Junta",0,H$9*$C28) | I38: =IF($B$5="Junta",0,I$9*$C28) | ... M38: =IF($B$5="Junta",0,M$9*$C28) | N38: =SUMIFS(B38:M38,$B$8:$M$8,"<="&$B$4) | O38: =SUM(B38:M38)
A39: Site Cali | B39: =IF($B$5="Junta",B$9*B20,B$9*$C29) | C39: =IF($B$5="Junta",C$9*C20,C$9*$C29) | D39: =IF($B$5="Junta",D$9*D20,D$9*$C29) | E39: =IF($B$5="Junta",E$9*E20,E$9*$C29) | F39: =IF($B$5="Junta",F$9*F20,F$9*$C29) | G39: =IF($B$5="Junta",G$9*G20,G$9*$C29) | H39: =IF($B$5="Junta",H$9*H20,H$9*$C29) | I39: =IF($B$5="Junta",I$9*I20,I$9*$C29) | ... M39: =IF($B$5="Junta",M$9*M20,M$9*$C29) | N39: =SUMIFS(B39:M39,$B$8:$M$8,"<="&$B$4) | O39: =SUM(B39:M39)
A40: Alternative Sales | B40: =IF($B$5="Junta",B$9*B21,B$9*$C30) | C40: =IF($B$5="Junta",C$9*C21,C$9*$C30) | D40: =IF($B$5="Junta",D$9*D21,D$9*$C30) | E40: =IF($B$5="Junta",E$9*E21,E$9*$C30) | F40: =IF($B$5="Junta",F$9*F21,F$9*$C30) | G40: =IF($B$5="Junta",G$9*G21,G$9*$C30) | H40: =IF($B$5="Junta",H$9*H21,H$9*$C30) | I40: =IF($B$5="Junta",I$9*I21,I$9*$C30) | ... M40: =IF($B$5="Junta",M$9*M21,M$9*$C30) | N40: =SUMIFS(B40:M40,$B$8:$M$8,"<="&$B$4) | O40: =SUM(B40:M40)
A41: TOTAL | B41: =SUM(B35:B40) | C41: =SUM(C35:C40) | D41: =SUM(D35:D40) | E41: =SUM(E35:E40) | F41: =SUM(F35:F40) | G41: =SUM(G35:G40) | H41: =SUM(H35:H40) | I41: =SUM(I35:I40) | ... O41: =SUM(O35:O40)
A43: Presupuesto por nueva estructura (m²) | B43: Ene | C43: Feb | D43: Mar | E43: Abr | F43: May | G43: Jun | H43: Jul | I43: Ago | J43: Sep | K43: Oct | L43: Nov | M43: Dic | N43: YTD (≤ corte) | O43: Total año
A44: Ventas Alternativas | B44: =B40 | C44: =C40 | D44: =D40 | E44: =E40 | F44: =F40 | G44: =G40 | H44: =H40 | I44: =I40 | ... M44: =M40 | N44: =SUMIFS(B44:M44,$B$8:$M$8,"<="&$B$4) | O44: =SUM(B44:M44)
A45: Industrial + Distribución (total − Alternativas) | B45: =B41-B44 | C45: =C41-C44 | D45: =D41-D44 | E45: =E41-E44 | F45: =F41-F44 | G45: =G41-G44 | H45: =H41-H44 | I45: =I41-I44 | ... M45: =M41-M44 | N45: =SUMIFS(B45:M45,$B$8:$M$8,"<="&$B$4) | O45: =SUM(B45:M45)
A46: % Industrial (prorrateo, hoja 22) | B46: ='22_Canales_Segmentos'!$F$17 | C46: ='22_Canales_Segmentos'!$F$17 | D46: ='22_Canales_Segmentos'!$F$17 | E46: ='22_Canales_Segmentos'!$F$17 | F46: ='22_Canales_Segmentos'!$F$17 | G46: ='22_Canales_Segmentos'!$F$17 | H46: ='22_Canales_Segmentos'!$F$17 | I46: ='22_Canales_Segmentos'!$F$17 | ... N46: ='22_Canales_Segmentos'!$F$17
A47: Industrial | B47: =B45*B46 | C47: =C45*C46 | D47: =D45*D46 | E47: =E45*E46 | F47: =F45*F46 | G47: =G45*G46 | H47: =H45*H46 | I47: =I45*I46 | ... M47: =M45*M46 | N47: =SUMIFS(B47:M47,$B$8:$M$8,"<="&$B$4) | O47: =SUM(B47:M47)
A48: Distribución | B48: =B45*(1-B46) | C48: =C45*(1-C46) | D48: =D45*(1-D46) | E48: =E45*(1-E46) | F48: =F45*(1-F46) | G48: =G45*(1-G46) | H48: =H45*(1-H46) | I48: =I45*(1-I46) | ... M48: =M45*(1-M46) | N48: =SUMIFS(B48:M48,$B$8:$M$8,"<="&$B$4) | O48: =SUM(B48:M48)
A49: Construcción | B49: =B41*'22_Canales_Segmentos'!$F$25 | C49: =C41*'22_Canales_Segmentos'!$F$25 | D49: =D41*'22_Canales_Segmentos'!$F$25 | E49: =E41*'22_Canales_Segmentos'!$F$25 | F49: =F41*'22_Canales_Segmentos'!$F$25 | G49: =G41*'22_Canales_Segmentos'!$F$25 | H49: =H41*'22_Canales_Segmentos'!$F$25 | I49: =I41*'22_Canales_Segmentos'!$F$25 | ... M49: =M41*'22_Canales_Segmentos'!$F$25 | N49: =SUMIFS(B49:M49,$B$8:$M$8,"<="&$B$4) | O49: =SUM(B49:M49)
A50: Refrigeración | B50: =B41*'22_Canales_Segmentos'!$F$26 | C50: =C41*'22_Canales_Segmentos'!$F$26 | D50: =D41*'22_Canales_Segmentos'!$F$26 | E50: =E41*'22_Canales_Segmentos'!$F$26 | F50: =F41*'22_Canales_Segmentos'!$F$26 | G50: =G41*'22_Canales_Segmentos'!$F$26 | H50: =H41*'22_Canales_Segmentos'!$F$26 | I50: =I41*'22_Canales_Segmentos'!$F$26 | ... M50: =M41*'22_Canales_Segmentos'!$F$26 | N50: =SUMIFS(B50:M50,$B$8:$M$8,"<="&$B$4) | O50: =SUM(B50:M50)

Sheet 04_Backlog
A1: 04 · Backlog – Octuber
A2: Tabla por producto + progresión mensual del backlog (COP MM) y margen
A4: Producto / métrica | B4: Mes actual | C4: PY | D4: Δ vs PY | E4: 1 Ene 2026 | F4: Δ vs 1 Ene
A5: IMP – Volume (m²) | B5: 525529 | C5: 360246 | D5: =IF(OR(B5="",C5=""),"",IF(C5=0,"n.a.",B5/C5-1)) | E5: 364496 | F5: =IF(OR(B5="",E5=""),"",IF(E5=0,"n.a.",B5/E5-1))
A6: Kingcore – Volume (m²) | B6: 78432 | C6: 38588 | D6: =IF(OR(B6="",C6=""),"",IF(C6=0,"n.a.",B6/C6-1)) | E6: 22362 | F6: =IF(OR(B6="",E6=""),"",IF(E6=0,"n.a.",B6/E6-1))
A7: Single Skin – Volume (m²) | B7: 57196 | C7: 21370 | D7: =IF(OR(B7="",C7=""),"",IF(C7=0,"n.a.",B7/C7-1)) | E7: 21486 | F7: =IF(OR(B7="",E7=""),"",IF(E7=0,"n.a.",B7/E7-1))
A8: Benchmark – Volume (m²) | B8: 12167 | C8: 894 | D8: =IF(OR(B8="",C8=""),"",IF(C8=0,"n.a.",B8/C8-1)) | E8: 349 | F8: =IF(OR(B8="",E8=""),"",IF(E8=0,"n.a.",B8/E8-1))
A9: IMP – Revenue (COP MM) | B9: 49836 | C9: 35225 | D9: =IF(OR(B9="",C9=""),"",IF(C9=0,"n.a.",B9/C9-1)) | E9: 35477 | F9: =IF(OR(B9="",E9=""),"",IF(E9=0,"n.a.",B9/E9-1))
A10: Margen (Std) | B10: 0.273 | C10: 0.25 | D10: =(B10-C10)*100 | E10: 0.25 | F10: =(B10-E10)*100
A11: Margen (Std) sin Canpack | B11: 0.277 | C11: 0.25 | D11: =(B11-C11)*100 | E11: 0.25 | F11: =(B11-E11)*100
A13: N° mes | B13: Mes | C13: Backlog CY (COP MM) | D13: Backlog PY (COP MM) | E13: YoY | F13: Margen CY % | G13: Etiqueta barra 2026: Backlog m² (input) | H13: Etiqueta barra 2025: Backlog m² (input)
A14: 1 | B14: Jan | C14: 35566.1 | D14: 30422.1 | E14: =IF(OR(C14="",D14=""),"",IF(D14=0,"n.a.",C14/D14-1)) | F14: 0.251
A15: 2 | B15: Feb | C15: 36104.5 | D15: 31461.6 | E15: =IF(OR(C15="",D15=""),"",IF(D15=0,"n.a.",C15/D15-1)) | F15: 0.254
A16: 3 | B16: Mar | C16: 39420.9 | D16: 36223.7 | E16: =IF(OR(C16="",D16=""),"",IF(D16=0,"n.a.",C16/D16-1)) | F16: 0.259
A17: 4 | B17: Apr | C17: 38886.8 | D17: 34454.1 | E17: =IF(OR(C17="",D17=""),"",IF(D17=0,"n.a.",C17/D17-1)) | F17: 0.253
A18: 5 | B18: May | C18: 55927.6 | D18: 31842.8 | E18: =IF(OR(C18="",D18=""),"",IF(D18=0,"n.a.",C18/D18-1)) | F18: 0.226
A19: 6 | B19: Jun | C19: 56477.9 | D19: 33251.2 | E19: =IF(OR(C19="",D19=""),"",IF(D19=0,"n.a.",C19/D19-1)) | F19: 0.239
A20: 7 | B20: Jul | C20: 57136.5 | D20: 30680.1 | E20: =IF(OR(C20="",D20=""),"",IF(D20=0,"n.a.",C20/D20-1)) | F20: 0.241
A21: 8 | B21: Aug | C21: 51456.1 | D21: 34736.9 | E21: =IF(OR(C21="",D21=""),"",IF(D21=0,"n.a.",C21/D21-1)) | F21: 0.241
A22: 9 | B22: Sep | C22: 50189 | D22: 33247.5 | E22: =IF(OR(C22="",D22=""),"",IF(D22=0,"n.a.",C22/D22-1)) | F22: 0.273 | G22: 498453 | H22: 347834
A23: 10 | B23: Oct | C23: 49836 | D23: 35224.5 | E23: =IF(OR(C23="",D23=""),"",IF(D23=0,"n.a.",C23/D23-1)) | F23: =B10 | G23: 525529 | H23: 360246
A24: 11 | B24: Nov | D24: 34456 | E24: =IF(OR(C24="",D24=""),"",IF(D24=0,"n.a.",C24/D24-1))
A25: 12 | B25: Dec | D25: 35476.9 | E25: =IF(OR(C25="",D25=""),"",IF(D25=0,"n.a.",C25/D25-1))

Sheet 05_Backlog_Canal
A1: 05 · Backlog por canal (IMP)
A2: CM se alimenta del backlog por RSM (hojas 09–14); PY y márgenes se diligencian | F2: 537065 | G2: 525529 | H2: =F2-G2
A4: Canal | B4: Backlog CM (m²) – RSM | C4: Backlog PY (m²) | D4: YoY | E4: GM % CM | F4: GM % PY | G4: Δ GM (pp) | H4: Mix % | I4: Backlog paneles | J4: Backlog otros
A5: Industrial | B5: =251984-11536 | C5: 170762.19 | D5: =IF(OR(B5="",C5=""),"",IF(C5=0,"n.a.",B5/C5-1)) | E5: 0.33117136 | F5: 0.28692083 | G5: =IF(OR(E5="",F5=""),"",(E5-F5)*100) | H5: =IFERROR(B5/$B$11,0) | I5: ='09_RSM_Industrial'!H18 | J5: ='09_RSM_Industrial'!I18
A6: Distribución | B6: 62499 | C6: 50628.625 | D6: =IF(OR(B6="",C6=""),"",IF(C6=0,"n.a.",B6/C6-1)) | E6: 0.29966956 | F6: 0.2701004 | G6: =IF(OR(E6="",F6=""),"",(E6-F6)*100) | H6: =IFERROR(B6/$B$11,0) | I6: ='10_RSM_Distribucion'!H20 | J6: ='10_RSM_Distribucion'!I20
A7: Otras Geografías | B7: 166377 | C7: 121006.42 | D7: =IF(OR(B7="",C7=""),"",IF(C7=0,"n.a.",B7/C7-1)) | E7: 0.14624363 | F7: 0.10427401 | G7: =IF(OR(E7="",F7=""),"",(E7-F7)*100) | H7: =IFERROR(B7/$B$11,0) | I7: ='11_RSM_Otras_Geo'!H20 | J7: ='11_RSM_Otras_Geo'!I20
A8: Cold Storage | B8: 28642 | C8: 1127.0509 | D8: =IF(OR(B8="",C8=""),"",IF(C8=0,"n.a.",B8/C8-1)) | E8: 0.28058377 | F8: 0.38680242 | G8: =IF(OR(E8="",F8=""),"",(E8-F8)*100) | H8: =IFERROR(B8/$B$11,0) | I8: ='12_RSM_Cold_Storage'!H20 | J8: ='12_RSM_Cold_Storage'!I20
A9: Site Cali | B9: 21774 | C9: 0 | D9: =IF(OR(B9="",C9=""),"",IF(C9=0,"n.a.",B9/C9-1)) | E9: 0.36773598 | F9: 0 | G9: =IF(OR(E9="",F9=""),"",(E9-F9)*100) | H9: =IFERROR(B9/$B$11,0) | I9: ='13_RSM_Site_Cali'!H20 | J9: ='13_RSM_Site_Cali'!I20
A10: Ventas Alternativas | B10: 5789 | C10: 4309.7179 | D10: =IF(OR(B10="",C10=""),"",IF(C10=0,"n.a.",B10/C10-1)) | E10: 0.45275886 | F10: 0.36956934 | G10: =IF(OR(E10="",F10=""),"",(E10-F10)*100) | H10: =IFERROR(B10/$B$11,0) | I10: ='14_RSM_Vtas_Alt'!H20 | J10: ='14_RSM_Vtas_Alt'!I20
A11: TOTAL | B11: =SUM(B5:B10) | C11: =IF(COUNT(C5:C10)=0,"",SUM(C5:C10)) | D11: =IF(OR(B11="",C11=""),"",IF(C11=0,"n.a.",B11/C11-1)) | G11: =IF(OR(E11="",F11=""),"",(E11-F11)*100) | H11: =SUM(H5:H10) | I11: =SUM(I5:I10) | J11: =SUM(J5:J10)
A12: Control: backlog RSM vs backlog IMP (hoja 04) | B12: =B11-'04_Backlog'!B5

Sheet 06_Perf_Forecast
A1: 06 · Performed / Forecast OI 2026
A2: Real vs forecast mensual, acumulados, trimestres y comparativo vs PY
A4: Mes de corte (último mes real) | B4: ='02_OI'!B4
A6: N° mes | B6: Mes | C6: Trimestre | D6: Estado | E6: Volumen m² | F6: Ingresos COP MM | G6: Acum. volumen m² | H6: Acum. ingresos COP MM | I6: Fuente gráfico: Real | J6: Fuente gráfico: Forecast
A7: 1 | B7: Jan | C7: ="Q"&ROUNDUP(A7/3,0) | D7: =IF(A7<=$B$4,"Real","Forecast") | E7: 104582 | F7: 9968.166 | G7: =SUM($E$7:E7) | H7: =SUM($F$7:F7) | I7: =IF(D7="Real",E7,0) | J7: =IF(D7="Forecast",E7,0)
A8: 2 | B8: Feb | C8: ="Q"&ROUNDUP(A8/3,0) | D8: =IF(A8<=$B$4,"Real","Forecast") | E8: 127405 | F8: 12767.714 | G8: =SUM($E$7:E8) | H8: =SUM($F$7:F8) | I8: =IF(D8="Real",E8,0) | J8: =IF(D8="Forecast",E8,0)
A9: 3 | B9: Mar | C9: ="Q"&ROUNDUP(A9/3,0) | D9: =IF(A9<=$B$4,"Real","Forecast") | E9: 152049 | F9: 14462.925 | G9: =SUM($E$7:E9) | H9: =SUM($F$7:F9) | I9: =IF(D9="Real",E9,0) | J9: =IF(D9="Forecast",E9,0)
A10: 4 | B10: Apr | C10: ="Q"&ROUNDUP(A10/3,0) | D10: =IF(A10<=$B$4,"Real","Forecast") | E10: 126530 | F10: 12270.448 | G10: =SUM($E$7:E10) | H10: =SUM($F$7:F10) | I10: =IF(D10="Real",E10,0) | J10: =IF(D10="Forecast",E10,0)
A11: 5 | B11: May | C11: ="Q"&ROUNDUP(A11/3,0) | D11: =IF(A11<=$B$4,"Real","Forecast") | E11: 181126 | F11: 27093.858 | G11: =SUM($E$7:E11) | H11: =SUM($F$7:F11) | I11: =IF(D11="Real",E11,0) | J11: =IF(D11="Forecast",E11,0)
A12: 6 | B12: Jun | C12: ="Q"&ROUNDUP(A12/3,0) | D12: =IF(A12<=$B$4,"Real","Forecast") | E12: 124406 | F12: 12022.773 | G12: =SUM($E$7:E12) | H12: =SUM($F$7:F12) | I12: =IF(D12="Real",E12,0) | J12: =IF(D12="Forecast",E12,0)
A13: 7 | B13: Jul | C13: ="Q"&ROUNDUP(A13/3,0) | D13: =IF(A13<=$B$4,"Real","Forecast") | E13: 114336 | F13: 11718.909 | G13: =SUM($E$7:E13) | H13: =SUM($F$7:F13) | I13: =IF(D13="Real",E13,0) | J13: =IF(D13="Forecast",E13,0)
A14: 8 | B14: Aug | C14: ="Q"&ROUNDUP(A14/3,0) | D14: =IF(A14<=$B$4,"Real","Forecast") | E14: 151623 | F14: 14500.72 | G14: =SUM($E$7:E14) | H14: =SUM($F$7:F14) | I14: =IF(D14="Real",E14,0) | J14: =IF(D14="Forecast",E14,0)
A15: 9 | B15: Sep | C15: ="Q"&ROUNDUP(A15/3,0) | D15: =IF(A15<=$B$4,"Real","Forecast") | E15: 146446 | F15: 13740.67 | G15: =SUM($E$7:E15) | H15: =SUM($F$7:F15) | I15: =IF(D15="Real",E15,0) | J15: =IF(D15="Forecast",E15,0)
A16: 10 | B16: Oct | C16: ="Q"&ROUNDUP(A16/3,0) | D16: =IF(A16<=$B$4,"Real","Forecast") | E16: 160547 | F16: 14484 | G16: =SUM($E$7:E16) | H16: =SUM($F$7:F16) | I16: =IF(D16="Real",E16,0) | J16: =IF(D16="Forecast",E16,0)
A17: 11 | B17: Nov | C17: ="Q"&ROUNDUP(A17/3,0) | D17: =IF(A17<=$B$4,"Real","Forecast") | E17: 140000 | F17: 15077.152 | G17: =SUM($E$7:E17) | H17: =SUM($F$7:F17) | I17: =IF(D17="Real",E17,0) | J17: =IF(D17="Forecast",E17,0)
A18: 12 | B18: Dec | C18: ="Q"&ROUNDUP(A18/3,0) | D18: =IF(A18<=$B$4,"Real","Forecast") | E18: 122000 | F18: 13335.741 | G18: =SUM($E$7:E18) | H18: =SUM($F$7:F18) | I18: =IF(D18="Real",E18,0) | J18: =IF(D18="Forecast",E18,0)
A20: Trimestre | E20: Volumen m² | F20: Ingresos COP MM
A21: Q1 | E21: =SUMIFS($E$7:$E$18,$C$7:$C$18,A21) | F21: =SUMIFS($F$7:$F$18,$C$7:$C$18,A21)
A22: Q2 | E22: =SUMIFS($E$7:$E$18,$C$7:$C$18,A22) | F22: =SUMIFS($F$7:$F$18,$C$7:$C$18,A22)
A23: Q3 | E23: =SUMIFS($E$7:$E$18,$C$7:$C$18,A23) | F23: =SUMIFS($F$7:$F$18,$C$7:$C$18,A23)
A24: Q4 | E24: =SUMIFS($E$7:$E$18,$C$7:$C$18,A24) | F24: =SUMIFS($F$7:$F$18,$C$7:$C$18,A24)
A26: Comparativo IMP | B26: 2026 (m²) | C26: 2025 PY (m²) | D26: YoY m² | E26: 2026 COP MM | F26: 2025 COP MM | G26: YoY COP | H26: GM 2026 | I26: GM 2025 | J26: Δ GM pp
A27: Mes actual (CM) | B27: 160547 | C27: 132619 | D27: =IF(OR(B27="",C27=""),"",IF(C27=0,"n.a.",B27/C27-1)) | E27: 14484 | F27: 10674 | G27: =IF(OR(E27="",F27=""),"",IF(F27=0,"n.a.",E27/F27-1)) | H27: 0.27 | I27: 0.24 | J27: =IF(OR(H27="",I27=""),"",(H27-I27)*100)
A28: YTD real | B28: 1400088 | C28: 1120898 | D28: =IF(OR(B28="",C28=""),"",IF(C28=0,"n.a.",B28/C28-1)) | E28: =SUMIFS(F7:F18,A7:A18,"<="&$B$4) | F28: 95505 | G28: =IF(OR(E28="",F28=""),"",IF(F28=0,"n.a.",E28/F28-1)) | H28: 0.25 | I28: 0.24 | J28: =IF(OR(H28="",I28=""),"",(H28-I28)*100)
A29: Forecast resto del año | B29: =SUMIFS(E7:E18,A7:A18,">"&$B$4) | C29: =C30-C28 | D29: =IF(OR(B29="",C29=""),"",IF(C29=0,"n.a.",B29/C29-1)) | E29: =SUMIFS(F7:F18,A7:A18,">"&$B$4) | F29: =F30-F28 | G29: =IF(OR(E29="",F29=""),"",IF(F29=0,"n.a.",E29/F29-1)) | J29: =IF(OR(H29="",I29=""),"",(H29-I29)*100)
A30: Cierre año (Real + Fcst) | B30: =SUM(E7:E18) | C30: 1359841 | D30: =IF(OR(B30="",C30=""),"",IF(C30=0,"n.a.",B30/C30-1)) | E30: =SUM(F7:F18) | F30: 131135.75 | G30: =IF(OR(E30="",F30=""),"",IF(F30=0,"n.a.",E30/F30-1)) | J30: =IF(OR(H30="",I30=""),"",(H30-I30)*100)
A32: Avance vs cierre año (volumen) | B32: =B28/B30

Sheet 07_Top_Opps
A1: 07 · Top Opportunities (pipeline abierto)
A2: Top 5 por segmento, automático desde la hoja Pipeline · criterio seleccionable
A4: Criterio de orden (cambiar en hoja Pipeline!C4): | E4: =Pipeline!C4
A6: Industrial – Top 5 oportunidades abiertas
A7: # | B7: Cliente | C7: Proyecto | D7: País | E7: Portafolio (Type) | F7: Ejecutivo | G7: m² | H7: USD | I7: Estado | J7: % Cierre | K7: Fecha cierre | L7: Valor ponderado
A8: 1 | B8: =IFERROR(IF(INDEX(Pipeline!$B$7:$B$67,MATCH(LARGE(Pipeline!$M$7:$M$67,1),Pipeline!$M$7:$M$67,0))="","—",INDEX(Pipeline!$B$7:$B$67,MATCH(LARGE(Pipeline!$M$7:$M$67,1),Pipeline!$M$7:$M$67,0))),"") | C8: =IFERROR(IF(INDEX(Pipeline!$C$7:$C$67,MATCH(LARGE(Pipeline!$M$7:$M$67,1),Pipeline!$M$7:$M$67,0))="","—",INDEX(Pipeline!$C$7:$C$67,MATCH(LARGE(Pipeline!$M$7:$M$67,1),Pipeline!$M$7:$M$67,0))),"") | D8: =IFERROR(IF(INDEX(Pipeline!$E$7:$E$67,MATCH(LARGE(Pipeline!$M$7:$M$67,1),Pipeline!$M$7:$M$67,0))="","—",INDEX(Pipeline!$E$7:$E$67,MATCH(LARGE(Pipeline!$M$7:$M$67,1),Pipeline!$M$7:$M$67,0))),"") | E8: =IFERROR(IF(INDEX(Pipeline!$F$7:$F$67,MATCH(LARGE(Pipeline!$M$7:$M$67,1),Pipeline!$M$7:$M$67,0))="","—",INDEX(Pipeline!$F$7:$F$67,MATCH(LARGE(Pipeline!$M$7:$M$67,1),Pipeline!$M$7:$M$67,0))),"") | F8: =IFERROR(IF(INDEX(Pipeline!$D$7:$D$67,MATCH(LARGE(Pipeline!$M$7:$M$67,1),Pipeline!$M$7:$M$67,0))="","—",INDEX(Pipeline!$D$7:$D$67,MATCH(LARGE(Pipeline!$M$7:$M$67,1),Pipeline!$M$7:$M$67,0))),"") | G8: =IFERROR(IF(INDEX(Pipeline!$G$7:$G$67,MATCH(LARGE(Pipeline!$M$7:$M$67,1),Pipeline!$M$7:$M$67,0))="","—",INDEX(Pipeline!$G$7:$G$67,MATCH(LARGE(Pipeline!$M$7:$M$67,1),Pipeline!$M$7:$M$67,0))),"") | H8: =IFERROR(IF(INDEX(Pipeline!$H$7:$H$67,MATCH(LARGE(Pipeline!$M$7:$M$67,1),Pipeline!$M$7:$M$67,0))="","—",INDEX(Pipeline!$H$7:$H$67,MATCH(LARGE(Pipeline!$M$7:$M$67,1),Pipeline!$M$7:$M$67,0))),"") | I8: =IFERROR(IF(INDEX(Pipeline!$I$7:$I$67,MATCH(LARGE(Pipeline!$M$7:$M$67,1),Pipeline!$M$7:$M$67,0))="","—",INDEX(Pipeline!$I$7:$I$67,MATCH(LARGE(Pipeline!$M$7:$M$67,1),Pipeline!$M$7:$M$67,0))),"") | J8: =IFERROR(IF(INDEX(Pipeline!$J$7:$J$67,MATCH(LARGE(Pipeline!$M$7:$M$67,1),Pipeline!$M$7:$M$67,0))="","—",INDEX(Pipeline!$J$7:$J$67,MATCH(LARGE(Pipeline!$M$7:$M$67,1),Pipeline!$M$7:$M$67,0))),"") | K8: =IFERROR(IF(INDEX(Pipeline!$K$7:$K$67,MATCH(LARGE(Pipeline!$M$7:$M$67,1),Pipeline!$M$7:$M$67,0))="","—",INDEX(Pipeline!$K$7:$K$67,MATCH(LARGE(Pipeline!$M$7:$M$67,1),Pipeline!$M$7:$M$67,0))),"") | L8: =IFERROR(IF(INDEX(Pipeline!$L$7:$L$67,MATCH(LARGE(Pipeline!$M$7:$M$67,1),Pipeline!$M$7:$M$67,0))="","—",INDEX(Pipeline!$L$7:$L$67,MATCH(LARGE(Pipeline!$M$7:$M$67,1),Pipeline!$M$7:$M$67,0))),"")
A9: 2 | B9: =IFERROR(IF(INDEX(Pipeline!$B$7:$B$67,MATCH(LARGE(Pipeline!$M$7:$M$67,2),Pipeline!$M$7:$M$67,0))="","—",INDEX(Pipeline!$B$7:$B$67,MATCH(LARGE(Pipeline!$M$7:$M$67,2),Pipeline!$M$7:$M$67,0))),"") | C9: =IFERROR(IF(INDEX(Pipeline!$C$7:$C$67,MATCH(LARGE(Pipeline!$M$7:$M$67,2),Pipeline!$M$7:$M$67,0))="","—",INDEX(Pipeline!$C$7:$C$67,MATCH(LARGE(Pipeline!$M$7:$M$67,2),Pipeline!$M$7:$M$67,0))),"") | D9: =IFERROR(IF(INDEX(Pipeline!$E$7:$E$67,MATCH(LARGE(Pipeline!$M$7:$M$67,2),Pipeline!$M$7:$M$67,0))="","—",INDEX(Pipeline!$E$7:$E$67,MATCH(LARGE(Pipeline!$M$7:$M$67,2),Pipeline!$M$7:$M$67,0))),"") | E9: =IFERROR(IF(INDEX(Pipeline!$F$7:$F$67,MATCH(LARGE(Pipeline!$M$7:$M$67,2),Pipeline!$M$7:$M$67,0))="","—",INDEX(Pipeline!$F$7:$F$67,MATCH(LARGE(Pipeline!$M$7:$M$67,2),Pipeline!$M$7:$M$67,0))),"") | F9: =IFERROR(IF(INDEX(Pipeline!$D$7:$D$67,MATCH(LARGE(Pipeline!$M$7:$M$67,2),Pipeline!$M$7:$M$67,0))="","—",INDEX(Pipeline!$D$7:$D$67,MATCH(LARGE(Pipeline!$M$7:$M$67,2),Pipeline!$M$7:$M$67,0))),"") | G9: 61000 | H9: 1694102 | I9: =IFERROR(IF(INDEX(Pipeline!$I$7:$I$67,MATCH(LARGE(Pipeline!$M$7:$M$67,2),Pipeline!$M$7:$M$67,0))="","—",INDEX(Pipeline!$I$7:$I$67,MATCH(LARGE(Pipeline!$M$7:$M$67,2),Pipeline!$M$7:$M$67,0))),"") | J9: =IFERROR(IF(INDEX(Pipeline!$J$7:$J$67,MATCH(LARGE(Pipeline!$M$7:$M$67,2),Pipeline!$M$7:$M$67,0))="","—",INDEX(Pipeline!$J$7:$J$67,MATCH(LARGE(Pipeline!$M$7:$M$67,2),Pipeline!$M$7:$M$67,0))),"") | K9: =IFERROR(IF(INDEX(Pipeline!$K$7:$K$67,MATCH(LARGE(Pipeline!$M$7:$M$67,2),Pipeline!$M$7:$M$67,0))="","—",INDEX(Pipeline!$K$7:$K$67,MATCH(LARGE(Pipeline!$M$7:$M$67,2),Pipeline!$M$7:$M$67,0))),"") | L9: =IFERROR(IF(INDEX(Pipeline!$L$7:$L$67,MATCH(LARGE(Pipeline!$M$7:$M$67,2),Pipeline!$M$7:$M$67,0))="","—",INDEX(Pipeline!$L$7:$L$67,MATCH(LARGE(Pipeline!$M$7:$M$67,2),Pipeline!$M$7:$M$67,0))),"")
A10: 3 | B10: =IFERROR(IF(INDEX(Pipeline!$B$7:$B$67,MATCH(LARGE(Pipeline!$M$7:$M$67,3),Pipeline!$M$7:$M$67,0))="","—",INDEX(Pipeline!$B$7:$B$67,MATCH(LARGE(Pipeline!$M$7:$M$67,3),Pipeline!$M$7:$M$67,0))),"") | C10: =IFERROR(IF(INDEX(Pipeline!$C$7:$C$67,MATCH(LARGE(Pipeline!$M$7:$M$67,3),Pipeline!$M$7:$M$67,0))="","—",INDEX(Pipeline!$C$7:$C$67,MATCH(LARGE(Pipeline!$M$7:$M$67,3),Pipeline!$M$7:$M$67,0))),"") | D10: =IFERROR(IF(INDEX(Pipeline!$E$7:$E$67,MATCH(LARGE(Pipeline!$M$7:$M$67,3),Pipeline!$M$7:$M$67,0))="","—",INDEX(Pipeline!$E$7:$E$67,MATCH(LARGE(Pipeline!$M$7:$M$67,3),Pipeline!$M$7:$M$67,0))),"") | E10: =IFERROR(IF(INDEX(Pipeline!$F$7:$F$67,MATCH(LARGE(Pipeline!$M$7:$M$67,3),Pipeline!$M$7:$M$67,0))="","—",INDEX(Pipeline!$F$7:$F$67,MATCH(LARGE(Pipeline!$M$7:$M$67,3),Pipeline!$M$7:$M$67,0))),"") | F10: =IFERROR(IF(INDEX(Pipeline!$D$7:$D$67,MATCH(LARGE(Pipeline!$M$7:$M$67,3),Pipeline!$M$7:$M$67,0))="","—",INDEX(Pipeline!$D$7:$D$67,MATCH(LARGE(Pipeline!$M$7:$M$67,3),Pipeline!$M$7:$M$67,0))),"") | G10: =IFERROR(IF(INDEX(Pipeline!$G$7:$G$67,MATCH(LARGE(Pipeline!$M$7:$M$67,3),Pipeline!$M$7:$M$67,0))="","—",INDEX(Pipeline!$G$7:$G$67,MATCH(LARGE(Pipeline!$M$7:$M$67,3),Pipeline!$M$7:$M$67,0))),"") | H10: =IFERROR(IF(INDEX(Pipeline!$H$7:$H$67,MATCH(LARGE(Pipeline!$M$7:$M$67,3),Pipeline!$M$7:$M$67,0))="","—",INDEX(Pipeline!$H$7:$H$67,MATCH(LARGE(Pipeline!$M$7:$M$67,3),Pipeline!$M$7:$M$67,0))),"") | I10: =IFERROR(IF(INDEX(Pipeline!$I$7:$I$67,MATCH(LARGE(Pipeline!$M$7:$M$67,3),Pipeline!$M$7:$M$67,0))="","—",INDEX(Pipeline!$I$7:$I$67,MATCH(LARGE(Pipeline!$M$7:$M$67,3),Pipeline!$M$7:$M$67,0))),"") | J10: =IFERROR(IF(INDEX(Pipeline!$J$7:$J$67,MATCH(LARGE(Pipeline!$M$7:$M$67,3),Pipeline!$M$7:$M$67,0))="","—",INDEX(Pipeline!$J$7:$J$67,MATCH(LARGE(Pipeline!$M$7:$M$67,3),Pipeline!$M$7:$M$67,0))),"") | K10: =IFERROR(IF(INDEX(Pipeline!$K$7:$K$67,MATCH(LARGE(Pipeline!$M$7:$M$67,3),Pipeline!$M$7:$M$67,0))="","—",INDEX(Pipeline!$K$7:$K$67,MATCH(LARGE(Pipeline!$M$7:$M$67,3),Pipeline!$M$7:$M$67,0))),"") | L10: =IFERROR(IF(INDEX(Pipeline!$L$7:$L$67,MATCH(LARGE(Pipeline!$M$7:$M$67,3),Pipeline!$M$7:$M$67,0))="","—",INDEX(Pipeline!$L$7:$L$67,MATCH(LARGE(Pipeline!$M$7:$M$67,3),Pipeline!$M$7:$M$67,0))),"")
A11: 4 | B11: =IFERROR(IF(INDEX(Pipeline!$B$7:$B$67,MATCH(LARGE(Pipeline!$M$7:$M$67,4),Pipeline!$M$7:$M$67,0))="","—",INDEX(Pipeline!$B$7:$B$67,MATCH(LARGE(Pipeline!$M$7:$M$67,4),Pipeline!$M$7:$M$67,0))),"") | C11: =IFERROR(IF(INDEX(Pipeline!$C$7:$C$67,MATCH(LARGE(Pipeline!$M$7:$M$67,4),Pipeline!$M$7:$M$67,0))="","—",INDEX(Pipeline!$C$7:$C$67,MATCH(LARGE(Pipeline!$M$7:$M$67,4),Pipeline!$M$7:$M$67,0))),"") | D11: =IFERROR(IF(INDEX(Pipeline!$E$7:$E$67,MATCH(LARGE(Pipeline!$M$7:$M$67,4),Pipeline!$M$7:$M$67,0))="","—",INDEX(Pipeline!$E$7:$E$67,MATCH(LARGE(Pipeline!$M$7:$M$67,4),Pipeline!$M$7:$M$67,0))),"") | E11: =IFERROR(IF(INDEX(Pipeline!$F$7:$F$67,MATCH(LARGE(Pipeline!$M$7:$M$67,4),Pipeline!$M$7:$M$67,0))="","—",INDEX(Pipeline!$F$7:$F$67,MATCH(LARGE(Pipeline!$M$7:$M$67,4),Pipeline!$M$7:$M$67,0))),"") | F11: =IFERROR(IF(INDEX(Pipeline!$D$7:$D$67,MATCH(LARGE(Pipeline!$M$7:$M$67,4),Pipeline!$M$7:$M$67,0))="","—",INDEX(Pipeline!$D$7:$D$67,MATCH(LARGE(Pipeline!$M$7:$M$67,4),Pipeline!$M$7:$M$67,0))),"") | G11: =IFERROR(IF(INDEX(Pipeline!$G$7:$G$67,MATCH(LARGE(Pipeline!$M$7:$M$67,4),Pipeline!$M$7:$M$67,0))="","—",INDEX(Pipeline!$G$7:$G$67,MATCH(LARGE(Pipeline!$M$7:$M$67,4),Pipeline!$M$7:$M$67,0))),"") | H11: =IFERROR(IF(INDEX(Pipeline!$H$7:$H$67,MATCH(LARGE(Pipeline!$M$7:$M$67,4),Pipeline!$M$7:$M$67,0))="","—",INDEX(Pipeline!$H$7:$H$67,MATCH(LARGE(Pipeline!$M$7:$M$67,4),Pipeline!$M$7:$M$67,0))),"") | I11: =IFERROR(IF(INDEX(Pipeline!$I$7:$I$67,MATCH(LARGE(Pipeline!$M$7:$M$67,4),Pipeline!$M$7:$M$67,0))="","—",INDEX(Pipeline!$I$7:$I$67,MATCH(LARGE(Pipeline!$M$7:$M$67,4),Pipeline!$M$7:$M$67,0))),"") | J11: =IFERROR(IF(INDEX(Pipeline!$J$7:$J$67,MATCH(LARGE(Pipeline!$M$7:$M$67,4),Pipeline!$M$7:$M$67,0))="","—",INDEX(Pipeline!$J$7:$J$67,MATCH(LARGE(Pipeline!$M$7:$M$67,4),Pipeline!$M$7:$M$67,0))),"") | K11: =IFERROR(IF(INDEX(Pipeline!$K$7:$K$67,MATCH(LARGE(Pipeline!$M$7:$M$67,4),Pipeline!$M$7:$M$67,0))="","—",INDEX(Pipeline!$K$7:$K$67,MATCH(LARGE(Pipeline!$M$7:$M$67,4),Pipeline!$M$7:$M$67,0))),"") | L11: =IFERROR(IF(INDEX(Pipeline!$L$7:$L$67,MATCH(LARGE(Pipeline!$M$7:$M$67,4),Pipeline!$M$7:$M$67,0))="","—",INDEX(Pipeline!$L$7:$L$67,MATCH(LARGE(Pipeline!$M$7:$M$67,4),Pipeline!$M$7:$M$67,0))),"")
A12: 5 | B12: =IFERROR(IF(INDEX(Pipeline!$B$7:$B$67,MATCH(LARGE(Pipeline!$M$7:$M$67,5),Pipeline!$M$7:$M$67,0))="","—",INDEX(Pipeline!$B$7:$B$67,MATCH(LARGE(Pipeline!$M$7:$M$67,5),Pipeline!$M$7:$M$67,0))),"") | C12: =IFERROR(IF(INDEX(Pipeline!$C$7:$C$67,MATCH(LARGE(Pipeline!$M$7:$M$67,5),Pipeline!$M$7:$M$67,0))="","—",INDEX(Pipeline!$C$7:$C$67,MATCH(LARGE(Pipeline!$M$7:$M$67,5),Pipeline!$M$7:$M$67,0))),"") | D12: =IFERROR(IF(INDEX(Pipeline!$E$7:$E$67,MATCH(LARGE(Pipeline!$M$7:$M$67,5),Pipeline!$M$7:$M$67,0))="","—",INDEX(Pipeline!$E$7:$E$67,MATCH(LARGE(Pipeline!$M$7:$M$67,5),Pipeline!$M$7:$M$67,0))),"") | E12: =IFERROR(IF(INDEX(Pipeline!$F$7:$F$67,MATCH(LARGE(Pipeline!$M$7:$M$67,5),Pipeline!$M$7:$M$67,0))="","—",INDEX(Pipeline!$F$7:$F$67,MATCH(LARGE(Pipeline!$M$7:$M$67,5),Pipeline!$M$7:$M$67,0))),"") | F12: =IFERROR(IF(INDEX(Pipeline!$D$7:$D$67,MATCH(LARGE(Pipeline!$M$7:$M$67,5),Pipeline!$M$7:$M$67,0))="","—",INDEX(Pipeline!$D$7:$D$67,MATCH(LARGE(Pipeline!$M$7:$M$67,5),Pipeline!$M$7:$M$67,0))),"") | G12: =IFERROR(IF(INDEX(Pipeline!$G$7:$G$67,MATCH(LARGE(Pipeline!$M$7:$M$67,5),Pipeline!$M$7:$M$67,0))="","—",INDEX(Pipeline!$G$7:$G$67,MATCH(LARGE(Pipeline!$M$7:$M$67,5),Pipeline!$M$7:$M$67,0))),"") | H12: =IFERROR(IF(INDEX(Pipeline!$H$7:$H$67,MATCH(LARGE(Pipeline!$M$7:$M$67,5),Pipeline!$M$7:$M$67,0))="","—",INDEX(Pipeline!$H$7:$H$67,MATCH(LARGE(Pipeline!$M$7:$M$67,5),Pipeline!$M$7:$M$67,0))),"") | I12: =IFERROR(IF(INDEX(Pipeline!$I$7:$I$67,MATCH(LARGE(Pipeline!$M$7:$M$67,5),Pipeline!$M$7:$M$67,0))="","—",INDEX(Pipeline!$I$7:$I$67,MATCH(LARGE(Pipeline!$M$7:$M$67,5),Pipeline!$M$7:$M$67,0))),"") | J12: =IFERROR(IF(INDEX(Pipeline!$J$7:$J$67,MATCH(LARGE(Pipeline!$M$7:$M$67,5),Pipeline!$M$7:$M$67,0))="","—",INDEX(Pipeline!$J$7:$J$67,MATCH(LARGE(Pipeline!$M$7:$M$67,5),Pipeline!$M$7:$M$67,0))),"") | K12: =IFERROR(IF(INDEX(Pipeline!$K$7:$K$67,MATCH(LARGE(Pipeline!$M$7:$M$67,5),Pipeline!$M$7:$M$67,0))="","—",INDEX(Pipeline!$K$7:$K$67,MATCH(LARGE(Pipeline!$M$7:$M$67,5),Pipeline!$M$7:$M$67,0))),"") | L12: =IFERROR(IF(INDEX(Pipeline!$L$7:$L$67,MATCH(LARGE(Pipeline!$M$7:$M$67,5),Pipeline!$M$7:$M$67,0))="","—",INDEX(Pipeline!$L$7:$L$67,MATCH(LARGE(Pipeline!$M$7:$M$67,5),Pipeline!$M$7:$M$67,0))),"")
B13: Total Top 5 | G13: =SUM(G8:G12) | H13: =SUM(H8:H12)
A15: Distribución – Top 5 oportunidades abiertas
A16: # | B16: Cliente | C16: Proyecto | D16: País | E16: Portafolio (Type) | F16: Ejecutivo | G16: m² | H16: USD | I16: Estado | J16: % Cierre | K16: Fecha cierre | L16: Valor ponderado
A17: 1 | B17: =IFERROR(IF(INDEX(Pipeline!$B$7:$B$67,MATCH(LARGE(Pipeline!$N$7:$N$67,1),Pipeline!$N$7:$N$67,0))="","—",INDEX(Pipeline!$B$7:$B$67,MATCH(LARGE(Pipeline!$N$7:$N$67,1),Pipeline!$N$7:$N$67,0))),"") | C17: =IFERROR(IF(INDEX(Pipeline!$C$7:$C$67,MATCH(LARGE(Pipeline!$N$7:$N$67,1),Pipeline!$N$7:$N$67,0))="","—",INDEX(Pipeline!$C$7:$C$67,MATCH(LARGE(Pipeline!$N$7:$N$67,1),Pipeline!$N$7:$N$67,0))),"") | D17: =IFERROR(IF(INDEX(Pipeline!$E$7:$E$67,MATCH(LARGE(Pipeline!$N$7:$N$67,1),Pipeline!$N$7:$N$67,0))="","—",INDEX(Pipeline!$E$7:$E$67,MATCH(LARGE(Pipeline!$N$7:$N$67,1),Pipeline!$N$7:$N$67,0))),"") | E17: =IFERROR(IF(INDEX(Pipeline!$F$7:$F$67,MATCH(LARGE(Pipeline!$N$7:$N$67,1),Pipeline!$N$7:$N$67,0))="","—",INDEX(Pipeline!$F$7:$F$67,MATCH(LARGE(Pipeline!$N$7:$N$67,1),Pipeline!$N$7:$N$67,0))),"") | F17: =IFERROR(IF(INDEX(Pipeline!$D$7:$D$67,MATCH(LARGE(Pipeline!$N$7:$N$67,1),Pipeline!$N$7:$N$67,0))="","—",INDEX(Pipeline!$D$7:$D$67,MATCH(LARGE(Pipeline!$N$7:$N$67,1),Pipeline!$N$7:$N$67,0))),"") | G17: =IFERROR(IF(INDEX(Pipeline!$G$7:$G$67,MATCH(LARGE(Pipeline!$N$7:$N$67,1),Pipeline!$N$7:$N$67,0))="","—",INDEX(Pipeline!$G$7:$G$67,MATCH(LARGE(Pipeline!$N$7:$N$67,1),Pipeline!$N$7:$N$67,0))),"") | H17: =IFERROR(IF(INDEX(Pipeline!$H$7:$H$67,MATCH(LARGE(Pipeline!$N$7:$N$67,1),Pipeline!$N$7:$N$67,0))="","—",INDEX(Pipeline!$H$7:$H$67,MATCH(LARGE(Pipeline!$N$7:$N$67,1),Pipeline!$N$7:$N$67,0))),"") | I17: Closed | J17: 1 | K17: =IFERROR(IF(INDEX(Pipeline!$K$7:$K$67,MATCH(LARGE(Pipeline!$N$7:$N$67,1),Pipeline!$N$7:$N$67,0))="","—",INDEX(Pipeline!$K$7:$K$67,MATCH(LARGE(Pipeline!$N$7:$N$67,1),Pipeline!$N$7:$N$67,0))),"") | L17: =IFERROR(IF(INDEX(Pipeline!$L$7:$L$67,MATCH(LARGE(Pipeline!$N$7:$N$67,1),Pipeline!$N$7:$N$67,0))="","—",INDEX(Pipeline!$L$7:$L$67,MATCH(LARGE(Pipeline!$N$7:$N$67,1),Pipeline!$N$7:$N$67,0))),"")
A18: 2 | B18: =IFERROR(IF(INDEX(Pipeline!$B$7:$B$67,MATCH(LARGE(Pipeline!$N$7:$N$67,2),Pipeline!$N$7:$N$67,0))="","—",INDEX(Pipeline!$B$7:$B$67,MATCH(LARGE(Pipeline!$N$7:$N$67,2),Pipeline!$N$7:$N$67,0))),"") | C18: =IFERROR(IF(INDEX(Pipeline!$C$7:$C$67,MATCH(LARGE(Pipeline!$N$7:$N$67,2),Pipeline!$N$7:$N$67,0))="","—",INDEX(Pipeline!$C$7:$C$67,MATCH(LARGE(Pipeline!$N$7:$N$67,2),Pipeline!$N$7:$N$67,0))),"") | D18: =IFERROR(IF(INDEX(Pipeline!$E$7:$E$67,MATCH(LARGE(Pipeline!$N$7:$N$67,2),Pipeline!$N$7:$N$67,0))="","—",INDEX(Pipeline!$E$7:$E$67,MATCH(LARGE(Pipeline!$N$7:$N$67,2),Pipeline!$N$7:$N$67,0))),"") | E18: =IFERROR(IF(INDEX(Pipeline!$F$7:$F$67,MATCH(LARGE(Pipeline!$N$7:$N$67,2),Pipeline!$N$7:$N$67,0))="","—",INDEX(Pipeline!$F$7:$F$67,MATCH(LARGE(Pipeline!$N$7:$N$67,2),Pipeline!$N$7:$N$67,0))),"") | F18: =IFERROR(IF(INDEX(Pipeline!$D$7:$D$67,MATCH(LARGE(Pipeline!$N$7:$N$67,2),Pipeline!$N$7:$N$67,0))="","—",INDEX(Pipeline!$D$7:$D$67,MATCH(LARGE(Pipeline!$N$7:$N$67,2),Pipeline!$N$7:$N$67,0))),"") | G18: =IFERROR(IF(INDEX(Pipeline!$G$7:$G$67,MATCH(LARGE(Pipeline!$N$7:$N$67,2),Pipeline!$N$7:$N$67,0))="","—",INDEX(Pipeline!$G$7:$G$67,MATCH(LARGE(Pipeline!$N$7:$N$67,2),Pipeline!$N$7:$N$67,0))),"") | H18: =IFERROR(IF(INDEX(Pipeline!$H$7:$H$67,MATCH(LARGE(Pipeline!$N$7:$N$67,2),Pipeline!$N$7:$N$67,0))="","—",INDEX(Pipeline!$H$7:$H$67,MATCH(LARGE(Pipeline!$N$7:$N$67,2),Pipeline!$N$7:$N$67,0))),"") | I18: =IFERROR(IF(INDEX(Pipeline!$I$7:$I$67,MATCH(LARGE(Pipeline!$N$7:$N$67,2),Pipeline!$N$7:$N$67,0))="","—",INDEX(Pipeline!$I$7:$I$67,MATCH(LARGE(Pipeline!$N$7:$N$67,2),Pipeline!$N$7:$N$67,0))),"") | J18: =IFERROR(IF(INDEX(Pipeline!$J$7:$J$67,MATCH(LARGE(Pipeline!$N$7:$N$67,2),Pipeline!$N$7:$N$67,0))="","—",INDEX(Pipeline!$J$7:$J$67,MATCH(LARGE(Pipeline!$N$7:$N$67,2),Pipeline!$N$7:$N$67,0))),"") | K18: =IFERROR(IF(INDEX(Pipeline!$K$7:$K$67,MATCH(LARGE(Pipeline!$N$7:$N$67,2),Pipeline!$N$7:$N$67,0))="","—",INDEX(Pipeline!$K$7:$K$67,MATCH(LARGE(Pipeline!$N$7:$N$67,2),Pipeline!$N$7:$N$67,0))),"") | L18: =IFERROR(IF(INDEX(Pipeline!$L$7:$L$67,MATCH(LARGE(Pipeline!$N$7:$N$67,2),Pipeline!$N$7:$N$67,0))="","—",INDEX(Pipeline!$L$7:$L$67,MATCH(LARGE(Pipeline!$N$7:$N$67,2),Pipeline!$N$7:$N$67,0))),"")
A19: 3 | B19: =IFERROR(IF(INDEX(Pipeline!$B$7:$B$67,MATCH(LARGE(Pipeline!$N$7:$N$67,3),Pipeline!$N$7:$N$67,0))="","—",INDEX(Pipeline!$B$7:$B$67,MATCH(LARGE(Pipeline!$N$7:$N$67,3),Pipeline!$N$7:$N$67,0))),"") | C19: =IFERROR(IF(INDEX(Pipeline!$C$7:$C$67,MATCH(LARGE(Pipeline!$N$7:$N$67,3),Pipeline!$N$7:$N$67,0))="","—",INDEX(Pipeline!$C$7:$C$67,MATCH(LARGE(Pipeline!$N$7:$N$67,3),Pipeline!$N$7:$N$67,0))),"") | D19: =IFERROR(IF(INDEX(Pipeline!$E$7:$E$67,MATCH(LARGE(Pipeline!$N$7:$N$67,3),Pipeline!$N$7:$N$67,0))="","—",INDEX(Pipeline!$E$7:$E$67,MATCH(LARGE(Pipeline!$N$7:$N$67,3),Pipeline!$N$7:$N$67,0))),"") | E19: =IFERROR(IF(INDEX(Pipeline!$F$7:$F$67,MATCH(LARGE(Pipeline!$N$7:$N$67,3),Pipeline!$N$7:$N$67,0))="","—",INDEX(Pipeline!$F$7:$F$67,MATCH(LARGE(Pipeline!$N$7:$N$67,3),Pipeline!$N$7:$N$67,0))),"") | F19: =IFERROR(IF(INDEX(Pipeline!$D$7:$D$67,MATCH(LARGE(Pipeline!$N$7:$N$67,3),Pipeline!$N$7:$N$67,0))="","—",INDEX(Pipeline!$D$7:$D$67,MATCH(LARGE(Pipeline!$N$7:$N$67,3),Pipeline!$N$7:$N$67,0))),"") | G19: =IFERROR(IF(INDEX(Pipeline!$G$7:$G$67,MATCH(LARGE(Pipeline!$N$7:$N$67,3),Pipeline!$N$7:$N$67,0))="","—",INDEX(Pipeline!$G$7:$G$67,MATCH(LARGE(Pipeline!$N$7:$N$67,3),Pipeline!$N$7:$N$67,0))),"") | H19: =IFERROR(IF(INDEX(Pipeline!$H$7:$H$67,MATCH(LARGE(Pipeline!$N$7:$N$67,3),Pipeline!$N$7:$N$67,0))="","—",INDEX(Pipeline!$H$7:$H$67,MATCH(LARGE(Pipeline!$N$7:$N$67,3),Pipeline!$N$7:$N$67,0))),"") | I19: =IFERROR(IF(INDEX(Pipeline!$I$7:$I$67,MATCH(LARGE(Pipeline!$N$7:$N$67,3),Pipeline!$N$7:$N$67,0))="","—",INDEX(Pipeline!$I$7:$I$67,MATCH(LARGE(Pipeline!$N$7:$N$67,3),Pipeline!$N$7:$N$67,0))),"") | J19: =IFERROR(IF(INDEX(Pipeline!$J$7:$J$67,MATCH(LARGE(Pipeline!$N$7:$N$67,3),Pipeline!$N$7:$N$67,0))="","—",INDEX(Pipeline!$J$7:$J$67,MATCH(LARGE(Pipeline!$N$7:$N$67,3),Pipeline!$N$7:$N$67,0))),"") | K19: =IFERROR(IF(INDEX(Pipeline!$K$7:$K$67,MATCH(LARGE(Pipeline!$N$7:$N$67,3),Pipeline!$N$7:$N$67,0))="","—",INDEX(Pipeline!$K$7:$K$67,MATCH(LARGE(Pipeline!$N$7:$N$67,3),Pipeline!$N$7:$N$67,0))),"") | L19: =IFERROR(IF(INDEX(Pipeline!$L$7:$L$67,MATCH(LARGE(Pipeline!$N$7:$N$67,3),Pipeline!$N$7:$N$67,0))="","—",INDEX(Pipeline!$L$7:$L$67,MATCH(LARGE(Pipeline!$N$7:$N$67,3),Pipeline!$N$7:$N$67,0))),"")
A20: 4 | B20: =IFERROR(IF(INDEX(Pipeline!$B$7:$B$67,MATCH(LARGE(Pipeline!$N$7:$N$67,4),Pipeline!$N$7:$N$67,0))="","—",INDEX(Pipeline!$B$7:$B$67,MATCH(LARGE(Pipeline!$N$7:$N$67,4),Pipeline!$N$7:$N$67,0))),"") | C20: =IFERROR(IF(INDEX(Pipeline!$C$7:$C$67,MATCH(LARGE(Pipeline!$N$7:$N$67,4),Pipeline!$N$7:$N$67,0))="","—",INDEX(Pipeline!$C$7:$C$67,MATCH(LARGE(Pipeline!$N$7:$N$67,4),Pipeline!$N$7:$N$67,0))),"") | D20: =IFERROR(IF(INDEX(Pipeline!$E$7:$E$67,MATCH(LARGE(Pipeline!$N$7:$N$67,4),Pipeline!$N$7:$N$67,0))="","—",INDEX(Pipeline!$E$7:$E$67,MATCH(LARGE(Pipeline!$N$7:$N$67,4),Pipeline!$N$7:$N$67,0))),"") | E20: =IFERROR(IF(INDEX(Pipeline!$F$7:$F$67,MATCH(LARGE(Pipeline!$N$7:$N$67,4),Pipeline!$N$7:$N$67,0))="","—",INDEX(Pipeline!$F$7:$F$67,MATCH(LARGE(Pipeline!$N$7:$N$67,4),Pipeline!$N$7:$N$67,0))),"") | F20: =IFERROR(IF(INDEX(Pipeline!$D$7:$D$67,MATCH(LARGE(Pipeline!$N$7:$N$67,4),Pipeline!$N$7:$N$67,0))="","—",INDEX(Pipeline!$D$7:$D$67,MATCH(LARGE(Pipeline!$N$7:$N$67,4),Pipeline!$N$7:$N$67,0))),"") | G20: =IFERROR(IF(INDEX(Pipeline!$G$7:$G$67,MATCH(LARGE(Pipeline!$N$7:$N$67,4),Pipeline!$N$7:$N$67,0))="","—",INDEX(Pipeline!$G$7:$G$67,MATCH(LARGE(Pipeline!$N$7:$N$67,4),Pipeline!$N$7:$N$67,0))),"") | H20: =IFERROR(IF(INDEX(Pipeline!$H$7:$H$67,MATCH(LARGE(Pipeline!$N$7:$N$67,4),Pipeline!$N$7:$N$67,0))="","—",INDEX(Pipeline!$H$7:$H$67,MATCH(LARGE(Pipeline!$N$7:$N$67,4),Pipeline!$N$7:$N$67,0))),"") | I20: =IFERROR(IF(INDEX(Pipeline!$I$7:$I$67,MATCH(LARGE(Pipeline!$N$7:$N$67,4),Pipeline!$N$7:$N$67,0))="","—",INDEX(Pipeline!$I$7:$I$67,MATCH(LARGE(Pipeline!$N$7:$N$67,4),Pipeline!$N$7:$N$67,0))),"") | J20: =IFERROR(IF(INDEX(Pipeline!$J$7:$J$67,MATCH(LARGE(Pipeline!$N$7:$N$67,4),Pipeline!$N$7:$N$67,0))="","—",INDEX(Pipeline!$J$7:$J$67,MATCH(LARGE(Pipeline!$N$7:$N$67,4),Pipeline!$N$7:$N$67,0))),"") | K20: =IFERROR(IF(INDEX(Pipeline!$K$7:$K$67,MATCH(LARGE(Pipeline!$N$7:$N$67,4),Pipeline!$N$7:$N$67,0))="","—",INDEX(Pipeline!$K$7:$K$67,MATCH(LARGE(Pipeline!$N$7:$N$67,4),Pipeline!$N$7:$N$67,0))),"") | L20: =IFERROR(IF(INDEX(Pipeline!$L$7:$L$67,MATCH(LARGE(Pipeline!$N$7:$N$67,4),Pipeline!$N$7:$N$67,0))="","—",INDEX(Pipeline!$L$7:$L$67,MATCH(LARGE(Pipeline!$N$7:$N$67,4),Pipeline!$N$7:$N$67,0))),"")
A21: 5 | B21: =IFERROR(IF(INDEX(Pipeline!$B$7:$B$67,MATCH(LARGE(Pipeline!$N$7:$N$67,5),Pipeline!$N$7:$N$67,0))="","—",INDEX(Pipeline!$B$7:$B$67,MATCH(LARGE(Pipeline!$N$7:$N$67,5),Pipeline!$N$7:$N$67,0))),"") | C21: =IFERROR(IF(INDEX(Pipeline!$C$7:$C$67,MATCH(LARGE(Pipeline!$N$7:$N$67,5),Pipeline!$N$7:$N$67,0))="","—",INDEX(Pipeline!$C$7:$C$67,MATCH(LARGE(Pipeline!$N$7:$N$67,5),Pipeline!$N$7:$N$67,0))),"") | D21: =IFERROR(IF(INDEX(Pipeline!$E$7:$E$67,MATCH(LARGE(Pipeline!$N$7:$N$67,5),Pipeline!$N$7:$N$67,0))="","—",INDEX(Pipeline!$E$7:$E$67,MATCH(LARGE(Pipeline!$N$7:$N$67,5),Pipeline!$N$7:$N$67,0))),"") | E21: =IFERROR(IF(INDEX(Pipeline!$F$7:$F$67,MATCH(LARGE(Pipeline!$N$7:$N$67,5),Pipeline!$N$7:$N$67,0))="","—",INDEX(Pipeline!$F$7:$F$67,MATCH(LARGE(Pipeline!$N$7:$N$67,5),Pipeline!$N$7:$N$67,0))),"") | F21: =IFERROR(IF(INDEX(Pipeline!$D$7:$D$67,MATCH(LARGE(Pipeline!$N$7:$N$67,5),Pipeline!$N$7:$N$67,0))="","—",INDEX(Pipeline!$D$7:$D$67,MATCH(LARGE(Pipeline!$N$7:$N$67,5),Pipeline!$N$7:$N$67,0))),"") | G21: 2088 | H21: =IFERROR(IF(INDEX(Pipeline!$H$7:$H$67,MATCH(LARGE(Pipeline!$N$7:$N$67,5),Pipeline!$N$7:$N$67,0))="","—",INDEX(Pipeline!$H$7:$H$67,MATCH(LARGE(Pipeline!$N$7:$N$67,5),Pipeline!$N$7:$N$67,0))),"") | I21: closed | J21: 1 | K21: Octuber | L21: =IFERROR(IF(INDEX(Pipeline!$L$7:$L$67,MATCH(LARGE(Pipeline!$N$7:$N$67,5),Pipeline!$N$7:$N$67,0))="","—",INDEX(Pipeline!$L$7:$L$67,MATCH(LARGE(Pipeline!$N$7:$N$67,5),Pipeline!$N$7:$N$67,0))),"")
B22: Total Top 5 | G22: =SUM(G17:G21) | H22: =SUM(H17:H21)
B24: Top 5 Industrial / pipeline Industrial USD | H24: =H13/SUMIFS(Pipeline!H7:H67,Pipeline!A7:A67,"Industrial")
B25: Top 5 Distribución / pipeline Distribución USD | H25: =H22/SUMIFS(Pipeline!H7:H67,Pipeline!A7:A67,"Distribución")

Sheet 08_Key_Projects
A1: 08 · Key Projects – Industrial y Distribución
A2: Top 5 por m² (todos los estados) + resumen de pipeline
A6: Industrial – Top 5 proyectos por m² (todos los estados)
A7: # | B7: Cliente | C7: Proyecto | D7: País | E7: Portafolio (Type) | F7: Ejecutivo | G7: m² | H7: USD | I7: Estado | J7: % Cierre | K7: Fecha cierre | L7: Valor ponderado
A8: 1 | B8: =IFERROR(IF(INDEX(Pipeline!$B$7:$B$67,MATCH(LARGE(Pipeline!$O$7:$O$67,1),Pipeline!$O$7:$O$67,0))="","—",INDEX(Pipeline!$B$7:$B$67,MATCH(LARGE(Pipeline!$O$7:$O$67,1),Pipeline!$O$7:$O$67,0))),"") | C8: =IFERROR(IF(INDEX(Pipeline!$C$7:$C$67,MATCH(LARGE(Pipeline!$O$7:$O$67,1),Pipeline!$O$7:$O$67,0))="","—",INDEX(Pipeline!$C$7:$C$67,MATCH(LARGE(Pipeline!$O$7:$O$67,1),Pipeline!$O$7:$O$67,0))),"") | D8: =IFERROR(IF(INDEX(Pipeline!$E$7:$E$67,MATCH(LARGE(Pipeline!$O$7:$O$67,1),Pipeline!$O$7:$O$67,0))="","—",INDEX(Pipeline!$E$7:$E$67,MATCH(LARGE(Pipeline!$O$7:$O$67,1),Pipeline!$O$7:$O$67,0))),"") | E8: =IFERROR(IF(INDEX(Pipeline!$F$7:$F$67,MATCH(LARGE(Pipeline!$O$7:$O$67,1),Pipeline!$O$7:$O$67,0))="","—",INDEX(Pipeline!$F$7:$F$67,MATCH(LARGE(Pipeline!$O$7:$O$67,1),Pipeline!$O$7:$O$67,0))),"") | F8: =IFERROR(IF(INDEX(Pipeline!$D$7:$D$67,MATCH(LARGE(Pipeline!$O$7:$O$67,1),Pipeline!$O$7:$O$67,0))="","—",INDEX(Pipeline!$D$7:$D$67,MATCH(LARGE(Pipeline!$O$7:$O$67,1),Pipeline!$O$7:$O$67,0))),"") | G8: =IFERROR(IF(INDEX(Pipeline!$G$7:$G$67,MATCH(LARGE(Pipeline!$O$7:$O$67,1),Pipeline!$O$7:$O$67,0))="","—",INDEX(Pipeline!$G$7:$G$67,MATCH(LARGE(Pipeline!$O$7:$O$67,1),Pipeline!$O$7:$O$67,0))),"") | H8: =IFERROR(IF(INDEX(Pipeline!$H$7:$H$67,MATCH(LARGE(Pipeline!$O$7:$O$67,1),Pipeline!$O$7:$O$67,0))="","—",INDEX(Pipeline!$H$7:$H$67,MATCH(LARGE(Pipeline!$O$7:$O$67,1),Pipeline!$O$7:$O$67,0))),"") | I8: =IFERROR(IF(INDEX(Pipeline!$I$7:$I$67,MATCH(LARGE(Pipeline!$O$7:$O$67,1),Pipeline!$O$7:$O$67,0))="","—",INDEX(Pipeline!$I$7:$I$67,MATCH(LARGE(Pipeline!$O$7:$O$67,1),Pipeline!$O$7:$O$67,0))),"") | J8: =IFERROR(IF(INDEX(Pipeline!$J$7:$J$67,MATCH(LARGE(Pipeline!$O$7:$O$67,1),Pipeline!$O$7:$O$67,0))="","—",INDEX(Pipeline!$J$7:$J$67,MATCH(LARGE(Pipeline!$O$7:$O$67,1),Pipeline!$O$7:$O$67,0))),"") | K8: =IFERROR(IF(INDEX(Pipeline!$K$7:$K$67,MATCH(LARGE(Pipeline!$O$7:$O$67,1),Pipeline!$O$7:$O$67,0))="","—",INDEX(Pipeline!$K$7:$K$67,MATCH(LARGE(Pipeline!$O$7:$O$67,1),Pipeline!$O$7:$O$67,0))),"") | L8: =IFERROR(IF(INDEX(Pipeline!$L$7:$L$67,MATCH(LARGE(Pipeline!$O$7:$O$67,1),Pipeline!$O$7:$O$67,0))="","—",INDEX(Pipeline!$L$7:$L$67,MATCH(LARGE(Pipeline!$O$7:$O$67,1),Pipeline!$O$7:$O$67,0))),"")
A9: 2 | B9: =IFERROR(IF(INDEX(Pipeline!$B$7:$B$67,MATCH(LARGE(Pipeline!$O$7:$O$67,2),Pipeline!$O$7:$O$67,0))="","—",INDEX(Pipeline!$B$7:$B$67,MATCH(LARGE(Pipeline!$O$7:$O$67,2),Pipeline!$O$7:$O$67,0))),"") | C9: =IFERROR(IF(INDEX(Pipeline!$C$7:$C$67,MATCH(LARGE(Pipeline!$O$7:$O$67,2),Pipeline!$O$7:$O$67,0))="","—",INDEX(Pipeline!$C$7:$C$67,MATCH(LARGE(Pipeline!$O$7:$O$67,2),Pipeline!$O$7:$O$67,0))),"") | D9: =IFERROR(IF(INDEX(Pipeline!$E$7:$E$67,MATCH(LARGE(Pipeline!$O$7:$O$67,2),Pipeline!$O$7:$O$67,0))="","—",INDEX(Pipeline!$E$7:$E$67,MATCH(LARGE(Pipeline!$O$7:$O$67,2),Pipeline!$O$7:$O$67,0))),"") | E9: =IFERROR(IF(INDEX(Pipeline!$F$7:$F$67,MATCH(LARGE(Pipeline!$O$7:$O$67,2),Pipeline!$O$7:$O$67,0))="","—",INDEX(Pipeline!$F$7:$F$67,MATCH(LARGE(Pipeline!$O$7:$O$67,2),Pipeline!$O$7:$O$67,0))),"") | F9: =IFERROR(IF(INDEX(Pipeline!$D$7:$D$67,MATCH(LARGE(Pipeline!$O$7:$O$67,2),Pipeline!$O$7:$O$67,0))="","—",INDEX(Pipeline!$D$7:$D$67,MATCH(LARGE(Pipeline!$O$7:$O$67,2),Pipeline!$O$7:$O$67,0))),"") | G9: =IFERROR(IF(INDEX(Pipeline!$G$7:$G$67,MATCH(LARGE(Pipeline!$O$7:$O$67,2),Pipeline!$O$7:$O$67,0))="","—",INDEX(Pipeline!$G$7:$G$67,MATCH(LARGE(Pipeline!$O$7:$O$67,2),Pipeline!$O$7:$O$67,0))),"") | H9: =IFERROR(IF(INDEX(Pipeline!$H$7:$H$67,MATCH(LARGE(Pipeline!$O$7:$O$67,2),Pipeline!$O$7:$O$67,0))="","—",INDEX(Pipeline!$H$7:$H$67,MATCH(LARGE(Pipeline!$O$7:$O$67,2),Pipeline!$O$7:$O$67,0))),"") | I9: =IFERROR(IF(INDEX(Pipeline!$I$7:$I$67,MATCH(LARGE(Pipeline!$O$7:$O$67,2),Pipeline!$O$7:$O$67,0))="","—",INDEX(Pipeline!$I$7:$I$67,MATCH(LARGE(Pipeline!$O$7:$O$67,2),Pipeline!$O$7:$O$67,0))),"") | J9: =IFERROR(IF(INDEX(Pipeline!$J$7:$J$67,MATCH(LARGE(Pipeline!$O$7:$O$67,2),Pipeline!$O$7:$O$67,0))="","—",INDEX(Pipeline!$J$7:$J$67,MATCH(LARGE(Pipeline!$O$7:$O$67,2),Pipeline!$O$7:$O$67,0))),"") | K9: =IFERROR(IF(INDEX(Pipeline!$K$7:$K$67,MATCH(LARGE(Pipeline!$O$7:$O$67,2),Pipeline!$O$7:$O$67,0))="","—",INDEX(Pipeline!$K$7:$K$67,MATCH(LARGE(Pipeline!$O$7:$O$67,2),Pipeline!$O$7:$O$67,0))),"") | L9: =IFERROR(IF(INDEX(Pipeline!$L$7:$L$67,MATCH(LARGE(Pipeline!$O$7:$O$67,2),Pipeline!$O$7:$O$67,0))="","—",INDEX(Pipeline!$L$7:$L$67,MATCH(LARGE(Pipeline!$O$7:$O$67,2),Pipeline!$O$7:$O$67,0))),"")
A10: 3 | B10: =IFERROR(IF(INDEX(Pipeline!$B$7:$B$67,MATCH(LARGE(Pipeline!$O$7:$O$67,3),Pipeline!$O$7:$O$67,0))="","—",INDEX(Pipeline!$B$7:$B$67,MATCH(LARGE(Pipeline!$O$7:$O$67,3),Pipeline!$O$7:$O$67,0))),"") | C10: =IFERROR(IF(INDEX(Pipeline!$C$7:$C$67,MATCH(LARGE(Pipeline!$O$7:$O$67,3),Pipeline!$O$7:$O$67,0))="","—",INDEX(Pipeline!$C$7:$C$67,MATCH(LARGE(Pipeline!$O$7:$O$67,3),Pipeline!$O$7:$O$67,0))),"") | D10: =IFERROR(IF(INDEX(Pipeline!$E$7:$E$67,MATCH(LARGE(Pipeline!$O$7:$O$67,3),Pipeline!$O$7:$O$67,0))="","—",INDEX(Pipeline!$E$7:$E$67,MATCH(LARGE(Pipeline!$O$7:$O$67,3),Pipeline!$O$7:$O$67,0))),"") | E10: =IFERROR(IF(INDEX(Pipeline!$F$7:$F$67,MATCH(LARGE(Pipeline!$O$7:$O$67,3),Pipeline!$O$7:$O$67,0))="","—",INDEX(Pipeline!$F$7:$F$67,MATCH(LARGE(Pipeline!$O$7:$O$67,3),Pipeline!$O$7:$O$67,0))),"") | F10: =IFERROR(IF(INDEX(Pipeline!$D$7:$D$67,MATCH(LARGE(Pipeline!$O$7:$O$67,3),Pipeline!$O$7:$O$67,0))="","—",INDEX(Pipeline!$D$7:$D$67,MATCH(LARGE(Pipeline!$O$7:$O$67,3),Pipeline!$O$7:$O$67,0))),"") | G10: =IFERROR(IF(INDEX(Pipeline!$G$7:$G$67,MATCH(LARGE(Pipeline!$O$7:$O$67,3),Pipeline!$O$7:$O$67,0))="","—",INDEX(Pipeline!$G$7:$G$67,MATCH(LARGE(Pipeline!$O$7:$O$67,3),Pipeline!$O$7:$O$67,0))),"") | H10: =IFERROR(IF(INDEX(Pipeline!$H$7:$H$67,MATCH(LARGE(Pipeline!$O$7:$O$67,3),Pipeline!$O$7:$O$67,0))="","—",INDEX(Pipeline!$H$7:$H$67,MATCH(LARGE(Pipeline!$O$7:$O$67,3),Pipeline!$O$7:$O$67,0))),"") | I10: =IFERROR(IF(INDEX(Pipeline!$I$7:$I$67,MATCH(LARGE(Pipeline!$O$7:$O$67,3),Pipeline!$O$7:$O$67,0))="","—",INDEX(Pipeline!$I$7:$I$67,MATCH(LARGE(Pipeline!$O$7:$O$67,3),Pipeline!$O$7:$O$67,0))),"") | J10: =IFERROR(IF(INDEX(Pipeline!$J$7:$J$67,MATCH(LARGE(Pipeline!$O$7:$O$67,3),Pipeline!$O$7:$O$67,0))="","—",INDEX(Pipeline!$J$7:$J$67,MATCH(LARGE(Pipeline!$O$7:$O$67,3),Pipeline!$O$7:$O$67,0))),"") | K10: =IFERROR(IF(INDEX(Pipeline!$K$7:$K$67,MATCH(LARGE(Pipeline!$O$7:$O$67,3),Pipeline!$O$7:$O$67,0))="","—",INDEX(Pipeline!$K$7:$K$67,MATCH(LARGE(Pipeline!$O$7:$O$67,3),Pipeline!$O$7:$O$67,0))),"") | L10: =IFERROR(IF(INDEX(Pipeline!$L$7:$L$67,MATCH(LARGE(Pipeline!$O$7:$O$67,3),Pipeline!$O$7:$O$67,0))="","—",INDEX(Pipeline!$L$7:$L$67,MATCH(LARGE(Pipeline!$O$7:$O$67,3),Pipeline!$O$7:$O$67,0))),"")
A11: 4 | B11: =IFERROR(IF(INDEX(Pipeline!$B$7:$B$67,MATCH(LARGE(Pipeline!$O$7:$O$67,4),Pipeline!$O$7:$O$67,0))="","—",INDEX(Pipeline!$B$7:$B$67,MATCH(LARGE(Pipeline!$O$7:$O$67,4),Pipeline!$O$7:$O$67,0))),"") | C11: =IFERROR(IF(INDEX(Pipeline!$C$7:$C$67,MATCH(LARGE(Pipeline!$O$7:$O$67,4),Pipeline!$O$7:$O$67,0))="","—",INDEX(Pipeline!$C$7:$C$67,MATCH(LARGE(Pipeline!$O$7:$O$67,4),Pipeline!$O$7:$O$67,0))),"") | D11: =IFERROR(IF(INDEX(Pipeline!$E$7:$E$67,MATCH(LARGE(Pipeline!$O$7:$O$67,4),Pipeline!$O$7:$O$67,0))="","—",INDEX(Pipeline!$E$7:$E$67,MATCH(LARGE(Pipeline!$O$7:$O$67,4),Pipeline!$O$7:$O$67,0))),"") | E11: =IFERROR(IF(INDEX(Pipeline!$F$7:$F$67,MATCH(LARGE(Pipeline!$O$7:$O$67,4),Pipeline!$O$7:$O$67,0))="","—",INDEX(Pipeline!$F$7:$F$67,MATCH(LARGE(Pipeline!$O$7:$O$67,4),Pipeline!$O$7:$O$67,0))),"") | F11: =IFERROR(IF(INDEX(Pipeline!$D$7:$D$67,MATCH(LARGE(Pipeline!$O$7:$O$67,4),Pipeline!$O$7:$O$67,0))="","—",INDEX(Pipeline!$D$7:$D$67,MATCH(LARGE(Pipeline!$O$7:$O$67,4),Pipeline!$O$7:$O$67,0))),"") | G11: =IFERROR(IF(INDEX(Pipeline!$G$7:$G$67,MATCH(LARGE(Pipeline!$O$7:$O$67,4),Pipeline!$O$7:$O$67,0))="","—",INDEX(Pipeline!$G$7:$G$67,MATCH(LARGE(Pipeline!$O$7:$O$67,4),Pipeline!$O$7:$O$67,0))),"") | H11: =IFERROR(IF(INDEX(Pipeline!$H$7:$H$67,MATCH(LARGE(Pipeline!$O$7:$O$67,4),Pipeline!$O$7:$O$67,0))="","—",INDEX(Pipeline!$H$7:$H$67,MATCH(LARGE(Pipeline!$O$7:$O$67,4),Pipeline!$O$7:$O$67,0))),"") | I11: =IFERROR(IF(INDEX(Pipeline!$I$7:$I$67,MATCH(LARGE(Pipeline!$O$7:$O$67,4),Pipeline!$O$7:$O$67,0))="","—",INDEX(Pipeline!$I$7:$I$67,MATCH(LARGE(Pipeline!$O$7:$O$67,4),Pipeline!$O$7:$O$67,0))),"") | J11: =IFERROR(IF(INDEX(Pipeline!$J$7:$J$67,MATCH(LARGE(Pipeline!$O$7:$O$67,4),Pipeline!$O$7:$O$67,0))="","—",INDEX(Pipeline!$J$7:$J$67,MATCH(LARGE(Pipeline!$O$7:$O$67,4),Pipeline!$O$7:$O$67,0))),"") | K11: =IFERROR(IF(INDEX(Pipeline!$K$7:$K$67,MATCH(LARGE(Pipeline!$O$7:$O$67,4),Pipeline!$O$7:$O$67,0))="","—",INDEX(Pipeline!$K$7:$K$67,MATCH(LARGE(Pipeline!$O$7:$O$67,4),Pipeline!$O$7:$O$67,0))),"") | L11: =IFERROR(IF(INDEX(Pipeline!$L$7:$L$67,MATCH(LARGE(Pipeline!$O$7:$O$67,4),Pipeline!$O$7:$O$67,0))="","—",INDEX(Pipeline!$L$7:$L$67,MATCH(LARGE(Pipeline!$O$7:$O$67,4),Pipeline!$O$7:$O$67,0))),"")
A12: 5 | B12: =IFERROR(IF(INDEX(Pipeline!$B$7:$B$67,MATCH(LARGE(Pipeline!$O$7:$O$67,5),Pipeline!$O$7:$O$67,0))="","—",INDEX(Pipeline!$B$7:$B$67,MATCH(LARGE(Pipeline!$O$7:$O$67,5),Pipeline!$O$7:$O$67,0))),"") | C12: =IFERROR(IF(INDEX(Pipeline!$C$7:$C$67,MATCH(LARGE(Pipeline!$O$7:$O$67,5),Pipeline!$O$7:$O$67,0))="","—",INDEX(Pipeline!$C$7:$C$67,MATCH(LARGE(Pipeline!$O$7:$O$67,5),Pipeline!$O$7:$O$67,0))),"") | D12: =IFERROR(IF(INDEX(Pipeline!$E$7:$E$67,MATCH(LARGE(Pipeline!$O$7:$O$67,5),Pipeline!$O$7:$O$67,0))="","—",INDEX(Pipeline!$E$7:$E$67,MATCH(LARGE(Pipeline!$O$7:$O$67,5),Pipeline!$O$7:$O$67,0))),"") | E12: =IFERROR(IF(INDEX(Pipeline!$F$7:$F$67,MATCH(LARGE(Pipeline!$O$7:$O$67,5),Pipeline!$O$7:$O$67,0))="","—",INDEX(Pipeline!$F$7:$F$67,MATCH(LARGE(Pipeline!$O$7:$O$67,5),Pipeline!$O$7:$O$67,0))),"") | F12: =IFERROR(IF(INDEX(Pipeline!$D$7:$D$67,MATCH(LARGE(Pipeline!$O$7:$O$67,5),Pipeline!$O$7:$O$67,0))="","—",INDEX(Pipeline!$D$7:$D$67,MATCH(LARGE(Pipeline!$O$7:$O$67,5),Pipeline!$O$7:$O$67,0))),"") | G12: =IFERROR(IF(INDEX(Pipeline!$G$7:$G$67,MATCH(LARGE(Pipeline!$O$7:$O$67,5),Pipeline!$O$7:$O$67,0))="","—",INDEX(Pipeline!$G$7:$G$67,MATCH(LARGE(Pipeline!$O$7:$O$67,5),Pipeline!$O$7:$O$67,0))),"") | H12: =IFERROR(IF(INDEX(Pipeline!$H$7:$H$67,MATCH(LARGE(Pipeline!$O$7:$O$67,5),Pipeline!$O$7:$O$67,0))="","—",INDEX(Pipeline!$H$7:$H$67,MATCH(LARGE(Pipeline!$O$7:$O$67,5),Pipeline!$O$7:$O$67,0))),"") | I12: =IFERROR(IF(INDEX(Pipeline!$I$7:$I$67,MATCH(LARGE(Pipeline!$O$7:$O$67,5),Pipeline!$O$7:$O$67,0))="","—",INDEX(Pipeline!$I$7:$I$67,MATCH(LARGE(Pipeline!$O$7:$O$67,5),Pipeline!$O$7:$O$67,0))),"") | J12: =IFERROR(IF(INDEX(Pipeline!$J$7:$J$67,MATCH(LARGE(Pipeline!$O$7:$O$67,5),Pipeline!$O$7:$O$67,0))="","—",INDEX(Pipeline!$J$7:$J$67,MATCH(LARGE(Pipeline!$O$7:$O$67,5),Pipeline!$O$7:$O$67,0))),"") | K12: =IFERROR(IF(INDEX(Pipeline!$K$7:$K$67,MATCH(LARGE(Pipeline!$O$7:$O$67,5),Pipeline!$O$7:$O$67,0))="","—",INDEX(Pipeline!$K$7:$K$67,MATCH(LARGE(Pipeline!$O$7:$O$67,5),Pipeline!$O$7:$O$67,0))),"") | L12: =IFERROR(IF(INDEX(Pipeline!$L$7:$L$67,MATCH(LARGE(Pipeline!$O$7:$O$67,5),Pipeline!$O$7:$O$67,0))="","—",INDEX(Pipeline!$L$7:$L$67,MATCH(LARGE(Pipeline!$O$7:$O$67,5),Pipeline!$O$7:$O$67,0))),"")
B13: Total Top 5 | G13: =SUM(G8:G12) | H13: =SUM(H8:H12)
A15: Distribución – Top 5 proyectos por m² (todos los estados)
A16: # | B16: Cliente | C16: Proyecto | D16: País | E16: Portafolio (Type) | F16: Ejecutivo | G16: m² | H16: USD | I16: Estado | J16: % Cierre | K16: Fecha cierre | L16: Valor ponderado
A17: 1 | B17: =IFERROR(IF(INDEX(Pipeline!$B$7:$B$67,MATCH(LARGE(Pipeline!$P$7:$P$67,1),Pipeline!$P$7:$P$67,0))="","—",INDEX(Pipeline!$B$7:$B$67,MATCH(LARGE(Pipeline!$P$7:$P$67,1),Pipeline!$P$7:$P$67,0))),"") | C17: =IFERROR(IF(INDEX(Pipeline!$C$7:$C$67,MATCH(LARGE(Pipeline!$P$7:$P$67,1),Pipeline!$P$7:$P$67,0))="","—",INDEX(Pipeline!$C$7:$C$67,MATCH(LARGE(Pipeline!$P$7:$P$67,1),Pipeline!$P$7:$P$67,0))),"") | D17: =IFERROR(IF(INDEX(Pipeline!$E$7:$E$67,MATCH(LARGE(Pipeline!$P$7:$P$67,1),Pipeline!$P$7:$P$67,0))="","—",INDEX(Pipeline!$E$7:$E$67,MATCH(LARGE(Pipeline!$P$7:$P$67,1),Pipeline!$P$7:$P$67,0))),"") | E17: =IFERROR(IF(INDEX(Pipeline!$F$7:$F$67,MATCH(LARGE(Pipeline!$P$7:$P$67,1),Pipeline!$P$7:$P$67,0))="","—",INDEX(Pipeline!$F$7:$F$67,MATCH(LARGE(Pipeline!$P$7:$P$67,1),Pipeline!$P$7:$P$67,0))),"") | F17: =IFERROR(IF(INDEX(Pipeline!$D$7:$D$67,MATCH(LARGE(Pipeline!$P$7:$P$67,1),Pipeline!$P$7:$P$67,0))="","—",INDEX(Pipeline!$D$7:$D$67,MATCH(LARGE(Pipeline!$P$7:$P$67,1),Pipeline!$P$7:$P$67,0))),"") | G17: =IFERROR(IF(INDEX(Pipeline!$G$7:$G$67,MATCH(LARGE(Pipeline!$P$7:$P$67,1),Pipeline!$P$7:$P$67,0))="","—",INDEX(Pipeline!$G$7:$G$67,MATCH(LARGE(Pipeline!$P$7:$P$67,1),Pipeline!$P$7:$P$67,0))),"") | H17: =IFERROR(IF(INDEX(Pipeline!$H$7:$H$67,MATCH(LARGE(Pipeline!$P$7:$P$67,1),Pipeline!$P$7:$P$67,0))="","—",INDEX(Pipeline!$H$7:$H$67,MATCH(LARGE(Pipeline!$P$7:$P$67,1),Pipeline!$P$7:$P$67,0))),"") | I17: =IFERROR(IF(INDEX(Pipeline!$I$7:$I$67,MATCH(LARGE(Pipeline!$P$7:$P$67,1),Pipeline!$P$7:$P$67,0))="","—",INDEX(Pipeline!$I$7:$I$67,MATCH(LARGE(Pipeline!$P$7:$P$67,1),Pipeline!$P$7:$P$67,0))),"") | J17: =IFERROR(IF(INDEX(Pipeline!$J$7:$J$67,MATCH(LARGE(Pipeline!$P$7:$P$67,1),Pipeline!$P$7:$P$67,0))="","—",INDEX(Pipeline!$J$7:$J$67,MATCH(LARGE(Pipeline!$P$7:$P$67,1),Pipeline!$P$7:$P$67,0))),"") | K17: =IFERROR(IF(INDEX(Pipeline!$K$7:$K$67,MATCH(LARGE(Pipeline!$P$7:$P$67,1),Pipeline!$P$7:$P$67,0))="","—",INDEX(Pipeline!$K$7:$K$67,MATCH(LARGE(Pipeline!$P$7:$P$67,1),Pipeline!$P$7:$P$67,0))),"") | L17: =IFERROR(IF(INDEX(Pipeline!$L$7:$L$67,MATCH(LARGE(Pipeline!$P$7:$P$67,1),Pipeline!$P$7:$P$67,0))="","—",INDEX(Pipeline!$L$7:$L$67,MATCH(LARGE(Pipeline!$P$7:$P$67,1),Pipeline!$P$7:$P$67,0))),"")
A18: 2 | B18: =IFERROR(IF(INDEX(Pipeline!$B$7:$B$67,MATCH(LARGE(Pipeline!$P$7:$P$67,2),Pipeline!$P$7:$P$67,0))="","—",INDEX(Pipeline!$B$7:$B$67,MATCH(LARGE(Pipeline!$P$7:$P$67,2),Pipeline!$P$7:$P$67,0))),"") | C18: =IFERROR(IF(INDEX(Pipeline!$C$7:$C$67,MATCH(LARGE(Pipeline!$P$7:$P$67,2),Pipeline!$P$7:$P$67,0))="","—",INDEX(Pipeline!$C$7:$C$67,MATCH(LARGE(Pipeline!$P$7:$P$67,2),Pipeline!$P$7:$P$67,0))),"") | D18: =IFERROR(IF(INDEX(Pipeline!$E$7:$E$67,MATCH(LARGE(Pipeline!$P$7:$P$67,2),Pipeline!$P$7:$P$67,0))="","—",INDEX(Pipeline!$E$7:$E$67,MATCH(LARGE(Pipeline!$P$7:$P$67,2),Pipeline!$P$7:$P$67,0))),"") | E18: =IFERROR(IF(INDEX(Pipeline!$F$7:$F$67,MATCH(LARGE(Pipeline!$P$7:$P$67,2),Pipeline!$P$7:$P$67,0))="","—",INDEX(Pipeline!$F$7:$F$67,MATCH(LARGE(Pipeline!$P$7:$P$67,2),Pipeline!$P$7:$P$67,0))),"") | F18: =IFERROR(IF(INDEX(Pipeline!$D$7:$D$67,MATCH(LARGE(Pipeline!$P$7:$P$67,2),Pipeline!$P$7:$P$67,0))="","—",INDEX(Pipeline!$D$7:$D$67,MATCH(LARGE(Pipeline!$P$7:$P$67,2),Pipeline!$P$7:$P$67,0))),"") | G18: =IFERROR(IF(INDEX(Pipeline!$G$7:$G$67,MATCH(LARGE(Pipeline!$P$7:$P$67,2),Pipeline!$P$7:$P$67,0))="","—",INDEX(Pipeline!$G$7:$G$67,MATCH(LARGE(Pipeline!$P$7:$P$67,2),Pipeline!$P$7:$P$67,0))),"") | H18: =IFERROR(IF(INDEX(Pipeline!$H$7:$H$67,MATCH(LARGE(Pipeline!$P$7:$P$67,2),Pipeline!$P$7:$P$67,0))="","—",INDEX(Pipeline!$H$7:$H$67,MATCH(LARGE(Pipeline!$P$7:$P$67,2),Pipeline!$P$7:$P$67,0))),"") | I18: =IFERROR(IF(INDEX(Pipeline!$I$7:$I$67,MATCH(LARGE(Pipeline!$P$7:$P$67,2),Pipeline!$P$7:$P$67,0))="","—",INDEX(Pipeline!$I$7:$I$67,MATCH(LARGE(Pipeline!$P$7:$P$67,2),Pipeline!$P$7:$P$67,0))),"") | J18: =IFERROR(IF(INDEX(Pipeline!$J$7:$J$67,MATCH(LARGE(Pipeline!$P$7:$P$67,2),Pipeline!$P$7:$P$67,0))="","—",INDEX(Pipeline!$J$7:$J$67,MATCH(LARGE(Pipeline!$P$7:$P$67,2),Pipeline!$P$7:$P$67,0))),"") | K18: =IFERROR(IF(INDEX(Pipeline!$K$7:$K$67,MATCH(LARGE(Pipeline!$P$7:$P$67,2),Pipeline!$P$7:$P$67,0))="","—",INDEX(Pipeline!$K$7:$K$67,MATCH(LARGE(Pipeline!$P$7:$P$67,2),Pipeline!$P$7:$P$67,0))),"") | L18: =IFERROR(IF(INDEX(Pipeline!$L$7:$L$67,MATCH(LARGE(Pipeline!$P$7:$P$67,2),Pipeline!$P$7:$P$67,0))="","—",INDEX(Pipeline!$L$7:$L$67,MATCH(LARGE(Pipeline!$P$7:$P$67,2),Pipeline!$P$7:$P$67,0))),"")
A19: 3 | B19: =IFERROR(IF(INDEX(Pipeline!$B$7:$B$67,MATCH(LARGE(Pipeline!$P$7:$P$67,3),Pipeline!$P$7:$P$67,0))="","—",INDEX(Pipeline!$B$7:$B$67,MATCH(LARGE(Pipeline!$P$7:$P$67,3),Pipeline!$P$7:$P$67,0))),"") | C19: =IFERROR(IF(INDEX(Pipeline!$C$7:$C$67,MATCH(LARGE(Pipeline!$P$7:$P$67,3),Pipeline!$P$7:$P$67,0))="","—",INDEX(Pipeline!$C$7:$C$67,MATCH(LARGE(Pipeline!$P$7:$P$67,3),Pipeline!$P$7:$P$67,0))),"") | D19: =IFERROR(IF(INDEX(Pipeline!$E$7:$E$67,MATCH(LARGE(Pipeline!$P$7:$P$67,3),Pipeline!$P$7:$P$67,0))="","—",INDEX(Pipeline!$E$7:$E$67,MATCH(LARGE(Pipeline!$P$7:$P$67,3),Pipeline!$P$7:$P$67,0))),"") | E19: =IFERROR(IF(INDEX(Pipeline!$F$7:$F$67,MATCH(LARGE(Pipeline!$P$7:$P$67,3),Pipeline!$P$7:$P$67,0))="","—",INDEX(Pipeline!$F$7:$F$67,MATCH(LARGE(Pipeline!$P$7:$P$67,3),Pipeline!$P$7:$P$67,0))),"") | F19: =IFERROR(IF(INDEX(Pipeline!$D$7:$D$67,MATCH(LARGE(Pipeline!$P$7:$P$67,3),Pipeline!$P$7:$P$67,0))="","—",INDEX(Pipeline!$D$7:$D$67,MATCH(LARGE(Pipeline!$P$7:$P$67,3),Pipeline!$P$7:$P$67,0))),"") | G19: =IFERROR(IF(INDEX(Pipeline!$G$7:$G$67,MATCH(LARGE(Pipeline!$P$7:$P$67,3),Pipeline!$P$7:$P$67,0))="","—",INDEX(Pipeline!$G$7:$G$67,MATCH(LARGE(Pipeline!$P$7:$P$67,3),Pipeline!$P$7:$P$67,0))),"") | H19: =IFERROR(IF(INDEX(Pipeline!$H$7:$H$67,MATCH(LARGE(Pipeline!$P$7:$P$67,3),Pipeline!$P$7:$P$67,0))="","—",INDEX(Pipeline!$H$7:$H$67,MATCH(LARGE(Pipeline!$P$7:$P$67,3),Pipeline!$P$7:$P$67,0))),"") | I19: =IFERROR(IF(INDEX(Pipeline!$I$7:$I$67,MATCH(LARGE(Pipeline!$P$7:$P$67,3),Pipeline!$P$7:$P$67,0))="","—",INDEX(Pipeline!$I$7:$I$67,MATCH(LARGE(Pipeline!$P$7:$P$67,3),Pipeline!$P$7:$P$67,0))),"") | J19: =IFERROR(IF(INDEX(Pipeline!$J$7:$J$67,MATCH(LARGE(Pipeline!$P$7:$P$67,3),Pipeline!$P$7:$P$67,0))="","—",INDEX(Pipeline!$J$7:$J$67,MATCH(LARGE(Pipeline!$P$7:$P$67,3),Pipeline!$P$7:$P$67,0))),"") | K19: =IFERROR(IF(INDEX(Pipeline!$K$7:$K$67,MATCH(LARGE(Pipeline!$P$7:$P$67,3),Pipeline!$P$7:$P$67,0))="","—",INDEX(Pipeline!$K$7:$K$67,MATCH(LARGE(Pipeline!$P$7:$P$67,3),Pipeline!$P$7:$P$67,0))),"") | L19: =IFERROR(IF(INDEX(Pipeline!$L$7:$L$67,MATCH(LARGE(Pipeline!$P$7:$P$67,3),Pipeline!$P$7:$P$67,0))="","—",INDEX(Pipeline!$L$7:$L$67,MATCH(LARGE(Pipeline!$P$7:$P$67,3),Pipeline!$P$7:$P$67,0))),"")
A20: 4 | B20: =IFERROR(IF(INDEX(Pipeline!$B$7:$B$67,MATCH(LARGE(Pipeline!$P$7:$P$67,4),Pipeline!$P$7:$P$67,0))="","—",INDEX(Pipeline!$B$7:$B$67,MATCH(LARGE(Pipeline!$P$7:$P$67,4),Pipeline!$P$7:$P$67,0))),"") | C20: =IFERROR(IF(INDEX(Pipeline!$C$7:$C$67,MATCH(LARGE(Pipeline!$P$7:$P$67,4),Pipeline!$P$7:$P$67,0))="","—",INDEX(Pipeline!$C$7:$C$67,MATCH(LARGE(Pipeline!$P$7:$P$67,4),Pipeline!$P$7:$P$67,0))),"") | D20: =IFERROR(IF(INDEX(Pipeline!$E$7:$E$67,MATCH(LARGE(Pipeline!$P$7:$P$67,4),Pipeline!$P$7:$P$67,0))="","—",INDEX(Pipeline!$E$7:$E$67,MATCH(LARGE(Pipeline!$P$7:$P$67,4),Pipeline!$P$7:$P$67,0))),"") | E20: =IFERROR(IF(INDEX(Pipeline!$F$7:$F$67,MATCH(LARGE(Pipeline!$P$7:$P$67,4),Pipeline!$P$7:$P$67,0))="","—",INDEX(Pipeline!$F$7:$F$67,MATCH(LARGE(Pipeline!$P$7:$P$67,4),Pipeline!$P$7:$P$67,0))),"") | F20: =IFERROR(IF(INDEX(Pipeline!$D$7:$D$67,MATCH(LARGE(Pipeline!$P$7:$P$67,4),Pipeline!$P$7:$P$67,0))="","—",INDEX(Pipeline!$D$7:$D$67,MATCH(LARGE(Pipeline!$P$7:$P$67,4),Pipeline!$P$7:$P$67,0))),"") | G20: =IFERROR(IF(INDEX(Pipeline!$G$7:$G$67,MATCH(LARGE(Pipeline!$P$7:$P$67,4),Pipeline!$P$7:$P$67,0))="","—",INDEX(Pipeline!$G$7:$G$67,MATCH(LARGE(Pipeline!$P$7:$P$67,4),Pipeline!$P$7:$P$67,0))),"") | H20: =IFERROR(IF(INDEX(Pipeline!$H$7:$H$67,MATCH(LARGE(Pipeline!$P$7:$P$67,4),Pipeline!$P$7:$P$67,0))="","—",INDEX(Pipeline!$H$7:$H$67,MATCH(LARGE(Pipeline!$P$7:$P$67,4),Pipeline!$P$7:$P$67,0))),"") | I20: =IFERROR(IF(INDEX(Pipeline!$I$7:$I$67,MATCH(LARGE(Pipeline!$P$7:$P$67,4),Pipeline!$P$7:$P$67,0))="","—",INDEX(Pipeline!$I$7:$I$67,MATCH(LARGE(Pipeline!$P$7:$P$67,4),Pipeline!$P$7:$P$67,0))),"") | J20: =IFERROR(IF(INDEX(Pipeline!$J$7:$J$67,MATCH(LARGE(Pipeline!$P$7:$P$67,4),Pipeline!$P$7:$P$67,0))="","—",INDEX(Pipeline!$J$7:$J$67,MATCH(LARGE(Pipeline!$P$7:$P$67,4),Pipeline!$P$7:$P$67,0))),"") | K20: =IFERROR(IF(INDEX(Pipeline!$K$7:$K$67,MATCH(LARGE(Pipeline!$P$7:$P$67,4),Pipeline!$P$7:$P$67,0))="","—",INDEX(Pipeline!$K$7:$K$67,MATCH(LARGE(Pipeline!$P$7:$P$67,4),Pipeline!$P$7:$P$67,0))),"") | L20: =IFERROR(IF(INDEX(Pipeline!$L$7:$L$67,MATCH(LARGE(Pipeline!$P$7:$P$67,4),Pipeline!$P$7:$P$67,0))="","—",INDEX(Pipeline!$L$7:$L$67,MATCH(LARGE(Pipeline!$P$7:$P$67,4),Pipeline!$P$7:$P$67,0))),"")
A21: 5 | B21: =IFERROR(IF(INDEX(Pipeline!$B$7:$B$67,MATCH(LARGE(Pipeline!$P$7:$P$67,5),Pipeline!$P$7:$P$67,0))="","—",INDEX(Pipeline!$B$7:$B$67,MATCH(LARGE(Pipeline!$P$7:$P$67,5),Pipeline!$P$7:$P$67,0))),"") | C21: =IFERROR(IF(INDEX(Pipeline!$C$7:$C$67,MATCH(LARGE(Pipeline!$P$7:$P$67,5),Pipeline!$P$7:$P$67,0))="","—",INDEX(Pipeline!$C$7:$C$67,MATCH(LARGE(Pipeline!$P$7:$P$67,5),Pipeline!$P$7:$P$67,0))),"") | D21: =IFERROR(IF(INDEX(Pipeline!$E$7:$E$67,MATCH(LARGE(Pipeline!$P$7:$P$67,5),Pipeline!$P$7:$P$67,0))="","—",INDEX(Pipeline!$E$7:$E$67,MATCH(LARGE(Pipeline!$P$7:$P$67,5),Pipeline!$P$7:$P$67,0))),"") | E21: =IFERROR(IF(INDEX(Pipeline!$F$7:$F$67,MATCH(LARGE(Pipeline!$P$7:$P$67,5),Pipeline!$P$7:$P$67,0))="","—",INDEX(Pipeline!$F$7:$F$67,MATCH(LARGE(Pipeline!$P$7:$P$67,5),Pipeline!$P$7:$P$67,0))),"") | F21: =IFERROR(IF(INDEX(Pipeline!$D$7:$D$67,MATCH(LARGE(Pipeline!$P$7:$P$67,5),Pipeline!$P$7:$P$67,0))="","—",INDEX(Pipeline!$D$7:$D$67,MATCH(LARGE(Pipeline!$P$7:$P$67,5),Pipeline!$P$7:$P$67,0))),"") | G21: =IFERROR(IF(INDEX(Pipeline!$G$7:$G$67,MATCH(LARGE(Pipeline!$P$7:$P$67,5),Pipeline!$P$7:$P$67,0))="","—",INDEX(Pipeline!$G$7:$G$67,MATCH(LARGE(Pipeline!$P$7:$P$67,5),Pipeline!$P$7:$P$67,0))),"") | H21: =IFERROR(IF(INDEX(Pipeline!$H$7:$H$67,MATCH(LARGE(Pipeline!$P$7:$P$67,5),Pipeline!$P$7:$P$67,0))="","—",INDEX(Pipeline!$H$7:$H$67,MATCH(LARGE(Pipeline!$P$7:$P$67,5),Pipeline!$P$7:$P$67,0))),"") | I21: =IFERROR(IF(INDEX(Pipeline!$I$7:$I$67,MATCH(LARGE(Pipeline!$P$7:$P$67,5),Pipeline!$P$7:$P$67,0))="","—",INDEX(Pipeline!$I$7:$I$67,MATCH(LARGE(Pipeline!$P$7:$P$67,5),Pipeline!$P$7:$P$67,0))),"") | J21: =IFERROR(IF(INDEX(Pipeline!$J$7:$J$67,MATCH(LARGE(Pipeline!$P$7:$P$67,5),Pipeline!$P$7:$P$67,0))="","—",INDEX(Pipeline!$J$7:$J$67,MATCH(LARGE(Pipeline!$P$7:$P$67,5),Pipeline!$P$7:$P$67,0))),"") | K21: =IFERROR(IF(INDEX(Pipeline!$K$7:$K$67,MATCH(LARGE(Pipeline!$P$7:$P$67,5),Pipeline!$P$7:$P$67,0))="","—",INDEX(Pipeline!$K$7:$K$67,MATCH(LARGE(Pipeline!$P$7:$P$67,5),Pipeline!$P$7:$P$67,0))),"") | L21: =IFERROR(IF(INDEX(Pipeline!$L$7:$L$67,MATCH(LARGE(Pipeline!$P$7:$P$67,5),Pipeline!$P$7:$P$67,0))="","—",INDEX(Pipeline!$L$7:$L$67,MATCH(LARGE(Pipeline!$P$7:$P$67,5),Pipeline!$P$7:$P$67,0))),"")
B22: Total Top 5 | G22: =SUM(G17:G21) | H22: =SUM(H17:H21)
B25: Resumen pipeline | C25: Industrial | D25: Distribución | E25: Total
B26: N° proyectos (filas) | C26: 41 | D26: =COUNTIFS(Pipeline!$A$7:$A$67,"Distribución") | E26: =C26+D26
B27: m² total | C27: 749389 | D27: =SUMIFS(Pipeline!$G$7:$G$67,Pipeline!$A$7:$A$67,"Distribución") | E27: =C27+D27
B28: USD total | C28: =SUMIFS(Pipeline!$H$7:$H$67,Pipeline!$A$7:$A$67,"Industrial") | D28: =SUMIFS(Pipeline!$H$7:$H$67,Pipeline!$A$7:$A$67,"Distribución") | E28: =C28+D28
B29: Closed Won – N° | C29: =COUNTIFS(Pipeline!$A$7:$A$67,"Industrial",Pipeline!$I$7:$I$67,"Closed Won") | D29: =COUNTIFS(Pipeline!$A$7:$A$67,"Distribución",Pipeline!$I$7:$I$67,"Closed Won") | E29: =C29+D29
B30: Closed Won – USD | C30: =SUMIFS(Pipeline!$H$7:$H$67,Pipeline!$A$7:$A$67,"Industrial",Pipeline!$I$7:$I$67,"Closed Won") | D30: =SUMIFS(Pipeline!$H$7:$H$67,Pipeline!$A$7:$A$67,"Distribución",Pipeline!$I$7:$I$67,"Closed Won") | E30: =C30+D30
B31: Specification – N° | C31: =COUNTIFS(Pipeline!$A$7:$A$67,"Industrial",Pipeline!$I$7:$I$67,"Specification") | D31: =COUNTIFS(Pipeline!$A$7:$A$67,"Distribución",Pipeline!$I$7:$I$67,"Specification") | E31: =C31+D31
B32: Pending – N° | C32: =COUNTIFS(Pipeline!$A$7:$A$67,"Industrial",Pipeline!$I$7:$I$67,"Pending") | D32: =COUNTIFS(Pipeline!$A$7:$A$67,"Distribución",Pipeline!$I$7:$I$67,"Pending") | E32: =C32+D32
B33: Pending – USD | C33: =SUMIFS(Pipeline!$H$7:$H$67,Pipeline!$A$7:$A$67,"Industrial",Pipeline!$I$7:$I$67,"Pending") | D33: =SUMIFS(Pipeline!$H$7:$H$67,Pipeline!$A$7:$A$67,"Distribución",Pipeline!$I$7:$I$67,"Pending") | E33: =C33+D33
B34: N° proyectos reportado (incl. grupo "Others") | C34: 38 | D34: =D26 | E34: =C34+D34
B35: Insight (texto para slide) | C35: =E34&" proyectos activos · USD "&TEXT(E28/1000000,"0.0")&" M · "&TEXT(E27/1000,"#,##0")&"k m²"

Sheet RSM_Resumen_Canales
A1: Resumen por canal – Order Intake, Ventas, Budget, Cumplimiento y Backlog (YTD)
A2: Alimenta el slide "Sales Performance by Channel (YTD)". Todo es fórmula: se actualiza desde las hojas RSM (detalle por consultor, no se presenta) y 05_Backlog_Canal.
A4: Canal (slide) | B4: Hoja RSM fuente | C4: Order Intake YTD (m²) | D4: Ventas YTD (m²) | E4: Budget anterior YTD (m²) | F4: Brecha vs budget (m²) | G4: % Cumplimiento | H4: Semáforo | I4: Backlog (m²) | J4: Margen backlog CM | K4: Margen backlog PY | L4: Δ margen (pp) | M4: Mix backlog | N4: Book-to-bill (OI/Ventas) | P4: # | Q4: Ranking cumplimiento (fuente gráfico) | R4: % Cumpl. | T4: Budget Junta YTD (m²) | U4: Brecha vs Junta (m²) | V4: % Cumpl. Junta | W4: Semáforo Junta
A5: Industrial | B5: 09_RSM_Industrial | C5: =INDEX('09_RSM_Industrial'!$C:$C,MATCH("TOTAL CANAL",'09_RSM_Industrial'!$A:$A,0)) | D5: =INDEX('09_RSM_Industrial'!$D:$D,MATCH("TOTAL CANAL",'09_RSM_Industrial'!$A:$A,0)) | E5: =INDEX('09_RSM_Industrial'!$E:$E,MATCH("TOTAL CANAL",'09_RSM_Industrial'!$A:$A,0)) | F5: =D5-E5 | G5: =IF(E5=0,0,D5/E5) | H5: =IF(ROUND(G5*100,0)<=60,"Rojo",IF(ROUND(G5*100,0)<=84,"Naranja",IF(ROUND(G5*100,0)<=100,"Verde claro","Verde oscuro"))) | I5: ='05_Backlog_Canal'!B5 | J5: ='05_Backlog_Canal'!E5 | K5: ='05_Backlog_Canal'!F5 | L5: =IF(OR(J5="",K5="",K5=0),"n.a.",(J5-K5)*100) | M5: =IFERROR(I5/$I$11,0) | N5: =IFERROR(C5/D5,"") | O5: =G5+(20-ROW())/1000000000 | P5: 1 | Q5: =INDEX($A$5:$A$10,MATCH(LARGE($O$5:$O$10,P5),$O$5:$O$10,0)) | R5: =INDEX($G$5:$G$10,MATCH(LARGE($O$5:$O$10,P5),$O$5:$O$10,0)) | T5: ='21_Ppto_Junta'!N35 | U5: =D5-T5 | V5: =IF(T5=0,0,D5/T5) | W5: =IF(ROUND(V5*100,0)<=60,"Rojo",IF(ROUND(V5*100,0)<=84,"Naranja",IF(ROUND(V5*100,0)<=100,"Verde claro","Verde oscuro")))
A6: Distribution | B6: 10_RSM_Distribucion | C6: =INDEX('10_RSM_Distribucion'!$C:$C,MATCH("TOTAL CANAL",'10_RSM_Distribucion'!$A:$A,0)) | D6: =INDEX('10_RSM_Distribucion'!$D:$D,MATCH("TOTAL CANAL",'10_RSM_Distribucion'!$A:$A,0)) | E6: =INDEX('10_RSM_Distribucion'!$E:$E,MATCH("TOTAL CANAL",'10_RSM_Distribucion'!$A:$A,0)) | F6: =D6-E6 | G6: =IF(E6=0,0,D6/E6) | H6: =IF(ROUND(G6*100,0)<=60,"Rojo",IF(ROUND(G6*100,0)<=84,"Naranja",IF(ROUND(G6*100,0)<=100,"Verde claro","Verde oscuro"))) | I6: ='05_Backlog_Canal'!B6 | J6: ='05_Backlog_Canal'!E6 | K6: ='05_Backlog_Canal'!F6 | L6: =IF(OR(J6="",K6="",K6=0),"n.a.",(J6-K6)*100) | M6: =IFERROR(I6/$I$11,0) | N6: =IFERROR(C6/D6,"") | O6: =G6+(20-ROW())/1000000000 | P6: 2 | Q6: =INDEX($A$5:$A$10,MATCH(LARGE($O$5:$O$10,P6),$O$5:$O$10,0)) | R6: =INDEX($G$5:$G$10,MATCH(LARGE($O$5:$O$10,P6),$O$5:$O$10,0)) | T6: ='21_Ppto_Junta'!N36 | U6: =D6-T6 | V6: =IF(T6=0,0,D6/T6) | W6: =IF(ROUND(V6*100,0)<=60,"Rojo",IF(ROUND(V6*100,0)<=84,"Naranja",IF(ROUND(V6*100,0)<=100,"Verde claro","Verde oscuro")))
A7: Other Geographies | B7: 11_RSM_Otras_Geo | C7: =INDEX('11_RSM_Otras_Geo'!$C:$C,MATCH("TOTAL CANAL",'11_RSM_Otras_Geo'!$A:$A,0)) | D7: =INDEX('11_RSM_Otras_Geo'!$D:$D,MATCH("TOTAL CANAL",'11_RSM_Otras_Geo'!$A:$A,0)) | E7: =INDEX('11_RSM_Otras_Geo'!$E:$E,MATCH("TOTAL CANAL",'11_RSM_Otras_Geo'!$A:$A,0)) | F7: =D7-E7 | G7: =IF(E7=0,0,D7/E7) | H7: =IF(ROUND(G7*100,0)<=60,"Rojo",IF(ROUND(G7*100,0)<=84,"Naranja",IF(ROUND(G7*100,0)<=100,"Verde claro","Verde oscuro"))) | I7: ='05_Backlog_Canal'!B7 | J7: ='05_Backlog_Canal'!E7 | K7: ='05_Backlog_Canal'!F7 | L7: =IF(OR(J7="",K7="",K7=0),"n.a.",(J7-K7)*100) | M7: =IFERROR(I7/$I$11,0) | N7: =IFERROR(C7/D7,"") | O7: =G7+(20-ROW())/1000000000 | P7: 3 | Q7: =INDEX($A$5:$A$10,MATCH(LARGE($O$5:$O$10,P7),$O$5:$O$10,0)) | R7: =INDEX($G$5:$G$10,MATCH(LARGE($O$5:$O$10,P7),$O$5:$O$10,0)) | T7: ='21_Ppto_Junta'!N37 | U7: =D7-T7 | V7: =IF(T7=0,0,D7/T7) | W7: =IF(ROUND(V7*100,0)<=60,"Rojo",IF(ROUND(V7*100,0)<=84,"Naranja",IF(ROUND(V7*100,0)<=100,"Verde claro","Verde oscuro")))
A8: Cold Storage | B8: 12_RSM_Cold_Storage | C8: =INDEX('12_RSM_Cold_Storage'!$C:$C,MATCH("TOTAL CANAL",'12_RSM_Cold_Storage'!$A:$A,0)) | D8: =INDEX('12_RSM_Cold_Storage'!$D:$D,MATCH("TOTAL CANAL",'12_RSM_Cold_Storage'!$A:$A,0)) | E8: =INDEX('12_RSM_Cold_Storage'!$E:$E,MATCH("TOTAL CANAL",'12_RSM_Cold_Storage'!$A:$A,0)) | F8: =D8-E8 | G8: =IF(E8=0,0,D8/E8) | H8: =IF(ROUND(G8*100,0)<=60,"Rojo",IF(ROUND(G8*100,0)<=84,"Naranja",IF(ROUND(G8*100,0)<=100,"Verde claro","Verde oscuro"))) | I8: ='05_Backlog_Canal'!B8 | J8: ='05_Backlog_Canal'!E8 | K8: ='05_Backlog_Canal'!F8 | L8: =IF(OR(J8="",K8="",K8=0),"n.a.",(J8-K8)*100) | M8: =IFERROR(I8/$I$11,0) | N8: =IFERROR(C8/D8,"") | O8: =G8+(20-ROW())/1000000000 | P8: 4 | Q8: =INDEX($A$5:$A$10,MATCH(LARGE($O$5:$O$10,P8),$O$5:$O$10,0)) | R8: =INDEX($G$5:$G$10,MATCH(LARGE($O$5:$O$10,P8),$O$5:$O$10,0)) | T8: ='21_Ppto_Junta'!N38 | U8: =D8-T8 | V8: =IF(T8=0,0,D8/T8) | W8: =IF(ROUND(V8*100,0)<=60,"Rojo",IF(ROUND(V8*100,0)<=84,"Naranja",IF(ROUND(V8*100,0)<=100,"Verde claro","Verde oscuro")))
A9: Site Cali | B9: 13_RSM_Site_Cali | C9: =INDEX('13_RSM_Site_Cali'!$C:$C,MATCH("TOTAL CANAL",'13_RSM_Site_Cali'!$A:$A,0)) | D9: =INDEX('13_RSM_Site_Cali'!$D:$D,MATCH("TOTAL CANAL",'13_RSM_Site_Cali'!$A:$A,0)) | E9: =INDEX('13_RSM_Site_Cali'!$E:$E,MATCH("TOTAL CANAL",'13_RSM_Site_Cali'!$A:$A,0)) | F9: =D9-E9 | G9: =IF(E9=0,0,D9/E9) | H9: =IF(ROUND(G9*100,0)<=60,"Rojo",IF(ROUND(G9*100,0)<=84,"Naranja",IF(ROUND(G9*100,0)<=100,"Verde claro","Verde oscuro"))) | I9: ='05_Backlog_Canal'!B9 | J9: ='05_Backlog_Canal'!E9 | K9: ='05_Backlog_Canal'!F9 | L9: =IF(OR(J9="",K9="",K9=0),"n.a.",(J9-K9)*100) | M9: =IFERROR(I9/$I$11,0) | N9: =IFERROR(C9/D9,"") | O9: =G9+(20-ROW())/1000000000 | P9: 5 | Q9: =INDEX($A$5:$A$10,MATCH(LARGE($O$5:$O$10,P9),$O$5:$O$10,0)) | R9: =INDEX($G$5:$G$10,MATCH(LARGE($O$5:$O$10,P9),$O$5:$O$10,0)) | T9: ='21_Ppto_Junta'!N39 | U9: =D9-T9 | V9: =IF(T9=0,0,D9/T9) | W9: =IF(ROUND(V9*100,0)<=60,"Rojo",IF(ROUND(V9*100,0)<=84,"Naranja",IF(ROUND(V9*100,0)<=100,"Verde claro","Verde oscuro")))
A10: Alternative Sales | B10: 14_RSM_Vtas_Alt | C10: =INDEX('14_RSM_Vtas_Alt'!$C:$C,MATCH("TOTAL CANAL",'14_RSM_Vtas_Alt'!$A:$A,0)) | D10: =INDEX('14_RSM_Vtas_Alt'!$D:$D,MATCH("TOTAL CANAL",'14_RSM_Vtas_Alt'!$A:$A,0)) | E10: =INDEX('14_RSM_Vtas_Alt'!$E:$E,MATCH("TOTAL CANAL",'14_RSM_Vtas_Alt'!$A:$A,0)) | F10: =D10-E10 | G10: =IF(E10=0,0,D10/E10) | H10: =IF(ROUND(G10*100,0)<=60,"Rojo",IF(ROUND(G10*100,0)<=84,"Naranja",IF(ROUND(G10*100,0)<=100,"Verde claro","Verde oscuro"))) | I10: ='05_Backlog_Canal'!B10 | J10: ='05_Backlog_Canal'!E10 | K10: ='05_Backlog_Canal'!F10 | L10: =IF(OR(J10="",K10="",K10=0),"n.a.",(J10-K10)*100) | M10: =IFERROR(I10/$I$11,0) | N10: =IFERROR(C10/D10,"") | O10: =G10+(20-ROW())/1000000000 | P10: 6 | Q10: =INDEX($A$5:$A$10,MATCH(LARGE($O$5:$O$10,P10),$O$5:$O$10,0)) | R10: =INDEX($G$5:$G$10,MATCH(LARGE($O$5:$O$10,P10),$O$5:$O$10,0)) | T10: ='21_Ppto_Junta'!N40 | U10: =D10-T10 | V10: =IF(T10=0,0,D10/T10) | W10: =IF(ROUND(V10*100,0)<=60,"Rojo",IF(ROUND(V10*100,0)<=84,"Naranja",IF(ROUND(V10*100,0)<=100,"Verde claro","Verde oscuro")))
A11: TOTAL | C11: =SUM(C5:C10) | D11: =SUM(D5:D10) | E11: =SUM(E5:E10) | F11: =SUM(F5:F10) | G11: =IF(E11=0,0,D11/E11) | H11: =IF(ROUND(G11*100,0)<=60,"Rojo",IF(ROUND(G11*100,0)<=84,"Naranja",IF(ROUND(G11*100,0)<=100,"Verde claro","Verde oscuro"))) | I11: =SUM(I5:I10) | J11: =IFERROR(SUMPRODUCT(I5:I10,J5:J10)/I11,0) | K11: =IFERROR(SUMPRODUCT('05_Backlog_Canal'!C5:C10,K5:K10)/'05_Backlog_Canal'!C11,0) | L11: =(J11-K11)*100 | M11: =SUM(M5:M10) | N11: =IFERROR(C11/D11,"") | T11: =SUM(T5:T10) | U11: =SUM(U5:U10) | V11: =IF(T11=0,0,D11/T11) | W11: =IF(ROUND(V11*100,0)<=60,"Rojo",IF(ROUND(V11*100,0)<=84,"Naranja",IF(ROUND(V11*100,0)<=100,"Verde claro","Verde oscuro")))
T12: Budget Junta = total Junta YTD × % participación del presupuesto anterior (o de la Junta, según 21_Ppto_Junta B5).
A13: KPIs del slide
A14: Order Intake YTD (m²) | C14: =C11
A15: Ventas YTD (m²) | C15: =D11
A16: Budget Junta YTD (m²) | C16: =T11
A17: Brecha vs Junta (m²) | C17: =U11
A18: % Cumplimiento vs Junta | C18: =V11
A19: Canales ≥100% budget Junta | C19: =COUNTIF(V5:V10,">=1")&" de 6"
A20: Backlog total (m²) | C20: =I11
A21: Margen backlog ponderado | C21: =J11
A22: Control: backlog vs IMP (hoja 04) | C22: =I11-'04_Backlog'!B5
A23: % de la brecha explicado por Industrial + Otras Geo | C23: =IFERROR((U5+U7)/U11,0)
A26: Semáforo cumplimiento: Rojo 0–60% · Naranja 61–84% · Verde claro 85–100% · Verde oscuro >100%
A28: Fuente slide "Sales vs Budget & Margin Evolution" (k m² y margen de backlog PY → CM)
A29: Canal | B29: Ventas YTD (k m²) | C29: Budget Junta YTD (k m²) | D29: Margen Sep-25 (PY) | E29: Margen Sep-26 (CM) | F29: Δ margen (pp) | G29: % Cumplimiento (Junta)
A30: =A5 | B30: =D5/1000 | C30: =T5/1000 | D30: =IF(K5=0,"n.a.",K5) | E30: =J5 | F30: =L5 | G30: =V5
A31: =A6 | B31: =D6/1000 | C31: =T6/1000 | D31: =IF(K6=0,"n.a.",K6) | E31: =J6 | F31: =L6 | G31: =V6
A32: =A7 | B32: =D7/1000 | C32: =T7/1000 | D32: =IF(K7=0,"n.a.",K7) | E32: =J7 | F32: =L7 | G32: =V7
A33: =A8 | B33: =D8/1000 | C33: =T8/1000 | D33: =IF(K8=0,"n.a.",K8) | E33: =J8 | F33: =L8 | G33: =V8
A34: =A9 | B34: =D9/1000 | C34: =T9/1000 | D34: =IF(K9=0,"n.a.",K9) | E34: =J9 | F34: =L9 | G34: =V9
A35: =A10 | B35: =D10/1000 | C35: =T10/1000 | D35: =IF(K10=0,"n.a.",K10) | E35: =J10 | F35: =L10 | G35: =V10
A36: =A11 | B36: =D11/1000 | C36: =T11/1000 | D36: =IF(K11=0,"n.a.",K11) | E36: =J11 | F36: =L11 | G36: =V11
A37: Nota: n.a. en margen PY = canal sin base PY. Para ver evolución mensual, agregar ventas/budget/margen por mes por canal.

Sheet 09_RSM_Industrial
A1: 09 · RSM Industrial – Cumplimiento y Backlog (YTD) [detalle interno – no se presenta en el deck]
A2: Diligencie la tabla izquierda; el ranking (derecha), totales y semáforos se calculan solos
A4: RSM (nombre completo) | B4: Nombre corto (slide) | C4: Order Intake m² | D4: Ventas Total m² | E4: Budget m² (paneles) | F4: % Cumpl. Budget | G4: Semáforo | H4: Backlog paneles m² | I4: Backlog otros m² | J4: Clave orden (aux) | L4: # | M4: Ranking – Fuente gráfico (mayor → menor cumplimiento) | N4: % Cumpl. | O4: Ventas m² | P4: Budget m²
A5: ARIAS GIRALDO ANA ISABEL | B5: Ana I. Arias | C5: 135074 | D5: 140201 | E5: 83093 | F5: =IF(A5="","",IF(E5=0,0,D5/E5)) | G5: =IF(F5="","",IF(F5>=1,"Verde",IF(F5>=0.7,"Ámbar","Rojo"))) | H5: 74948 | I5: 0 | J5: =IF(A5="","",F5+D5/1000000000+(100-ROW())/1000000000000) | L5: 1 | M5: =IF(L5>COUNT($J$5:$J$17),"",INDEX($B$5:$B$17,MATCH(LARGE($J$5:$J$17,L5),$J$5:$J$17,0))) | N5: =IF(M5="","",INDEX($F$5:$F$17,MATCH(LARGE($J$5:$J$17,L5),$J$5:$J$17,0))) | O5: =IF(M5="","",INDEX($D$5:$D$17,MATCH(LARGE($J$5:$J$17,L5),$J$5:$J$17,0))) | P5: =IF(M5="","",INDEX($E$5:$E$17,MATCH(LARGE($J$5:$J$17,L5),$J$5:$J$17,0)))
A6: EJECUTIVO VENTAS ZONA NORTE | B6: Ejec. Zona Norte | C6: =47727+2040+2699 | D6: =30473+4728 | E6: =36220+27698 | F6: =IF(A6="","",IF(E6=0,0,D6/E6)) | G6: =IF(F6="","",IF(F6>=1,"Verde",IF(F6>=0.7,"Ámbar","Rojo"))) | H6: 29686 | I6: 0 | J6: =IF(A6="","",F6+D6/1000000000+(100-ROW())/1000000000000) | L6: 2 | M6: =IF(L6>COUNT($J$5:$J$17),"",INDEX($B$5:$B$17,MATCH(LARGE($J$5:$J$17,L6),$J$5:$J$17,0))) | N6: =IF(M6="","",INDEX($F$5:$F$17,MATCH(LARGE($J$5:$J$17,L6),$J$5:$J$17,0))) | O6: =IF(M6="","",INDEX($D$5:$D$17,MATCH(LARGE($J$5:$J$17,L6),$J$5:$J$17,0))) | P6: =IF(M6="","",INDEX($E$5:$E$17,MATCH(LARGE($J$5:$J$17,L6),$J$5:$J$17,0)))
A7: GUERRERO ESPINOSA JULIO CESAR | B7: Julio C. Guerrero | C7: 115336 | D7: 103583 | E7: 73860 | F7: =IF(A7="","",IF(E7=0,0,D7/E7)) | G7: =IF(F7="","",IF(F7>=1,"Verde",IF(F7>=0.7,"Ámbar","Rojo"))) | H7: 18759 | I7: 0 | J7: =IF(A7="","",F7+D7/1000000000+(100-ROW())/1000000000000) | L7: 3 | M7: =IF(L7>COUNT($J$5:$J$17),"",INDEX($B$5:$B$17,MATCH(LARGE($J$5:$J$17,L7),$J$5:$J$17,0))) | N7: =IF(M7="","",INDEX($F$5:$F$17,MATCH(LARGE($J$5:$J$17,L7),$J$5:$J$17,0))) | O7: =IF(M7="","",INDEX($D$5:$D$17,MATCH(LARGE($J$5:$J$17,L7),$J$5:$J$17,0))) | P7: =IF(M7="","",INDEX($E$5:$E$17,MATCH(LARGE($J$5:$J$17,L7),$J$5:$J$17,0)))
A8: CALDERON CHANTRE DIEGO ALFONSO | B8: Diego A. Calderón | C8: 42594 | D8: 29075 | E8: 35456 | F8: =IF(A8="","",IF(E8=0,0,D8/E8)) | G8: =IF(F8="","",IF(F8>=1,"Verde",IF(F8>=0.7,"Ámbar","Rojo"))) | H8: 27745 | I8: 0 | J8: =IF(A8="","",F8+D8/1000000000+(100-ROW())/1000000000000) | L8: 4 | M8: =IF(L8>COUNT($J$5:$J$17),"",INDEX($B$5:$B$17,MATCH(LARGE($J$5:$J$17,L8),$J$5:$J$17,0))) | N8: =IF(M8="","",INDEX($F$5:$F$17,MATCH(LARGE($J$5:$J$17,L8),$J$5:$J$17,0))) | O8: =IF(M8="","",INDEX($D$5:$D$17,MATCH(LARGE($J$5:$J$17,L8),$J$5:$J$17,0))) | P8: =IF(M8="","",INDEX($E$5:$E$17,MATCH(LARGE($J$5:$J$17,L8),$J$5:$J$17,0)))
A9: CANDELA HERNANDEZ YOLANDA | B9: Yolanda Candela | C9: 36716 | D9: 27897 | E9: 58259 | F9: =IF(A9="","",IF(E9=0,0,D9/E9)) | G9: =IF(F9="","",IF(F9>=1,"Verde",IF(F9>=0.7,"Ámbar","Rojo"))) | H9: 22797 | I9: 18 | J9: =IF(A9="","",F9+D9/1000000000+(100-ROW())/1000000000000) | L9: 5 | M9: =IF(L9>COUNT($J$5:$J$17),"",INDEX($B$5:$B$17,MATCH(LARGE($J$5:$J$17,L9),$J$5:$J$17,0))) | N9: =IF(M9="","",INDEX($F$5:$F$17,MATCH(LARGE($J$5:$J$17,L9),$J$5:$J$17,0))) | O9: =IF(M9="","",INDEX($D$5:$D$17,MATCH(LARGE($J$5:$J$17,L9),$J$5:$J$17,0))) | P9: =IF(M9="","",INDEX($E$5:$E$17,MATCH(LARGE($J$5:$J$17,L9),$J$5:$J$17,0)))
A10: EJECUTIVO VENTAS ZONA CUENTAS CLAVES | B10: Ejec. Cuentas Clave | C10: 10539 | D10: 2608 | E10: 31201.125 | F10: =IF(A10="","",IF(E10=0,0,D10/E10)) | G10: =IF(F10="","",IF(F10>=1,"Verde",IF(F10>=0.7,"Ámbar","Rojo"))) | H10: 0 | I10: 0 | J10: =IF(A10="","",F10+D10/1000000000+(100-ROW())/1000000000000) | L10: 7 | M10: =IF(L10>COUNT($J$5:$J$17),"",INDEX($B$5:$B$17,MATCH(LARGE($J$5:$J$17,L10),$J$5:$J$17,0))) | N10: =IF(M10="","",INDEX($F$5:$F$17,MATCH(LARGE($J$5:$J$17,L10),$J$5:$J$17,0))) | O10: =IF(M10="","",INDEX($D$5:$D$17,MATCH(LARGE($J$5:$J$17,L10),$J$5:$J$17,0))) | P10: =IF(M10="","",INDEX($E$5:$E$17,MATCH(LARGE($J$5:$J$17,L10),$J$5:$J$17,0)))
A11: NARANJO VELEZ LEON ALEXIS | B11: León A. Naranjo | C11: 14965 | D11: 924 | E11: 28161 | F11: =IF(A11="","",IF(E11=0,0,D11/E11)) | G11: =IF(F11="","",IF(F11>=1,"Verde",IF(F11>=0.7,"Ámbar","Rojo"))) | H11: 14041 | I11: 1895 | J11: =IF(A11="","",F11+D11/1000000000+(100-ROW())/1000000000000) | L11: 9 | M11: =IF(L11>COUNT($J$5:$J$17),"",INDEX($B$5:$B$17,MATCH(LARGE($J$5:$J$17,L11),$J$5:$J$17,0))) | N11: =IF(M11="","",INDEX($F$5:$F$17,MATCH(LARGE($J$5:$J$17,L11),$J$5:$J$17,0))) | O11: =IF(M11="","",INDEX($D$5:$D$17,MATCH(LARGE($J$5:$J$17,L11),$J$5:$J$17,0))) | P11: =IF(M11="","",INDEX($E$5:$E$17,MATCH(LARGE($J$5:$J$17,L11),$J$5:$J$17,0)))
A12: FONTALVO MENDIETA ADRIANA MARCELA | B12: Adriana M. Fontalvo | C12: 22878 | D12: 99 | E12: 19175 | F12: =IF(A12="","",IF(E12=0,0,D12/E12)) | G12: =IF(F12="","",IF(F12>=1,"Verde",IF(F12>=0.7,"Ámbar","Rojo"))) | H12: 22779 | I12: 0 | J12: =IF(A12="","",F12+D12/1000000000+(100-ROW())/1000000000000) | L12: 10 | M12: =IF(L12>COUNT($J$5:$J$17),"",INDEX($B$5:$B$17,MATCH(LARGE($J$5:$J$17,L12),$J$5:$J$17,0))) | N12: =IF(M12="","",INDEX($F$5:$F$17,MATCH(LARGE($J$5:$J$17,L12),$J$5:$J$17,0))) | O12: =IF(M12="","",INDEX($D$5:$D$17,MATCH(LARGE($J$5:$J$17,L12),$J$5:$J$17,0))) | P12: =IF(M12="","",INDEX($E$5:$E$17,MATCH(LARGE($J$5:$J$17,L12),$J$5:$J$17,0)))
A13: EJECUTIVO VENTAS ZONA BOGOTA | B13: Ejec. Zona Bogotá | C13: 0 | D13: 0 | E13: 50778.75 | F13: =IF(A13="","",IF(E13=0,0,D13/E13)) | G13: =IF(F13="","",IF(F13>=1,"Verde",IF(F13>=0.7,"Ámbar","Rojo"))) | H13: 0 | I13: 0 | J13: =IF(A13="","",F13+D13/1000000000+(100-ROW())/1000000000000) | L13: 11 | M13: =IF(L13>COUNT($J$5:$J$17),"",INDEX($B$5:$B$17,MATCH(LARGE($J$5:$J$17,L13),$J$5:$J$17,0))) | N13: =IF(M13="","",INDEX($F$5:$F$17,MATCH(LARGE($J$5:$J$17,L13),$J$5:$J$17,0))) | O13: =IF(M13="","",INDEX($D$5:$D$17,MATCH(LARGE($J$5:$J$17,L13),$J$5:$J$17,0))) | P13: =IF(M13="","",INDEX($E$5:$E$17,MATCH(LARGE($J$5:$J$17,L13),$J$5:$J$17,0)))
F14: =IF(A14="","",IF(E14=0,0,D14/E14)) | G14: =IF(F14="","",IF(F14>=1,"Verde",IF(F14>=0.7,"Ámbar","Rojo"))) | J14: =IF(A14="","",F14+D14/1000000000+(100-ROW())/1000000000000) | L14: 12 | M14: =IF(L14>COUNT($J$5:$J$17),"",INDEX($B$5:$B$17,MATCH(LARGE($J$5:$J$17,L14),$J$5:$J$17,0))) | N14: =IF(M14="","",INDEX($F$5:$F$17,MATCH(LARGE($J$5:$J$17,L14),$J$5:$J$17,0))) | O14: =IF(M14="","",INDEX($D$5:$D$17,MATCH(LARGE($J$5:$J$17,L14),$J$5:$J$17,0))) | P14: =IF(M14="","",INDEX($E$5:$E$17,MATCH(LARGE($J$5:$J$17,L14),$J$5:$J$17,0)))
F15: =IF(A15="","",IF(E15=0,0,D15/E15)) | G15: =IF(F15="","",IF(F15>=1,"Verde",IF(F15>=0.7,"Ámbar","Rojo"))) | J15: =IF(A15="","",F15+D15/1000000000+(100-ROW())/1000000000000) | L15: 13 | M15: =IF(L15>COUNT($J$5:$J$17),"",INDEX($B$5:$B$17,MATCH(LARGE($J$5:$J$17,L15),$J$5:$J$17,0))) | N15: =IF(M15="","",INDEX($F$5:$F$17,MATCH(LARGE($J$5:$J$17,L15),$J$5:$J$17,0))) | O15: =IF(M15="","",INDEX($D$5:$D$17,MATCH(LARGE($J$5:$J$17,L15),$J$5:$J$17,0))) | P15: =IF(M15="","",INDEX($E$5:$E$17,MATCH(LARGE($J$5:$J$17,L15),$J$5:$J$17,0)))
F16: =IF(A16="","",IF(E16=0,0,D16/E16)) | G16: =IF(F16="","",IF(F16>=1,"Verde",IF(F16>=0.7,"Ámbar","Rojo"))) | J16: =IF(A16="","",F16+D16/1000000000+(100-ROW())/1000000000000) | L16: 14 | M16: =IF(L16>COUNT($J$5:$J$17),"",INDEX($B$5:$B$17,MATCH(LARGE($J$5:$J$17,L16),$J$5:$J$17,0))) | N16: =IF(M16="","",INDEX($F$5:$F$17,MATCH(LARGE($J$5:$J$17,L16),$J$5:$J$17,0))) | O16: =IF(M16="","",INDEX($D$5:$D$17,MATCH(LARGE($J$5:$J$17,L16),$J$5:$J$17,0))) | P16: =IF(M16="","",INDEX($E$5:$E$17,MATCH(LARGE($J$5:$J$17,L16),$J$5:$J$17,0)))
F17: =IF(A17="","",IF(E17=0,0,D17/E17)) | G17: =IF(F17="","",IF(F17>=1,"Verde",IF(F17>=0.7,"Ámbar","Rojo"))) | J17: =IF(A17="","",F17+D17/1000000000+(100-ROW())/1000000000000) | L17: 15 | M17: =IF(L17>COUNT($J$5:$J$17),"",INDEX($B$5:$B$17,MATCH(LARGE($J$5:$J$17,L17),$J$5:$J$17,0))) | N17: =IF(M17="","",INDEX($F$5:$F$17,MATCH(LARGE($J$5:$J$17,L17),$J$5:$J$17,0))) | O17: =IF(M17="","",INDEX($D$5:$D$17,MATCH(LARGE($J$5:$J$17,L17),$J$5:$J$17,0))) | P17: =IF(M17="","",INDEX($E$5:$E$17,MATCH(LARGE($J$5:$J$17,L17),$J$5:$J$17,0)))
A18: TOTAL CANAL | B18: =COUNTA(A5:A17)&" RSM" | C18: =SUM(C5:C17) | D18: =SUM(D5:D17) | E18: =SUM(E5:E17) | F18: =IF(E18=0,0,D18/E18) | G18: =IF(F18>=1,"Verde",IF(F18>=0.7,"Ámbar","Rojo")) | H18: =SUM(H5:H17) | I18: =SUM(I5:I17)
A20: KPIs canal
A21: RSM ≥100% budget | B21: =COUNTIF(F5:F17,">=1")
A22: RSM <70% budget | B22: =COUNTIFS(F5:F17,"<0.7",A5:A17,"<>")
A23: Brecha vs budget (m²) | B23: =D18-E18
A24: Backlog total (m²) | B24: =H18+I18
A25: Book-to-bill (OI/Ventas) | B25: =IFERROR(C18/D18,"")

Sheet 10_RSM_Distribucion
A1: 10 · RSM Distribución – Cumplimiento y Backlog (YTD) [detalle interno – no se presenta en el deck]
A2: Diligencie la tabla izquierda; el ranking (derecha), totales y semáforos se calculan solos
A4: RSM (nombre completo) | B4: Nombre corto (slide) | C4: Order Intake m² | D4: Ventas Total m² | E4: Budget m² (paneles) | F4: % Cumpl. Budget | G4: Semáforo | H4: Backlog paneles m² | I4: Backlog otros m² | J4: Clave orden (aux) | L4: # | M4: Ranking – Fuente gráfico (mayor → menor cumplimiento) | N4: % Cumpl. | O4: Ventas m² | P4: Budget m²
A5: EJECUTIVO DE VENTAS SUR | B5: Ejec. Ventas Sur | C5: 4476 | D5: 10800 | E5: 5611 | F5: =IF(A5="","",IF(E5=0,0,D5/E5)) | G5: =IF(F5="","",IF(F5>=1,"Verde",IF(F5>=0.7,"Ámbar","Rojo"))) | H5: 0 | I5: 0 | J5: =IF(A5="","",F5+D5/1000000000+(100-ROW())/1000000000000) | L5: 1 | M5: =IF(L5>COUNT($J$5:$J$19),"",INDEX($B$5:$B$19,MATCH(LARGE($J$5:$J$19,L5),$J$5:$J$19,0))) | N5: =IF(M5="","",INDEX($F$5:$F$19,MATCH(LARGE($J$5:$J$19,L5),$J$5:$J$19,0))) | O5: =IF(M5="","",INDEX($D$5:$D$19,MATCH(LARGE($J$5:$J$19,L5),$J$5:$J$19,0))) | P5: =IF(M5="","",INDEX($E$5:$E$19,MATCH(LARGE($J$5:$J$19,L5),$J$5:$J$19,0)))
A6: EJECUTIVO DE VENTAS EJE CAFETERO | B6: Ejec. Eje Cafetero | C6: 7780 | D6: 11129 | E6: 5611 | F6: =IF(A6="","",IF(E6=0,0,D6/E6)) | G6: =IF(F6="","",IF(F6>=1,"Verde",IF(F6>=0.7,"Ámbar","Rojo"))) | H6: 0 | I6: 0 | J6: =IF(A6="","",F6+D6/1000000000+(100-ROW())/1000000000000) | L6: 2 | M6: =IF(L6>COUNT($J$5:$J$19),"",INDEX($B$5:$B$19,MATCH(LARGE($J$5:$J$19,L6),$J$5:$J$19,0))) | N6: =IF(M6="","",INDEX($F$5:$F$19,MATCH(LARGE($J$5:$J$19,L6),$J$5:$J$19,0))) | O6: =IF(M6="","",INDEX($D$5:$D$19,MATCH(LARGE($J$5:$J$19,L6),$J$5:$J$19,0))) | P6: =IF(M6="","",INDEX($E$5:$E$19,MATCH(LARGE($J$5:$J$19,L6),$J$5:$J$19,0)))
A7: CANDELA HERNANDEZ YOLANDA | B7: Yolanda Candela | C7: 38269 | D7: 39934 | E7: 22361 | F7: =IF(A7="","",IF(E7=0,0,D7/E7)) | G7: =IF(F7="","",IF(F7>=1,"Verde",IF(F7>=0.7,"Ámbar","Rojo"))) | H7: 7750 | I7: 0 | J7: =IF(A7="","",F7+D7/1000000000+(100-ROW())/1000000000000) | L7: 3 | M7: =IF(L7>COUNT($J$5:$J$19),"",INDEX($B$5:$B$19,MATCH(LARGE($J$5:$J$19,L7),$J$5:$J$19,0))) | N7: =IF(M7="","",INDEX($F$5:$F$19,MATCH(LARGE($J$5:$J$19,L7),$J$5:$J$19,0))) | O7: =IF(M7="","",INDEX($D$5:$D$19,MATCH(LARGE($J$5:$J$19,L7),$J$5:$J$19,0))) | P7: =IF(M7="","",INDEX($E$5:$E$19,MATCH(LARGE($J$5:$J$19,L7),$J$5:$J$19,0)))
A8: GARCIA RUIZ MONICA ALEXANDRA | B8: Mónica A. García | C8: 25763 | D8: 20362 | E8: 12000 | F8: =IF(A8="","",IF(E8=0,0,D8/E8)) | G8: =IF(F8="","",IF(F8>=1,"Verde",IF(F8>=0.7,"Ámbar","Rojo"))) | H8: 8016 | I8: 0 | J8: =IF(A8="","",F8+D8/1000000000+(100-ROW())/1000000000000) | L8: 4 | M8: =IF(L8>COUNT($J$5:$J$19),"",INDEX($B$5:$B$19,MATCH(LARGE($J$5:$J$19,L8),$J$5:$J$19,0))) | N8: =IF(M8="","",INDEX($F$5:$F$19,MATCH(LARGE($J$5:$J$19,L8),$J$5:$J$19,0))) | O8: =IF(M8="","",INDEX($D$5:$D$19,MATCH(LARGE($J$5:$J$19,L8),$J$5:$J$19,0))) | P8: =IF(M8="","",INDEX($E$5:$E$19,MATCH(LARGE($J$5:$J$19,L8),$J$5:$J$19,0)))
A9: PEREZ RESTREPO EIDY JOANA | B9: Eidy J. Pérez | C9: 76135 | D9: 80285 | E9: 70977 | F9: =IF(A9="","",IF(E9=0,0,D9/E9)) | G9: =IF(F9="","",IF(F9>=1,"Verde",IF(F9>=0.7,"Ámbar","Rojo"))) | H9: 14515 | I9: 1979 | J9: =IF(A9="","",F9+D9/1000000000+(100-ROW())/1000000000000) | L9: 5 | M9: =IF(L9>COUNT($J$5:$J$19),"",INDEX($B$5:$B$19,MATCH(LARGE($J$5:$J$19,L9),$J$5:$J$19,0))) | N9: =IF(M9="","",INDEX($F$5:$F$19,MATCH(LARGE($J$5:$J$19,L9),$J$5:$J$19,0))) | O9: =IF(M9="","",INDEX($D$5:$D$19,MATCH(LARGE($J$5:$J$19,L9),$J$5:$J$19,0))) | P9: =IF(M9="","",INDEX($E$5:$E$19,MATCH(LARGE($J$5:$J$19,L9),$J$5:$J$19,0)))
A10: SALAZAR LOPEZ EDWAR ANDRES | B10: Edwar A. Salazar | C10: 21078 | D10: 14678 | E10: 21500 | F10: =IF(A10="","",IF(E10=0,0,D10/E10)) | G10: =IF(F10="","",IF(F10>=1,"Verde",IF(F10>=0.7,"Ámbar","Rojo"))) | H10: 6400 | I10: 0 | J10: =IF(A10="","",F10+D10/1000000000+(100-ROW())/1000000000000) | L10: 6 | M10: =IF(L10>COUNT($J$5:$J$19),"",INDEX($B$5:$B$19,MATCH(LARGE($J$5:$J$19,L10),$J$5:$J$19,0))) | N10: =IF(M10="","",INDEX($F$5:$F$19,MATCH(LARGE($J$5:$J$19,L10),$J$5:$J$19,0))) | O10: =IF(M10="","",INDEX($D$5:$D$19,MATCH(LARGE($J$5:$J$19,L10),$J$5:$J$19,0))) | P10: =IF(M10="","",INDEX($E$5:$E$19,MATCH(LARGE($J$5:$J$19,L10),$J$5:$J$19,0)))
A11: ACOSTA HERNANDEZ HENRY ALEJANDRO | B11: Henry A. Acosta | C11: 14822 | D11: 6805 | E11: 11596 | F11: =IF(A11="","",IF(E11=0,0,D11/E11)) | G11: =IF(F11="","",IF(F11>=1,"Verde",IF(F11>=0.7,"Ámbar","Rojo"))) | H11: 8016 | I11: 0 | J11: =IF(A11="","",F11+D11/1000000000+(100-ROW())/1000000000000) | L11: 7 | M11: =IF(L11>COUNT($J$5:$J$19),"",INDEX($B$5:$B$19,MATCH(LARGE($J$5:$J$19,L11),$J$5:$J$19,0))) | N11: =IF(M11="","",INDEX($F$5:$F$19,MATCH(LARGE($J$5:$J$19,L11),$J$5:$J$19,0))) | O11: =IF(M11="","",INDEX($D$5:$D$19,MATCH(LARGE($J$5:$J$19,L11),$J$5:$J$19,0))) | P11: =IF(M11="","",INDEX($E$5:$E$19,MATCH(LARGE($J$5:$J$19,L11),$J$5:$J$19,0)))
A12: VALENZUELA TORRES RONALD | B12: Ronald Valenzuela | C12: 15745 | D12: 17303 | E12: 38653 | F12: =IF(A12="","",IF(E12=0,0,D12/E12)) | G12: =IF(F12="","",IF(F12>=1,"Verde",IF(F12>=0.7,"Ámbar","Rojo"))) | H12: 0 | I12: 0 | J12: =IF(A12="","",F12+D12/1000000000+(100-ROW())/1000000000000) | L12: 8 | M12: =IF(L12>COUNT($J$5:$J$19),"",INDEX($B$5:$B$19,MATCH(LARGE($J$5:$J$19,L12),$J$5:$J$19,0))) | N12: =IF(M12="","",INDEX($F$5:$F$19,MATCH(LARGE($J$5:$J$19,L12),$J$5:$J$19,0))) | O12: =IF(M12="","",INDEX($D$5:$D$19,MATCH(LARGE($J$5:$J$19,L12),$J$5:$J$19,0))) | P12: =IF(M12="","",INDEX($E$5:$E$19,MATCH(LARGE($J$5:$J$19,L12),$J$5:$J$19,0)))
A13: MENDEZ GONZALEZ RONALD ENRIQUE | B13: Ronald E. Méndez | C13: 13157 | D13: 19032 | E13: 45720 | F13: =IF(A13="","",IF(E13=0,0,D13/E13)) | G13: =IF(F13="","",IF(F13>=1,"Verde",IF(F13>=0.7,"Ámbar","Rojo"))) | H13: 0 | I13: 0 | J13: =IF(A13="","",F13+D13/1000000000+(100-ROW())/1000000000000) | L13: 9 | M13: =IF(L13>COUNT($J$5:$J$19),"",INDEX($B$5:$B$19,MATCH(LARGE($J$5:$J$19,L13),$J$5:$J$19,0))) | N13: =IF(M13="","",INDEX($F$5:$F$19,MATCH(LARGE($J$5:$J$19,L13),$J$5:$J$19,0))) | O13: =IF(M13="","",INDEX($D$5:$D$19,MATCH(LARGE($J$5:$J$19,L13),$J$5:$J$19,0))) | P13: =IF(M13="","",INDEX($E$5:$E$19,MATCH(LARGE($J$5:$J$19,L13),$J$5:$J$19,0)))
A14: RIOS NUÑEZ ERWIN ANTONIO | B14: Erwin A. Ríos | C14: 19126 | D14: 6688 | E14: 14495 | F14: =IF(A14="","",IF(E14=0,0,D14/E14)) | G14: =IF(F14="","",IF(F14>=1,"Verde",IF(F14>=0.7,"Ámbar","Rojo"))) | H14: 17840 | I14: 0 | J14: =IF(A14="","",F14+D14/1000000000+(100-ROW())/1000000000000) | L14: 10 | M14: =IF(L14>COUNT($J$5:$J$19),"",INDEX($B$5:$B$19,MATCH(LARGE($J$5:$J$19,L14),$J$5:$J$19,0))) | N14: =IF(M14="","",INDEX($F$5:$F$19,MATCH(LARGE($J$5:$J$19,L14),$J$5:$J$19,0))) | O14: =IF(M14="","",INDEX($D$5:$D$19,MATCH(LARGE($J$5:$J$19,L14),$J$5:$J$19,0))) | P14: =IF(M14="","",INDEX($E$5:$E$19,MATCH(LARGE($J$5:$J$19,L14),$J$5:$J$19,0)))
F15: =IF(A15="","",IF(E15=0,0,D15/E15)) | G15: =IF(F15="","",IF(F15>=1,"Verde",IF(F15>=0.7,"Ámbar","Rojo"))) | J15: =IF(A15="","",F15+D15/1000000000+(100-ROW())/1000000000000) | L15: 11 | M15: =IF(L15>COUNT($J$5:$J$19),"",INDEX($B$5:$B$19,MATCH(LARGE($J$5:$J$19,L15),$J$5:$J$19,0))) | N15: =IF(M15="","",INDEX($F$5:$F$19,MATCH(LARGE($J$5:$J$19,L15),$J$5:$J$19,0))) | O15: =IF(M15="","",INDEX($D$5:$D$19,MATCH(LARGE($J$5:$J$19,L15),$J$5:$J$19,0))) | P15: =IF(M15="","",INDEX($E$5:$E$19,MATCH(LARGE($J$5:$J$19,L15),$J$5:$J$19,0)))
F16: =IF(A16="","",IF(E16=0,0,D16/E16)) | G16: =IF(F16="","",IF(F16>=1,"Verde",IF(F16>=0.7,"Ámbar","Rojo"))) | J16: =IF(A16="","",F16+D16/1000000000+(100-ROW())/1000000000000) | L16: 12 | M16: =IF(L16>COUNT($J$5:$J$19),"",INDEX($B$5:$B$19,MATCH(LARGE($J$5:$J$19,L16),$J$5:$J$19,0))) | N16: =IF(M16="","",INDEX($F$5:$F$19,MATCH(LARGE($J$5:$J$19,L16),$J$5:$J$19,0))) | O16: =IF(M16="","",INDEX($D$5:$D$19,MATCH(LARGE($J$5:$J$19,L16),$J$5:$J$19,0))) | P16: =IF(M16="","",INDEX($E$5:$E$19,MATCH(LARGE($J$5:$J$19,L16),$J$5:$J$19,0)))
F17: =IF(A17="","",IF(E17=0,0,D17/E17)) | G17: =IF(F17="","",IF(F17>=1,"Verde",IF(F17>=0.7,"Ámbar","Rojo"))) | J17: =IF(A17="","",F17+D17/1000000000+(100-ROW())/1000000000000) | L17: 13 | M17: =IF(L17>COUNT($J$5:$J$19),"",INDEX($B$5:$B$19,MATCH(LARGE($J$5:$J$19,L17),$J$5:$J$19,0))) | N17: =IF(M17="","",INDEX($F$5:$F$19,MATCH(LARGE($J$5:$J$19,L17),$J$5:$J$19,0))) | O17: =IF(M17="","",INDEX($D$5:$D$19,MATCH(LARGE($J$5:$J$19,L17),$J$5:$J$19,0))) | P17: =IF(M17="","",INDEX($E$5:$E$19,MATCH(LARGE($J$5:$J$19,L17),$J$5:$J$19,0)))
F18: =IF(A18="","",IF(E18=0,0,D18/E18)) | G18: =IF(F18="","",IF(F18>=1,"Verde",IF(F18>=0.7,"Ámbar","Rojo"))) | J18: =IF(A18="","",F18+D18/1000000000+(100-ROW())/1000000000000) | L18: 14 | M18: =IF(L18>COUNT($J$5:$J$19),"",INDEX($B$5:$B$19,MATCH(LARGE($J$5:$J$19,L18),$J$5:$J$19,0))) | N18: =IF(M18="","",INDEX($F$5:$F$19,MATCH(LARGE($J$5:$J$19,L18),$J$5:$J$19,0))) | O18: =IF(M18="","",INDEX($D$5:$D$19,MATCH(LARGE($J$5:$J$19,L18),$J$5:$J$19,0))) | P18: =IF(M18="","",INDEX($E$5:$E$19,MATCH(LARGE($J$5:$J$19,L18),$J$5:$J$19,0)))
F19: =IF(A19="","",IF(E19=0,0,D19/E19)) | G19: =IF(F19="","",IF(F19>=1,"Verde",IF(F19>=0.7,"Ámbar","Rojo"))) | J19: =IF(A19="","",F19+D19/1000000000+(100-ROW())/1000000000000) | L19: 15 | M19: =IF(L19>COUNT($J$5:$J$19),"",INDEX($B$5:$B$19,MATCH(LARGE($J$5:$J$19,L19),$J$5:$J$19,0))) | N19: =IF(M19="","",INDEX($F$5:$F$19,MATCH(LARGE($J$5:$J$19,L19),$J$5:$J$19,0))) | O19: =IF(M19="","",INDEX($D$5:$D$19,MATCH(LARGE($J$5:$J$19,L19),$J$5:$J$19,0))) | P19: =IF(M19="","",INDEX($E$5:$E$19,MATCH(LARGE($J$5:$J$19,L19),$J$5:$J$19,0)))
A20: TOTAL CANAL | B20: =COUNTA(A5:A19)&" RSM" | C20: =SUM(C5:C19) | D20: =SUM(D5:D19) | E20: =SUM(E5:E19) | F20: =IF(E20=0,0,D20/E20) | G20: =IF(F20>=1,"Verde",IF(F20>=0.7,"Ámbar","Rojo")) | H20: =SUM(H5:H19) | I20: =SUM(I5:I19)
A22: KPIs canal
A23: RSM ≥100% budget | B23: =COUNTIF(F5:F19,">=1")
A24: RSM <70% budget | B24: =COUNTIFS(F5:F19,"<0.7",A5:A19,"<>")
A25: Brecha vs budget (m²) | B25: =D20-E20
A26: Backlog total (m²) | B26: =H20+I20
A27: Book-to-bill (OI/Ventas) | B27: =IFERROR(C20/D20,"")

Sheet 11_RSM_Otras_Geo
A1: 11 · RSM Otras Geografías (Exportación) – Cumplimiento y Backlog (YTD) [detalle interno – no se presenta en el deck]
A2: Diligencie la tabla izquierda; el ranking (derecha), totales y semáforos se calculan solos
A4: RSM (nombre completo) | B4: Nombre corto (slide) | C4: Order Intake m² | D4: Ventas Total m² | E4: Budget m² (paneles) | F4: % Cumpl. Budget | G4: Semáforo | H4: Backlog paneles m² | I4: Backlog otros m² | J4: Clave orden (aux) | L4: # | M4: Ranking – Fuente gráfico (mayor → menor cumplimiento) | N4: % Cumpl. | O4: Ventas m² | P4: Budget m²
A5: KAM ACOUNT MANAGER ECUADOR | B5: KAM 2 - Ecuador | C5: 0 | D5: 7006 | E5: 59844 | F5: =IF(A5="","",IF(E5=0,0,D5/E5)) | G5: =IF(F5="","",IF(F5>=1,"Verde",IF(F5>=0.7,"Ámbar","Rojo"))) | H5: 0 | I5: 0 | J5: =IF(A5="","",F5+D5/1000000000+(100-ROW())/1000000000000) | L5: 1 | M5: =IF(L5>COUNT($J$5:$J$19),"",INDEX($B$5:$B$19,MATCH(LARGE($J$5:$J$19,L5),$J$5:$J$19,0))) | N5: =IF(M5="","",INDEX($F$5:$F$19,MATCH(LARGE($J$5:$J$19,L5),$J$5:$J$19,0))) | O5: =IF(M5="","",INDEX($D$5:$D$19,MATCH(LARGE($J$5:$J$19,L5),$J$5:$J$19,0))) | P5: =IF(M5="","",INDEX($E$5:$E$19,MATCH(LARGE($J$5:$J$19,L5),$J$5:$J$19,0)))
A6: TORRES AREVALO LAURA MARCELA | B6: Laura M. Torres | C6: 127061 | D6: 91114 | E6: 65564 | F6: =IF(A6="","",IF(E6=0,0,D6/E6)) | G6: =IF(F6="","",IF(F6>=1,"Verde",IF(F6>=0.7,"Ámbar","Rojo"))) | H6: 40920 | I6: 0 | J6: =IF(A6="","",F6+D6/1000000000+(100-ROW())/1000000000000) | L6: 2 | M6: =IF(L6>COUNT($J$5:$J$19),"",INDEX($B$5:$B$19,MATCH(LARGE($J$5:$J$19,L6),$J$5:$J$19,0))) | N6: =IF(M6="","",INDEX($F$5:$F$19,MATCH(LARGE($J$5:$J$19,L6),$J$5:$J$19,0))) | O6: =IF(M6="","",INDEX($D$5:$D$19,MATCH(LARGE($J$5:$J$19,L6),$J$5:$J$19,0))) | P6: =IF(M6="","",INDEX($E$5:$E$19,MATCH(LARGE($J$5:$J$19,L6),$J$5:$J$19,0)))
A7: CALDERON DURAN MARIA YELITZA | B7: María Y. Calderón | C7: 46249 | D7: 26427 | E7: 19434 | F7: =IF(A7="","",IF(E7=0,0,D7/E7)) | G7: =IF(F7="","",IF(F7>=1,"Verde",IF(F7>=0.7,"Ámbar","Rojo"))) | H7: 21052 | I7: 247 | J7: =IF(A7="","",F7+D7/1000000000+(100-ROW())/1000000000000) | L7: 3 | M7: =IF(L7>COUNT($J$5:$J$19),"",INDEX($B$5:$B$19,MATCH(LARGE($J$5:$J$19,L7),$J$5:$J$19,0))) | N7: =IF(M7="","",INDEX($F$5:$F$19,MATCH(LARGE($J$5:$J$19,L7),$J$5:$J$19,0))) | O7: =IF(M7="","",INDEX($D$5:$D$19,MATCH(LARGE($J$5:$J$19,L7),$J$5:$J$19,0))) | P7: =IF(M7="","",INDEX($E$5:$E$19,MATCH(LARGE($J$5:$J$19,L7),$J$5:$J$19,0)))
A8: HINOSTROZA GAMBOA ERICK | B8: Erick Hinostroza | C8: 22789 | D8: 23798 | E8: 23613 | F8: =IF(A8="","",IF(E8=0,0,D8/E8)) | G8: =IF(F8="","",IF(F8>=1,"Verde",IF(F8>=0.7,"Ámbar","Rojo"))) | H8: 1061 | I8: 0 | J8: =IF(A8="","",F8+D8/1000000000+(100-ROW())/1000000000000) | L8: 4 | M8: =IF(L8>COUNT($J$5:$J$19),"",INDEX($B$5:$B$19,MATCH(LARGE($J$5:$J$19,L8),$J$5:$J$19,0))) | N8: =IF(M8="","",INDEX($F$5:$F$19,MATCH(LARGE($J$5:$J$19,L8),$J$5:$J$19,0))) | O8: =IF(M8="","",INDEX($D$5:$D$19,MATCH(LARGE($J$5:$J$19,L8),$J$5:$J$19,0))) | P8: =IF(M8="","",INDEX($E$5:$E$19,MATCH(LARGE($J$5:$J$19,L8),$J$5:$J$19,0)))
A9: RODRIGUEZ GONZALEZ CARLOS ALFREDO | B9: Carlos A. Rodríguez | C9: 119514 | D9: 112953 | E9: 111329 | F9: =IF(A9="","",IF(E9=0,0,D9/E9)) | G9: =IF(F9="","",IF(F9>=1,"Verde",IF(F9>=0.7,"Ámbar","Rojo"))) | H9: 54879 | I9: 0 | J9: =IF(A9="","",F9+D9/1000000000+(100-ROW())/1000000000000) | L9: 5 | M9: =IF(L9>COUNT($J$5:$J$19),"",INDEX($B$5:$B$19,MATCH(LARGE($J$5:$J$19,L9),$J$5:$J$19,0))) | N9: =IF(M9="","",INDEX($F$5:$F$19,MATCH(LARGE($J$5:$J$19,L9),$J$5:$J$19,0))) | O9: =IF(M9="","",INDEX($D$5:$D$19,MATCH(LARGE($J$5:$J$19,L9),$J$5:$J$19,0))) | P9: =IF(M9="","",INDEX($E$5:$E$19,MATCH(LARGE($J$5:$J$19,L9),$J$5:$J$19,0)))
A10: KAM ACOUNT MANAGER COSTA RICA | B10: KAM - Costa Rica | C10: 6245 | D10: 7471 | E10: 46495 | F10: =IF(A10="","",IF(E10=0,0,D10/E10)) | G10: =IF(F10="","",IF(F10>=1,"Verde",IF(F10>=0.7,"Ámbar","Rojo"))) | H10: 0 | I10: 0 | J10: =IF(A10="","",F10+D10/1000000000+(100-ROW())/1000000000000) | L10: 6 | M10: =IF(L10>COUNT($J$5:$J$19),"",INDEX($B$5:$B$19,MATCH(LARGE($J$5:$J$19,L10),$J$5:$J$19,0))) | N10: =IF(M10="","",INDEX($F$5:$F$19,MATCH(LARGE($J$5:$J$19,L10),$J$5:$J$19,0))) | O10: =IF(M10="","",INDEX($D$5:$D$19,MATCH(LARGE($J$5:$J$19,L10),$J$5:$J$19,0))) | P10: =IF(M10="","",INDEX($E$5:$E$19,MATCH(LARGE($J$5:$J$19,L10),$J$5:$J$19,0)))
A11: NAVAS ESCOBAR MAYRA ALEJANDRA | B11: Mayra A. Navas | C11: =45379 | D11: =37307 | E11: =59834 | F11: =IF(A11="","",IF(E11=0,0,D11/E11)) | G11: =IF(F11="","",IF(F11>=1,"Verde",IF(F11>=0.7,"Ámbar","Rojo"))) | H11: 18220 | I11: 333 | J11: =IF(A11="","",F11+D11/1000000000+(100-ROW())/1000000000000) | L11: 7 | M11: =IF(L11>COUNT($J$5:$J$19),"",INDEX($B$5:$B$19,MATCH(LARGE($J$5:$J$19,L11),$J$5:$J$19,0))) | N11: =IF(M11="","",INDEX($F$5:$F$19,MATCH(LARGE($J$5:$J$19,L11),$J$5:$J$19,0))) | O11: =IF(M11="","",INDEX($D$5:$D$19,MATCH(LARGE($J$5:$J$19,L11),$J$5:$J$19,0))) | P11: =IF(M11="","",INDEX($E$5:$E$19,MATCH(LARGE($J$5:$J$19,L11),$J$5:$J$19,0)))
A12: FERNANDINI MOLINA ANGIE PAOLA | B12: Angie P. Fernandini | C12: 0 | D12: 0 | E12: 2000 | F12: =IF(A12="","",IF(E12=0,0,D12/E12)) | G12: =IF(F12="","",IF(F12>=1,"Verde",IF(F12>=0.7,"Ámbar","Rojo"))) | H12: 0 | I12: 0 | J12: =IF(A12="","",F12+D12/1000000000+(100-ROW())/1000000000000) | L12: 8 | M12: =IF(L12>COUNT($J$5:$J$19),"",INDEX($B$5:$B$19,MATCH(LARGE($J$5:$J$19,L12),$J$5:$J$19,0))) | N12: =IF(M12="","",INDEX($F$5:$F$19,MATCH(LARGE($J$5:$J$19,L12),$J$5:$J$19,0))) | O12: =IF(M12="","",INDEX($D$5:$D$19,MATCH(LARGE($J$5:$J$19,L12),$J$5:$J$19,0))) | P12: =IF(M12="","",INDEX($E$5:$E$19,MATCH(LARGE($J$5:$J$19,L12),$J$5:$J$19,0)))
F13: =IF(A13="","",IF(E13=0,0,D13/E13)) | G13: =IF(F13="","",IF(F13>=1,"Verde",IF(F13>=0.7,"Ámbar","Rojo"))) | J13: =IF(A13="","",F13+D13/1000000000+(100-ROW())/1000000000000) | L13: 9 | M13: =IF(L13>COUNT($J$5:$J$19),"",INDEX($B$5:$B$19,MATCH(LARGE($J$5:$J$19,L13),$J$5:$J$19,0))) | N13: =IF(M13="","",INDEX($F$5:$F$19,MATCH(LARGE($J$5:$J$19,L13),$J$5:$J$19,0))) | O13: =IF(M13="","",INDEX($D$5:$D$19,MATCH(LARGE($J$5:$J$19,L13),$J$5:$J$19,0))) | P13: =IF(M13="","",INDEX($E$5:$E$19,MATCH(LARGE($J$5:$J$19,L13),$J$5:$J$19,0)))
F14: =IF(A14="","",IF(E14=0,0,D14/E14)) | G14: =IF(F14="","",IF(F14>=1,"Verde",IF(F14>=0.7,"Ámbar","Rojo"))) | J14: =IF(A14="","",F14+D14/1000000000+(100-ROW())/1000000000000) | L14: 10 | M14: =IF(L14>COUNT($J$5:$J$19),"",INDEX($B$5:$B$19,MATCH(LARGE($J$5:$J$19,L14),$J$5:$J$19,0))) | N14: =IF(M14="","",INDEX($F$5:$F$19,MATCH(LARGE($J$5:$J$19,L14),$J$5:$J$19,0))) | O14: =IF(M14="","",INDEX($D$5:$D$19,MATCH(LARGE($J$5:$J$19,L14),$J$5:$J$19,0))) | P14: =IF(M14="","",INDEX($E$5:$E$19,MATCH(LARGE($J$5:$J$19,L14),$J$5:$J$19,0)))
F15: =IF(A15="","",IF(E15=0,0,D15/E15)) | G15: =IF(F15="","",IF(F15>=1,"Verde",IF(F15>=0.7,"Ámbar","Rojo"))) | J15: =IF(A15="","",F15+D15/1000000000+(100-ROW())/1000000000000) | L15: 11 | M15: =IF(L15>COUNT($J$5:$J$19),"",INDEX($B$5:$B$19,MATCH(LARGE($J$5:$J$19,L15),$J$5:$J$19,0))) | N15: =IF(M15="","",INDEX($F$5:$F$19,MATCH(LARGE($J$5:$J$19,L15),$J$5:$J$19,0))) | O15: =IF(M15="","",INDEX($D$5:$D$19,MATCH(LARGE($J$5:$J$19,L15),$J$5:$J$19,0))) | P15: =IF(M15="","",INDEX($E$5:$E$19,MATCH(LARGE($J$5:$J$19,L15),$J$5:$J$19,0)))
F16: =IF(A16="","",IF(E16=0,0,D16/E16)) | G16: =IF(F16="","",IF(F16>=1,"Verde",IF(F16>=0.7,"Ámbar","Rojo"))) | J16: =IF(A16="","",F16+D16/1000000000+(100-ROW())/1000000000000) | L16: 12 | M16: =IF(L16>COUNT($J$5:$J$19),"",INDEX($B$5:$B$19,MATCH(LARGE($J$5:$J$19,L16),$J$5:$J$19,0))) | N16: =IF(M16="","",INDEX($F$5:$F$19,MATCH(LARGE($J$5:$J$19,L16),$J$5:$J$19,0))) | O16: =IF(M16="","",INDEX($D$5:$D$19,MATCH(LARGE($J$5:$J$19,L16),$J$5:$J$19,0))) | P16: =IF(M16="","",INDEX($E$5:$E$19,MATCH(LARGE($J$5:$J$19,L16),$J$5:$J$19,0)))
F17: =IF(A17="","",IF(E17=0,0,D17/E17)) | G17: =IF(F17="","",IF(F17>=1,"Verde",IF(F17>=0.7,"Ámbar","Rojo"))) | J17: =IF(A17="","",F17+D17/1000000000+(100-ROW())/1000000000000) | L17: 13 | M17: =IF(L17>COUNT($J$5:$J$19),"",INDEX($B$5:$B$19,MATCH(LARGE($J$5:$J$19,L17),$J$5:$J$19,0))) | N17: =IF(M17="","",INDEX($F$5:$F$19,MATCH(LARGE($J$5:$J$19,L17),$J$5:$J$19,0))) | O17: =IF(M17="","",INDEX($D$5:$D$19,MATCH(LARGE($J$5:$J$19,L17),$J$5:$J$19,0))) | P17: =IF(M17="","",INDEX($E$5:$E$19,MATCH(LARGE($J$5:$J$19,L17),$J$5:$J$19,0)))
F18: =IF(A18="","",IF(E18=0,0,D18/E18)) | G18: =IF(F18="","",IF(F18>=1,"Verde",IF(F18>=0.7,"Ámbar","Rojo"))) | J18: =IF(A18="","",F18+D18/1000000000+(100-ROW())/1000000000000) | L18: 14 | M18: =IF(L18>COUNT($J$5:$J$19),"",INDEX($B$5:$B$19,MATCH(LARGE($J$5:$J$19,L18),$J$5:$J$19,0))) | N18: =IF(M18="","",INDEX($F$5:$F$19,MATCH(LARGE($J$5:$J$19,L18),$J$5:$J$19,0))) | O18: =IF(M18="","",INDEX($D$5:$D$19,MATCH(LARGE($J$5:$J$19,L18),$J$5:$J$19,0))) | P18: =IF(M18="","",INDEX($E$5:$E$19,MATCH(LARGE($J$5:$J$19,L18),$J$5:$J$19,0)))
F19: =IF(A19="","",IF(E19=0,0,D19/E19)) | G19: =IF(F19="","",IF(F19>=1,"Verde",IF(F19>=0.7,"Ámbar","Rojo"))) | J19: =IF(A19="","",F19+D19/1000000000+(100-ROW())/1000000000000) | L19: 15 | M19: =IF(L19>COUNT($J$5:$J$19),"",INDEX($B$5:$B$19,MATCH(LARGE($J$5:$J$19,L19),$J$5:$J$19,0))) | N19: =IF(M19="","",INDEX($F$5:$F$19,MATCH(LARGE($J$5:$J$19,L19),$J$5:$J$19,0))) | O19: =IF(M19="","",INDEX($D$5:$D$19,MATCH(LARGE($J$5:$J$19,L19),$J$5:$J$19,0))) | P19: =IF(M19="","",INDEX($E$5:$E$19,MATCH(LARGE($J$5:$J$19,L19),$J$5:$J$19,0)))
A20: TOTAL CANAL | B20: =COUNTA(A5:A19)&" RSM" | C20: =SUM(C5:C19) | D20: =SUM(D5:D19) | E20: =SUM(E5:E19) | F20: =IF(E20=0,0,D20/E20) | G20: =IF(F20>=1,"Verde",IF(F20>=0.7,"Ámbar","Rojo")) | H20: =SUM(H5:H19) | I20: =SUM(I5:I19)
A22: KPIs canal
A23: RSM ≥100% budget | B23: =COUNTIF(F5:F19,">=1")
A24: RSM <70% budget | B24: =COUNTIFS(F5:F19,"<0.7",A5:A19,"<>")
A25: Brecha vs budget (m²) | B25: =D20-E20
A26: Backlog total (m²) | B26: =H20+I20
A27: Book-to-bill (OI/Ventas) | B27: =IFERROR(C20/D20,"")

Sheet 12_RSM_Cold_Storage
A1: 12 · RSM Refrigeración (Cold Storage) – Cumplimiento y Backlog (YTD) [detalle interno – no se presenta en el deck]
A2: Diligencie la tabla izquierda; el ranking (derecha), totales y semáforos se calculan solos
A4: RSM (nombre completo) | B4: Nombre corto (slide) | C4: Order Intake m² | D4: Ventas Total m² | E4: Budget m² (paneles) | F4: % Cumpl. Budget | G4: Semáforo | H4: Backlog paneles m² | I4: Backlog otros m² | J4: Clave orden (aux) | L4: # | M4: Ranking – Fuente gráfico (mayor → menor cumplimiento) | N4: % Cumpl. | O4: Ventas m² | P4: Budget m²
A5: RODRIGUEZ HENAO LAURA MARCELA | B5: Laura M. Rodríguez | C5: 20966 | D5: 5303 | E5: 4500 | F5: =IF(A5="","",IF(E5=0,0,D5/E5)) | G5: =IF(F5="","",IF(F5>=1,"Verde",IF(F5>=0.7,"Ámbar","Rojo"))) | H5: 15042 | I5: 468 | J5: =IF(A5="","",F5+D5/1000000000+(100-ROW())/1000000000000) | L5: 1 | M5: =IF(L5>COUNT($J$5:$J$19),"",INDEX($B$5:$B$19,MATCH(LARGE($J$5:$J$19,L5),$J$5:$J$19,0))) | N5: =IF(M5="","",INDEX($F$5:$F$19,MATCH(LARGE($J$5:$J$19,L5),$J$5:$J$19,0))) | O5: =IF(M5="","",INDEX($D$5:$D$19,MATCH(LARGE($J$5:$J$19,L5),$J$5:$J$19,0))) | P5: =IF(M5="","",INDEX($E$5:$E$19,MATCH(LARGE($J$5:$J$19,L5),$J$5:$J$19,0)))
A6: MENENDEZ ICABALCETA JUAN CARLOS | B6: Juan C. Menéndez | C6: 0 | D6: 0 | E6: 3000 | F6: =IF(A6="","",IF(E6=0,0,D6/E6)) | G6: =IF(F6="","",IF(F6>=1,"Verde",IF(F6>=0.7,"Ámbar","Rojo"))) | H6: 0 | I6: 0 | J6: =IF(A6="","",F6+D6/1000000000+(100-ROW())/1000000000000) | L6: 2 | M6: =IF(L6>COUNT($J$5:$J$19),"",INDEX($B$5:$B$19,MATCH(LARGE($J$5:$J$19,L6),$J$5:$J$19,0))) | N6: =IF(M6="","",INDEX($F$5:$F$19,MATCH(LARGE($J$5:$J$19,L6),$J$5:$J$19,0))) | O6: =IF(M6="","",INDEX($D$5:$D$19,MATCH(LARGE($J$5:$J$19,L6),$J$5:$J$19,0))) | P6: =IF(M6="","",INDEX($E$5:$E$19,MATCH(LARGE($J$5:$J$19,L6),$J$5:$J$19,0)))
A7: URIBE JIMENEZ SANDRA MILENA | B7: Sandra M. Uribe | C7: 15459 | D7: 3888 | E7: 2500 | F7: =IF(A7="","",IF(E7=0,0,D7/E7)) | G7: =IF(F7="","",IF(F7>=1,"Verde",IF(F7>=0.7,"Ámbar","Rojo"))) | H7: 12191 | I7: 2734 | J7: =IF(A7="","",F7+D7/1000000000+(100-ROW())/1000000000000) | L7: 3 | M7: =IF(L7>COUNT($J$5:$J$19),"",INDEX($B$5:$B$19,MATCH(LARGE($J$5:$J$19,L7),$J$5:$J$19,0))) | N7: =IF(M7="","",INDEX($F$5:$F$19,MATCH(LARGE($J$5:$J$19,L7),$J$5:$J$19,0))) | O7: =IF(M7="","",INDEX($D$5:$D$19,MATCH(LARGE($J$5:$J$19,L7),$J$5:$J$19,0))) | P7: =IF(M7="","",INDEX($E$5:$E$19,MATCH(LARGE($J$5:$J$19,L7),$J$5:$J$19,0)))
F8: =IF(A8="","",IF(E8=0,0,D8/E8)) | G8: =IF(F8="","",IF(F8>=1,"Verde",IF(F8>=0.7,"Ámbar","Rojo"))) | J8: =IF(A8="","",F8+D8/1000000000+(100-ROW())/1000000000000) | L8: 4 | M8: =IF(L8>COUNT($J$5:$J$19),"",INDEX($B$5:$B$19,MATCH(LARGE($J$5:$J$19,L8),$J$5:$J$19,0))) | N8: =IF(M8="","",INDEX($F$5:$F$19,MATCH(LARGE($J$5:$J$19,L8),$J$5:$J$19,0))) | O8: =IF(M8="","",INDEX($D$5:$D$19,MATCH(LARGE($J$5:$J$19,L8),$J$5:$J$19,0))) | P8: =IF(M8="","",INDEX($E$5:$E$19,MATCH(LARGE($J$5:$J$19,L8),$J$5:$J$19,0)))
F9: =IF(A9="","",IF(E9=0,0,D9/E9)) | G9: =IF(F9="","",IF(F9>=1,"Verde",IF(F9>=0.7,"Ámbar","Rojo"))) | J9: =IF(A9="","",F9+D9/1000000000+(100-ROW())/1000000000000) | L9: 5 | M9: =IF(L9>COUNT($J$5:$J$19),"",INDEX($B$5:$B$19,MATCH(LARGE($J$5:$J$19,L9),$J$5:$J$19,0))) | N9: =IF(M9="","",INDEX($F$5:$F$19,MATCH(LARGE($J$5:$J$19,L9),$J$5:$J$19,0))) | O9: =IF(M9="","",INDEX($D$5:$D$19,MATCH(LARGE($J$5:$J$19,L9),$J$5:$J$19,0))) | P9: =IF(M9="","",INDEX($E$5:$E$19,MATCH(LARGE($J$5:$J$19,L9),$J$5:$J$19,0)))
F10: =IF(A10="","",IF(E10=0,0,D10/E10)) | G10: =IF(F10="","",IF(F10>=1,"Verde",IF(F10>=0.7,"Ámbar","Rojo"))) | J10: =IF(A10="","",F10+D10/1000000000+(100-ROW())/1000000000000) | L10: 6 | M10: =IF(L10>COUNT($J$5:$J$19),"",INDEX($B$5:$B$19,MATCH(LARGE($J$5:$J$19,L10),$J$5:$J$19,0))) | N10: =IF(M10="","",INDEX($F$5:$F$19,MATCH(LARGE($J$5:$J$19,L10),$J$5:$J$19,0))) | O10: =IF(M10="","",INDEX($D$5:$D$19,MATCH(LARGE($J$5:$J$19,L10),$J$5:$J$19,0))) | P10: =IF(M10="","",INDEX($E$5:$E$19,MATCH(LARGE($J$5:$J$19,L10),$J$5:$J$19,0)))
F11: =IF(A11="","",IF(E11=0,0,D11/E11)) | G11: =IF(F11="","",IF(F11>=1,"Verde",IF(F11>=0.7,"Ámbar","Rojo"))) | J11: =IF(A11="","",F11+D11/1000000000+(100-ROW())/1000000000000) | L11: 7 | M11: =IF(L11>COUNT($J$5:$J$19),"",INDEX($B$5:$B$19,MATCH(LARGE($J$5:$J$19,L11),$J$5:$J$19,0))) | N11: =IF(M11="","",INDEX($F$5:$F$19,MATCH(LARGE($J$5:$J$19,L11),$J$5:$J$19,0))) | O11: =IF(M11="","",INDEX($D$5:$D$19,MATCH(LARGE($J$5:$J$19,L11),$J$5:$J$19,0))) | P11: =IF(M11="","",INDEX($E$5:$E$19,MATCH(LARGE($J$5:$J$19,L11),$J$5:$J$19,0)))
F12: =IF(A12="","",IF(E12=0,0,D12/E12)) | G12: =IF(F12="","",IF(F12>=1,"Verde",IF(F12>=0.7,"Ámbar","Rojo"))) | J12: =IF(A12="","",F12+D12/1000000000+(100-ROW())/1000000000000) | L12: 8 | M12: =IF(L12>COUNT($J$5:$J$19),"",INDEX($B$5:$B$19,MATCH(LARGE($J$5:$J$19,L12),$J$5:$J$19,0))) | N12: =IF(M12="","",INDEX($F$5:$F$19,MATCH(LARGE($J$5:$J$19,L12),$J$5:$J$19,0))) | O12: =IF(M12="","",INDEX($D$5:$D$19,MATCH(LARGE($J$5:$J$19,L12),$J$5:$J$19,0))) | P12: =IF(M12="","",INDEX($E$5:$E$19,MATCH(LARGE($J$5:$J$19,L12),$J$5:$J$19,0)))
F13: =IF(A13="","",IF(E13=0,0,D13/E13)) | G13: =IF(F13="","",IF(F13>=1,"Verde",IF(F13>=0.7,"Ámbar","Rojo"))) | J13: =IF(A13="","",F13+D13/1000000000+(100-ROW())/1000000000000) | L13: 9 | M13: =IF(L13>COUNT($J$5:$J$19),"",INDEX($B$5:$B$19,MATCH(LARGE($J$5:$J$19,L13),$J$5:$J$19,0))) | N13: =IF(M13="","",INDEX($F$5:$F$19,MATCH(LARGE($J$5:$J$19,L13),$J$5:$J$19,0))) | O13: =IF(M13="","",INDEX($D$5:$D$19,MATCH(LARGE($J$5:$J$19,L13),$J$5:$J$19,0))) | P13: =IF(M13="","",INDEX($E$5:$E$19,MATCH(LARGE($J$5:$J$19,L13),$J$5:$J$19,0)))
F14: =IF(A14="","",IF(E14=0,0,D14/E14)) | G14: =IF(F14="","",IF(F14>=1,"Verde",IF(F14>=0.7,"Ámbar","Rojo"))) | J14: =IF(A14="","",F14+D14/1000000000+(100-ROW())/1000000000000) | L14: 10 | M14: =IF(L14>COUNT($J$5:$J$19),"",INDEX($B$5:$B$19,MATCH(LARGE($J$5:$J$19,L14),$J$5:$J$19,0))) | N14: =IF(M14="","",INDEX($F$5:$F$19,MATCH(LARGE($J$5:$J$19,L14),$J$5:$J$19,0))) | O14: =IF(M14="","",INDEX($D$5:$D$19,MATCH(LARGE($J$5:$J$19,L14),$J$5:$J$19,0))) | P14: =IF(M14="","",INDEX($E$5:$E$19,MATCH(LARGE($J$5:$J$19,L14),$J$5:$J$19,0)))
F15: =IF(A15="","",IF(E15=0,0,D15/E15)) | G15: =IF(F15="","",IF(F15>=1,"Verde",IF(F15>=0.7,"Ámbar","Rojo"))) | J15: =IF(A15="","",F15+D15/1000000000+(100-ROW())/1000000000000) | L15: 11 | M15: =IF(L15>COUNT($J$5:$J$19),"",INDEX($B$5:$B$19,MATCH(LARGE($J$5:$J$19,L15),$J$5:$J$19,0))) | N15: =IF(M15="","",INDEX($F$5:$F$19,MATCH(LARGE($J$5:$J$19,L15),$J$5:$J$19,0))) | O15: =IF(M15="","",INDEX($D$5:$D$19,MATCH(LARGE($J$5:$J$19,L15),$J$5:$J$19,0))) | P15: =IF(M15="","",INDEX($E$5:$E$19,MATCH(LARGE($J$5:$J$19,L15),$J$5:$J$19,0)))
F16: =IF(A16="","",IF(E16=0,0,D16/E16)) | G16: =IF(F16="","",IF(F16>=1,"Verde",IF(F16>=0.7,"Ámbar","Rojo"))) | J16: =IF(A16="","",F16+D16/1000000000+(100-ROW())/1000000000000) | L16: 12 | M16: =IF(L16>COUNT($J$5:$J$19),"",INDEX($B$5:$B$19,MATCH(LARGE($J$5:$J$19,L16),$J$5:$J$19,0))) | N16: =IF(M16="","",INDEX($F$5:$F$19,MATCH(LARGE($J$5:$J$19,L16),$J$5:$J$19,0))) | O16: =IF(M16="","",INDEX($D$5:$D$19,MATCH(LARGE($J$5:$J$19,L16),$J$5:$J$19,0))) | P16: =IF(M16="","",INDEX($E$5:$E$19,MATCH(LARGE($J$5:$J$19,L16),$J$5:$J$19,0)))
F17: =IF(A17="","",IF(E17=0,0,D17/E17)) | G17: =IF(F17="","",IF(F17>=1,"Verde",IF(F17>=0.7,"Ámbar","Rojo"))) | J17: =IF(A17="","",F17+D17/1000000000+(100-ROW())/1000000000000) | L17: 13 | M17: =IF(L17>COUNT($J$5:$J$19),"",INDEX($B$5:$B$19,MATCH(LARGE($J$5:$J$19,L17),$J$5:$J$19,0))) | N17: =IF(M17="","",INDEX($F$5:$F$19,MATCH(LARGE($J$5:$J$19,L17),$J$5:$J$19,0))) | O17: =IF(M17="","",INDEX($D$5:$D$19,MATCH(LARGE($J$5:$J$19,L17),$J$5:$J$19,0))) | P17: =IF(M17="","",INDEX($E$5:$E$19,MATCH(LARGE($J$5:$J$19,L17),$J$5:$J$19,0)))
F18: =IF(A18="","",IF(E18=0,0,D18/E18)) | G18: =IF(F18="","",IF(F18>=1,"Verde",IF(F18>=0.7,"Ámbar","Rojo"))) | J18: =IF(A18="","",F18+D18/1000000000+(100-ROW())/1000000000000) | L18: 14 | M18: =IF(L18>COUNT($J$5:$J$19),"",INDEX($B$5:$B$19,MATCH(LARGE($J$5:$J$19,L18),$J$5:$J$19,0))) | N18: =IF(M18="","",INDEX($F$5:$F$19,MATCH(LARGE($J$5:$J$19,L18),$J$5:$J$19,0))) | O18: =IF(M18="","",INDEX($D$5:$D$19,MATCH(LARGE($J$5:$J$19,L18),$J$5:$J$19,0))) | P18: =IF(M18="","",INDEX($E$5:$E$19,MATCH(LARGE($J$5:$J$19,L18),$J$5:$J$19,0)))
F19: =IF(A19="","",IF(E19=0,0,D19/E19)) | G19: =IF(F19="","",IF(F19>=1,"Verde",IF(F19>=0.7,"Ámbar","Rojo"))) | J19: =IF(A19="","",F19+D19/1000000000+(100-ROW())/1000000000000) | L19: 15 | M19: =IF(L19>COUNT($J$5:$J$19),"",INDEX($B$5:$B$19,MATCH(LARGE($J$5:$J$19,L19),$J$5:$J$19,0))) | N19: =IF(M19="","",INDEX($F$5:$F$19,MATCH(LARGE($J$5:$J$19,L19),$J$5:$J$19,0))) | O19: =IF(M19="","",INDEX($D$5:$D$19,MATCH(LARGE($J$5:$J$19,L19),$J$5:$J$19,0))) | P19: =IF(M19="","",INDEX($E$5:$E$19,MATCH(LARGE($J$5:$J$19,L19),$J$5:$J$19,0)))
A20: TOTAL CANAL | B20: =COUNTA(A5:A19)&" RSM" | C20: =SUM(C5:C19) | D20: =SUM(D5:D19) | E20: =SUM(E5:E19) | F20: =IF(E20=0,0,D20/E20) | G20: =IF(F20>=1,"Verde",IF(F20>=0.7,"Ámbar","Rojo")) | H20: =SUM(H5:H19) | I20: =SUM(I5:I19)
A22: KPIs canal
A23: RSM ≥100% budget | B23: =COUNTIF(F5:F19,">=1")
A24: RSM <70% budget | B24: =COUNTIFS(F5:F19,"<0.7",A5:A19,"<>")
A25: Brecha vs budget (m²) | B25: =D20-E20
A26: Backlog total (m²) | B26: =H20+I20
A27: Book-to-bill (OI/Ventas) | B27: =IFERROR(C20/D20,"")

Sheet 13_RSM_Site_Cali
A1: 13 · RSM Site Cali – Cumplimiento y Backlog (YTD) [detalle interno – no se presenta en el deck]
A2: Diligencie la tabla izquierda; el ranking (derecha), totales y semáforos se calculan solos
A4: RSM (nombre completo) | B4: Nombre corto (slide) | C4: Order Intake m² | D4: Ventas Total m² | E4: Budget m² (paneles) | F4: % Cumpl. Budget | G4: Semáforo | H4: Backlog paneles m² | I4: Backlog otros m² | J4: Clave orden (aux) | L4: # | M4: Ranking – Fuente gráfico (mayor → menor cumplimiento) | N4: % Cumpl. | O4: Ventas m² | P4: Budget m²
A5: ALTAMIRANO PUENTES YAZMIN | B5: Yazmín Altamirano | C5: 52792 | D5: 42195 | E5: 23401 | F5: =IF(A5="","",IF(E5=0,0,D5/E5)) | G5: =IF(F5="","",IF(F5>=1,"Verde",IF(F5>=0.7,"Ámbar","Rojo"))) | H5: 8580 | I5: 456 | J5: =IF(A5="","",F5+D5/1000000000+(100-ROW())/1000000000000) | L5: 1 | M5: =IF(L5>COUNT($J$5:$J$19),"",INDEX($B$5:$B$19,MATCH(LARGE($J$5:$J$19,L5),$J$5:$J$19,0))) | N5: =IF(M5="","",INDEX($F$5:$F$19,MATCH(LARGE($J$5:$J$19,L5),$J$5:$J$19,0))) | O5: =IF(M5="","",INDEX($D$5:$D$19,MATCH(LARGE($J$5:$J$19,L5),$J$5:$J$19,0))) | P5: =IF(M5="","",INDEX($E$5:$E$19,MATCH(LARGE($J$5:$J$19,L5),$J$5:$J$19,0)))
A6: CALDERON CHANTRE DIEGO ALFONSO | B6: Diego A. Calderón | C6: =81941+5399 | D6: =54854+9666 | E6: =50460+37595 | F6: =IF(A6="","",IF(E6=0,0,D6/E6)) | G6: =IF(F6="","",IF(F6>=1,"Verde",IF(F6>=0.7,"Ámbar","Rojo"))) | H6: 25839 | I6: 14490 | J6: =IF(A6="","",F6+D6/1000000000+(100-ROW())/1000000000000) | L6: 2 | M6: =IF(L6>COUNT($J$5:$J$19),"",INDEX($B$5:$B$19,MATCH(LARGE($J$5:$J$19,L6),$J$5:$J$19,0))) | N6: =IF(M6="","",INDEX($F$5:$F$19,MATCH(LARGE($J$5:$J$19,L6),$J$5:$J$19,0))) | O6: =IF(M6="","",INDEX($D$5:$D$19,MATCH(LARGE($J$5:$J$19,L6),$J$5:$J$19,0))) | P6: =IF(M6="","",INDEX($E$5:$E$19,MATCH(LARGE($J$5:$J$19,L6),$J$5:$J$19,0)))
F7: =IF(A7="","",IF(E7=0,0,D7/E7)) | G7: =IF(F7="","",IF(F7>=1,"Verde",IF(F7>=0.7,"Ámbar","Rojo"))) | J7: =IF(A7="","",F7+D7/1000000000+(100-ROW())/1000000000000) | L7: 3 | M7: =IF(L7>COUNT($J$5:$J$19),"",INDEX($B$5:$B$19,MATCH(LARGE($J$5:$J$19,L7),$J$5:$J$19,0))) | N7: =IF(M7="","",INDEX($F$5:$F$19,MATCH(LARGE($J$5:$J$19,L7),$J$5:$J$19,0))) | O7: =IF(M7="","",INDEX($D$5:$D$19,MATCH(LARGE($J$5:$J$19,L7),$J$5:$J$19,0))) | P7: =IF(M7="","",INDEX($E$5:$E$19,MATCH(LARGE($J$5:$J$19,L7),$J$5:$J$19,0)))
F8: =IF(A8="","",IF(E8=0,0,D8/E8)) | G8: =IF(F8="","",IF(F8>=1,"Verde",IF(F8>=0.7,"Ámbar","Rojo"))) | J8: =IF(A8="","",F8+D8/1000000000+(100-ROW())/1000000000000) | L8: 4 | M8: =IF(L8>COUNT($J$5:$J$19),"",INDEX($B$5:$B$19,MATCH(LARGE($J$5:$J$19,L8),$J$5:$J$19,0))) | N8: =IF(M8="","",INDEX($F$5:$F$19,MATCH(LARGE($J$5:$J$19,L8),$J$5:$J$19,0))) | O8: =IF(M8="","",INDEX($D$5:$D$19,MATCH(LARGE($J$5:$J$19,L8),$J$5:$J$19,0))) | P8: =IF(M8="","",INDEX($E$5:$E$19,MATCH(LARGE($J$5:$J$19,L8),$J$5:$J$19,0)))
F9: =IF(A9="","",IF(E9=0,0,D9/E9)) | G9: =IF(F9="","",IF(F9>=1,"Verde",IF(F9>=0.7,"Ámbar","Rojo"))) | J9: =IF(A9="","",F9+D9/1000000000+(100-ROW())/1000000000000) | L9: 5 | M9: =IF(L9>COUNT($J$5:$J$19),"",INDEX($B$5:$B$19,MATCH(LARGE($J$5:$J$19,L9),$J$5:$J$19,0))) | N9: =IF(M9="","",INDEX($F$5:$F$19,MATCH(LARGE($J$5:$J$19,L9),$J$5:$J$19,0))) | O9: =IF(M9="","",INDEX($D$5:$D$19,MATCH(LARGE($J$5:$J$19,L9),$J$5:$J$19,0))) | P9: =IF(M9="","",INDEX($E$5:$E$19,MATCH(LARGE($J$5:$J$19,L9),$J$5:$J$19,0)))
F10: =IF(A10="","",IF(E10=0,0,D10/E10)) | G10: =IF(F10="","",IF(F10>=1,"Verde",IF(F10>=0.7,"Ámbar","Rojo"))) | J10: =IF(A10="","",F10+D10/1000000000+(100-ROW())/1000000000000) | L10: 6 | M10: =IF(L10>COUNT($J$5:$J$19),"",INDEX($B$5:$B$19,MATCH(LARGE($J$5:$J$19,L10),$J$5:$J$19,0))) | N10: =IF(M10="","",INDEX($F$5:$F$19,MATCH(LARGE($J$5:$J$19,L10),$J$5:$J$19,0))) | O10: =IF(M10="","",INDEX($D$5:$D$19,MATCH(LARGE($J$5:$J$19,L10),$J$5:$J$19,0))) | P10: =IF(M10="","",INDEX($E$5:$E$19,MATCH(LARGE($J$5:$J$19,L10),$J$5:$J$19,0)))
F11: =IF(A11="","",IF(E11=0,0,D11/E11)) | G11: =IF(F11="","",IF(F11>=1,"Verde",IF(F11>=0.7,"Ámbar","Rojo"))) | J11: =IF(A11="","",F11+D11/1000000000+(100-ROW())/1000000000000) | L11: 7 | M11: =IF(L11>COUNT($J$5:$J$19),"",INDEX($B$5:$B$19,MATCH(LARGE($J$5:$J$19,L11),$J$5:$J$19,0))) | N11: =IF(M11="","",INDEX($F$5:$F$19,MATCH(LARGE($J$5:$J$19,L11),$J$5:$J$19,0))) | O11: =IF(M11="","",INDEX($D$5:$D$19,MATCH(LARGE($J$5:$J$19,L11),$J$5:$J$19,0))) | P11: =IF(M11="","",INDEX($E$5:$E$19,MATCH(LARGE($J$5:$J$19,L11),$J$5:$J$19,0)))
F12: =IF(A12="","",IF(E12=0,0,D12/E12)) | G12: =IF(F12="","",IF(F12>=1,"Verde",IF(F12>=0.7,"Ámbar","Rojo"))) | J12: =IF(A12="","",F12+D12/1000000000+(100-ROW())/1000000000000) | L12: 8 | M12: =IF(L12>COUNT($J$5:$J$19),"",INDEX($B$5:$B$19,MATCH(LARGE($J$5:$J$19,L12),$J$5:$J$19,0))) | N12: =IF(M12="","",INDEX($F$5:$F$19,MATCH(LARGE($J$5:$J$19,L12),$J$5:$J$19,0))) | O12: =IF(M12="","",INDEX($D$5:$D$19,MATCH(LARGE($J$5:$J$19,L12),$J$5:$J$19,0))) | P12: =IF(M12="","",INDEX($E$5:$E$19,MATCH(LARGE($J$5:$J$19,L12),$J$5:$J$19,0)))
F13: =IF(A13="","",IF(E13=0,0,D13/E13)) | G13: =IF(F13="","",IF(F13>=1,"Verde",IF(F13>=0.7,"Ámbar","Rojo"))) | J13: =IF(A13="","",F13+D13/1000000000+(100-ROW())/1000000000000) | L13: 9 | M13: =IF(L13>COUNT($J$5:$J$19),"",INDEX($B$5:$B$19,MATCH(LARGE($J$5:$J$19,L13),$J$5:$J$19,0))) | N13: =IF(M13="","",INDEX($F$5:$F$19,MATCH(LARGE($J$5:$J$19,L13),$J$5:$J$19,0))) | O13: =IF(M13="","",INDEX($D$5:$D$19,MATCH(LARGE($J$5:$J$19,L13),$J$5:$J$19,0))) | P13: =IF(M13="","",INDEX($E$5:$E$19,MATCH(LARGE($J$5:$J$19,L13),$J$5:$J$19,0)))
F14: =IF(A14="","",IF(E14=0,0,D14/E14)) | G14: =IF(F14="","",IF(F14>=1,"Verde",IF(F14>=0.7,"Ámbar","Rojo"))) | J14: =IF(A14="","",F14+D14/1000000000+(100-ROW())/1000000000000) | L14: 10 | M14: =IF(L14>COUNT($J$5:$J$19),"",INDEX($B$5:$B$19,MATCH(LARGE($J$5:$J$19,L14),$J$5:$J$19,0))) | N14: =IF(M14="","",INDEX($F$5:$F$19,MATCH(LARGE($J$5:$J$19,L14),$J$5:$J$19,0))) | O14: =IF(M14="","",INDEX($D$5:$D$19,MATCH(LARGE($J$5:$J$19,L14),$J$5:$J$19,0))) | P14: =IF(M14="","",INDEX($E$5:$E$19,MATCH(LARGE($J$5:$J$19,L14),$J$5:$J$19,0)))
F15: =IF(A15="","",IF(E15=0,0,D15/E15)) | G15: =IF(F15="","",IF(F15>=1,"Verde",IF(F15>=0.7,"Ámbar","Rojo"))) | J15: =IF(A15="","",F15+D15/1000000000+(100-ROW())/1000000000000) | L15: 11 | M15: =IF(L15>COUNT($J$5:$J$19),"",INDEX($B$5:$B$19,MATCH(LARGE($J$5:$J$19,L15),$J$5:$J$19,0))) | N15: =IF(M15="","",INDEX($F$5:$F$19,MATCH(LARGE($J$5:$J$19,L15),$J$5:$J$19,0))) | O15: =IF(M15="","",INDEX($D$5:$D$19,MATCH(LARGE($J$5:$J$19,L15),$J$5:$J$19,0))) | P15: =IF(M15="","",INDEX($E$5:$E$19,MATCH(LARGE($J$5:$J$19,L15),$J$5:$J$19,0)))
F16: =IF(A16="","",IF(E16=0,0,D16/E16)) | G16: =IF(F16="","",IF(F16>=1,"Verde",IF(F16>=0.7,"Ámbar","Rojo"))) | J16: =IF(A16="","",F16+D16/1000000000+(100-ROW())/1000000000000) | L16: 12 | M16: =IF(L16>COUNT($J$5:$J$19),"",INDEX($B$5:$B$19,MATCH(LARGE($J$5:$J$19,L16),$J$5:$J$19,0))) | N16: =IF(M16="","",INDEX($F$5:$F$19,MATCH(LARGE($J$5:$J$19,L16),$J$5:$J$19,0))) | O16: =IF(M16="","",INDEX($D$5:$D$19,MATCH(LARGE($J$5:$J$19,L16),$J$5:$J$19,0))) | P16: =IF(M16="","",INDEX($E$5:$E$19,MATCH(LARGE($J$5:$J$19,L16),$J$5:$J$19,0)))
F17: =IF(A17="","",IF(E17=0,0,D17/E17)) | G17: =IF(F17="","",IF(F17>=1,"Verde",IF(F17>=0.7,"Ámbar","Rojo"))) | J17: =IF(A17="","",F17+D17/1000000000+(100-ROW())/1000000000000) | L17: 13 | M17: =IF(L17>COUNT($J$5:$J$19),"",INDEX($B$5:$B$19,MATCH(LARGE($J$5:$J$19,L17),$J$5:$J$19,0))) | N17: =IF(M17="","",INDEX($F$5:$F$19,MATCH(LARGE($J$5:$J$19,L17),$J$5:$J$19,0))) | O17: =IF(M17="","",INDEX($D$5:$D$19,MATCH(LARGE($J$5:$J$19,L17),$J$5:$J$19,0))) | P17: =IF(M17="","",INDEX($E$5:$E$19,MATCH(LARGE($J$5:$J$19,L17),$J$5:$J$19,0)))
F18: =IF(A18="","",IF(E18=0,0,D18/E18)) | G18: =IF(F18="","",IF(F18>=1,"Verde",IF(F18>=0.7,"Ámbar","Rojo"))) | J18: =IF(A18="","",F18+D18/1000000000+(100-ROW())/1000000000000) | L18: 14 | M18: =IF(L18>COUNT($J$5:$J$19),"",INDEX($B$5:$B$19,MATCH(LARGE($J$5:$J$19,L18),$J$5:$J$19,0))) | N18: =IF(M18="","",INDEX($F$5:$F$19,MATCH(LARGE($J$5:$J$19,L18),$J$5:$J$19,0))) | O18: =IF(M18="","",INDEX($D$5:$D$19,MATCH(LARGE($J$5:$J$19,L18),$J$5:$J$19,0))) | P18: =IF(M18="","",INDEX($E$5:$E$19,MATCH(LARGE($J$5:$J$19,L18),$J$5:$J$19,0)))
F19: =IF(A19="","",IF(E19=0,0,D19/E19)) | G19: =IF(F19="","",IF(F19>=1,"Verde",IF(F19>=0.7,"Ámbar","Rojo"))) | J19: =IF(A19="","",F19+D19/1000000000+(100-ROW())/1000000000000) | L19: 15 | M19: =IF(L19>COUNT($J$5:$J$19),"",INDEX($B$5:$B$19,MATCH(LARGE($J$5:$J$19,L19),$J$5:$J$19,0))) | N19: =IF(M19="","",INDEX($F$5:$F$19,MATCH(LARGE($J$5:$J$19,L19),$J$5:$J$19,0))) | O19: =IF(M19="","",INDEX($D$5:$D$19,MATCH(LARGE($J$5:$J$19,L19),$J$5:$J$19,0))) | P19: =IF(M19="","",INDEX($E$5:$E$19,MATCH(LARGE($J$5:$J$19,L19),$J$5:$J$19,0)))
A20: TOTAL CANAL | B20: =COUNTA(A5:A19)&" RSM" | C20: =SUM(C5:C19) | D20: =SUM(D5:D19) | E20: =SUM(E5:E19) | F20: =IF(E20=0,0,D20/E20) | G20: =IF(F20>=1,"Verde",IF(F20>=0.7,"Ámbar","Rojo")) | H20: =SUM(H5:H19) | I20: =SUM(I5:I19)
A22: KPIs canal
A23: RSM ≥100% budget | B23: =COUNTIF(F5:F19,">=1")
A24: RSM <70% budget | B24: =COUNTIFS(F5:F19,"<0.7",A5:A19,"<>")
A25: Brecha vs budget (m²) | B25: =D20-E20
A26: Backlog total (m²) | B26: =H20+I20
A27: Book-to-bill (OI/Ventas) | B27: =IFERROR(C20/D20,"")

Sheet 14_RSM_Vtas_Alt
A1: 14 · RSM Ventas Alternativas – Cumplimiento y Backlog (YTD) [detalle interno – no se presenta en el deck]
A2: Diligencie la tabla izquierda; el ranking (derecha), totales y semáforos se calculan solos
A4: RSM (nombre completo) | B4: Nombre corto (slide) | C4: Order Intake m² | D4: Ventas Total m² | E4: Budget m² (paneles) | F4: % Cumpl. Budget | G4: Semáforo | H4: Backlog paneles m² | I4: Backlog otros m² | J4: Clave orden (aux) | L4: # | M4: Ranking – Fuente gráfico (mayor → menor cumplimiento) | N4: % Cumpl. | O4: Ventas m² | P4: Budget m²
A5: ALTAMIRANO PUENTES YAZMIN | B5: Yazmín Altamirano | C5: 850 | D5: 1752 | E5: 1118 | F5: =IF(A5="","",IF(E5=0,0,D5/E5)) | G5: =IF(F5="","",IF(F5>=1,"Verde",IF(F5>=0.7,"Ámbar","Rojo"))) | H5: 0 | I5: 0 | J5: =IF(A5="","",F5+D5/1000000000+(100-ROW())/1000000000000) | L5: 1 | M5: =IF(L5>COUNT($J$5:$J$19),"",INDEX($B$5:$B$19,MATCH(LARGE($J$5:$J$19,L5),$J$5:$J$19,0))) | N5: =IF(M5="","",INDEX($F$5:$F$19,MATCH(LARGE($J$5:$J$19,L5),$J$5:$J$19,0))) | O5: =IF(M5="","",INDEX($D$5:$D$19,MATCH(LARGE($J$5:$J$19,L5),$J$5:$J$19,0))) | P5: =IF(M5="","",INDEX($E$5:$E$19,MATCH(LARGE($J$5:$J$19,L5),$J$5:$J$19,0)))
A6: QUINTANA BARRIOS JAIRO ALONSO | B6: Jairo A. Quintana | C6: 57561 | D6: 67678 | E6: 44250 | F6: =IF(A6="","",IF(E6=0,0,D6/E6)) | G6: =IF(F6="","",IF(F6>=1,"Verde",IF(F6>=0.7,"Ámbar","Rojo"))) | H6: 6066 | I6: 0 | J6: =IF(A6="","",F6+D6/1000000000+(100-ROW())/1000000000000) | L6: 2 | M6: =IF(L6>COUNT($J$5:$J$19),"",INDEX($B$5:$B$19,MATCH(LARGE($J$5:$J$19,L6),$J$5:$J$19,0))) | N6: =IF(M6="","",INDEX($F$5:$F$19,MATCH(LARGE($J$5:$J$19,L6),$J$5:$J$19,0))) | O6: =IF(M6="","",INDEX($D$5:$D$19,MATCH(LARGE($J$5:$J$19,L6),$J$5:$J$19,0))) | P6: =IF(M6="","",INDEX($E$5:$E$19,MATCH(LARGE($J$5:$J$19,L6),$J$5:$J$19,0)))
F7: =IF(A7="","",IF(E7=0,0,D7/E7)) | G7: =IF(F7="","",IF(F7>=1,"Verde",IF(F7>=0.7,"Ámbar","Rojo"))) | J7: =IF(A7="","",F7+D7/1000000000+(100-ROW())/1000000000000) | L7: 3 | M7: =IF(L7>COUNT($J$5:$J$19),"",INDEX($B$5:$B$19,MATCH(LARGE($J$5:$J$19,L7),$J$5:$J$19,0))) | N7: =IF(M7="","",INDEX($F$5:$F$19,MATCH(LARGE($J$5:$J$19,L7),$J$5:$J$19,0))) | O7: =IF(M7="","",INDEX($D$5:$D$19,MATCH(LARGE($J$5:$J$19,L7),$J$5:$J$19,0))) | P7: =IF(M7="","",INDEX($E$5:$E$19,MATCH(LARGE($J$5:$J$19,L7),$J$5:$J$19,0)))
F8: =IF(A8="","",IF(E8=0,0,D8/E8)) | G8: =IF(F8="","",IF(F8>=1,"Verde",IF(F8>=0.7,"Ámbar","Rojo"))) | J8: =IF(A8="","",F8+D8/1000000000+(100-ROW())/1000000000000) | L8: 4 | M8: =IF(L8>COUNT($J$5:$J$19),"",INDEX($B$5:$B$19,MATCH(LARGE($J$5:$J$19,L8),$J$5:$J$19,0))) | N8: =IF(M8="","",INDEX($F$5:$F$19,MATCH(LARGE($J$5:$J$19,L8),$J$5:$J$19,0))) | O8: =IF(M8="","",INDEX($D$5:$D$19,MATCH(LARGE($J$5:$J$19,L8),$J$5:$J$19,0))) | P8: =IF(M8="","",INDEX($E$5:$E$19,MATCH(LARGE($J$5:$J$19,L8),$J$5:$J$19,0)))
F9: =IF(A9="","",IF(E9=0,0,D9/E9)) | G9: =IF(F9="","",IF(F9>=1,"Verde",IF(F9>=0.7,"Ámbar","Rojo"))) | J9: =IF(A9="","",F9+D9/1000000000+(100-ROW())/1000000000000) | L9: 5 | M9: =IF(L9>COUNT($J$5:$J$19),"",INDEX($B$5:$B$19,MATCH(LARGE($J$5:$J$19,L9),$J$5:$J$19,0))) | N9: =IF(M9="","",INDEX($F$5:$F$19,MATCH(LARGE($J$5:$J$19,L9),$J$5:$J$19,0))) | O9: =IF(M9="","",INDEX($D$5:$D$19,MATCH(LARGE($J$5:$J$19,L9),$J$5:$J$19,0))) | P9: =IF(M9="","",INDEX($E$5:$E$19,MATCH(LARGE($J$5:$J$19,L9),$J$5:$J$19,0)))
F10: =IF(A10="","",IF(E10=0,0,D10/E10)) | G10: =IF(F10="","",IF(F10>=1,"Verde",IF(F10>=0.7,"Ámbar","Rojo"))) | J10: =IF(A10="","",F10+D10/1000000000+(100-ROW())/1000000000000) | L10: 6 | M10: =IF(L10>COUNT($J$5:$J$19),"",INDEX($B$5:$B$19,MATCH(LARGE($J$5:$J$19,L10),$J$5:$J$19,0))) | N10: =IF(M10="","",INDEX($F$5:$F$19,MATCH(LARGE($J$5:$J$19,L10),$J$5:$J$19,0))) | O10: =IF(M10="","",INDEX($D$5:$D$19,MATCH(LARGE($J$5:$J$19,L10),$J$5:$J$19,0))) | P10: =IF(M10="","",INDEX($E$5:$E$19,MATCH(LARGE($J$5:$J$19,L10),$J$5:$J$19,0)))
F11: =IF(A11="","",IF(E11=0,0,D11/E11)) | G11: =IF(F11="","",IF(F11>=1,"Verde",IF(F11>=0.7,"Ámbar","Rojo"))) | J11: =IF(A11="","",F11+D11/1000000000+(100-ROW())/1000000000000) | L11: 7 | M11: =IF(L11>COUNT($J$5:$J$19),"",INDEX($B$5:$B$19,MATCH(LARGE($J$5:$J$19,L11),$J$5:$J$19,0))) | N11: =IF(M11="","",INDEX($F$5:$F$19,MATCH(LARGE($J$5:$J$19,L11),$J$5:$J$19,0))) | O11: =IF(M11="","",INDEX($D$5:$D$19,MATCH(LARGE($J$5:$J$19,L11),$J$5:$J$19,0))) | P11: =IF(M11="","",INDEX($E$5:$E$19,MATCH(LARGE($J$5:$J$19,L11),$J$5:$J$19,0)))
F12: =IF(A12="","",IF(E12=0,0,D12/E12)) | G12: =IF(F12="","",IF(F12>=1,"Verde",IF(F12>=0.7,"Ámbar","Rojo"))) | J12: =IF(A12="","",F12+D12/1000000000+(100-ROW())/1000000000000) | L12: 8 | M12: =IF(L12>COUNT($J$5:$J$19),"",INDEX($B$5:$B$19,MATCH(LARGE($J$5:$J$19,L12),$J$5:$J$19,0))) | N12: =IF(M12="","",INDEX($F$5:$F$19,MATCH(LARGE($J$5:$J$19,L12),$J$5:$J$19,0))) | O12: =IF(M12="","",INDEX($D$5:$D$19,MATCH(LARGE($J$5:$J$19,L12),$J$5:$J$19,0))) | P12: =IF(M12="","",INDEX($E$5:$E$19,MATCH(LARGE($J$5:$J$19,L12),$J$5:$J$19,0)))
F13: =IF(A13="","",IF(E13=0,0,D13/E13)) | G13: =IF(F13="","",IF(F13>=1,"Verde",IF(F13>=0.7,"Ámbar","Rojo"))) | J13: =IF(A13="","",F13+D13/1000000000+(100-ROW())/1000000000000) | L13: 9 | M13: =IF(L13>COUNT($J$5:$J$19),"",INDEX($B$5:$B$19,MATCH(LARGE($J$5:$J$19,L13),$J$5:$J$19,0))) | N13: =IF(M13="","",INDEX($F$5:$F$19,MATCH(LARGE($J$5:$J$19,L13),$J$5:$J$19,0))) | O13: =IF(M13="","",INDEX($D$5:$D$19,MATCH(LARGE($J$5:$J$19,L13),$J$5:$J$19,0))) | P13: =IF(M13="","",INDEX($E$5:$E$19,MATCH(LARGE($J$5:$J$19,L13),$J$5:$J$19,0)))
F14: =IF(A14="","",IF(E14=0,0,D14/E14)) | G14: =IF(F14="","",IF(F14>=1,"Verde",IF(F14>=0.7,"Ámbar","Rojo"))) | J14: =IF(A14="","",F14+D14/1000000000+(100-ROW())/1000000000000) | L14: 10 | M14: =IF(L14>COUNT($J$5:$J$19),"",INDEX($B$5:$B$19,MATCH(LARGE($J$5:$J$19,L14),$J$5:$J$19,0))) | N14: =IF(M14="","",INDEX($F$5:$F$19,MATCH(LARGE($J$5:$J$19,L14),$J$5:$J$19,0))) | O14: =IF(M14="","",INDEX($D$5:$D$19,MATCH(LARGE($J$5:$J$19,L14),$J$5:$J$19,0))) | P14: =IF(M14="","",INDEX($E$5:$E$19,MATCH(LARGE($J$5:$J$19,L14),$J$5:$J$19,0)))
F15: =IF(A15="","",IF(E15=0,0,D15/E15)) | G15: =IF(F15="","",IF(F15>=1,"Verde",IF(F15>=0.7,"Ámbar","Rojo"))) | J15: =IF(A15="","",F15+D15/1000000000+(100-ROW())/1000000000000) | L15: 11 | M15: =IF(L15>COUNT($J$5:$J$19),"",INDEX($B$5:$B$19,MATCH(LARGE($J$5:$J$19,L15),$J$5:$J$19,0))) | N15: =IF(M15="","",INDEX($F$5:$F$19,MATCH(LARGE($J$5:$J$19,L15),$J$5:$J$19,0))) | O15: =IF(M15="","",INDEX($D$5:$D$19,MATCH(LARGE($J$5:$J$19,L15),$J$5:$J$19,0))) | P15: =IF(M15="","",INDEX($E$5:$E$19,MATCH(LARGE($J$5:$J$19,L15),$J$5:$J$19,0)))
F16: =IF(A16="","",IF(E16=0,0,D16/E16)) | G16: =IF(F16="","",IF(F16>=1,"Verde",IF(F16>=0.7,"Ámbar","Rojo"))) | J16: =IF(A16="","",F16+D16/1000000000+(100-ROW())/1000000000000) | L16: 12 | M16: =IF(L16>COUNT($J$5:$J$19),"",INDEX($B$5:$B$19,MATCH(LARGE($J$5:$J$19,L16),$J$5:$J$19,0))) | N16: =IF(M16="","",INDEX($F$5:$F$19,MATCH(LARGE($J$5:$J$19,L16),$J$5:$J$19,0))) | O16: =IF(M16="","",INDEX($D$5:$D$19,MATCH(LARGE($J$5:$J$19,L16),$J$5:$J$19,0))) | P16: =IF(M16="","",INDEX($E$5:$E$19,MATCH(LARGE($J$5:$J$19,L16),$J$5:$J$19,0)))
F17: =IF(A17="","",IF(E17=0,0,D17/E17)) | G17: =IF(F17="","",IF(F17>=1,"Verde",IF(F17>=0.7,"Ámbar","Rojo"))) | J17: =IF(A17="","",F17+D17/1000000000+(100-ROW())/1000000000000) | L17: 13 | M17: =IF(L17>COUNT($J$5:$J$19),"",INDEX($B$5:$B$19,MATCH(LARGE($J$5:$J$19,L17),$J$5:$J$19,0))) | N17: =IF(M17="","",INDEX($F$5:$F$19,MATCH(LARGE($J$5:$J$19,L17),$J$5:$J$19,0))) | O17: =IF(M17="","",INDEX($D$5:$D$19,MATCH(LARGE($J$5:$J$19,L17),$J$5:$J$19,0))) | P17: =IF(M17="","",INDEX($E$5:$E$19,MATCH(LARGE($J$5:$J$19,L17),$J$5:$J$19,0)))
F18: =IF(A18="","",IF(E18=0,0,D18/E18)) | G18: =IF(F18="","",IF(F18>=1,"Verde",IF(F18>=0.7,"Ámbar","Rojo"))) | J18: =IF(A18="","",F18+D18/1000000000+(100-ROW())/1000000000000) | L18: 14 | M18: =IF(L18>COUNT($J$5:$J$19),"",INDEX($B$5:$B$19,MATCH(LARGE($J$5:$J$19,L18),$J$5:$J$19,0))) | N18: =IF(M18="","",INDEX($F$5:$F$19,MATCH(LARGE($J$5:$J$19,L18),$J$5:$J$19,0))) | O18: =IF(M18="","",INDEX($D$5:$D$19,MATCH(LARGE($J$5:$J$19,L18),$J$5:$J$19,0))) | P18: =IF(M18="","",INDEX($E$5:$E$19,MATCH(LARGE($J$5:$J$19,L18),$J$5:$J$19,0)))
F19: =IF(A19="","",IF(E19=0,0,D19/E19)) | G19: =IF(F19="","",IF(F19>=1,"Verde",IF(F19>=0.7,"Ámbar","Rojo"))) | J19: =IF(A19="","",F19+D19/1000000000+(100-ROW())/1000000000000) | L19: 15 | M19: =IF(L19>COUNT($J$5:$J$19),"",INDEX($B$5:$B$19,MATCH(LARGE($J$5:$J$19,L19),$J$5:$J$19,0))) | N19: =IF(M19="","",INDEX($F$5:$F$19,MATCH(LARGE($J$5:$J$19,L19),$J$5:$J$19,0))) | O19: =IF(M19="","",INDEX($D$5:$D$19,MATCH(LARGE($J$5:$J$19,L19),$J$5:$J$19,0))) | P19: =IF(M19="","",INDEX($E$5:$E$19,MATCH(LARGE($J$5:$J$19,L19),$J$5:$J$19,0)))
A20: TOTAL CANAL | B20: =COUNTA(A5:A19)&" RSM" | C20: =SUM(C5:C19) | D20: =SUM(D5:D19) | E20: =SUM(E5:E19) | F20: =IF(E20=0,0,D20/E20) | G20: =IF(F20>=1,"Verde",IF(F20>=0.7,"Ámbar","Rojo")) | H20: =SUM(H5:H19) | I20: =SUM(I5:I19)
A22: KPIs canal
A23: RSM ≥100% budget | B23: =COUNTIF(F5:F19,">=1")
A24: RSM <70% budget | B24: =COUNTIFS(F5:F19,"<0.7",A5:A19,"<>")
A25: Brecha vs budget (m²) | B25: =D20-E20
A26: Backlog total (m²) | B26: =H20+I20
A27: Book-to-bill (OI/Ventas) | B27: =IFERROR(C20/D20,"")

Sheet 15_Highlights
A1: 15 · Highlights septiembre – Comercial
A2: KPIs de gestión comercial e hitos del mes
A4: KPI | B4: Valor | C4: Unidad / detalle
A5: Visitas a clientes | B5: 218 | C5: visitas
A6: Clientes nuevos | B6: 26 | C6: clientes
A7: m² clientes nuevos | B7: 7400 | C7: m²
A8: USD clientes nuevos | B8: 197235 | C8: USD
A9: Personas capacitadas | B9: 122 | C9: personas (clientes + portafolio cold storage)
A10: Ferias / eventos | B10: 2 | C10: eventos
A11: m² especificados en paneles | B11: 163801 | C11: m²
A12: m² especificados línea arquitectónica | B12: 49626 | C12: m²
A13: USD promedio por cliente nuevo | B13: =IFERROR(B8/B6,0)
A14: m² especificados – total | B14: =B11+B12
A16: Hito | B16: Qué se hizo | C16: Impacto / siguiente paso
A17: Evento Binacional – Cúcuta | B17: Participación en rueda de negocios conectando empresas colombianas con compradores venezolanos | C17: Pipeline de nuevas oportunidades en Venezuela; seguimiento a contactos
A18: Formación de clientes | B18: Capacitaciones a clientes y portafolio general / cold storage (122 personas); portafolio cold storage para Grupo Nutresa | C18: Especificación temprana y fidelización de cuentas clave
A19: Proyecto destacado – Smartfit | B19: Fachada Smartfit 599 m² | C19: Referencia arquitectónica para retail / fitness
A20: Proyecto destacado – Dollarcity Mamatoco | B20: Suministro de solución de cubierta para nueva tienda | C20: Replicable al plan de expansión de la cadena

Sheet Pipeline
A1: Pipeline de proyectos – Industrial y Distribución (input)
A2: Una fila por proyecto. Las columnas grises son auxiliares (no editar).
A4: Criterio Top Opportunities (USD o m2) | C4: USD
A6: Segmento | B6: Cliente | C6: Proyecto | D6: Responsable | E6: País | F6: Portafolio | G6: m² | H6: USD | I6: Estado | J6: % Cierre | K6: Fecha cierre proy. | L6: Valor ponderado USD | M6: Clave Top Opps Ind | N6: Clave Top Opps Dis | O6: Clave m² Ind | P6: Clave m² Dis
A7: Industrial | B7: Construplan | C7: Walmart | D7: Carlos Rodriguez | E7: Guatemala | F7: King Wall / King Frio / King Roof | G7: 100000 | H7: 2787794 | I7: Specification | J7: 0.75 | K7: Noviembre | L7: =IF(J7="","",H7*J7) | M7: =IF(AND(A7="Industrial",I7<>"Closed Won",B7<>"Others"),IF($C$4="m2",G7,H7)+(1000-ROW())/1000000,"") | N7: =IF(AND(A7="Distribución",I7<>"Closed Won",B7<>"Others"),IF($C$4="m2",G7,H7)+(1000-ROW())/1000000,"") | O7: =IF(AND(A7="Industrial",B7<>"Others"),G7+(1000-ROW())/1000000,"") | P7: =IF(AND(A7="Distribución",B7<>"Others"),G7+(1000-ROW())/1000000,"")
A8: Industrial | B8: Haceb | C8: Recambio | D8: Ana Arias | E8: Colombia | F8: KingWall / KingRoof | G8: 61000 | H8: 1700505 | I8: Pending | J8: 0.8 | K8: Noviembre | L8: =IF(J8="","",H8*J8) | M8: =IF(AND(A8="Industrial",I8<>"Closed Won",B8<>"Others"),IF($C$4="m2",G8,H8)+(1000-ROW())/1000000,"") | N8: =IF(AND(A8="Distribución",I8<>"Closed Won",B8<>"Others"),IF($C$4="m2",G8,H8)+(1000-ROW())/1000000,"") | O8: =IF(AND(A8="Industrial",B8<>"Others"),G8+(1000-ROW())/1000000,"") | P8: =IF(AND(A8="Distribución",B8<>"Others"),G8+(1000-ROW())/1000000,"")
A9: Industrial | B9: Conmetal | C9: Bodegas AMT | D9: Carlos Rodriguez | E9: Guatemala | F9: KingRoof / KingWall | G9: 50000 | H9: 1200000 | I9: Pending | J9: 0.6 | K9: Diciembre | L9: =IF(J9="","",H9*J9) | M9: =IF(AND(A9="Industrial",I9<>"Closed Won",B9<>"Others"),IF($C$4="m2",G9,H9)+(1000-ROW())/1000000,"") | N9: =IF(AND(A9="Distribución",I9<>"Closed Won",B9<>"Others"),IF($C$4="m2",G9,H9)+(1000-ROW())/1000000,"") | O9: =IF(AND(A9="Industrial",B9<>"Others"),G9+(1000-ROW())/1000000,"") | P9: =IF(AND(A9="Distribución",B9<>"Others"),G9+(1000-ROW())/1000000,"")
A10: Industrial | B10: Imbert Dominguez | C10: INDAL-IDA | D10: Laura Torres | E10: Dominicana | F10: KingRoof / KingWall / KingFrigo | G10: 50000 | H10: 1550000 | I10: Pending | J10: 0.75 | K10: Noviembre | L10: =IF(J10="","",H10*J10) | M10: =IF(AND(A10="Industrial",I10<>"Closed Won",B10<>"Others"),IF($C$4="m2",G10,H10)+(1000-ROW())/1000000,"") | N10: =IF(AND(A10="Distribución",I10<>"Closed Won",B10<>"Others"),IF($C$4="m2",G10,H10)+(1000-ROW())/1000000,"") | O10: =IF(AND(A10="Industrial",B10<>"Others"),G10+(1000-ROW())/1000000,"") | P10: =IF(AND(A10="Distribución",B10<>"Others"),G10+(1000-ROW())/1000000,"")
A11: Industrial | B11: Magnetron | C11: — | D11: Julio Guerrero | E11: Colombia | F11: KingRoof, KingMetalRoof, KingWall | G11: 45000 | H11: 892114 | I11: Pending | L11: =IF(J11="","",H11*J11) | M11: =IF(AND(A11="Industrial",I11<>"Closed Won",B11<>"Others"),IF($C$4="m2",G11,H11)+(1000-ROW())/1000000,"") | N11: =IF(AND(A11="Distribución",I11<>"Closed Won",B11<>"Others"),IF($C$4="m2",G11,H11)+(1000-ROW())/1000000,"") | O11: =IF(AND(A11="Industrial",B11<>"Others"),G11+(1000-ROW())/1000000,"") | P11: =IF(AND(A11="Distribución",B11<>"Others"),G11+(1000-ROW())/1000000,"")
A12: Industrial | B12: Amo Contratistas | C12: Nave Lima | D12: Erick Hinestroza | E12: Perú | F12: KingRoof / KingWall | G12: 38000 | H12: 890000 | I12: Pending | L12: =IF(J12="","",H12*J12) | M12: =IF(AND(A12="Industrial",I12<>"Closed Won",B12<>"Others"),IF($C$4="m2",G12,H12)+(1000-ROW())/1000000,"") | N12: =IF(AND(A12="Distribución",I12<>"Closed Won",B12<>"Others"),IF($C$4="m2",G12,H12)+(1000-ROW())/1000000,"") | O12: =IF(AND(A12="Industrial",B12<>"Others"),G12+(1000-ROW())/1000000,"") | P12: =IF(AND(A12="Distribución",B12<>"Others"),G12+(1000-ROW())/1000000,"")
A13: Industrial | B13: Super Alimentos Zona Franca | C13: Fábrica | D13: Diego Calderón | E13: Colombia | F13: KingRoof / KingWall / KingFrigo | G13: 35000 | H13: 875000 | I13: Pending | L13: =IF(J13="","",H13*J13) | M13: =IF(AND(A13="Industrial",I13<>"Closed Won",B13<>"Others"),IF($C$4="m2",G13,H13)+(1000-ROW())/1000000,"") | N13: =IF(AND(A13="Distribución",I13<>"Closed Won",B13<>"Others"),IF($C$4="m2",G13,H13)+(1000-ROW())/1000000,"") | O13: =IF(AND(A13="Industrial",B13<>"Others"),G13+(1000-ROW())/1000000,"") | P13: =IF(AND(A13="Distribución",B13<>"Others"),G13+(1000-ROW())/1000000,"")
A14: Industrial | B14: Ministerio de Vivienda SV | C14: Casas El Salvador | D14: Carlos Rodriguez | E14: El Salvador | F14: KingRoof / KingWall | G14: 30000 | H14: 900000 | I14: Pending | L14: =IF(J14="","",H14*J14) | M14: =IF(AND(A14="Industrial",I14<>"Closed Won",B14<>"Others"),IF($C$4="m2",G14,H14)+(1000-ROW())/1000000,"") | N14: =IF(AND(A14="Distribución",I14<>"Closed Won",B14<>"Others"),IF($C$4="m2",G14,H14)+(1000-ROW())/1000000,"") | O14: =IF(AND(A14="Industrial",B14<>"Others"),G14+(1000-ROW())/1000000,"") | P14: =IF(AND(A14="Distribución",B14<>"Others"),G14+(1000-ROW())/1000000,"")
A15: Industrial | B15: Haceb | C15: Recambio | D15: Ana Arias | E15: Colombia | F15: KingWall / KingRoof | G15: 24000 | H15: 669120 | I15: Closed Won | L15: =IF(J15="","",H15*J15) | O15: =IF(AND(A15="Industrial",B15<>"Others"),G15+(1000-ROW())/1000000,"") | P15: =IF(AND(A15="Distribución",B15<>"Others"),G15+(1000-ROW())/1000000,"")
A16: Industrial | B16: Prosein | C16: Casa Venezuela | D16: María Yelitza Calderón | E16: Venezuela | F16: KingFrigo / KingRoof | G16: 22000 | H16: 891749 | I16: Pending | L16: =IF(J16="","",H16*J16) | M16: =IF(AND(A16="Industrial",I16<>"Closed Won",B16<>"Others"),IF($C$4="m2",G16,H16)+(1000-ROW())/1000000,"") | N16: =IF(AND(A16="Distribución",I16<>"Closed Won",B16<>"Others"),IF($C$4="m2",G16,H16)+(1000-ROW())/1000000,"") | O16: =IF(AND(A16="Industrial",B16<>"Others"),G16+(1000-ROW())/1000000,"") | P16: =IF(AND(A16="Distribución",B16<>"Others"),G16+(1000-ROW())/1000000,"")
A17: Industrial | B17: Remar | C17: Casa Venezuela | D17: María Yelitza Calderón | E17: Venezuela | F17: KingFrigo / KingRoof | G17: 20000 | H17: 577429 | I17: Pending | L17: =IF(J17="","",H17*J17) | M17: =IF(AND(A17="Industrial",I17<>"Closed Won",B17<>"Others"),IF($C$4="m2",G17,H17)+(1000-ROW())/1000000,"") | N17: =IF(AND(A17="Distribución",I17<>"Closed Won",B17<>"Others"),IF($C$4="m2",G17,H17)+(1000-ROW())/1000000,"") | O17: =IF(AND(A17="Industrial",B17<>"Others"),G17+(1000-ROW())/1000000,"") | P17: =IF(AND(A17="Distribución",B17<>"Others"),G17+(1000-ROW())/1000000,"")
A18: Industrial | B18: Cubic 33 | C18: Mapei | D18: Erick Hinestroza | E18: Perú | F18: King Wall / King Frio / King Roof | G18: 18000 | H18: 360000 | I18: Pending | L18: =IF(J18="","",H18*J18) | M18: =IF(AND(A18="Industrial",I18<>"Closed Won",B18<>"Others"),IF($C$4="m2",G18,H18)+(1000-ROW())/1000000,"") | N18: =IF(AND(A18="Distribución",I18<>"Closed Won",B18<>"Others"),IF($C$4="m2",G18,H18)+(1000-ROW())/1000000,"") | O18: =IF(AND(A18="Industrial",B18<>"Others"),G18+(1000-ROW())/1000000,"") | P18: =IF(AND(A18="Distribución",B18<>"Others"),G18+(1000-ROW())/1000000,"")
A19: Industrial | B19: Mecalfab | C19: Trinidad Sea Food | D19: Laura Torres | E19: Trinidad | F19: King Frio | G19: 16000 | H19: 550000 | I19: Closed Won | L19: =IF(J19="","",H19*J19) | M19: =IF(AND(A19="Industrial",I19<>"Closed Won",B19<>"Others"),IF($C$4="m2",G19,H19)+(1000-ROW())/1000000,"") | N19: =IF(AND(A19="Distribución",I19<>"Closed Won",B19<>"Others"),IF($C$4="m2",G19,H19)+(1000-ROW())/1000000,"") | O19: =IF(AND(A19="Industrial",B19<>"Others"),G19+(1000-ROW())/1000000,"") | P19: =IF(AND(A19="Distribución",B19<>"Others"),G19+(1000-ROW())/1000000,"")
A20: Industrial | B20: Conconcreto | C20: Planta Arroz Diana B/quilla | D20: Ana Arias | E20: Colombia | F20: KingWall / KingRoof | G20: 13000 | H20: 481132 | I20: Pending | L20: =IF(J20="","",H20*J20) | M20: =IF(AND(A20="Industrial",I20<>"Closed Won",B20<>"Others"),IF($C$4="m2",G20,H20)+(1000-ROW())/1000000,"") | N20: =IF(AND(A20="Distribución",I20<>"Closed Won",B20<>"Others"),IF($C$4="m2",G20,H20)+(1000-ROW())/1000000,"") | O20: =IF(AND(A20="Industrial",B20<>"Others"),G20+(1000-ROW())/1000000,"") | P20: =IF(AND(A20="Distribución",B20<>"Others"),G20+(1000-ROW())/1000000,"")
A21: Industrial | B21: Scadia | C21: Angar Avianca (Bogotá) | D21: Julio Guerrero | E21: Colombia | F21: KingWall / KingRoof o SS | G21: 13000 | H21: 1203774 | I21: Pending | J21: 0.6 | K21: Diciembre | L21: =IF(J21="","",H21*J21) | M21: =IF(AND(A21="Industrial",I21<>"Closed Won",B21<>"Others"),IF($C$4="m2",G21,H21)+(1000-ROW())/1000000,"") | N21: =IF(AND(A21="Distribución",I21<>"Closed Won",B21<>"Others"),IF($C$4="m2",G21,H21)+(1000-ROW())/1000000,"") | O21: =IF(AND(A21="Industrial",B21<>"Others"),G21+(1000-ROW())/1000000,"") | P21: =IF(AND(A21="Distribución",B21<>"Others"),G21+(1000-ROW())/1000000,"")
A22: Industrial | B22: Dolarcity | C22: Dolarcity | D22: Julio Guerrero | E22: Colombia | F22: KingWall | G22: 12000 | H22: 408282 | I22: Pending | L22: =IF(J22="","",H22*J22) | M22: =IF(AND(A22="Industrial",I22<>"Closed Won",B22<>"Others"),IF($C$4="m2",G22,H22)+(1000-ROW())/1000000,"") | N22: =IF(AND(A22="Distribución",I22<>"Closed Won",B22<>"Others"),IF($C$4="m2",G22,H22)+(1000-ROW())/1000000,"") | O22: =IF(AND(A22="Industrial",B22<>"Others"),G22+(1000-ROW())/1000000,"") | P22: =IF(AND(A22="Distribución",B22<>"Others"),G22+(1000-ROW())/1000000,"")
A23: Industrial | B23: Nestlé | C23: Planta Bugalagrande | D23: Diego Calderón | E23: Colombia | F23: KingFrigo | G23: 12000 | H23: 617547 | I23: Pending | L23: =IF(J23="","",H23*J23) | M23: =IF(AND(A23="Industrial",I23<>"Closed Won",B23<>"Others"),IF($C$4="m2",G23,H23)+(1000-ROW())/1000000,"") | N23: =IF(AND(A23="Distribución",I23<>"Closed Won",B23<>"Others"),IF($C$4="m2",G23,H23)+(1000-ROW())/1000000,"") | O23: =IF(AND(A23="Industrial",B23<>"Others"),G23+(1000-ROW())/1000000,"") | P23: =IF(AND(A23="Distribución",B23<>"Others"),G23+(1000-ROW())/1000000,"")
A24: Industrial | B24: Metalmecánica | C24: Indulogix | D24: Carlos Rodriguez | E24: Guatemala | F24: KingWall / KingRoof | G24: 11500 | H24: 310000 | I24: Closed Won | L24: =IF(J24="","",H24*J24) | M24: =IF(AND(A24="Industrial",I24<>"Closed Won",B24<>"Others"),IF($C$4="m2",G24,H24)+(1000-ROW())/1000000,"") | N24: =IF(AND(A24="Distribución",I24<>"Closed Won",B24<>"Others"),IF($C$4="m2",G24,H24)+(1000-ROW())/1000000,"") | O24: =IF(AND(A24="Industrial",B24<>"Others"),G24+(1000-ROW())/1000000,"") | P24: =IF(AND(A24="Distribución",B24<>"Others"),G24+(1000-ROW())/1000000,"")
A25: Industrial | B25: Fluitec | C25: Nave Sein | D25: Laura Torres | E25: Dominicana | F25: KingRoof / KingWall | G25: 11000 | H25: 307000 | I25: Closed Won | L25: =IF(J25="","",H25*J25) | M25: =IF(AND(A25="Industrial",I25<>"Closed Won",B25<>"Others"),IF($C$4="m2",G25,H25)+(1000-ROW())/1000000,"") | N25: =IF(AND(A25="Distribución",I25<>"Closed Won",B25<>"Others"),IF($C$4="m2",G25,H25)+(1000-ROW())/1000000,"") | O25: =IF(AND(A25="Industrial",B25<>"Others"),G25+(1000-ROW())/1000000,"") | P25: =IF(AND(A25="Distribución",B25<>"Others"),G25+(1000-ROW())/1000000,"")
A26: Industrial | B26: Ménsula / Conconcreto | C26: Viva Suba / Claro | D26: Ana Arias | E26: Colombia | F26: KingRoof / Benchmark | G26: 10289 | H26: 1600000 | I26: Pending | L26: =IF(J26="","",H26*J26) | M26: =IF(AND(A26="Industrial",I26<>"Closed Won",B26<>"Others"),IF($C$4="m2",G26,H26)+(1000-ROW())/1000000,"") | N26: =IF(AND(A26="Distribución",I26<>"Closed Won",B26<>"Others"),IF($C$4="m2",G26,H26)+(1000-ROW())/1000000,"") | O26: =IF(AND(A26="Industrial",B26<>"Others"),G26+(1000-ROW())/1000000,"") | P26: =IF(AND(A26="Distribución",B26<>"Others"),G26+(1000-ROW())/1000000,"")
A27: Industrial | B27: COPREFA | C27: Campamento Modular | D27: Erick Hinestroza | E27: Perú | F27: KingFrigo / KingRoof | G27: 8000 | H27: 290000 | I27: Pending | L27: =IF(J27="","",H27*J27) | M27: =IF(AND(A27="Industrial",I27<>"Closed Won",B27<>"Others"),IF($C$4="m2",G27,H27)+(1000-ROW())/1000000,"") | N27: =IF(AND(A27="Distribución",I27<>"Closed Won",B27<>"Others"),IF($C$4="m2",G27,H27)+(1000-ROW())/1000000,"") | O27: =IF(AND(A27="Industrial",B27<>"Others"),G27+(1000-ROW())/1000000,"") | P27: =IF(AND(A27="Distribución",B27<>"Others"),G27+(1000-ROW())/1000000,"")
A28: Industrial | B28: Tronex Fachada | C28: Proyecto Itagüí | D28: Ana Arias | E28: Colombia | F28: KingWall / KingRoof | G28: 6000 | H28: 94118 | I28: Pending | L28: =IF(J28="","",H28*J28) | M28: =IF(AND(A28="Industrial",I28<>"Closed Won",B28<>"Others"),IF($C$4="m2",G28,H28)+(1000-ROW())/1000000,"") | N28: =IF(AND(A28="Distribución",I28<>"Closed Won",B28<>"Others"),IF($C$4="m2",G28,H28)+(1000-ROW())/1000000,"") | O28: =IF(AND(A28="Industrial",B28<>"Others"),G28+(1000-ROW())/1000000,"") | P28: =IF(AND(A28="Distribución",B28<>"Others"),G28+(1000-ROW())/1000000,"")
A29: Industrial | B29: Xperto | C29: Xperto | D29: Alejandra Navas | E29: Ecuador | F29: KingFrigo | G29: 5500 | H29: 288750 | I29: Pending | L29: =IF(J29="","",H29*J29) | M29: =IF(AND(A29="Industrial",I29<>"Closed Won",B29<>"Others"),IF($C$4="m2",G29,H29)+(1000-ROW())/1000000,"") | N29: =IF(AND(A29="Distribución",I29<>"Closed Won",B29<>"Others"),IF($C$4="m2",G29,H29)+(1000-ROW())/1000000,"") | O29: =IF(AND(A29="Industrial",B29<>"Others"),G29+(1000-ROW())/1000000,"") | P29: =IF(AND(A29="Distribución",B29<>"Others"),G29+(1000-ROW())/1000000,"")
A30: Industrial | B30: JT Allum | C30: JT Allum | D30: Laura Torres | E30: Trinidad | F30: KingRoof | G30: 5000 | H30: 170000 | I30: Pending | L30: =IF(J30="","",H30*J30) | M30: =IF(AND(A30="Industrial",I30<>"Closed Won",B30<>"Others"),IF($C$4="m2",G30,H30)+(1000-ROW())/1000000,"") | N30: =IF(AND(A30="Distribución",I30<>"Closed Won",B30<>"Others"),IF($C$4="m2",G30,H30)+(1000-ROW())/1000000,"") | O30: =IF(AND(A30="Industrial",B30<>"Others"),G30+(1000-ROW())/1000000,"") | P30: =IF(AND(A30="Distribución",B30<>"Others"),G30+(1000-ROW())/1000000,"")
A31: Industrial | B31: Inversiones Cold | C31: Proyecto | D31: María Yelitza Calderón | E31: Venezuela | F31: KingRoof / KingFrigo | G31: 5000 | H31: 120000 | I31: Closed Won | L31: =IF(J31="","",H31*J31) | M31: =IF(AND(A31="Industrial",I31<>"Closed Won",B31<>"Others"),IF($C$4="m2",G31,H31)+(1000-ROW())/1000000,"") | N31: =IF(AND(A31="Distribución",I31<>"Closed Won",B31<>"Others"),IF($C$4="m2",G31,H31)+(1000-ROW())/1000000,"") | O31: =IF(AND(A31="Industrial",B31<>"Others"),G31+(1000-ROW())/1000000,"") | P31: =IF(AND(A31="Distribución",B31<>"Others"),G31+(1000-ROW())/1000000,"")
A32: Industrial | B32: Grupo Constructor Industrial | C32: Planta de líquidos Hada | D32: Ana Arias | E32: Colombia | F32: KingWall / King Frio | G32: 4600 | H32: 226730 | I32: Pending | L32: =IF(J32="","",H32*J32) | M32: =IF(AND(A32="Industrial",I32<>"Closed Won",B32<>"Others"),IF($C$4="m2",G32,H32)+(1000-ROW())/1000000,"") | N32: =IF(AND(A32="Distribución",I32<>"Closed Won",B32<>"Others"),IF($C$4="m2",G32,H32)+(1000-ROW())/1000000,"") | O32: =IF(AND(A32="Industrial",B32<>"Others"),G32+(1000-ROW())/1000000,"") | P32: =IF(AND(A32="Distribución",B32<>"Others"),G32+(1000-ROW())/1000000,"")
A33: Industrial | B33: Arklit | C33: Proyecto Hiper Santo Domingo | D33: Alejandra Navas | E33: Ecuador | F33: KingWall | G33: 4300 | H33: 90300 | I33: Pending | L33: =IF(J33="","",H33*J33) | M33: =IF(AND(A33="Industrial",I33<>"Closed Won",B33<>"Others"),IF($C$4="m2",G33,H33)+(1000-ROW())/1000000,"") | N33: =IF(AND(A33="Distribución",I33<>"Closed Won",B33<>"Others"),IF($C$4="m2",G33,H33)+(1000-ROW())/1000000,"") | O33: =IF(AND(A33="Industrial",B33<>"Others"),G33+(1000-ROW())/1000000,"") | P33: =IF(AND(A33="Distribución",B33<>"Others"),G33+(1000-ROW())/1000000,"")
A34: Industrial | B34: Others | C34: Different projects | D34: — | E34: Others | F34: King Wall / King Frio / King Roof | G34: 32582 | H34: 986673 | I34: Pending | L34: =IF(J34="","",H34*J34) | M34: =IF(AND(A34="Industrial",I34<>"Closed Won",B34<>"Others"),IF($C$4="m2",G34,H34)+(1000-ROW())/1000000,"") | N34: =IF(AND(A34="Distribución",I34<>"Closed Won",B34<>"Others"),IF($C$4="m2",G34,H34)+(1000-ROW())/1000000,"") | O34: =IF(AND(A34="Industrial",B34<>"Others"),G34+(1000-ROW())/1000000,"") | P34: =IF(AND(A34="Distribución",B34<>"Others"),G34+(1000-ROW())/1000000,"")
A35: Distribución | B35: Colcover | C35: Proyecto | D35: Henry Acosta | E35: Colombia | F35: KingRoof | G35: 21528 | H35: 411564.71 | I35: Pending | J35: 0.8 | K35: Noviembre | L35: =IF(J35="","",H35*J35) | M35: =IF(AND(A35="Industrial",I35<>"Closed Won",B35<>"Others"),IF($C$4="m2",G35,H35)+(1000-ROW())/1000000,"") | N35: =IF(AND(A35="Distribución",I35<>"Closed Won",B35<>"Others"),IF($C$4="m2",G35,H35)+(1000-ROW())/1000000,"") | O35: =IF(AND(A35="Industrial",B35<>"Others"),G35+(1000-ROW())/1000000,"") | P35: =IF(AND(A35="Distribución",B35<>"Others"),G35+(1000-ROW())/1000000,"")
A36: Distribución | B36: Galvaceros | C36: Colegios Sucre | D36: Joana Perez | E36: Colombia | F36: KingRoof | G36: 14000 | H36: 333529 | I36: Pending | J36: 0.82 | K36: Noviembre | L36: =IF(J36="","",H36*J36) | M36: =IF(AND(A36="Industrial",I36<>"Closed Won",B36<>"Others"),IF($C$4="m2",G36,H36)+(1000-ROW())/1000000,"") | N36: =IF(AND(A36="Distribución",I36<>"Closed Won",B36<>"Others"),IF($C$4="m2",G36,H36)+(1000-ROW())/1000000,"") | O36: =IF(AND(A36="Industrial",B36<>"Others"),G36+(1000-ROW())/1000000,"") | P36: =IF(AND(A36="Distribución",B36<>"Others"),G36+(1000-ROW())/1000000,"")
A37: Distribución | B37: RFS | C37: Cold Storage | D37: Juan Carlos Menendez | E37: Costa Rica | F37: KingFrigo | G37: 12500 | H37: 312500 | I37: Closed Won | L37: =IF(J37="","",H37*J37) | M37: =IF(AND(A37="Industrial",I37<>"Closed Won",B37<>"Others"),IF($C$4="m2",G37,H37)+(1000-ROW())/1000000,"") | N37: =IF(AND(A37="Distribución",I37<>"Closed Won",B37<>"Others"),IF($C$4="m2",G37,H37)+(1000-ROW())/1000000,"") | O37: =IF(AND(A37="Industrial",B37<>"Others"),G37+(1000-ROW())/1000000,"") | P37: =IF(AND(A37="Distribución",B37<>"Others"),G37+(1000-ROW())/1000000,"")
A38: Distribución | B38: CIA Caribe Mar | C38: Antártica | D38: María Yelitza Calderón | E38: Venezuela | F38: KingFrigo | G38: 12000 | H38: 360000 | I38: Specification | J38: 0.9 | K38: Noviembre | L38: =IF(J38="","",H38*J38) | M38: =IF(AND(A38="Industrial",I38<>"Closed Won",B38<>"Others"),IF($C$4="m2",G38,H38)+(1000-ROW())/1000000,"") | N38: =IF(AND(A38="Distribución",I38<>"Closed Won",B38<>"Others"),IF($C$4="m2",G38,H38)+(1000-ROW())/1000000,"") | O38: =IF(AND(A38="Industrial",B38<>"Others"),G38+(1000-ROW())/1000000,"") | P38: =IF(AND(A38="Distribución",B38<>"Others"),G38+(1000-ROW())/1000000,"")
A39: Distribución | B39: Galvaceros | C39: Panandina Data Center | D39: Joana Perez | E39: Colombia | F39: KingRoof / KingWall LMR | G39: 4106 | H39: 494712 | I39: Pending | J39: 0.85 | K39: Diciembre | L39: =IF(J39="","",H39*J39) | M39: =IF(AND(A39="Industrial",I39<>"Closed Won",B39<>"Others"),IF($C$4="m2",G39,H39)+(1000-ROW())/1000000,"") | N39: =IF(AND(A39="Distribución",I39<>"Closed Won",B39<>"Others"),IF($C$4="m2",G39,H39)+(1000-ROW())/1000000,"") | O39: =IF(AND(A39="Industrial",B39<>"Others"),G39+(1000-ROW())/1000000,"") | P39: =IF(AND(A39="Distribución",B39<>"Others"),G39+(1000-ROW())/1000000,"")
A40: Distribución | B40: Espuma SantaFe | C40: Recambio | D40: Henry Acosta | E40: Colombia | F40: KingRoof / KingWall | G40: 4000 | H40: 152072 | I40: Pending | J40: 0.8 | K40: Diciembre | L40: =IF(J40="","",H40*J40) | M40: =IF(AND(A40="Industrial",I40<>"Closed Won",B40<>"Others"),IF($C$4="m2",G40,H40)+(1000-ROW())/1000000,"") | N40: =IF(AND(A40="Distribución",I40<>"Closed Won",B40<>"Others"),IF($C$4="m2",G40,H40)+(1000-ROW())/1000000,"") | O40: =IF(AND(A40="Industrial",B40<>"Others"),G40+(1000-ROW())/1000000,"") | P40: =IF(AND(A40="Distribución",B40<>"Others"),G40+(1000-ROW())/1000000,"")
A41: Distribución | B41: Galvaceros | C41: Bodega Amazon etapa 2 | D41: Joana Perez | E41: Colombia | F41: KingRoof | G41: 4000 | H41: 136094 | I41: Pending | L41: =IF(J41="","",H41*J41) | M41: =IF(AND(A41="Industrial",I41<>"Closed Won",B41<>"Others"),IF($C$4="m2",G41,H41)+(1000-ROW())/1000000,"") | N41: =IF(AND(A41="Distribución",I41<>"Closed Won",B41<>"Others"),IF($C$4="m2",G41,H41)+(1000-ROW())/1000000,"") | O41: =IF(AND(A41="Industrial",B41<>"Others"),G41+(1000-ROW())/1000000,"") | P41: =IF(AND(A41="Distribución",B41<>"Others"),G41+(1000-ROW())/1000000,"")
A42: Distribución | B42: Agropecuaria SantaCruz | C42: Cuarto Frío | D42: Erwin Ríos | E42: Colombia | F42: KingFrigo | G42: 2715 | H42: 119437 | I42: Closed Won | L42: =IF(J42="","",H42*J42) | M42: =IF(AND(A42="Industrial",I42<>"Closed Won",B42<>"Others"),IF($C$4="m2",G42,H42)+(1000-ROW())/1000000,"") | N42: =IF(AND(A42="Distribución",I42<>"Closed Won",B42<>"Others"),IF($C$4="m2",G42,H42)+(1000-ROW())/1000000,"") | O42: =IF(AND(A42="Industrial",B42<>"Others"),G42+(1000-ROW())/1000000,"") | P42: =IF(AND(A42="Distribución",B42<>"Others"),G42+(1000-ROW())/1000000,"")
A43: Distribución | B43: Tejas Cubiertas e Ingeniería | C43: Recambio | D43: Edwar Salazar | E43: Colombia | F43: KingWall | G43: 2405 | H43: 79598 | I43: Pending | L43: =IF(J43="","",H43*J43) | M43: =IF(AND(A43="Industrial",I43<>"Closed Won",B43<>"Others"),IF($C$4="m2",G43,H43)+(1000-ROW())/1000000,"") | N43: =IF(AND(A43="Distribución",I43<>"Closed Won",B43<>"Others"),IF($C$4="m2",G43,H43)+(1000-ROW())/1000000,"") | O43: =IF(AND(A43="Industrial",B43<>"Others"),G43+(1000-ROW())/1000000,"") | P43: =IF(AND(A43="Distribución",B43<>"Others"),G43+(1000-ROW())/1000000,"")
A44: Distribución | B44: Técnica Industrial Duarte | C44: Stock | D44: María Yelitza Calderón | E44: Venezuela | F44: KingFrigo | G44: 2000 | H44: 60000 | I44: Closed Won | L44: =IF(J44="","",H44*J44) | M44: =IF(AND(A44="Industrial",I44<>"Closed Won",B44<>"Others"),IF($C$4="m2",G44,H44)+(1000-ROW())/1000000,"") | N44: =IF(AND(A44="Distribución",I44<>"Closed Won",B44<>"Others"),IF($C$4="m2",G44,H44)+(1000-ROW())/1000000,"") | O44: =IF(AND(A44="Industrial",B44<>"Others"),G44+(1000-ROW())/1000000,"") | P44: =IF(AND(A44="Distribución",B44<>"Others"),G44+(1000-ROW())/1000000,"")
L45: =IF(J45="","",H45*J45) | M45: =IF(AND(A45="Industrial",I45<>"Closed Won",B45<>"Others"),IF($C$4="m2",G45,H45)+(1000-ROW())/1000000,"") | N45: =IF(AND(A45="Distribución",I45<>"Closed Won",B45<>"Others"),IF($C$4="m2",G45,H45)+(1000-ROW())/1000000,"") | O45: =IF(AND(A45="Industrial",B45<>"Others"),G45+(1000-ROW())/1000000,"") | P45: =IF(AND(A45="Distribución",B45<>"Others"),G45+(1000-ROW())/1000000,"")
L46: =IF(J46="","",H46*J46) | M46: =IF(AND(A46="Industrial",I46<>"Closed Won",B46<>"Others"),IF($C$4="m2",G46,H46)+(1000-ROW())/1000000,"") | N46: =IF(AND(A46="Distribución",I46<>"Closed Won",B46<>"Others"),IF($C$4="m2",G46,H46)+(1000-ROW())/1000000,"") | O46: =IF(AND(A46="Industrial",B46<>"Others"),G46+(1000-ROW())/1000000,"") | P46: =IF(AND(A46="Distribución",B46<>"Others"),G46+(1000-ROW())/1000000,"")
L47: =IF(J47="","",H47*J47) | M47: =IF(AND(A47="Industrial",I47<>"Closed Won",B47<>"Others"),IF($C$4="m2",G47,H47)+(1000-ROW())/1000000,"") | N47: =IF(AND(A47="Distribución",I47<>"Closed Won",B47<>"Others"),IF($C$4="m2",G47,H47)+(1000-ROW())/1000000,"") | O47: =IF(AND(A47="Industrial",B47<>"Others"),G47+(1000-ROW())/1000000,"") | P47: =IF(AND(A47="Distribución",B47<>"Others"),G47+(1000-ROW())/1000000,"")
L48: =IF(J48="","",H48*J48) | M48: =IF(AND(A48="Industrial",I48<>"Closed Won",B48<>"Others"),IF($C$4="m2",G48,H48)+(1000-ROW())/1000000,"") | N48: =IF(AND(A48="Distribución",I48<>"Closed Won",B48<>"Others"),IF($C$4="m2",G48,H48)+(1000-ROW())/1000000,"") | O48: =IF(AND(A48="Industrial",B48<>"Others"),G48+(1000-ROW())/1000000,"") | P48: =IF(AND(A48="Distribución",B48<>"Others"),G48+(1000-ROW())/1000000,"")
L49: =IF(J49="","",H49*J49) | M49: =IF(AND(A49="Industrial",I49<>"Closed Won",B49<>"Others"),IF($C$4="m2",G49,H49)+(1000-ROW())/1000000,"") | N49: =IF(AND(A49="Distribución",I49<>"Closed Won",B49<>"Others"),IF($C$4="m2",G49,H49)+(1000-ROW())/1000000,"") | O49: =IF(AND(A49="Industrial",B49<>"Others"),G49+(1000-ROW())/1000000,"") | P49: =IF(AND(A49="Distribución",B49<>"Others"),G49+(1000-ROW())/1000000,"")
L50: =IF(J50="","",H50*J50) | M50: =IF(AND(A50="Industrial",I50<>"Closed Won",B50<>"Others"),IF($C$4="m2",G50,H50)+(1000-ROW())/1000000,"") | N50: =IF(AND(A50="Distribución",I50<>"Closed Won",B50<>"Others"),IF($C$4="m2",G50,H50)+(1000-ROW())/1000000,"") | O50: =IF(AND(A50="Industrial",B50<>"Others"),G50+(1000-ROW())/1000000,"") | P50: =IF(AND(A50="Distribución",B50<>"Others"),G50+(1000-ROW())/1000000,"")
L51: =IF(J51="","",H51*J51) | M51: =IF(AND(A51="Industrial",I51<>"Closed Won",B51<>"Others"),IF($C$4="m2",G51,H51)+(1000-ROW())/1000000,"") | N51: =IF(AND(A51="Distribución",I51<>"Closed Won",B51<>"Others"),IF($C$4="m2",G51,H51)+(1000-ROW())/1000000,"") | O51: =IF(AND(A51="Industrial",B51<>"Others"),G51+(1000-ROW())/1000000,"") | P51: =IF(AND(A51="Distribución",B51<>"Others"),G51+(1000-ROW())/1000000,"")
L52: =IF(J52="","",H52*J52) | M52: =IF(AND(A52="Industrial",I52<>"Closed Won",B52<>"Others"),IF($C$4="m2",G52,H52)+(1000-ROW())/1000000,"") | N52: =IF(AND(A52="Distribución",I52<>"Closed Won",B52<>"Others"),IF($C$4="m2",G52,H52)+(1000-ROW())/1000000,"") | O52: =IF(AND(A52="Industrial",B52<>"Others"),G52+(1000-ROW())/1000000,"") | P52: =IF(AND(A52="Distribución",B52<>"Others"),G52+(1000-ROW())/1000000,"")
L53: =IF(J53="","",H53*J53) | M53: =IF(AND(A53="Industrial",I53<>"Closed Won",B53<>"Others"),IF($C$4="m2",G53,H53)+(1000-ROW())/1000000,"") | N53: =IF(AND(A53="Distribución",I53<>"Closed Won",B53<>"Others"),IF($C$4="m2",G53,H53)+(1000-ROW())/1000000,"") | O53: =IF(AND(A53="Industrial",B53<>"Others"),G53+(1000-ROW())/1000000,"") | P53: =IF(AND(A53="Distribución",B53<>"Others"),G53+(1000-ROW())/1000000,"")
L54: =IF(J54="","",H54*J54) | M54: =IF(AND(A54="Industrial",I54<>"Closed Won",B54<>"Others"),IF($C$4="m2",G54,H54)+(1000-ROW())/1000000,"") | N54: =IF(AND(A54="Distribución",I54<>"Closed Won",B54<>"Others"),IF($C$4="m2",G54,H54)+(1000-ROW())/1000000,"") | O54: =IF(AND(A54="Industrial",B54<>"Others"),G54+(1000-ROW())/1000000,"") | P54: =IF(AND(A54="Distribución",B54<>"Others"),G54+(1000-ROW())/1000000,"")
L55: =IF(J55="","",H55*J55) | M55: =IF(AND(A55="Industrial",I55<>"Closed Won",B55<>"Others"),IF($C$4="m2",G55,H55)+(1000-ROW())/1000000,"") | N55: =IF(AND(A55="Distribución",I55<>"Closed Won",B55<>"Others"),IF($C$4="m2",G55,H55)+(1000-ROW())/1000000,"") | O55: =IF(AND(A55="Industrial",B55<>"Others"),G55+(1000-ROW())/1000000,"") | P55: =IF(AND(A55="Distribución",B55<>"Others"),G55+(1000-ROW())/1000000,"")
L56: =IF(J56="","",H56*J56) | M56: =IF(AND(A56="Industrial",I56<>"Closed Won",B56<>"Others"),IF($C$4="m2",G56,H56)+(1000-ROW())/1000000,"") | N56: =IF(AND(A56="Distribución",I56<>"Closed Won",B56<>"Others"),IF($C$4="m2",G56,H56)+(1000-ROW())/1000000,"") | O56: =IF(AND(A56="Industrial",B56<>"Others"),G56+(1000-ROW())/1000000,"") | P56: =IF(AND(A56="Distribución",B56<>"Others"),G56+(1000-ROW())/1000000,"")
... L67: =IF(J67="","",H67*J67) | M67: =IF(AND(A67="Industrial",I67<>"Closed Won",B67<>"Others"),IF($C$4="m2",G67,H67)+(1000-ROW())/1000000,"") | N67: =IF(AND(A67="Distribución",I67<>"Closed Won",B67<>"Others"),IF($C$4="m2",G67,H67)+(1000-ROW())/1000000,"") | O67: =IF(AND(A67="Industrial",B67<>"Others"),G67+(1000-ROW())/1000000,"") | P67: =IF(AND(A67="Distribución",B67<>"Others"),G67+(1000-ROW())/1000000,"")

Sheet Validaciones
A1: Validaciones de datos – deck original vs motor
A2: Inconsistencias detectadas al reconstruir el reporte (revisar con la fuente)
A3: Puntos abiertos (deben ser 0 antes del deck final): | E3: =COUNTIF(E5:E40,"Abierto")
A4: # | B4: Slide | C4: Hallazgo | D4: Tratamiento en esta versión | E4: Estado | F4: Cifra validada / responsable
A5: 1 | B5: Commercial Overview | C5: Order Intake rotulado "August" y YTD "1,293,5K m²"; la tabla OI muestra Sep = 146.446 y YTD = 1.239.541. | D5: Se rotula Sep-26 y se usa 1.239.541 (YoY +25,4%). | E5: Cerrado
A6: 2 | B6: Commercial Overview | C6: Ventas: solo se reportan % (YoY, MoM); no hay PY ni mes anterior absolutos. | D6: PY y Ago derivados del %; marcados como input a reemplazar. | E6: Cerrado
A7: 3 | B7: Order Intake / Backlog | C7: Tarjetas de margen dicen "August 2026". | D7: Se rotulan Sep-26. | E7: Cerrado
A8: 4 | B8: Performed / Forecast | C8: Ingreso Jul = 13.652.194 (duplica Jun). Con el valor del gráfico (11.718.909) el acumulado YTD cuadra con 130.176 COP MM. | D8: Jul corregido → cierre forecast 172.899 COP MM (+31,8% YoY) en lugar de 174.832 (+33%). | E8: Cerrado
A9: 5 | B9: Performed / Forecast | C9: Acumulado volumen Ene = 86.671 (debe ser 104.582) y acumulado ingreso Ene = 7.958.800 (es el PY). | D9: Acumulados recalculados por fórmula. | E9: Cerrado
A10: 6 | B10: Order Intake | C10: Gráfico OI Abr = 13.170 COP MM vs tabla Performed 12.270. | D10: Se usa 12.270 (cuadra con YTD 130.176). Validar. | E10: Cerrado
A11: 7 | B11: Backlog | C11: Ingreso PY = 10.617 (duplica Single Skin PY). | D11: Se usa 33.248 COP MM (gráfico de progresión Sep-25). | E11: Cerrado
A12: 8 | B12: Key Projects Industrial | C12: Suma de filas m² = 662.771 vs total reportado 658.771 (USD cuadra: 21.038.017). | D12: Se usa suma por fórmula; validar m² de alguna fila. | E12: Cerrado
A13: 9 | B13: Key Projects Industrial | C13: Se reportan 38 proyectos; la tabla tiene 26 filas + "Others". | D13: Se asume que "Others" agrupa 12 proyectos. | E13: Cerrado
A14: 10 | B14: Commercial Overview | C14: Top pedidos con encabezado "USD (mm)" y valores $306/$236/$173. | D14: Se conserva la unidad del deck; validar (¿USD miles?). | E14: Cerrado
A15: 11 | B15: Por canal (03 y 05) | C15: No hay OI/backlog mensual por canal ni PY/GM por canal en el deck. | D15: YTD y backlog por canal se toman de las tablas RSM; CM/PY/GM quedan como input. | E15: Cerrado
A16: 12 | B16: Overview / OI / Performed | C16: OI YTD: 1.239.541 m² (tabla OI) vs 1.228.503 m² (Performed, junio corregido). | D16: Definir una sola cifra y alinear slides 3–4 y 8. | E16: Abierto
... A26: 22 | B26: RSM by groups | C26: Detalle RSM (ventas 1.058.016 m², OI 1.269.124 m²) no cuadra con el IMP a octubre (ventas 1.199.504, OI 1.400.088): hojas 09–14 parecen cortadas a septiembre. | D26: Actualizar hojas 09–14 a octubre; el budget de Junta usa el mismo mes de corte. | E26: Abierto

Sheet 16_Iniciativas
A1: 16 · Iniciativas estratégicas (agosto) – semáforo de seguimiento
A2: Slides 15–16. Una fila por iniciativa. Diligenciar meta y resultado numérico para que el % de avance y el estado sugerido se calculen; el estado final se elige en la lista.
A4: # | B4: Iniciativa | C4: Compromiso / meta (presentado en agosto) | D4: KPI de medición | E4: Meta (número) | F4: Resultado sep (número) | G4: % avance | H4: Resultado sep (texto para slide) | I4: Estado sugerido | J4: Estado final | K4: Responsable | L4: Próximo paso | M4: Fecha | N4: Comentarios
A5: 1 | B5: Inteligencia competitiva / market share | G5: =IF(OR(E5="",F5="",E5=0),"",F5/E5) | I5: =IF(G5="","Definir",IF(G5>=0.9,"Verde",IF(G5>=0.7,"Amarillo","Rojo")))
A6: 2 | B6: Nuevos productos | G6: =IF(OR(E6="",F6="",E6=0),"",F6/E6) | I6: =IF(G6="","Definir",IF(G6>=0.9,"Verde",IF(G6>=0.7,"Amarillo","Rojo")))
A7: 3 | B7: Venezuela y Ecuador | G7: =IF(OR(E7="",F7="",E7=0),"",F7/E7) | H7: Evento Binacional Cúcuta; pipeline VE: CIA Caribe Mar USD 360k (especificación), Prosein + Remar USD 1,47 M; 1 proyecto VE ganado. Cuenta Ecuador por debajo de budget | I7: =IF(G7="","Definir",IF(G7>=0.9,"Verde",IF(G7>=0.7,"Amarillo","Rojo")))
A8: 4 | B8: Distribución | G8: =IF(OR(E8="",F8="",E8=0),"",F8/E8) | H8: 91% del budget de ventas YTD; backlog 64,5k m² (+27% YoY) con margen 30% (+3 pp) | I8: =IF(G8="","Definir",IF(G8>=0.9,"Verde",IF(G8>=0.7,"Amarillo","Rojo")))
A9: 5 | B9: Single Skin | G9: =IF(OR(E9="",F9="",E9=0),"",F9/E9) | H9: OI YTD 106k m² (2,8x PY); sep −4% YoY; backlog 40k m² (3,8x PY) | I9: =IF(G9="","Definir",IF(G9>=0.9,"Verde",IF(G9>=0.7,"Amarillo","Rojo")))
A10: 6 | B10: Benchmark / línea arquitectónica | G10: =IF(OR(E10="",F10="",E10=0),"",F10/E10) | H10: Benchmark OI YTD 5,8k m² (vs 0,4k PY); backlog 4,7k m²; 49,6k m² especificados línea arquitectónica; fachada Smartfit 599 m² | I10: =IF(G10="","Definir",IF(G10>=0.9,"Verde",IF(G10>=0.7,"Amarillo","Rojo")))
A11: 7 | B11: Top 20 proyectos | G11: =IF(OR(E11="",F11="",E11=0),"",F11/E11) | H11: Top 20 abiertos = USD 19,2 M (605k m²), 93% del pipeline abierto; Top 10 ponderado USD 8,3 M | I11: =IF(G11="","Definir",IF(G11>=0.9,"Verde",IF(G11>=0.7,"Amarillo","Rojo")))
A12: 8 | B12: Cali-Site | G12: =IF(OR(E12="",F12="",E12=0),"",F12/E12) | H12: 96% del budget de ventas YTD; OI YTD 140k m²; backlog 49k m² (margen 37%) | I12: =IF(G12="","Definir",IF(G12>=0.9,"Verde",IF(G12>=0.7,"Amarillo","Rojo")))
A14: Resumen
B15: Verde | C15: =COUNTIF(J5:J12,"Verde")
B16: Amarillo | C16: =COUNTIF(J5:J12,"Amarillo")
B17: Rojo | C17: =COUNTIF(J5:J12,"Rojo")
B18: Sin definir | C18: =8-COUNTIF(J5:J12,"Verde")-COUNTIF(J5:J12,"Amarillo")-COUNTIF(J5:J12,"Rojo")
A20: Regla estado sugerido: avance ≥90% = Verde · 70–89% = Amarillo · <70% = Rojo. Estado final (lista) prevalece en el slide.

Sheet 17_Actividad_Impacto
A1: 17 · De la actividad al impacto
A2: Slide 17. Indicadores de actividad (input) conectados con indicadores de impacto (fórmula cuando existe la fuente; input cuando no).
A4: Bloque | B4: Indicador | C4: Valor | D4: Unidad | E4: Fuente / nota
A5: Actividad | B5: Visitas a clientes | C5: ='15_Highlights'!B5 | D5: visitas | E5: 15_Highlights
A6: Actividad | B6: Personas capacitadas | C6: ='15_Highlights'!B9 | D6: personas | E6: 15_Highlights
A7: Actividad | B7: Clientes nuevos | C7: ='15_Highlights'!B6 | D7: clientes | E7: 15_Highlights
A8: Actividad | B8: m² especificados (paneles + arquitectónica) | C8: ='15_Highlights'!B14 | D8: m² | E8: 15_Highlights
A9: Impacto | B9: Oportunidades generadas por la actividad del mes (#) | D9: # | E9: INPUT – CRM: oportunidades creadas en el mes con origen visita/capacitación/especificación
A10: Impacto | B10: Valor de oportunidades generadas (USD) | D10: USD | E10: INPUT – CRM
A11: Impacto | B11: Valor pipeline total (USD) | C11: =SUM(Pipeline!H7:H67) | D11: USD | E11: Pipeline
A12: Impacto | B12: Closed won (USD) | C12: =SUMIFS(Pipeline!H7:H67,Pipeline!I7:I67,"Closed Won") | D12: USD | E12: Pipeline
A13: Impacto | B13: Conversión (closed won / pipeline) | C13: =IFERROR(C12/C11,0) | D13: % | E13: Calculado
A14: Impacto | B14: m² especificados convertidos en pedidos | D14: m² | E14: INPUT
A15: Impacto | B15: Conversión especificación → pedido | C15: =IF(C14="","",IFERROR(C14/C8,"")) | D15: % | E15: Calculado
A16: Impacto | B16: Pedidos clientes nuevos (m²) | C16: ='15_Highlights'!B7 | D16: m² | E16: 15_Highlights
A17: Impacto | B17: Pedidos clientes nuevos (USD) | C17: ='15_Highlights'!B8 | D17: USD | E17: 15_Highlights
A18: Impacto | B18: Order Intake del mes (m²) | C18: ='02_OI'!B7 | D18: m² | E18: 02_OI
A19: Impacto | B19: Ventas YTD (m²) | C19: =RSM_Resumen_Canales!D11 | D19: m² | E19: RSM_Resumen_Canales
A20: Impacto | B20: Margen OI del mes | C20: ='02_OI'!B12 | D20: % | E20: 02_OI
A21: Ratio | B21: USD de pipeline por visita | C21: =IFERROR(C11/C5,0) | D21: USD/visita | E21: Calculado
A22: Ratio | B22: Oportunidades generadas por cada 10 visitas | C22: =IF(C9="","",IFERROR(C9/C5*10,"")) | D22: # | E22: Calculado

Sheet 18_Acciones_Decisiones
A1: 18 · Decisiones y próximos pasos
A2: Slide 19. Filas 1–5 son propuestas derivadas del análisis: confirmar, editar o eliminar. Estado en lista.
A4: # | B4: Decisión / acción requerida | C4: Tipo | D4: Impacto esperado | E4: Responsable | F4: Fecha | G4: Estado | H4: Seguimiento / comentario
A5: 1 | B5: Cubrir territorios Industrial abiertos (Bogotá, cuentas clave) – contratar / reasignar cobertura | C5: Decisión | D5: ~82k m² de budget hoy sin ventas | G5: Abierta
A6: 2 | B6: Plan de recuperación cuentas Ecuador y Costa Rica | C6: Acción | D6: Cerrar parte de la brecha de −92k m² vs budget | G6: Abierta
A7: 3 | B7: Asegurar cierre Top 10 oportunidades (USD 9,4 M esperados en noviembre) | C7: Acción | D7: USD 8,3 M pipeline ponderado | G7: Abierta
A8: 4 | B8: Revisar pricing / mix del backlog Cold Storage | C8: Acción | D8: Recuperar margen −10,6 pp vs PY | G8: Abierta
A9: 5 | B9: Validar cifra única de OI YTD y cerrar notas pendientes antes del deck final | C9: Acción | D9: Una sola cifra validada para la junta | G9: Abierta
A10: 6
A11: 7
A12: 8
A13: 9
A14: 10
B16: Abiertas / en curso | C16: =COUNTIF(G5:G14,"Abierta")+COUNTIF(G5:G14,"En curso")

Sheet 20_Lost_Business
A1: 20 · Lost Business – negocios perdidos del mes
